Workbook

Sheet Setup
A1: Short-Term Rental Profit Tracker
A2: Manual entry, no sync. Fill your properties in once — every other tab reads from here.
B4: MANUAL ENTRY — this file does not log in to any platform, import calendars or sync with anything. You type eight cells per booking; fees, cleaning, laundry, consumables, net and the whole turnover plan calculate themselves.
B6: START HERE — four steps
B7: 1 · Overwrite the three example properties below with your own. Column L warns you about duplicate names and about characters that break lookups.
B8: 2 · Add your cleaning team in the second table (row 40) — those names become the dropdown in the Cleaning tab.
B9: 3 · Bookings tab: one row per stay. Property, platform, status, guest, check-in, check-out, guests, gross booking value. That is the whole job.
B10: 4 · Dashboard: pick a year and a month and read what each property actually earned. Never type anything else on that tab.
B12: THE THREE RULES THIS FILE COUNTS BY
B13: · Money (booking value, fees, cleaning, consumables) is counted in the month a stay CHECKS OUT. Nights and occupancy are split across months by the actual dates, so a stay over a month border shows nights in both months but money in one.
B14: · Gross booking value = the total the guest paid, including any cleaning fee you charged them. What you pay your cleaner is a cost — it belongs in column E below, never in the Bookings tab.
B15: · Fixed monthly costs (column J) run in EVERY month you look at, including months before you owned the place. Never log them again in the Costs tab; clear the field before you check earlier months.
B17: START EMPTY IN 30 SECONDS — in Bookings clear B5:G16, I5:K16 and S5:S16 (white cells only), in Cleaning clear J5:L16, in Costs clear B5:H9, then overwrite the three example properties below. Nothing else.
B18: GREY CELLS CALCULATE THEMSELVES — never clear or type in one, and leave the numbered # column alone. Deleted a grey cell by accident? Undo with Ctrl+Z / Cmd+Z, or copy the same cell from the row below and paste it back.
... B21: CURRENCY-NEUTRAL — no currency symbol is hard-coded. Select the number columns and apply your own currency format in one click.
A23: YOUR PROPERTIES — fill this in first
A24: Property name | B24: City / label | C24: Bedrooms | D24: Platform fee % (default) | E24: Cleaner pay per turnover | F24: Laundry per turnover | G24: Consumables per stay | H24: Consumables per night | I24: Linen sets per turnover | J24: Fixed monthly costs | K24: Notes | L24: Check
A25: Riverside Loft | B25: Porto | C25: 1 | D25: 0.03 | E25: 45 | F25: 12 | G25: 6 | H25: 1.5 | I25: 2 | J25: 62 | K25: EXAMPLE — overwrite with your own | L25: =IF($A25="","—",IF(COUNTIF($A$25:$A$36,$A25)>1,"⚠ duplicate name",IF(SUMPRODUCT(--ISNUMBER(FIND({"*";"?";"~"},$A25)))>0,"⚠ remove * ? ~ from the name","OK"))) -> OK
A26: Harbour Studio | B26: Porto | C26: 1 | D26: 0.15 | E26: 38 | F26: 9 | G26: 4.5 | H26: 1.2 | I26: 1 | J26: 48 | K26: EXAMPLE — overwrite with your own | L26: =IF($A26="","—",IF(COUNTIF($A$25:$A$36,$A26)>1,"⚠ duplicate name",IF(SUMPRODUCT(--ISNUMBER(FIND({"*";"?";"~"},$A26)))>0,"⚠ remove * ? ~ from the name","OK"))) -> OK
A27: Garden Cottage | B27: Braga | C27: 2 | D27: 0.08 | E27: 60 | F27: 18 | G27: 8 | H27: 2 | I27: 3 | J27: 74 | K27: EXAMPLE — overwrite with your own | L27: =IF($A27="","—",IF(COUNTIF($A$25:$A$36,$A27)>1,"⚠ duplicate name",IF(SUMPRODUCT(--ISNUMBER(FIND({"*";"?";"~"},$A27)))>0,"⚠ remove * ? ~ from the name","OK"))) -> OK
L28: =IF($A28="","—",IF(COUNTIF($A$25:$A$36,$A28)>1,"⚠ duplicate name",IF(SUMPRODUCT(--ISNUMBER(FIND({"*";"?";"~"},$A28)))>0,"⚠ remove * ? ~ from the name","OK"))) -> —
L29: =IF($A29="","—",IF(COUNTIF($A$25:$A$36,$A29)>1,"⚠ duplicate name",IF(SUMPRODUCT(--ISNUMBER(FIND({"*";"?";"~"},$A29)))>0,"⚠ remove * ? ~ from the name","OK"))) -> —
L30: =IF($A30="","—",IF(COUNTIF($A$25:$A$36,$A30)>1,"⚠ duplicate name",IF(SUMPRODUCT(--ISNUMBER(FIND({"*";"?";"~"},$A30)))>0,"⚠ remove * ? ~ from the name","OK"))) -> —
L31: =IF($A31="","—",IF(COUNTIF($A$25:$A$36,$A31)>1,"⚠ duplicate name",IF(SUMPRODUCT(--ISNUMBER(FIND({"*";"?";"~"},$A31)))>0,"⚠ remove * ? ~ from the name","OK"))) -> —
L32: =IF($A32="","—",IF(COUNTIF($A$25:$A$36,$A32)>1,"⚠ duplicate name",IF(SUMPRODUCT(--ISNUMBER(FIND({"*";"?";"~"},$A32)))>0,"⚠ remove * ? ~ from the name","OK"))) -> —
L33: =IF($A33="","—",IF(COUNTIF($A$25:$A$36,$A33)>1,"⚠ duplicate name",IF(SUMPRODUCT(--ISNUMBER(FIND({"*";"?";"~"},$A33)))>0,"⚠ remove * ? ~ from the name","OK"))) -> —
L34: =IF($A34="","—",IF(COUNTIF($A$25:$A$36,$A34)>1,"⚠ duplicate name",IF(SUMPRODUCT(--ISNUMBER(FIND({"*";"?";"~"},$A34)))>0,"⚠ remove * ? ~ from the name","OK"))) -> —
L35: =IF($A35="","—",IF(COUNTIF($A$25:$A$36,$A35)>1,"⚠ duplicate name",IF(SUMPRODUCT(--ISNUMBER(FIND({"*";"?";"~"},$A35)))>0,"⚠ remove * ? ~ from the name","OK"))) -> —
L36: =IF($A36="","—",IF(COUNTIF($A$25:$A$36,$A36)>1,"⚠ duplicate name",IF(SUMPRODUCT(--ISNUMBER(FIND({"*";"?";"~"},$A36)))>0,"⚠ remove * ? ~ from the name","OK"))) -> —
A38: CLEANING TEAM (feeds the dropdown in the Cleaning tab)
A39: Cleaner name | B39: Phone / contact | C39: Rate note
A40: Ana | B40: +351 000 000 000 | C40: EXAMPLE — overwrite
A41: Marco | B41: +351 000 000 000 | C41: EXAMPLE — overwrite
A42: CleanCo (agency) | B42: office@example.com | C42: EXAMPLE — overwrite
A43: Me (owner) | C43: EXAMPLE — overwrite
B49: GOOD TO KNOW
B50: Google Sheets: File ▸ Import ▸ Upload this file. Formulas, dropdowns and colours carry over. The Dashboard's write-protection is an Excel feature and does not — in Google Sheets just avoid typing on that tab.
B51: Excel: the Dashboard is write-protected so you cannot type over a formula by accident. Review ▸ Unprotect Sheet (no password) if you want to restyle it.
B52: Filtering and sorting: use the filter arrows in row 4 to filter. If you want to sort, select the whole table first (Bookings A4:W304, Cleaning A4:L304, 'data has header row') — never sort a single column on its own. The numbered # column keeps Bookings and Cleaning linked either way.
B53: More than 300 bookings? Select the last row of Bookings and drag it down, then do the same in Cleaning so both sheets stay the same length — and widen the ranges in the Dashboard formulas, which read rows 5–304 today.
B54: Property names: avoid the characters * ? and ~ . Spreadsheets read them as wildcards and they would quietly mismatch your bookings. Column L tells you if one slipped in.
B55: Percentages: type 3% or 0.03, not 3. The file corrects an obvious 15 into 15% for you, but typing the % sign keeps Excel and Google Sheets identical.
B57: HANDING THE CLEANING LIST TO A CLEANER
B58: Sharing this file always shares every tab, including your money. To give a cleaner their own list: right-click the Cleaning tab ▸ Copy to ▸ New spreadsheet, then Edit ▸ Paste special ▸ Values only, and delete column I — it shows what you pay per turnover.
B59: Guest names are personal data. Only share that list with people who need it.
B61: This is a spreadsheet for your own bookkeeping-free overview. It is not tax, legal or accounting advice, and it does not calculate tax of any kind. Check any figure before you rely on it.
B62: Built for Excel and Google Sheets — no macros, no add-ons, no plug-ins, nothing to install.
... B64: Questions, or a formula that looks wrong? Message us on Etsy — we reply within 48 h.

Sheet Dashboard
A1: Dashboard — one month, every property side by side
A2: Pick a year and a month in the two white cells. Everything else on this tab calculates itself from Bookings, Cleaning and Costs. | O2: Period start | P2: =IFERROR(DATE($B$4,MATCH($D$4,Lists!$G$1:$G$12,0),1),DATE(YEAR(TODAY()),MONTH(TODAY()),1)) -> 46204
O3: Period end | P3: =IFERROR(DATE(YEAR($P$2),MONTH($P$2)+1,0),$P$2) -> 46234
A4: Year | B4: =IFERROR(YEAR(TODAY()),2025) -> 2026 | C4: Month | D4: =IFERROR(INDEX(Lists!$G$1:$G$12,MONTH(TODAY())),"January") -> July | F4: =IF(OR(NOT(ISNUMBER($P$2)),NOT(ISNUMBER($P$3))),"Pick a year in B4 and a month in D4.","Showing "&DAY($P$2)&" "&INDEX(Lists!$G$1:$G$12,MONTH($P$2))&" "&YEAR($P$2)&" to "&DAY($P$3)&" "&INDEX(Lists!$G$1:$G$12,MONTH($P$3))&" "&YEAR($P$3)&" · money is counted in the month a stay CHECKS OUT; nights are split by actual date") -> Showing 1 July 2026 to 31 July 2026 · money is counted in the month a stay CHECKS OUT; nights are split by actual date | O4: Days in month | P4: =IF(NOT(ISNUMBER($P$3)),"—",DAY($P$3)) -> 31
A6: Net (tracked costs only) | C6: Gross booking value | E6: Total tracked costs | G6: Occupancy | I6: Net per available night | K6: Cleanings still open
A7: =IF(NOT(ISNUMBER($L$23)),"—",$L$23) -> 2549.2 | C7: =IF(NOT(ISNUMBER($E$23)),"—",$E$23) -> 3890 | E7: =IF(NOT(ISNUMBER($K$23)),"—",$K$23) -> 1340.8 | G7: =IF(NOT(ISNUMBER($D$23)),"—",$D$23) -> 0.4 | I7: =IF(NOT(ISNUMBER($M$23)),"—",$M$23) -> 28.32 | K7: =IF(COUNTIFS(Cleaning!$D$5:$D$304,">="&$P$2,Cleaning!$D$5:$D$304,"<="&$P$3)=0,"—",IF(COUNTIFS(Cleaning!$D$5:$D$304,">="&$P$2,Cleaning!$D$5:$D$304,"<="&$P$3)-COUNTIFS(Cleaning!$D$5:$D$304,">="&$P$2,Cleaning!$D$5:$D$304,"<="&$P$3,Cleaning!$K$5:$K$304,"Done")=0,"All done ✓",COUNTIFS(Cleaning!$D$5:$D$304,">="&$P$2,Cleaning!$D$5:$D$304,"<="&$P$3)-COUNTIFS(Cleaning!$D$5:$D$304,">="&$P$2,Cleaning!$D$5:$D$304,"<="&$P$3,Cleaning!$K$5:$K$304,"Done"))) -> 1
A9: PER PROPERTY — selected month
A10: Property | B10: Nights booked | C10: Nights available | D10: Occupancy % | E10: Gross booking value | F10: Platform fees | G10: Cleaning & laundry | H10: Consumables | I10: Fixed monthly | J10: Other logged costs | K10: Total costs | L10: Net after tracked costs | M10: Net per available night
A11: =IF(Setup!$A25="","—",Setup!$A25) -> Riverside Loft | B11: =IF($A11="—","—",IF(SUMIFS(Bookings!$T$5:$T$304,Bookings!$B$5:$B$304,$A11)=0,"—",SUMIFS(Bookings!$T$5:$T$304,Bookings!$B$5:$B$304,$A11))) -> 16 | C11: =IF(OR($A11="—",NOT(ISNUMBER($P$4))),"—",$P$4-SUMIFS(Bookings!$U$5:$U$304,Bookings!$B$5:$B$304,$A11)) -> 31 | D11: =IFERROR(IF(OR($A11="—",NOT(ISNUMBER($C11)),$C11<=0),"—",IF(ISNUMBER($B11),$B11,0)/$C11),"—") -> 0.51612903 | E11: =IF($A11="—","—",IF(SUMIFS(Bookings!$W$5:$W$304,Bookings!$B$5:$B$304,$A11,Bookings!$G$5:$G$304,">="&$P$2,Bookings!$G$5:$G$304,"<="&$P$3)=0,"—",SUMIFS(Bookings!$W$5:$W$304,Bookings!$B$5:$B$304,$A11,Bookings!$G$5:$G$304,">="&$P$2,Bookings!$G$5:$G$304,"<="&$P$3))) -> 1935 | F11: =IF($A11="—","—",IF(SUMIFS(Bookings!$L$5:$L$304,Bookings!$B$5:$B$304,$A11,Bookings!$G$5:$G$304,">="&$P$2,Bookings!$G$5:$G$304,"<="&$P$3)=0,"—",SUMIFS(Bookings!$L$5:$L$304,Bookings!$B$5:$B$304,$A11,Bookings!$G$5:$G$304,">="&$P$2,Bookings!$G$5:$G$304,"<="&$P$3))) -> 66.65 | G11: =IF($A11="—","—",IF(SUMIFS(Bookings!$N$5:$N$304,Bookings!$B$5:$B$304,$A11,Bookings!$G$5:$G$304,">="&$P$2,Bookings!$G$5:$G$304,"<="&$P$3)+SUMIFS(Bookings!$O$5:$O$304,Bookings!$B$5:$B$304,$A11,Bookings!$G$5:$G$304,">="&$P$2,Bookings!$G$5:$G$304,"<="&$P$3)=0,"—",SUMIFS(Bookings!$N$5:$N$304,Bookings!$B$5:$B$304,$A11,Bookings!$G$5:$G$304,">="&$P$2,Bookings!$G$5:$G$304,"<="&$P$3)+SUMIFS(Bookings!$O$5:$O$304,Bookings!$B$5:$B$304,$A11,Bookings!$G$5:$G$304,">="&$P$2,Bookings!$G$5:$G$304,"<="&$P$3))) -> 228 | H11: =IF($A11="—","—",IF(SUMIFS(Bookings!$P$5:$P$304,Bookings!$B$5:$B$304,$A11,Bookings!$G$5:$G$304,">="&$P$2,Bookings!$G$5:$G$304,"<="&$P$3)=0,"—",SUMIFS(Bookings!$P$5:$P$304,Bookings!$B$5:$B$304,$A11,Bookings!$G$5:$G$304,">="&$P$2,Bookings!$G$5:$G$304,"<="&$P$3))) -> 49.5 | I11: =IF($A11="—","—",IFERROR(IF(INDEX(Setup!$J$25:$J$36,MATCH($A11,Setup!$A$25:$A$36,0))=0,"—",INDEX(Setup!$J$25:$J$36,MATCH($A11,Setup!$A$25:$A$36,0))),"—")) -> 62 | J11: =IF($A11="—","—",IF(SUMIFS(Costs!$F$5:$F$254,Costs!$C$5:$C$254,$A11,Costs!$B$5:$B$254,">="&$P$2,Costs!$B$5:$B$254,"<="&$P$3)=0,"—",SUMIFS(Costs!$F$5:$F$254,Costs!$C$5:$C$254,$A11,Costs!$B$5:$B$254,">="&$P$2,Costs!$B$5:$B$254,"<="&$P$3))) -> 148.5 | K11: =IF(OR($A11="—",COUNT($F11:$J11)=0),"—",ROUND(SUM($F11:$J11),2)) -> 554.65 | L11: =IF(OR($A11="—",COUNT($E11,$K11)=0),"—",ROUND(IF(ISNUMBER($E11),$E11,0)-IF(ISNUMBER($K11),$K11,0),2)) -> 1380.35 | M11: =IF(OR(NOT(ISNUMBER($L11)),NOT(ISNUMBER($C11)),$C11<=0),"—",ROUND($L11/$C11,2)) -> 44.53
A12: =IF(Setup!$A26="","—",Setup!$A26) -> Harbour Studio | B12: =IF($A12="—","—",IF(SUMIFS(Bookings!$T$5:$T$304,Bookings!$B$5:$B$304,$A12)=0,"—",SUMIFS(Bookings!$T$5:$T$304,Bookings!$B$5:$B$304,$A12))) -> 14 | C12: =IF(OR($A12="—",NOT(ISNUMBER($P$4))),"—",$P$4-SUMIFS(Bookings!$U$5:$U$304,Bookings!$B$5:$B$304,$A12)) -> 31 | D12: =IFERROR(IF(OR($A12="—",NOT(ISNUMBER($C12)),$C12<=0),"—",IF(ISNUMBER($B12),$B12,0)/$C12),"—") -> 0.4516129 | E12: =IF($A12="—","—",IF(SUMIFS(Bookings!$W$5:$W$304,Bookings!$B$5:$B$304,$A12,Bookings!$G$5:$G$304,">="&$P$2,Bookings!$G$5:$G$304,"<="&$P$3)=0,"—",SUMIFS(Bookings!$W$5:$W$304,Bookings!$B$5:$B$304,$A12,Bookings!$G$5:$G$304,">="&$P$2,Bookings!$G$5:$G$304,"<="&$P$3))) -> 1065 | F12: =IF($A12="—","—",IF(SUMIFS(Bookings!$L$5:$L$304,Bookings!$B$5:$B$304,$A12,Bookings!$G$5:$G$304,">="&$P$2,Bookings!$G$5:$G$304,"<="&$P$3)=0,"—",SUMIFS(Bookings!$L$5:$L$304,Bookings!$B$5:$B$304,$A12,Bookings!$G$5:$G$304,">="&$P$2,Bookings!$G$5:$G$304,"<="&$P$3))) -> 123.75 | G12: =IF($A12="—","—",IF(SUMIFS(Bookings!$N$5:$N$304,Bookings!$B$5:$B$304,$A12,Bookings!$G$5:$G$304,">="&$P$2,Bookings!$G$5:$G$304,"<="&$P$3)+SUMIFS(Bookings!$O$5:$O$304,Bookings!$B$5:$B$304,$A12,Bookings!$G$5:$G$304,">="&$P$2,Bookings!$G$5:$G$304,"<="&$P$3)=0,"—",SUMIFS(Bookings!$N$5:$N$304,Bookings!$B$5:$B$304,$A12,Bookings!$G$5:$G$304,">="&$P$2,Bookings!$G$5:$G$304,"<="&$P$3)+SUMIFS(Bookings!$O$5:$O$304,Bookings!$B$5:$B$304,$A12,Bookings!$G$5:$G$304,">="&$P$2,Bookings!$G$5:$G$304,"<="&$P$3))) -> 141 | H12: =IF($A12="—","—",IF(SUMIFS(Bookings!$P$5:$P$304,Bookings!$B$5:$B$304,$A12,Bookings!$G$5:$G$304,">="&$P$2,Bookings!$G$5:$G$304,"<="&$P$3)=0,"—",SUMIFS(Bookings!$P$5:$P$304,Bookings!$B$5:$B$304,$A12,Bookings!$G$5:$G$304,">="&$P$2,Bookings!$G$5:$G$304,"<="&$P$3))) -> 30.3 | I12: =IF($A12="—","—",IFERROR(IF(INDEX(Setup!$J$25:$J$36,MATCH($A12,Setup!$A$25:$A$36,0))=0,"—",INDEX(Setup!$J$25:$J$36,MATCH($A12,Setup!$A$25:$A$36,0))),"—")) -> 48 | J12: =IF($A12="—","—",IF(SUMIFS(Costs!$F$5:$F$254,Costs!$C$5:$C$254,$A12,Costs!$B$5:$B$254,">="&$P$2,Costs!$B$5:$B$254,"<="&$P$3)=0,"—",SUMIFS(Costs!$F$5:$F$254,Costs!$C$5:$C$254,$A12,Costs!$B$5:$B$254,">="&$P$2,Costs!$B$5:$B$254,"<="&$P$3))) -> 34.9 | K12: =IF(OR($A12="—",COUNT($F12:$J12)=0),"—",ROUND(SUM($F12:$J12),2)) -> 377.95 | L12: =IF(OR($A12="—",COUNT($E12,$K12)=0),"—",ROUND(IF(ISNUMBER($E12),$E12,0)-IF(ISNUMBER($K12),$K12,0),2)) -> 687.05 | M12: =IF(OR(NOT(ISNUMBER($L12)),NOT(ISNUMBER($C12)),$C12<=0),"—",ROUND($L12/$C12,2)) -> 22.16
A13: =IF(Setup!$A27="","—",Setup!$A27) -> Garden Cottage | B13: =IF($A13="—","—",IF(SUMIFS(Bookings!$T$5:$T$304,Bookings!$B$5:$B$304,$A13)=0,"—",SUMIFS(Bookings!$T$5:$T$304,Bookings!$B$5:$B$304,$A13))) -> 6 | C13: =IF(OR($A13="—",NOT(ISNUMBER($P$4))),"—",$P$4-SUMIFS(Bookings!$U$5:$U$304,Bookings!$B$5:$B$304,$A13)) -> 28 | D13: =IFERROR(IF(OR($A13="—",NOT(ISNUMBER($C13)),$C13<=0),"—",IF(ISNUMBER($B13),$B13,0)/$C13),"—") -> 0.21428571 | E13: =IF($A13="—","—",IF(SUMIFS(Bookings!$W$5:$W$304,Bookings!$B$5:$B$304,$A13,Bookings!$G$5:$G$304,">="&$P$2,Bookings!$G$5:$G$304,"<="&$P$3)=0,"—",SUMIFS(Bookings!$W$5:$W$304,Bookings!$B$5:$B$304,$A13,Bookings!$G$5:$G$304,">="&$P$2,Bookings!$G$5:$G$304,"<="&$P$3))) -> 890 | F13: =IF($A13="—","—",IF(SUMIFS(Bookings!$L$5:$L$304,Bookings!$B$5:$B$304,$A13,Bookings!$G$5:$G$304,">="&$P$2,Bookings!$G$5:$G$304,"<="&$P$3)=0,"—",SUMIFS(Bookings!$L$5:$L$304,Bookings!$B$5:$B$304,$A13,Bookings!$G$5:$G$304,">="&$P$2,Bookings!$G$5:$G$304,"<="&$P$3))) -> 71.2 | G13: =IF($A13="—","—",IF(SUMIFS(Bookings!$N$5:$N$304,Bookings!$B$5:$B$304,$A13,Bookings!$G$5:$G$304,">="&$P$2,Bookings!$G$5:$G$304,"<="&$P$3)+SUMIFS(Bookings!$O$5:$O$304,Bookings!$B$5:$B$304,$A13,Bookings!$G$5:$G$304,">="&$P$2,Bookings!$G$5:$G$304,"<="&$P$3)=0,"—",SUMIFS(Bookings!$N$5:$N$304,Bookings!$B$5:$B$304,$A13,Bookings!$G$5:$G$304,">="&$P$2,Bookings!$G$5:$G$304,"<="&$P$3)+SUMIFS(Bookings!$O$5:$O$304,Bookings!$B$5:$B$304,$A13,Bookings!$G$5:$G$304,">="&$P$2,Bookings!$G$5:$G$304,"<="&$P$3))) -> 156 | H13: =IF($A13="—","—",IF(SUMIFS(Bookings!$P$5:$P$304,Bookings!$B$5:$B$304,$A13,Bookings!$G$5:$G$304,">="&$P$2,Bookings!$G$5:$G$304,"<="&$P$3)=0,"—",SUMIFS(Bookings!$P$5:$P$304,Bookings!$B$5:$B$304,$A13,Bookings!$G$5:$G$304,">="&$P$2,Bookings!$G$5:$G$304,"<="&$P$3))) -> 20 | I13: =IF($A13="—","—",IFERROR(IF(INDEX(Setup!$J$25:$J$36,MATCH($A13,Setup!$A$25:$A$36,0))=0,"—",INDEX(Setup!$J$25:$J$36,MATCH($A13,Setup!$A$25:$A$36,0))),"—")) -> 74 | J13: =IF($A13="—","—",IF(SUMIFS(Costs!$F$5:$F$254,Costs!$C$5:$C$254,$A13,Costs!$B$5:$B$254,">="&$P$2,Costs!$B$5:$B$254,"<="&$P$3)=0,"—",SUMIFS(Costs!$F$5:$F$254,Costs!$C$5:$C$254,$A13,Costs!$B$5:$B$254,">="&$P$2,Costs!$B$5:$B$254,"<="&$P$3))) -> 87 | K13: =IF(OR($A13="—",COUNT($F13:$J13)=0),"—",ROUND(SUM($F13:$J13),2)) -> 408.2 | L13: =IF(OR($A13="—",COUNT($E13,$K13)=0),"—",ROUND(IF(ISNUMBER($E13),$E13,0)-IF(ISNUMBER($K13),$K13,0),2)) -> 481.8 | M13: =IF(OR(NOT(ISNUMBER($L13)),NOT(ISNUMBER($C13)),$C13<=0),"—",ROUND($L13/$C13,2)) -> 17.21
A14: =IF(Setup!$A28="","—",Setup!$A28) -> — | B14: =IF($A14="—","—",IF(SUMIFS(Bookings!$T$5:$T$304,Bookings!$B$5:$B$304,$A14)=0,"—",SUMIFS(Bookings!$T$5:$T$304,Bookings!$B$5:$B$304,$A14))) -> — | C14: =IF(OR($A14="—",NOT(ISNUMBER($P$4))),"—",$P$4-SUMIFS(Bookings!$U$5:$U$304,Bookings!$B$5:$B$304,$A14)) -> — | D14: =IFERROR(IF(OR($A14="—",NOT(ISNUMBER($C14)),$C14<=0),"—",IF(ISNUMBER($B14),$B14,0)/$C14),"—") -> — | E14: =IF($A14="—","—",IF(SUMIFS(Bookings!$W$5:$W$304,Bookings!$B$5:$B$304,$A14,Bookings!$G$5:$G$304,">="&$P$2,Bookings!$G$5:$G$304,"<="&$P$3)=0,"—",SUMIFS(Bookings!$W$5:$W$304,Bookings!$B$5:$B$304,$A14,Bookings!$G$5:$G$304,">="&$P$2,Bookings!$G$5:$G$304,"<="&$P$3))) -> — | F14: =IF($A14="—","—",IF(SUMIFS(Bookings!$L$5:$L$304,Bookings!$B$5:$B$304,$A14,Bookings!$G$5:$G$304,">="&$P$2,Bookings!$G$5:$G$304,"<="&$P$3)=0,"—",SUMIFS(Bookings!$L$5:$L$304,Bookings!$B$5:$B$304,$A14,Bookings!$G$5:$G$304,">="&$P$2,Bookings!$G$5:$G$304,"<="&$P$3))) -> — | G14: =IF($A14="—","—",IF(SUMIFS(Bookings!$N$5:$N$304,Bookings!$B$5:$B$304,$A14,Bookings!$G$5:$G$304,">="&$P$2,Bookings!$G$5:$G$304,"<="&$P$3)+SUMIFS(Bookings!$O$5:$O$304,Bookings!$B$5:$B$304,$A14,Bookings!$G$5:$G$304,">="&$P$2,Bookings!$G$5:$G$304,"<="&$P$3)=0,"—",SUMIFS(Bookings!$N$5:$N$304,Bookings!$B$5:$B$304,$A14,Bookings!$G$5:$G$304,">="&$P$2,Bookings!$G$5:$G$304,"<="&$P$3)+SUMIFS(Bookings!$O$5:$O$304,Bookings!$B$5:$B$304,$A14,Bookings!$G$5:$G$304,">="&$P$2,Bookings!$G$5:$G$304,"<="&$P$3))) -> — | H14: =IF($A14="—","—",IF(SUMIFS(Bookings!$P$5:$P$304,Bookings!$B$5:$B$304,$A14,Bookings!$G$5:$G$304,">="&$P$2,Bookings!$G$5:$G$304,"<="&$P$3)=0,"—",SUMIFS(Bookings!$P$5:$P$304,Bookings!$B$5:$B$304,$A14,Bookings!$G$5:$G$304,">="&$P$2,Bookings!$G$5:$G$304,"<="&$P$3))) -> — | I14: =IF($A14="—","—",IFERROR(IF(INDEX(Setup!$J$25:$J$36,MATCH($A14,Setup!$A$25:$A$36,0))=0,"—",INDEX(Setup!$J$25:$J$36,MATCH($A14,Setup!$A$25:$A$36,0))),"—")) -> — | J14: =IF($A14="—","—",IF(SUMIFS(Costs!$F$5:$F$254,Costs!$C$5:$C$254,$A14,Costs!$B$5:$B$254,">="&$P$2,Costs!$B$5:$B$254,"<="&$P$3)=0,"—",SUMIFS(Costs!$F$5:$F$254,Costs!$C$5:$C$254,$A14,Costs!$B$5:$B$254,">="&$P$2,Costs!$B$5:$B$254,"<="&$P$3))) -> — | K14: =IF(OR($A14="—",COUNT($F14:$J14)=0),"—",ROUND(SUM($F14:$J14),2)) -> — | L14: =IF(OR($A14="—",COUNT($E14,$K14)=0),"—",ROUND(IF(ISNUMBER($E14),$E14,0)-IF(ISNUMBER($K14),$K14,0),2)) -> — | M14: =IF(OR(NOT(ISNUMBER($L14)),NOT(ISNUMBER($C14)),$C14<=0),"—",ROUND($L14/$C14,2)) -> —
A15: =IF(Setup!$A29="","—",Setup!$A29) -> — | B15: =IF($A15="—","—",IF(SUMIFS(Bookings!$T$5:$T$304,Bookings!$B$5:$B$304,$A15)=0,"—",SUMIFS(Bookings!$T$5:$T$304,Bookings!$B$5:$B$304,$A15))) -> — | C15: =IF(OR($A15="—",NOT(ISNUMBER($P$4))),"—",$P$4-SUMIFS(Bookings!$U$5:$U$304,Bookings!$B$5:$B$304,$A15)) -> — | D15: =IFERROR(IF(OR($A15="—",NOT(ISNUMBER($C15)),$C15<=0),"—",IF(ISNUMBER($B15),$B15,0)/$C15),"—") -> — | E15: =IF($A15="—","—",IF(SUMIFS(Bookings!$W$5:$W$304,Bookings!$B$5:$B$304,$A15,Bookings!$G$5:$G$304,">="&$P$2,Bookings!$G$5:$G$304,"<="&$P$3)=0,"—",SUMIFS(Bookings!$W$5:$W$304,Bookings!$B$5:$B$304,$A15,Bookings!$G$5:$G$304,">="&$P$2,Bookings!$G$5:$G$304,"<="&$P$3))) -> — | F15: =IF($A15="—","—",IF(SUMIFS(Bookings!$L$5:$L$304,Bookings!$B$5:$B$304,$A15,Bookings!$G$5:$G$304,">="&$P$2,Bookings!$G$5:$G$304,"<="&$P$3)=0,"—",SUMIFS(Bookings!$L$5:$L$304,Bookings!$B$5:$B$304,$A15,Bookings!$G$5:$G$304,">="&$P$2,Bookings!$G$5:$G$304,"<="&$P$3))) -> — | G15: =IF($A15="—","—",IF(SUMIFS(Bookings!$N$5:$N$304,Bookings!$B$5:$B$304,$A15,Bookings!$G$5:$G$304,">="&$P$2,Bookings!$G$5:$G$304,"<="&$P$3)+SUMIFS(Bookings!$O$5:$O$304,Bookings!$B$5:$B$304,$A15,Bookings!$G$5:$G$304,">="&$P$2,Bookings!$G$5:$G$304,"<="&$P$3)=0,"—",SUMIFS(Bookings!$N$5:$N$304,Bookings!$B$5:$B$304,$A15,Bookings!$G$5:$G$304,">="&$P$2,Bookings!$G$5:$G$304,"<="&$P$3)+SUMIFS(Bookings!$O$5:$O$304,Bookings!$B$5:$B$304,$A15,Bookings!$G$5:$G$304,">="&$P$2,Bookings!$G$5:$G$304,"<="&$P$3))) -> — | H15: =IF($A15="—","—",IF(SUMIFS(Bookings!$P$5:$P$304,Bookings!$B$5:$B$304,$A15,Bookings!$G$5:$G$304,">="&$P$2,Bookings!$G$5:$G$304,"<="&$P$3)=0,"—",SUMIFS(Bookings!$P$5:$P$304,Bookings!$B$5:$B$304,$A15,Bookings!$G$5:$G$304,">="&$P$2,Bookings!$G$5:$G$304,"<="&$P$3))) -> — | I15: =IF($A15="—","—",IFERROR(IF(INDEX(Setup!$J$25:$J$36,MATCH($A15,Setup!$A$25:$A$36,0))=0,"—",INDEX(Setup!$J$25:$J$36,MATCH($A15,Setup!$A$25:$A$36,0))),"—")) -> — | J15: =IF($A15="—","—",IF(SUMIFS(Costs!$F$5:$F$254,Costs!$C$5:$C$254,$A15,Costs!$B$5:$B$254,">="&$P$2,Costs!$B$5:$B$254,"<="&$P$3)=0,"—",SUMIFS(Costs!$F$5:$F$254,Costs!$C$5:$C$254,$A15,Costs!$B$5:$B$254,">="&$P$2,Costs!$B$5:$B$254,"<="&$P$3))) -> — | K15: =IF(OR($A15="—",COUNT($F15:$J15)=0),"—",ROUND(SUM($F15:$J15),2)) -> — | L15: =IF(OR($A15="—",COUNT($E15,$K15)=0),"—",ROUND(IF(ISNUMBER($E15),$E15,0)-IF(ISNUMBER($K15),$K15,0),2)) -> — | M15: =IF(OR(NOT(ISNUMBER($L15)),NOT(ISNUMBER($C15)),$C15<=0),"—",ROUND($L15/$C15,2)) -> —
A16: =IF(Setup!$A30="","—",Setup!$A30) -> — | B16: =IF($A16="—","—",IF(SUMIFS(Bookings!$T$5:$T$304,Bookings!$B$5:$B$304,$A16)=0,"—",SUMIFS(Bookings!$T$5:$T$304,Bookings!$B$5:$B$304,$A16))) -> — | C16: =IF(OR($A16="—",NOT(ISNUMBER($P$4))),"—",$P$4-SUMIFS(Bookings!$U$5:$U$304,Bookings!$B$5:$B$304,$A16)) -> — | D16: =IFERROR(IF(OR($A16="—",NOT(ISNUMBER($C16)),$C16<=0),"—",IF(ISNUMBER($B16),$B16,0)/$C16),"—") -> — | E16: =IF($A16="—","—",IF(SUMIFS(Bookings!$W$5:$W$304,Bookings!$B$5:$B$304,$A16,Bookings!$G$5:$G$304,">="&$P$2,Bookings!$G$5:$G$304,"<="&$P$3)=0,"—",SUMIFS(Bookings!$W$5:$W$304,Bookings!$B$5:$B$304,$A16,Bookings!$G$5:$G$304,">="&$P$2,Bookings!$G$5:$G$304,"<="&$P$3))) -> — | F16: =IF($A16="—","—",IF(SUMIFS(Bookings!$L$5:$L$304,Bookings!$B$5:$B$304,$A16,Bookings!$G$5:$G$304,">="&$P$2,Bookings!$G$5:$G$304,"<="&$P$3)=0,"—",SUMIFS(Bookings!$L$5:$L$304,Bookings!$B$5:$B$304,$A16,Bookings!$G$5:$G$304,">="&$P$2,Bookings!$G$5:$G$304,"<="&$P$3))) -> — | G16: =IF($A16="—","—",IF(SUMIFS(Bookings!$N$5:$N$304,Bookings!$B$5:$B$304,$A16,Bookings!$G$5:$G$304,">="&$P$2,Bookings!$G$5:$G$304,"<="&$P$3)+SUMIFS(Bookings!$O$5:$O$304,Bookings!$B$5:$B$304,$A16,Bookings!$G$5:$G$304,">="&$P$2,Bookings!$G$5:$G$304,"<="&$P$3)=0,"—",SUMIFS(Bookings!$N$5:$N$304,Bookings!$B$5:$B$304,$A16,Bookings!$G$5:$G$304,">="&$P$2,Bookings!$G$5:$G$304,"<="&$P$3)+SUMIFS(Bookings!$O$5:$O$304,Bookings!$B$5:$B$304,$A16,Bookings!$G$5:$G$304,">="&$P$2,Bookings!$G$5:$G$304,"<="&$P$3))) -> — | H16: =IF($A16="—","—",IF(SUMIFS(Bookings!$P$5:$P$304,Bookings!$B$5:$B$304,$A16,Bookings!$G$5:$G$304,">="&$P$2,Bookings!$G$5:$G$304,"<="&$P$3)=0,"—",SUMIFS(Bookings!$P$5:$P$304,Bookings!$B$5:$B$304,$A16,Bookings!$G$5:$G$304,">="&$P$2,Bookings!$G$5:$G$304,"<="&$P$3))) -> — | I16: =IF($A16="—","—",IFERROR(IF(INDEX(Setup!$J$25:$J$36,MATCH($A16,Setup!$A$25:$A$36,0))=0,"—",INDEX(Setup!$J$25:$J$36,MATCH($A16,Setup!$A$25:$A$36,0))),"—")) -> — | J16: =IF($A16="—","—",IF(SUMIFS(Costs!$F$5:$F$254,Costs!$C$5:$C$254,$A16,Costs!$B$5:$B$254,">="&$P$2,Costs!$B$5:$B$254,"<="&$P$3)=0,"—",SUMIFS(Costs!$F$5:$F$254,Costs!$C$5:$C$254,$A16,Costs!$B$5:$B$254,">="&$P$2,Costs!$B$5:$B$254,"<="&$P$3))) -> — | K16: =IF(OR($A16="—",COUNT($F16:$J16)=0),"—",ROUND(SUM($F16:$J16),2)) -> — | L16: =IF(OR($A16="—",COUNT($E16,$K16)=0),"—",ROUND(IF(ISNUMBER($E16),$E16,0)-IF(ISNUMBER($K16),$K16,0),2)) -> — | M16: =IF(OR(NOT(ISNUMBER($L16)),NOT(ISNUMBER($C16)),$C16<=0),"—",ROUND($L16/$C16,2)) -> —
A17: =IF(Setup!$A31="","—",Setup!$A31) -> — | B17: =IF($A17="—","—",IF(SUMIFS(Bookings!$T$5:$T$304,Bookings!$B$5:$B$304,$A17)=0,"—",SUMIFS(Bookings!$T$5:$T$304,Bookings!$B$5:$B$304,$A17))) -> — | C17: =IF(OR($A17="—",NOT(ISNUMBER($P$4))),"—",$P$4-SUMIFS(Bookings!$U$5:$U$304,Bookings!$B$5:$B$304,$A17)) -> — | D17: =IFERROR(IF(OR($A17="—",NOT(ISNUMBER($C17)),$C17<=0),"—",IF(ISNUMBER($B17),$B17,0)/$C17),"—") -> — | E17: =IF($A17="—","—",IF(SUMIFS(Bookings!$W$5:$W$304,Bookings!$B$5:$B$304,$A17,Bookings!$G$5:$G$304,">="&$P$2,Bookings!$G$5:$G$304,"<="&$P$3)=0,"—",SUMIFS(Bookings!$W$5:$W$304,Bookings!$B$5:$B$304,$A17,Bookings!$G$5:$G$304,">="&$P$2,Bookings!$G$5:$G$304,"<="&$P$3))) -> — | F17: =IF($A17="—","—",IF(SUMIFS(Bookings!$L$5:$L$304,Bookings!$B$5:$B$304,$A17,Bookings!$G$5:$G$304,">="&$P$2,Bookings!$G$5:$G$304,"<="&$P$3)=0,"—",SUMIFS(Bookings!$L$5:$L$304,Bookings!$B$5:$B$304,$A17,Bookings!$G$5:$G$304,">="&$P$2,Bookings!$G$5:$G$304,"<="&$P$3))) -> — | G17: =IF($A17="—","—",IF(SUMIFS(Bookings!$N$5:$N$304,Bookings!$B$5:$B$304,$A17,Bookings!$G$5:$G$304,">="&$P$2,Bookings!$G$5:$G$304,"<="&$P$3)+SUMIFS(Bookings!$O$5:$O$304,Bookings!$B$5:$B$304,$A17,Bookings!$G$5:$G$304,">="&$P$2,Bookings!$G$5:$G$304,"<="&$P$3)=0,"—",SUMIFS(Bookings!$N$5:$N$304,Bookings!$B$5:$B$304,$A17,Bookings!$G$5:$G$304,">="&$P$2,Bookings!$G$5:$G$304,"<="&$P$3)+SUMIFS(Bookings!$O$5:$O$304,Bookings!$B$5:$B$304,$A17,Bookings!$G$5:$G$304,">="&$P$2,Bookings!$G$5:$G$304,"<="&$P$3))) -> — | H17: =IF($A17="—","—",IF(SUMIFS(Bookings!$P$5:$P$304,Bookings!$B$5:$B$304,$A17,Bookings!$G$5:$G$304,">="&$P$2,Bookings!$G$5:$G$304,"<="&$P$3)=0,"—",SUMIFS(Bookings!$P$5:$P$304,Bookings!$B$5:$B$304,$A17,Bookings!$G$5:$G$304,">="&$P$2,Bookings!$G$5:$G$304,"<="&$P$3))) -> — | I17: =IF($A17="—","—",IFERROR(IF(INDEX(Setup!$J$25:$J$36,MATCH($A17,Setup!$A$25:$A$36,0))=0,"—",INDEX(Setup!$J$25:$J$36,MATCH($A17,Setup!$A$25:$A$36,0))),"—")) -> — | J17: =IF($A17="—","—",IF(SUMIFS(Costs!$F$5:$F$254,Costs!$C$5:$C$254,$A17,Costs!$B$5:$B$254,">="&$P$2,Costs!$B$5:$B$254,"<="&$P$3)=0,"—",SUMIFS(Costs!$F$5:$F$254,Costs!$C$5:$C$254,$A17,Costs!$B$5:$B$254,">="&$P$2,Costs!$B$5:$B$254,"<="&$P$3))) -> — | K17: =IF(OR($A17="—",COUNT($F17:$J17)=0),"—",ROUND(SUM($F17:$J17),2)) -> — | L17: =IF(OR($A17="—",COUNT($E17,$K17)=0),"—",ROUND(IF(ISNUMBER($E17),$E17,0)-IF(ISNUMBER($K17),$K17,0),2)) -> — | M17: =IF(OR(NOT(ISNUMBER($L17)),NOT(ISNUMBER($C17)),$C17<=0),"—",ROUND($L17/$C17,2)) -> —
A18: =IF(Setup!$A32="","—",Setup!$A32) -> — | B18: =IF($A18="—","—",IF(SUMIFS(Bookings!$T$5:$T$304,Bookings!$B$5:$B$304,$A18)=0,"—",SUMIFS(Bookings!$T$5:$T$304,Bookings!$B$5:$B$304,$A18))) -> — | C18: =IF(OR($A18="—",NOT(ISNUMBER($P$4))),"—",$P$4-SUMIFS(Bookings!$U$5:$U$304,Bookings!$B$5:$B$304,$A18)) -> — | D18: =IFERROR(IF(OR($A18="—",NOT(ISNUMBER($C18)),$C18<=0),"—",IF(ISNUMBER($B18),$B18,0)/$C18),"—") -> — | E18: =IF($A18="—","—",IF(SUMIFS(Bookings!$W$5:$W$304,Bookings!$B$5:$B$304,$A18,Bookings!$G$5:$G$304,">="&$P$2,Bookings!$G$5:$G$304,"<="&$P$3)=0,"—",SUMIFS(Bookings!$W$5:$W$304,Bookings!$B$5:$B$304,$A18,Bookings!$G$5:$G$304,">="&$P$2,Bookings!$G$5:$G$304,"<="&$P$3))) -> — | F18: =IF($A18="—","—",IF(SUMIFS(Bookings!$L$5:$L$304,Bookings!$B$5:$B$304,$A18,Bookings!$G$5:$G$304,">="&$P$2,Bookings!$G$5:$G$304,"<="&$P$3)=0,"—",SUMIFS(Bookings!$L$5:$L$304,Bookings!$B$5:$B$304,$A18,Bookings!$G$5:$G$304,">="&$P$2,Bookings!$G$5:$G$304,"<="&$P$3))) -> — | G18: =IF($A18="—","—",IF(SUMIFS(Bookings!$N$5:$N$304,Bookings!$B$5:$B$304,$A18,Bookings!$G$5:$G$304,">="&$P$2,Bookings!$G$5:$G$304,"<="&$P$3)+SUMIFS(Bookings!$O$5:$O$304,Bookings!$B$5:$B$304,$A18,Bookings!$G$5:$G$304,">="&$P$2,Bookings!$G$5:$G$304,"<="&$P$3)=0,"—",SUMIFS(Bookings!$N$5:$N$304,Bookings!$B$5:$B$304,$A18,Bookings!$G$5:$G$304,">="&$P$2,Bookings!$G$5:$G$304,"<="&$P$3)+SUMIFS(Bookings!$O$5:$O$304,Bookings!$B$5:$B$304,$A18,Bookings!$G$5:$G$304,">="&$P$2,Bookings!$G$5:$G$304,"<="&$P$3))) -> — | H18: =IF($A18="—","—",IF(SUMIFS(Bookings!$P$5:$P$304,Bookings!$B$5:$B$304,$A18,Bookings!$G$5:$G$304,">="&$P$2,Bookings!$G$5:$G$304,"<="&$P$3)=0,"—",SUMIFS(Bookings!$P$5:$P$304,Bookings!$B$5:$B$304,$A18,Bookings!$G$5:$G$304,">="&$P$2,Bookings!$G$5:$G$304,"<="&$P$3))) -> — | I18: =IF($A18="—","—",IFERROR(IF(INDEX(Setup!$J$25:$J$36,MATCH($A18,Setup!$A$25:$A$36,0))=0,"—",INDEX(Setup!$J$25:$J$36,MATCH($A18,Setup!$A$25:$A$36,0))),"—")) -> — | J18: =IF($A18="—","—",IF(SUMIFS(Costs!$F$5:$F$254,Costs!$C$5:$C$254,$A18,Costs!$B$5:$B$254,">="&$P$2,Costs!$B$5:$B$254,"<="&$P$3)=0,"—",SUMIFS(Costs!$F$5:$F$254,Costs!$C$5:$C$254,$A18,Costs!$B$5:$B$254,">="&$P$2,Costs!$B$5:$B$254,"<="&$P$3))) -> — | K18: =IF(OR($A18="—",COUNT($F18:$J18)=0),"—",ROUND(SUM($F18:$J18),2)) -> — | L18: =IF(OR($A18="—",COUNT($E18,$K18)=0),"—",ROUND(IF(ISNUMBER($E18),$E18,0)-IF(ISNUMBER($K18),$K18,0),2)) -> — | M18: =IF(OR(NOT(ISNUMBER($L18)),NOT(ISNUMBER($C18)),$C18<=0),"—",ROUND($L18/$C18,2)) -> —
A19: =IF(Setup!$A33="","—",Setup!$A33) -> — | B19: =IF($A19="—","—",IF(SUMIFS(Bookings!$T$5:$T$304,Bookings!$B$5:$B$304,$A19)=0,"—",SUMIFS(Bookings!$T$5:$T$304,Bookings!$B$5:$B$304,$A19))) -> — | C19: =IF(OR($A19="—",NOT(ISNUMBER($P$4))),"—",$P$4-SUMIFS(Bookings!$U$5:$U$304,Bookings!$B$5:$B$304,$A19)) -> — | D19: =IFERROR(IF(OR($A19="—",NOT(ISNUMBER($C19)),$C19<=0),"—",IF(ISNUMBER($B19),$B19,0)/$C19),"—") -> — | E19: =IF($A19="—","—",IF(SUMIFS(Bookings!$W$5:$W$304,Bookings!$B$5:$B$304,$A19,Bookings!$G$5:$G$304,">="&$P$2,Bookings!$G$5:$G$304,"<="&$P$3)=0,"—",SUMIFS(Bookings!$W$5:$W$304,Bookings!$B$5:$B$304,$A19,Bookings!$G$5:$G$304,">="&$P$2,Bookings!$G$5:$G$304,"<="&$P$3))) -> — | F19: =IF($A19="—","—",IF(SUMIFS(Bookings!$L$5:$L$304,Bookings!$B$5:$B$304,$A19,Bookings!$G$5:$G$304,">="&$P$2,Bookings!$G$5:$G$304,"<="&$P$3)=0,"—",SUMIFS(Bookings!$L$5:$L$304,Bookings!$B$5:$B$304,$A19,Bookings!$G$5:$G$304,">="&$P$2,Bookings!$G$5:$G$304,"<="&$P$3))) -> — | G19: =IF($A19="—","—",IF(SUMIFS(Bookings!$N$5:$N$304,Bookings!$B$5:$B$304,$A19,Bookings!$G$5:$G$304,">="&$P$2,Bookings!$G$5:$G$304,"<="&$P$3)+SUMIFS(Bookings!$O$5:$O$304,Bookings!$B$5:$B$304,$A19,Bookings!$G$5:$G$304,">="&$P$2,Bookings!$G$5:$G$304,"<="&$P$3)=0,"—",SUMIFS(Bookings!$N$5:$N$304,Bookings!$B$5:$B$304,$A19,Bookings!$G$5:$G$304,">="&$P$2,Bookings!$G$5:$G$304,"<="&$P$3)+SUMIFS(Bookings!$O$5:$O$304,Bookings!$B$5:$B$304,$A19,Bookings!$G$5:$G$304,">="&$P$2,Bookings!$G$5:$G$304,"<="&$P$3))) -> — | H19: =IF($A19="—","—",IF(SUMIFS(Bookings!$P$5:$P$304,Bookings!$B$5:$B$304,$A19,Bookings!$G$5:$G$304,">="&$P$2,Bookings!$G$5:$G$304,"<="&$P$3)=0,"—",SUMIFS(Bookings!$P$5:$P$304,Bookings!$B$5:$B$304,$A19,Bookings!$G$5:$G$304,">="&$P$2,Bookings!$G$5:$G$304,"<="&$P$3))) -> — | I19: =IF($A19="—","—",IFERROR(IF(INDEX(Setup!$J$25:$J$36,MATCH($A19,Setup!$A$25:$A$36,0))=0,"—",INDEX(Setup!$J$25:$J$36,MATCH($A19,Setup!$A$25:$A$36,0))),"—")) -> — | J19: =IF($A19="—","—",IF(SUMIFS(Costs!$F$5:$F$254,Costs!$C$5:$C$254,$A19,Costs!$B$5:$B$254,">="&$P$2,Costs!$B$5:$B$254,"<="&$P$3)=0,"—",SUMIFS(Costs!$F$5:$F$254,Costs!$C$5:$C$254,$A19,Costs!$B$5:$B$254,">="&$P$2,Costs!$B$5:$B$254,"<="&$P$3))) -> — | K19: =IF(OR($A19="—",COUNT($F19:$J19)=0),"—",ROUND(SUM($F19:$J19),2)) -> — | L19: =IF(OR($A19="—",COUNT($E19,$K19)=0),"—",ROUND(IF(ISNUMBER($E19),$E19,0)-IF(ISNUMBER($K19),$K19,0),2)) -> — | M19: =IF(OR(NOT(ISNUMBER($L19)),NOT(ISNUMBER($C19)),$C19<=0),"—",ROUND($L19/$C19,2)) -> —
A20: =IF(Setup!$A34="","—",Setup!$A34) -> — | B20: =IF($A20="—","—",IF(SUMIFS(Bookings!$T$5:$T$304,Bookings!$B$5:$B$304,$A20)=0,"—",SUMIFS(Bookings!$T$5:$T$304,Bookings!$B$5:$B$304,$A20))) -> — | C20: =IF(OR($A20="—",NOT(ISNUMBER($P$4))),"—",$P$4-SUMIFS(Bookings!$U$5:$U$304,Bookings!$B$5:$B$304,$A20)) -> — | D20: =IFERROR(IF(OR($A20="—",NOT(ISNUMBER($C20)),$C20<=0),"—",IF(ISNUMBER($B20),$B20,0)/$C20),"—") -> — | E20: =IF($A20="—","—",IF(SUMIFS(Bookings!$W$5:$W$304,Bookings!$B$5:$B$304,$A20,Bookings!$G$5:$G$304,">="&$P$2,Bookings!$G$5:$G$304,"<="&$P$3)=0,"—",SUMIFS(Bookings!$W$5:$W$304,Bookings!$B$5:$B$304,$A20,Bookings!$G$5:$G$304,">="&$P$2,Bookings!$G$5:$G$304,"<="&$P$3))) -> — | F20: =IF($A20="—","—",IF(SUMIFS(Bookings!$L$5:$L$304,Bookings!$B$5:$B$304,$A20,Bookings!$G$5:$G$304,">="&$P$2,Bookings!$G$5:$G$304,"<="&$P$3)=0,"—",SUMIFS(Bookings!$L$5:$L$304,Bookings!$B$5:$B$304,$A20,Bookings!$G$5:$G$304,">="&$P$2,Bookings!$G$5:$G$304,"<="&$P$3))) -> — | G20: =IF($A20="—","—",IF(SUMIFS(Bookings!$N$5:$N$304,Bookings!$B$5:$B$304,$A20,Bookings!$G$5:$G$304,">="&$P$2,Bookings!$G$5:$G$304,"<="&$P$3)+SUMIFS(Bookings!$O$5:$O$304,Bookings!$B$5:$B$304,$A20,Bookings!$G$5:$G$304,">="&$P$2,Bookings!$G$5:$G$304,"<="&$P$3)=0,"—",SUMIFS(Bookings!$N$5:$N$304,Bookings!$B$5:$B$304,$A20,Bookings!$G$5:$G$304,">="&$P$2,Bookings!$G$5:$G$304,"<="&$P$3)+SUMIFS(Bookings!$O$5:$O$304,Bookings!$B$5:$B$304,$A20,Bookings!$G$5:$G$304,">="&$P$2,Bookings!$G$5:$G$304,"<="&$P$3))) -> — | H20: =IF($A20="—","—",IF(SUMIFS(Bookings!$P$5:$P$304,Bookings!$B$5:$B$304,$A20,Bookings!$G$5:$G$304,">="&$P$2,Bookings!$G$5:$G$304,"<="&$P$3)=0,"—",SUMIFS(Bookings!$P$5:$P$304,Bookings!$B$5:$B$304,$A20,Bookings!$G$5:$G$304,">="&$P$2,Bookings!$G$5:$G$304,"<="&$P$3))) -> — | I20: =IF($A20="—","—",IFERROR(IF(INDEX(Setup!$J$25:$J$36,MATCH($A20,Setup!$A$25:$A$36,0))=0,"—",INDEX(Setup!$J$25:$J$36,MATCH($A20,Setup!$A$25:$A$36,0))),"—")) -> — | J20: =IF($A20="—","—",IF(SUMIFS(Costs!$F$5:$F$254,Costs!$C$5:$C$254,$A20,Costs!$B$5:$B$254,">="&$P$2,Costs!$B$5:$B$254,"<="&$P$3)=0,"—",SUMIFS(Costs!$F$5:$F$254,Costs!$C$5:$C$254,$A20,Costs!$B$5:$B$254,">="&$P$2,Costs!$B$5:$B$254,"<="&$P$3))) -> — | K20: =IF(OR($A20="—",COUNT($F20:$J20)=0),"—",ROUND(SUM($F20:$J20),2)) -> — | L20: =IF(OR($A20="—",COUNT($E20,$K20)=0),"—",ROUND(IF(ISNUMBER($E20),$E20,0)-IF(ISNUMBER($K20),$K20,0),2)) -> — | M20: =IF(OR(NOT(ISNUMBER($L20)),NOT(ISNUMBER($C20)),$C20<=0),"—",ROUND($L20/$C20,2)) -> —
A21: =IF(Setup!$A35="","—",Setup!$A35) -> — | B21: =IF($A21="—","—",IF(SUMIFS(Bookings!$T$5:$T$304,Bookings!$B$5:$B$304,$A21)=0,"—",SUMIFS(Bookings!$T$5:$T$304,Bookings!$B$5:$B$304,$A21))) -> — | C21: =IF(OR($A21="—",NOT(ISNUMBER($P$4))),"—",$P$4-SUMIFS(Bookings!$U$5:$U$304,Bookings!$B$5:$B$304,$A21)) -> — | D21: =IFERROR(IF(OR($A21="—",NOT(ISNUMBER($C21)),$C21<=0),"—",IF(ISNUMBER($B21),$B21,0)/$C21),"—") -> — | E21: =IF($A21="—","—",IF(SUMIFS(Bookings!$W$5:$W$304,Bookings!$B$5:$B$304,$A21,Bookings!$G$5:$G$304,">="&$P$2,Bookings!$G$5:$G$304,"<="&$P$3)=0,"—",SUMIFS(Bookings!$W$5:$W$304,Bookings!$B$5:$B$304,$A21,Bookings!$G$5:$G$304,">="&$P$2,Bookings!$G$5:$G$304,"<="&$P$3))) -> — | F21: =IF($A21="—","—",IF(SUMIFS(Bookings!$L$5:$L$304,Bookings!$B$5:$B$304,$A21,Bookings!$G$5:$G$304,">="&$P$2,Bookings!$G$5:$G$304,"<="&$P$3)=0,"—",SUMIFS(Bookings!$L$5:$L$304,Bookings!$B$5:$B$304,$A21,Bookings!$G$5:$G$304,">="&$P$2,Bookings!$G$5:$G$304,"<="&$P$3))) -> — | G21: =IF($A21="—","—",IF(SUMIFS(Bookings!$N$5:$N$304,Bookings!$B$5:$B$304,$A21,Bookings!$G$5:$G$304,">="&$P$2,Bookings!$G$5:$G$304,"<="&$P$3)+SUMIFS(Bookings!$O$5:$O$304,Bookings!$B$5:$B$304,$A21,Bookings!$G$5:$G$304,">="&$P$2,Bookings!$G$5:$G$304,"<="&$P$3)=0,"—",SUMIFS(Bookings!$N$5:$N$304,Bookings!$B$5:$B$304,$A21,Bookings!$G$5:$G$304,">="&$P$2,Bookings!$G$5:$G$304,"<="&$P$3)+SUMIFS(Bookings!$O$5:$O$304,Bookings!$B$5:$B$304,$A21,Bookings!$G$5:$G$304,">="&$P$2,Bookings!$G$5:$G$304,"<="&$P$3))) -> — | H21: =IF($A21="—","—",IF(SUMIFS(Bookings!$P$5:$P$304,Bookings!$B$5:$B$304,$A21,Bookings!$G$5:$G$304,">="&$P$2,Bookings!$G$5:$G$304,"<="&$P$3)=0,"—",SUMIFS(Bookings!$P$5:$P$304,Bookings!$B$5:$B$304,$A21,Bookings!$G$5:$G$304,">="&$P$2,Bookings!$G$5:$G$304,"<="&$P$3))) -> — | I21: =IF($A21="—","—",IFERROR(IF(INDEX(Setup!$J$25:$J$36,MATCH($A21,Setup!$A$25:$A$36,0))=0,"—",INDEX(Setup!$J$25:$J$36,MATCH($A21,Setup!$A$25:$A$36,0))),"—")) -> — | J21: =IF($A21="—","—",IF(SUMIFS(Costs!$F$5:$F$254,Costs!$C$5:$C$254,$A21,Costs!$B$5:$B$254,">="&$P$2,Costs!$B$5:$B$254,"<="&$P$3)=0,"—",SUMIFS(Costs!$F$5:$F$254,Costs!$C$5:$C$254,$A21,Costs!$B$5:$B$254,">="&$P$2,Costs!$B$5:$B$254,"<="&$P$3))) -> — | K21: =IF(OR($A21="—",COUNT($F21:$J21)=0),"—",ROUND(SUM($F21:$J21),2)) -> — | L21: =IF(OR($A21="—",COUNT($E21,$K21)=0),"—",ROUND(IF(ISNUMBER($E21),$E21,0)-IF(ISNUMBER($K21),$K21,0),2)) -> — | M21: =IF(OR(NOT(ISNUMBER($L21)),NOT(ISNUMBER($C21)),$C21<=0),"—",ROUND($L21/$C21,2)) -> —
A22: =IF(Setup!$A36="","—",Setup!$A36) -> — | B22: =IF($A22="—","—",IF(SUMIFS(Bookings!$T$5:$T$304,Bookings!$B$5:$B$304,$A22)=0,"—",SUMIFS(Bookings!$T$5:$T$304,Bookings!$B$5:$B$304,$A22))) -> — | C22: =IF(OR($A22="—",NOT(ISNUMBER($P$4))),"—",$P$4-SUMIFS(Bookings!$U$5:$U$304,Bookings!$B$5:$B$304,$A22)) -> — | D22: =IFERROR(IF(OR($A22="—",NOT(ISNUMBER($C22)),$C22<=0),"—",IF(ISNUMBER($B22),$B22,0)/$C22),"—") -> — | E22: =IF($A22="—","—",IF(SUMIFS(Bookings!$W$5:$W$304,Bookings!$B$5:$B$304,$A22,Bookings!$G$5:$G$304,">="&$P$2,Bookings!$G$5:$G$304,"<="&$P$3)=0,"—",SUMIFS(Bookings!$W$5:$W$304,Bookings!$B$5:$B$304,$A22,Bookings!$G$5:$G$304,">="&$P$2,Bookings!$G$5:$G$304,"<="&$P$3))) -> — | F22: =IF($A22="—","—",IF(SUMIFS(Bookings!$L$5:$L$304,Bookings!$B$5:$B$304,$A22,Bookings!$G$5:$G$304,">="&$P$2,Bookings!$G$5:$G$304,"<="&$P$3)=0,"—",SUMIFS(Bookings!$L$5:$L$304,Bookings!$B$5:$B$304,$A22,Bookings!$G$5:$G$304,">="&$P$2,Bookings!$G$5:$G$304,"<="&$P$3))) -> — | G22: =IF($A22="—","—",IF(SUMIFS(Bookings!$N$5:$N$304,Bookings!$B$5:$B$304,$A22,Bookings!$G$5:$G$304,">="&$P$2,Bookings!$G$5:$G$304,"<="&$P$3)+SUMIFS(Bookings!$O$5:$O$304,Bookings!$B$5:$B$304,$A22,Bookings!$G$5:$G$304,">="&$P$2,Bookings!$G$5:$G$304,"<="&$P$3)=0,"—",SUMIFS(Bookings!$N$5:$N$304,Bookings!$B$5:$B$304,$A22,Bookings!$G$5:$G$304,">="&$P$2,Bookings!$G$5:$G$304,"<="&$P$3)+SUMIFS(Bookings!$O$5:$O$304,Bookings!$B$5:$B$304,$A22,Bookings!$G$5:$G$304,">="&$P$2,Bookings!$G$5:$G$304,"<="&$P$3))) -> — | H22: =IF($A22="—","—",IF(SUMIFS(Bookings!$P$5:$P$304,Bookings!$B$5:$B$304,$A22,Bookings!$G$5:$G$304,">="&$P$2,Bookings!$G$5:$G$304,"<="&$P$3)=0,"—",SUMIFS(Bookings!$P$5:$P$304,Bookings!$B$5:$B$304,$A22,Bookings!$G$5:$G$304,">="&$P$2,Bookings!$G$5:$G$304,"<="&$P$3))) -> — | I22: =IF($A22="—","—",IFERROR(IF(INDEX(Setup!$J$25:$J$36,MATCH($A22,Setup!$A$25:$A$36,0))=0,"—",INDEX(Setup!$J$25:$J$36,MATCH($A22,Setup!$A$25:$A$36,0))),"—")) -> — | J22: =IF($A22="—","—",IF(SUMIFS(Costs!$F$5:$F$254,Costs!$C$5:$C$254,$A22,Costs!$B$5:$B$254,">="&$P$2,Costs!$B$5:$B$254,"<="&$P$3)=0,"—",SUMIFS(Costs!$F$5:$F$254,Costs!$C$5:$C$254,$A22,Costs!$B$5:$B$254,">="&$P$2,Costs!$B$5:$B$254,"<="&$P$3))) -> — | K22: =IF(OR($A22="—",COUNT($F22:$J22)=0),"—",ROUND(SUM($F22:$J22),2)) -> — | L22: =IF(OR($A22="—",COUNT($E22,$K22)=0),"—",ROUND(IF(ISNUMBER($E22),$E22,0)-IF(ISNUMBER($K22),$K22,0),2)) -> — | M22: =IF(OR(NOT(ISNUMBER($L22)),NOT(ISNUMBER($C22)),$C22<=0),"—",ROUND($L22/$C22,2)) -> —
A23: PORTFOLIO TOTAL | B23: =IF(COUNT(B$11:B$22)=0,"—",ROUND(SUM(B$11:B$22),2)) -> 36 | C23: =IF(COUNT(C$11:C$22)=0,"—",ROUND(SUM(C$11:C$22),2)) -> 90 | D23: =IF(OR(NOT(ISNUMBER($C23)),$C23<=0),"—",IF(ISNUMBER($B23),$B23,0)/$C23) -> 0.4 | E23: =IF(COUNT(E$11:E$22)=0,"—",ROUND(SUM(E$11:E$22),2)) -> 3890 | F23: =IF(COUNT(F$11:F$22)=0,"—",ROUND(SUM(F$11:F$22),2)) -> 261.6 | G23: =IF(COUNT(G$11:G$22)=0,"—",ROUND(SUM(G$11:G$22),2)) -> 525 | H23: =IF(COUNT(H$11:H$22)=0,"—",ROUND(SUM(H$11:H$22),2)) -> 99.8 | I23: =IF(COUNT(I$11:I$22)=0,"—",ROUND(SUM(I$11:I$22),2)) -> 184 | J23: =IF(COUNT(J$11:J$22)=0,"—",ROUND(SUM(J$11:J$22),2)) -> 270.4 | K23: =IF(COUNT(K$11:K$22)=0,"—",ROUND(SUM(K$11:K$22),2)) -> 1340.8 | L23: =IF(COUNT(L$11:L$22)=0,"—",ROUND(SUM(L$11:L$22),2)) -> 2549.2 | M23: =IF(OR(NOT(ISNUMBER($L23)),NOT(ISNUMBER($C23)),$C23<=0),"—",ROUND($L23/$C23,2)) -> 28.32
A25: =IF(COUNTIF(Bookings!$V$5:$V$304,"⚠*")+COUNTIF(Costs!$I$5:$I$254,"⚠*")>0,"Data check: "&(COUNTIF(Bookings!$V$5:$V$304,"⚠*")+COUNTIF(Costs!$I$5:$I$254,"⚠*"))&" row(s) are NOT counted anywhere — see the Check column in Bookings and Costs.",IF(COUNTA(Bookings!$B$5:$B$304)+COUNTA(Costs!$C$5:$C$254)=0,"Data check: no rows entered yet — start in the Setup tab, then the Bookings tab.","Data check: every row is linked to a property in Setup.")) -> Data check: every row is linked to a property in Setup.
A27: HOW THE MATH WORKS
A28: 1 · Money (booking value, fees, cleaning, consumables) is counted in the month a stay CHECKS OUT. Nights and occupancy are split across months by the actual dates, so a stay spanning two months shows nights in both but money in one.
A29: 2 · Gross booking value = the total the guest paid, including any cleaning fee you charge. What you pay your cleaner is a cost in Setup.
A30: 3 · Fixed monthly costs come from Setup and run in every month you look at — never enter them again in the Costs tab. If you only owned a property part of the year, clear that field before checking earlier months.
A31: 4 · Colour thresholds are our convention, not a benchmark: occupancy green from 60%, amber from 40%; the cost tile turns amber when tracked costs pass 70% of gross. Change them in the conditional formatting menu whenever you like.
A32: 5 · 'Net after tracked costs' is gross minus exactly what you typed into this workbook. It is not a tax, accounting or bookkeeping figure, and no tax of any kind is calculated here.
A33: Never type on this sheet except the two month pickers. Excel: Review ▸ Unprotect Sheet (no password) if you want to restyle it. Google Sheets does not carry that protection over — just don't type here.

Sheet Bookings
A1: Bookings — one row per stay
A2: Type the white cells only: property, platform, status, guest, the two dates, guests and the gross booking value. Grey columns calculate themselves. Manual entry — no login, no API, no calendar sync.
A4: # | B4: Property | C4: Platform | D4: Status | E4: Guest / reference | F4: Check-in | G4: Check-out | H4: Nights | I4: Guests | J4: Gross booking value | K4: Platform fee % override | L4: Platform fee | M4: Estimated payout after platform fee | N4: Cleaning | O4: Laundry | P4: Consumables | Q4: Net after direct costs | R4: Net per night | S4: Notes | T4: Nights in selected month — guest (changes with the Dashboard month picker) | U4: Nights in selected month — owner block (changes with the Dashboard month picker) | V4: Check | W4: Gross counted in this file
A5: 1 | B5: Riverside Loft | C5: Airbnb | D5: Completed | E5: EXAMPLE — A. Pereira | F5: =IFERROR(DATE(YEAR(TODAY()),MONTH(TODAY()),1),"") -> 46204 | G5: =IFERROR(DATE(YEAR(TODAY()),MONTH(TODAY()),5),"") -> 46208 | H5: =IF(OR(NOT(ISNUMBER($F5)),NOT(ISNUMBER($G5))),"—",IF($G5<=$F5,"⚠ check dates",$G5-$F5)) -> 4 | I5: 2 | J5: 480 | L5: =IF(OR($B5="",NOT(ISNUMBER($J5)),$D5="Cancelled",$D5="Owner block"),"—",ROUND($J5*IF(ISNUMBER($K5),IF($K5>1,$K5/100,$K5),IF(IFERROR(INDEX(Setup!$D$25:$D$36,MATCH($B5,Setup!$A$25:$A$36,0)),0)>1,IFERROR(INDEX(Setup!$D$25:$D$36,MATCH($B5,Setup!$A$25:$A$36,0)),0)/100,IFERROR(INDEX(Setup!$D$25:$D$36,MATCH($B5,Setup!$A$25:$A$36,0)),0))),2)) -> 14.4 | M5: =IF(NOT(ISNUMBER($L5)),"—",ROUND($J5-$L5,2)) -> 465.6 | N5: =IF(OR($B5="",$G5="",$D5="Cancelled"),"—",IFERROR(IF(INDEX(Setup!$E$25:$E$36,MATCH($B5,Setup!$A$25:$A$36,0))=0,"—",INDEX(Setup!$E$25:$E$36,MATCH($B5,Setup!$A$25:$A$36,0))),"—")) -> 45 | O5: =IF(OR($B5="",$G5="",$D5="Cancelled"),"—",IFERROR(IF(INDEX(Setup!$F$25:$F$36,MATCH($B5,Setup!$A$25:$A$36,0))=0,"—",INDEX(Setup!$F$25:$F$36,MATCH($B5,Setup!$A$25:$A$36,0))),"—")) -> 12 | P5: =IF(OR($B5="",$G5="",$D5="Cancelled",$D5="Owner block"),"—",IF(IFERROR(INDEX(Setup!$G$25:$G$36,MATCH($B5,Setup!$A$25:$A$36,0)),0)+IFERROR(INDEX(Setup!$H$25:$H$36,MATCH($B5,Setup!$A$25:$A$36,0)),0)*IF(ISNUMBER($H5),$H5,0)=0,"—",ROUND(IFERROR(INDEX(Setup!$G$25:$G$36,MATCH($B5,Setup!$A$25:$A$36,0)),0)+IFERROR(INDEX(Setup!$H$25:$H$36,MATCH($B5,Setup!$A$25:$A$36,0)),0)*IF(ISNUMBER($H5),$H5,0),2))) -> 12 | Q5: =IF(OR($B5="",$D5="Cancelled"),"—",IF(AND(NOT(ISNUMBER($M5)),COUNT($N5:$P5)=0),"—",ROUND(IF(ISNUMBER($M5),$M5,0)-SUM($N5:$P5),2))) -> 396.6 | R5: =IF(OR(NOT(ISNUMBER($Q5)),NOT(ISNUMBER($H5)),$H5<=0),"—",ROUND($Q5/$H5,2)) -> 99.15 | T5: =IF(OR(NOT(ISNUMBER($F5)),NOT(ISNUMBER($G5)),NOT(ISNUMBER(Dashboard!$P$2)),NOT(ISNUMBER(Dashboard!$P$3)),$D5="Cancelled",$D5="Owner block"),"—",IF(MAX(0,MIN($G5,Dashboard!$P$3+1)-MAX($F5,Dashboard!$P$2))=0,"—",MAX(0,MIN($G5,Dashboard!$P$3+1)-MAX($F5,Dashboard!$P$2)))) -> 4 | U5: =IF(OR(NOT(ISNUMBER($F5)),NOT(ISNUMBER($G5)),NOT(ISNUMBER(Dashboard!$P$2)),NOT(ISNUMBER(Dashboard!$P$3)),$D5<>"Owner block"),"—",IF(MAX(0,MIN($G5,Dashboard!$P$3+1)-MAX($F5,Dashboard!$P$2))=0,"—",MAX(0,MIN($G5,Dashboard!$P$3+1)-MAX($F5,Dashboard!$P$2)))) -> — | V5: =IF($B5="",IF(COUNTA($C5:$G5,$I5:$K5,$S5)=0,"","⚠ no property — not counted"),IF(COUNTIF(Setup!$A$25:$A$36,$B5)=0,"⚠ property not in Setup",IF(AND($F5<>"",NOT(ISNUMBER($F5))),"⚠ check-in is not a real date",IF(AND($G5<>"",NOT(ISNUMBER($G5))),"⚠ check-out is not a real date",IF(AND($J5<>"",NOT(ISNUMBER($J5))),"⚠ booking value is not a number","OK"))))) -> OK | W5: =IF(OR($B5="",NOT(ISNUMBER($J5)),$D5="Cancelled",$D5="Owner block"),"—",$J5) -> 480
A6: 2 | B6: Riverside Loft | C6: Airbnb | D6: Completed | E6: EXAMPLE — J. Meyer | F6: =IFERROR(DATE(YEAR(TODAY()),MONTH(TODAY()),7),"") -> 46210 | G6: =IFERROR(DATE(YEAR(TODAY()),MONTH(TODAY()),11),"") -> 46214 | H6: =IF(OR(NOT(ISNUMBER($F6)),NOT(ISNUMBER($G6))),"—",IF($G6<=$F6,"⚠ check dates",$G6-$F6)) -> 4 | I6: 2 | J6: 505 | L6: =IF(OR($B6="",NOT(ISNUMBER($J6)),$D6="Cancelled",$D6="Owner block"),"—",ROUND($J6*IF(ISNUMBER($K6),IF($K6>1,$K6/100,$K6),IF(IFERROR(INDEX(Setup!$D$25:$D$36,MATCH($B6,Setup!$A$25:$A$36,0)),0)>1,IFERROR(INDEX(Setup!$D$25:$D$36,MATCH($B6,Setup!$A$25:$A$36,0)),0)/100,IFERROR(INDEX(Setup!$D$25:$D$36,MATCH($B6,Setup!$A$25:$A$36,0)),0))),2)) -> 15.15 | M6: =IF(NOT(ISNUMBER($L6)),"—",ROUND($J6-$L6,2)) -> 489.85 | N6: =IF(OR($B6="",$G6="",$D6="Cancelled"),"—",IFERROR(IF(INDEX(Setup!$E$25:$E$36,MATCH($B6,Setup!$A$25:$A$36,0))=0,"—",INDEX(Setup!$E$25:$E$36,MATCH($B6,Setup!$A$25:$A$36,0))),"—")) -> 45 | O6: =IF(OR($B6="",$G6="",$D6="Cancelled"),"—",IFERROR(IF(INDEX(Setup!$F$25:$F$36,MATCH($B6,Setup!$A$25:$A$36,0))=0,"—",INDEX(Setup!$F$25:$F$36,MATCH($B6,Setup!$A$25:$A$36,0))),"—")) -> 12 | P6: =IF(OR($B6="",$G6="",$D6="Cancelled",$D6="Owner block"),"—",IF(IFERROR(INDEX(Setup!$G$25:$G$36,MATCH($B6,Setup!$A$25:$A$36,0)),0)+IFERROR(INDEX(Setup!$H$25:$H$36,MATCH($B6,Setup!$A$25:$A$36,0)),0)*IF(ISNUMBER($H6),$H6,0)=0,"—",ROUND(IFERROR(INDEX(Setup!$G$25:$G$36,MATCH($B6,Setup!$A$25:$A$36,0)),0)+IFERROR(INDEX(Setup!$H$25:$H$36,MATCH($B6,Setup!$A$25:$A$36,0)),0)*IF(ISNUMBER($H6),$H6,0),2))) -> 12 | Q6: =IF(OR($B6="",$D6="Cancelled"),"—",IF(AND(NOT(ISNUMBER($M6)),COUNT($N6:$P6)=0),"—",ROUND(IF(ISNUMBER($M6),$M6,0)-SUM($N6:$P6),2))) -> 420.85 | R6: =IF(OR(NOT(ISNUMBER($Q6)),NOT(ISNUMBER($H6)),$H6<=0),"—",ROUND($Q6/$H6,2)) -> 105.21 | T6: =IF(OR(NOT(ISNUMBER($F6)),NOT(ISNUMBER($G6)),NOT(ISNUMBER(Dashboard!$P$2)),NOT(ISNUMBER(Dashboard!$P$3)),$D6="Cancelled",$D6="Owner block"),"—",IF(MAX(0,MIN($G6,Dashboard!$P$3+1)-MAX($F6,Dashboard!$P$2))=0,"—",MAX(0,MIN($G6,Dashboard!$P$3+1)-MAX($F6,Dashboard!$P$2)))) -> 4 | U6: =IF(OR(NOT(ISNUMBER($F6)),NOT(ISNUMBER($G6)),NOT(ISNUMBER(Dashboard!$P$2)),NOT(ISNUMBER(Dashboard!$P$3)),$D6<>"Owner block"),"—",IF(MAX(0,MIN($G6,Dashboard!$P$3+1)-MAX($F6,Dashboard!$P$2))=0,"—",MAX(0,MIN($G6,Dashboard!$P$3+1)-MAX($F6,Dashboard!$P$2)))) -> — | V6: =IF($B6="",IF(COUNTA($C6:$G6,$I6:$K6,$S6)=0,"","⚠ no property — not counted"),IF(COUNTIF(Setup!$A$25:$A$36,$B6)=0,"⚠ property not in Setup",IF(AND($F6<>"",NOT(ISNUMBER($F6))),"⚠ check-in is not a real date",IF(AND($G6<>"",NOT(ISNUMBER($G6))),"⚠ check-out is not a real date",IF(AND($J6<>"",NOT(ISNUMBER($J6))),"⚠ booking value is not a number","OK"))))) -> OK | W6: =IF(OR($B6="",NOT(ISNUMBER($J6)),$D6="Cancelled",$D6="Owner block"),"—",$J6) -> 505
A7: 3 | B7: Riverside Loft | C7: Vrbo | D7: Completed | E7: EXAMPLE — L. Rossi | F7: =IFERROR(DATE(YEAR(TODAY()),MONTH(TODAY()),12),"") -> 46215 | G7: =IFERROR(DATE(YEAR(TODAY()),MONTH(TODAY()),16),"") -> 46219 | H7: =IF(OR(NOT(ISNUMBER($F7)),NOT(ISNUMBER($G7))),"—",IF($G7<=$F7,"⚠ check dates",$G7-$F7)) -> 4 | I7: 3 | J7: 430 | K7: 0.05 | L7: =IF(OR($B7="",NOT(ISNUMBER($J7)),$D7="Cancelled",$D7="Owner block"),"—",ROUND($J7*IF(ISNUMBER($K7),IF($K7>1,$K7/100,$K7),IF(IFERROR(INDEX(Setup!$D$25:$D$36,MATCH($B7,Setup!$A$25:$A$36,0)),0)>1,IFERROR(INDEX(Setup!$D$25:$D$36,MATCH($B7,Setup!$A$25:$A$36,0)),0)/100,IFERROR(INDEX(Setup!$D$25:$D$36,MATCH($B7,Setup!$A$25:$A$36,0)),0))),2)) -> 21.5 | M7: =IF(NOT(ISNUMBER($L7)),"—",ROUND($J7-$L7,2)) -> 408.5 | N7: =IF(OR($B7="",$G7="",$D7="Cancelled"),"—",IFERROR(IF(INDEX(Setup!$E$25:$E$36,MATCH($B7,Setup!$A$25:$A$36,0))=0,"—",INDEX(Setup!$E$25:$E$36,MATCH($B7,Setup!$A$25:$A$36,0))),"—")) -> 45 | O7: =IF(OR($B7="",$G7="",$D7="Cancelled"),"—",IFERROR(IF(INDEX(Setup!$F$25:$F$36,MATCH($B7,Setup!$A$25:$A$36,0))=0,"—",INDEX(Setup!$F$25:$F$36,MATCH($B7,Setup!$A$25:$A$36,0))),"—")) -> 12 | P7: =IF(OR($B7="",$G7="",$D7="Cancelled",$D7="Owner block"),"—",IF(IFERROR(INDEX(Setup!$G$25:$G$36,MATCH($B7,Setup!$A$25:$A$36,0)),0)+IFERROR(INDEX(Setup!$H$25:$H$36,MATCH($B7,Setup!$A$25:$A$36,0)),0)*IF(ISNUMBER($H7),$H7,0)=0,"—",ROUND(IFERROR(INDEX(Setup!$G$25:$G$36,MATCH($B7,Setup!$A$25:$A$36,0)),0)+IFERROR(INDEX(Setup!$H$25:$H$36,MATCH($B7,Setup!$A$25:$A$36,0)),0)*IF(ISNUMBER($H7),$H7,0),2))) -> 12 | Q7: =IF(OR($B7="",$D7="Cancelled"),"—",IF(AND(NOT(ISNUMBER($M7)),COUNT($N7:$P7)=0),"—",ROUND(IF(ISNUMBER($M7),$M7,0)-SUM($N7:$P7),2))) -> 339.5 | R7: =IF(OR(NOT(ISNUMBER($Q7)),NOT(ISNUMBER($H7)),$H7<=0),"—",ROUND($Q7/$H7,2)) -> 84.88 | T7: =IF(OR(NOT(ISNUMBER($F7)),NOT(ISNUMBER($G7)),NOT(ISNUMBER(Dashboard!$P$2)),NOT(ISNUMBER(Dashboard!$P$3)),$D7="Cancelled",$D7="Owner block"),"—",IF(MAX(0,MIN($G7,Dashboard!$P$3+1)-MAX($F7,Dashboard!$P$2))=0,"—",MAX(0,MIN($G7,Dashboard!$P$3+1)-MAX($F7,Dashboard!$P$2)))) -> 4 | U7: =IF(OR(NOT(ISNUMBER($F7)),NOT(ISNUMBER($G7)),NOT(ISNUMBER(Dashboard!$P$2)),NOT(ISNUMBER(Dashboard!$P$3)),$D7<>"Owner block"),"—",IF(MAX(0,MIN($G7,Dashboard!$P$3+1)-MAX($F7,Dashboard!$P$2))=0,"—",MAX(0,MIN($G7,Dashboard!$P$3+1)-MAX($F7,Dashboard!$P$2)))) -> — | V7: =IF($B7="",IF(COUNTA($C7:$G7,$I7:$K7,$S7)=0,"","⚠ no property — not counted"),IF(COUNTIF(Setup!$A$25:$A$36,$B7)=0,"⚠ property not in Setup",IF(AND($F7<>"",NOT(ISNUMBER($F7))),"⚠ check-in is not a real date",IF(AND($G7<>"",NOT(ISNUMBER($G7))),"⚠ check-out is not a real date",IF(AND($J7<>"",NOT(ISNUMBER($J7))),"⚠ booking value is not a number","OK"))))) -> OK | W7: =IF(OR($B7="",NOT(ISNUMBER($J7)),$D7="Cancelled",$D7="Owner block"),"—",$J7) -> 430
A8: 4 | B8: Riverside Loft | C8: Airbnb | D8: Confirmed | E8: EXAMPLE — S. Novak | F8: =IFERROR(TODAY()+1,"") -> 46233 | G8: =IFERROR(TODAY()+3,"") -> 46235 | H8: =IF(OR(NOT(ISNUMBER($F8)),NOT(ISNUMBER($G8))),"—",IF($G8<=$F8,"⚠ check dates",$G8-$F8)) -> 2 | I8: 2 | J8: 560 | L8: =IF(OR($B8="",NOT(ISNUMBER($J8)),$D8="Cancelled",$D8="Owner block"),"—",ROUND($J8*IF(ISNUMBER($K8),IF($K8>1,$K8/100,$K8),IF(IFERROR(INDEX(Setup!$D$25:$D$36,MATCH($B8,Setup!$A$25:$A$36,0)),0)>1,IFERROR(INDEX(Setup!$D$25:$D$36,MATCH($B8,Setup!$A$25:$A$36,0)),0)/100,IFERROR(INDEX(Setup!$D$25:$D$36,MATCH($B8,Setup!$A$25:$A$36,0)),0))),2)) -> 16.8 | M8: =IF(NOT(ISNUMBER($L8)),"—",ROUND($J8-$L8,2)) -> 543.2 | N8: =IF(OR($B8="",$G8="",$D8="Cancelled"),"—",IFERROR(IF(INDEX(Setup!$E$25:$E$36,MATCH($B8,Setup!$A$25:$A$36,0))=0,"—",INDEX(Setup!$E$25:$E$36,MATCH($B8,Setup!$A$25:$A$36,0))),"—")) -> 45 | O8: =IF(OR($B8="",$G8="",$D8="Cancelled"),"—",IFERROR(IF(INDEX(Setup!$F$25:$F$36,MATCH($B8,Setup!$A$25:$A$36,0))=0,"—",INDEX(Setup!$F$25:$F$36,MATCH($B8,Setup!$A$25:$A$36,0))),"—")) -> 12 | P8: =IF(OR($B8="",$G8="",$D8="Cancelled",$D8="Owner block"),"—",IF(IFERROR(INDEX(Setup!$G$25:$G$36,MATCH($B8,Setup!$A$25:$A$36,0)),0)+IFERROR(INDEX(Setup!$H$25:$H$36,MATCH($B8,Setup!$A$25:$A$36,0)),0)*IF(ISNUMBER($H8),$H8,0)=0,"—",ROUND(IFERROR(INDEX(Setup!$G$25:$G$36,MATCH($B8,Setup!$A$25:$A$36,0)),0)+IFERROR(INDEX(Setup!$H$25:$H$36,MATCH($B8,Setup!$A$25:$A$36,0)),0)*IF(ISNUMBER($H8),$H8,0),2))) -> 9 | Q8: =IF(OR($B8="",$D8="Cancelled"),"—",IF(AND(NOT(ISNUMBER($M8)),COUNT($N8:$P8)=0),"—",ROUND(IF(ISNUMBER($M8),$M8,0)-SUM($N8:$P8),2))) -> 477.2 | R8: =IF(OR(NOT(ISNUMBER($Q8)),NOT(ISNUMBER($H8)),$H8<=0),"—",ROUND($Q8/$H8,2)) -> 238.6 | S8: Still ahead: the Cleaning tab counts the days down to this turnover. | T8: =IF(OR(NOT(ISNUMBER($F8)),NOT(ISNUMBER($G8)),NOT(ISNUMBER(Dashboard!$P$2)),NOT(ISNUMBER(Dashboard!$P$3)),$D8="Cancelled",$D8="Owner block"),"—",IF(MAX(0,MIN($G8,Dashboard!$P$3+1)-MAX($F8,Dashboard!$P$2))=0,"—",MAX(0,MIN($G8,Dashboard!$P$3+1)-MAX($F8,Dashboard!$P$2)))) -> 2 | U8: =IF(OR(NOT(ISNUMBER($F8)),NOT(ISNUMBER($G8)),NOT(ISNUMBER(Dashboard!$P$2)),NOT(ISNUMBER(Dashboard!$P$3)),$D8<>"Owner block"),"—",IF(MAX(0,MIN($G8,Dashboard!$P$3+1)-MAX($F8,Dashboard!$P$2))=0,"—",MAX(0,MIN($G8,Dashboard!$P$3+1)-MAX($F8,Dashboard!$P$2)))) -> — | V8: =IF($B8="",IF(COUNTA($C8:$G8,$I8:$K8,$S8)=0,"","⚠ no property — not counted"),IF(COUNTIF(Setup!$A$25:$A$36,$B8)=0,"⚠ property not in Setup",IF(AND($F8<>"",NOT(ISNUMBER($F8))),"⚠ check-in is not a real date",IF(AND($G8<>"",NOT(ISNUMBER($G8))),"⚠ check-out is not a real date",IF(AND($J8<>"",NOT(ISNUMBER($J8))),"⚠ booking value is not a number","OK"))))) -> OK | W8: =IF(OR($B8="",NOT(ISNUMBER($J8)),$D8="Cancelled",$D8="Owner block"),"—",$J8) -> 560
A9: 5 | B9: Harbour Studio | C9: Booking.com | D9: Completed | E9: EXAMPLE — T. Brandt | F9: =IFERROR(DATE(YEAR(TODAY()),MONTH(TODAY()),2),"") -> 46205 | G9: =IFERROR(DATE(YEAR(TODAY()),MONTH(TODAY()),6),"") -> 46209 | H9: =IF(OR(NOT(ISNUMBER($F9)),NOT(ISNUMBER($G9))),"—",IF($G9<=$F9,"⚠ check dates",$G9-$F9)) -> 4 | I9: 2 | J9: 310 | L9: =IF(OR($B9="",NOT(ISNUMBER($J9)),$D9="Cancelled",$D9="Owner block"),"—",ROUND($J9*IF(ISNUMBER($K9),IF($K9>1,$K9/100,$K9),IF(IFERROR(INDEX(Setup!$D$25:$D$36,MATCH($B9,Setup!$A$25:$A$36,0)),0)>1,IFERROR(INDEX(Setup!$D$25:$D$36,MATCH($B9,Setup!$A$25:$A$36,0)),0)/100,IFERROR(INDEX(Setup!$D$25:$D$36,MATCH($B9,Setup!$A$25:$A$36,0)),0))),2)) -> 46.5 | M9: =IF(NOT(ISNUMBER($L9)),"—",ROUND($J9-$L9,2)) -> 263.5 | N9: =IF(OR($B9="",$G9="",$D9="Cancelled"),"—",IFERROR(IF(INDEX(Setup!$E$25:$E$36,MATCH($B9,Setup!$A$25:$A$36,0))=0,"—",INDEX(Setup!$E$25:$E$36,MATCH($B9,Setup!$A$25:$A$36,0))),"—")) -> 38 | O9: =IF(OR($B9="",$G9="",$D9="Cancelled"),"—",IFERROR(IF(INDEX(Setup!$F$25:$F$36,MATCH($B9,Setup!$A$25:$A$36,0))=0,"—",INDEX(Setup!$F$25:$F$36,MATCH($B9,Setup!$A$25:$A$36,0))),"—")) -> 9 | P9: =IF(OR($B9="",$G9="",$D9="Cancelled",$D9="Owner block"),"—",IF(IFERROR(INDEX(Setup!$G$25:$G$36,MATCH($B9,Setup!$A$25:$A$36,0)),0)+IFERROR(INDEX(Setup!$H$25:$H$36,MATCH($B9,Setup!$A$25:$A$36,0)),0)*IF(ISNUMBER($H9),$H9,0)=0,"—",ROUND(IFERROR(INDEX(Setup!$G$25:$G$36,MATCH($B9,Setup!$A$25:$A$36,0)),0)+IFERROR(INDEX(Setup!$H$25:$H$36,MATCH($B9,Setup!$A$25:$A$36,0)),0)*IF(ISNUMBER($H9),$H9,0),2))) -> 9.3 | Q9: =IF(OR($B9="",$D9="Cancelled"),"—",IF(AND(NOT(ISNUMBER($M9)),COUNT($N9:$P9)=0),"—",ROUND(IF(ISNUMBER($M9),$M9,0)-SUM($N9:$P9),2))) -> 207.2 | R9: =IF(OR(NOT(ISNUMBER($Q9)),NOT(ISNUMBER($H9)),$H9<=0),"—",ROUND($Q9/$H9,2)) -> 51.8 | T9: =IF(OR(NOT(ISNUMBER($F9)),NOT(ISNUMBER($G9)),NOT(ISNUMBER(Dashboard!$P$2)),NOT(ISNUMBER(Dashboard!$P$3)),$D9="Cancelled",$D9="Owner block"),"—",IF(MAX(0,MIN($G9,Dashboard!$P$3+1)-MAX($F9,Dashboard!$P$2))=0,"—",MAX(0,MIN($G9,Dashboard!$P$3+1)-MAX($F9,Dashboard!$P$2)))) -> 4 | U9: =IF(OR(NOT(ISNUMBER($F9)),NOT(ISNUMBER($G9)),NOT(ISNUMBER(Dashboard!$P$2)),NOT(ISNUMBER(Dashboard!$P$3)),$D9<>"Owner block"),"—",IF(MAX(0,MIN($G9,Dashboard!$P$3+1)-MAX($F9,Dashboard!$P$2))=0,"—",MAX(0,MIN($G9,Dashboard!$P$3+1)-MAX($F9,Dashboard!$P$2)))) -> — | V9: =IF($B9="",IF(COUNTA($C9:$G9,$I9:$K9,$S9)=0,"","⚠ no property — not counted"),IF(COUNTIF(Setup!$A$25:$A$36,$B9)=0,"⚠ property not in Setup",IF(AND($F9<>"",NOT(ISNUMBER($F9))),"⚠ check-in is not a real date",IF(AND($G9<>"",NOT(ISNUMBER($G9))),"⚠ check-out is not a real date",IF(AND($J9<>"",NOT(ISNUMBER($J9))),"⚠ booking value is not a number","OK"))))) -> OK | W9: =IF(OR($B9="",NOT(ISNUMBER($J9)),$D9="Cancelled",$D9="Owner block"),"—",$J9) -> 310
A10: 6 | B10: Harbour Studio | C10: Booking.com | D10: Completed | E10: EXAMPLE — M. Silva | F10: =IFERROR(DATE(YEAR(TODAY()),MONTH(TODAY()),8),"") -> 46211 | G10: =IFERROR(DATE(YEAR(TODAY()),MONTH(TODAY()),14),"") -> 46217 | H10: =IF(OR(NOT(ISNUMBER($F10)),NOT(ISNUMBER($G10))),"—",IF($G10<=$F10,"⚠ check dates",$G10-$F10)) -> 6 | I10: 2 | J10: 455 | L10: =IF(OR($B10="",NOT(ISNUMBER($J10)),$D10="Cancelled",$D10="Owner block"),"—",ROUND($J10*IF(ISNUMBER($K10),IF($K10>1,$K10/100,$K10),IF(IFERROR(INDEX(Setup!$D$25:$D$36,MATCH($B10,Setup!$A$25:$A$36,0)),0)>1,IFERROR(INDEX(Setup!$D$25:$D$36,MATCH($B10,Setup!$A$25:$A$36,0)),0)/100,IFERROR(INDEX(Setup!$D$25:$D$36,MATCH($B10,Setup!$A$25:$A$36,0)),0))),2)) -> 68.25 | M10: =IF(NOT(ISNUMBER($L10)),"—",ROUND($J10-$L10,2)) -> 386.75 | N10: =IF(OR($B10="",$G10="",$D10="Cancelled"),"—",IFERROR(IF(INDEX(Setup!$E$25:$E$36,MATCH($B10,Setup!$A$25:$A$36,0))=0,"—",INDEX(Setup!$E$25:$E$36,MATCH($B10,Setup!$A$25:$A$36,0))),"—")) -> 38 | O10: =IF(OR($B10="",$G10="",$D10="Cancelled"),"—",IFERROR(IF(INDEX(Setup!$F$25:$F$36,MATCH($B10,Setup!$A$25:$A$36,0))=0,"—",INDEX(Setup!$F$25:$F$36,MATCH($B10,Setup!$A$25:$A$36,0))),"—")) -> 9 | P10: =IF(OR($B10="",$G10="",$D10="Cancelled",$D10="Owner block"),"—",IF(IFERROR(INDEX(Setup!$G$25:$G$36,MATCH($B10,Setup!$A$25:$A$36,0)),0)+IFERROR(INDEX(Setup!$H$25:$H$36,MATCH($B10,Setup!$A$25:$A$36,0)),0)*IF(ISNUMBER($H10),$H10,0)=0,"—",ROUND(IFERROR(INDEX(Setup!$G$25:$G$36,MATCH($B10,Setup!$A$25:$A$36,0)),0)+IFERROR(INDEX(Setup!$H$25:$H$36,MATCH($B10,Setup!$A$25:$A$36,0)),0)*IF(ISNUMBER($H10),$H10,0),2))) -> 11.7 | Q10: =IF(OR($B10="",$D10="Cancelled"),"—",IF(AND(NOT(ISNUMBER($M10)),COUNT($N10:$P10)=0),"—",ROUND(IF(ISNUMBER($M10),$M10,0)-SUM($N10:$P10),2))) -> 328.05 | R10: =IF(OR(NOT(ISNUMBER($Q10)),NOT(ISNUMBER($H10)),$H10<=0),"—",ROUND($Q10/$H10,2)) -> 54.68 | S10: The next row checks in the day this guest leaves — the Cleaning tab flags a SAME-DAY TURN. | T10: =IF(OR(NOT(ISNUMBER($F10)),NOT(ISNUMBER($G10)),NOT(ISNUMBER(Dashboard!$P$2)),NOT(ISNUMBER(Dashboard!$P$3)),$D10="Cancelled",$D10="Owner block"),"—",IF(MAX(0,MIN($G10,Dashboard!$P$3+1)-MAX($F10,Dashboard!$P$2))=0,"—",MAX(0,MIN($G10,Dashboard!$P$3+1)-MAX($F10,Dashboard!$P$2)))) -> 6 | U10: =IF(OR(NOT(ISNUMBER($F10)),NOT(ISNUMBER($G10)),NOT(ISNUMBER(Dashboard!$P$2)),NOT(ISNUMBER(Dashboard!$P$3)),$D10<>"Owner block"),"—",IF(MAX(0,MIN($G10,Dashboard!$P$3+1)-MAX($F10,Dashboard!$P$2))=0,"—",MAX(0,MIN($G10,Dashboard!$P$3+1)-MAX($F10,Dashboard!$P$2)))) -> — | V10: =IF($B10="",IF(COUNTA($C10:$G10,$I10:$K10,$S10)=0,"","⚠ no property — not counted"),IF(COUNTIF(Setup!$A$25:$A$36,$B10)=0,"⚠ property not in Setup",IF(AND($F10<>"",NOT(ISNUMBER($F10))),"⚠ check-in is not a real date",IF(AND($G10<>"",NOT(ISNUMBER($G10))),"⚠ check-out is not a real date",IF(AND($J10<>"",NOT(ISNUMBER($J10))),"⚠ booking value is not a number","OK"))))) -> OK | W10: =IF(OR($B10="",NOT(ISNUMBER($J10)),$D10="Cancelled",$D10="Owner block"),"—",$J10) -> 455
A11: 7 | B11: Harbour Studio | C11: Airbnb | D11: Completed | E11: EXAMPLE — K. Owusu | F11: =IFERROR(DATE(YEAR(TODAY()),MONTH(TODAY()),14),"") -> 46217 | G11: =IFERROR(DATE(YEAR(TODAY()),MONTH(TODAY()),18),"") -> 46221 | H11: =IF(OR(NOT(ISNUMBER($F11)),NOT(ISNUMBER($G11))),"—",IF($G11<=$F11,"⚠ check dates",$G11-$F11)) -> 4 | I11: 1 | J11: 300 | K11: 0.03 | L11: =IF(OR($B11="",NOT(ISNUMBER($J11)),$D11="Cancelled",$D11="Owner block"),"—",ROUND($J11*IF(ISNUMBER($K11),IF($K11>1,$K11/100,$K11),IF(IFERROR(INDEX(Setup!$D$25:$D$36,MATCH($B11,Setup!$A$25:$A$36,0)),0)>1,IFERROR(INDEX(Setup!$D$25:$D$36,MATCH($B11,Setup!$A$25:$A$36,0)),0)/100,IFERROR(INDEX(Setup!$D$25:$D$36,MATCH($B11,Setup!$A$25:$A$36,0)),0))),2)) -> 9 | M11: =IF(NOT(ISNUMBER($L11)),"—",ROUND($J11-$L11,2)) -> 291 | N11: =IF(OR($B11="",$G11="",$D11="Cancelled"),"—",IFERROR(IF(INDEX(Setup!$E$25:$E$36,MATCH($B11,Setup!$A$25:$A$36,0))=0,"—",INDEX(Setup!$E$25:$E$36,MATCH($B11,Setup!$A$25:$A$36,0))),"—")) -> 38 | O11: =IF(OR($B11="",$G11="",$D11="Cancelled"),"—",IFERROR(IF(INDEX(Setup!$F$25:$F$36,MATCH($B11,Setup!$A$25:$A$36,0))=0,"—",INDEX(Setup!$F$25:$F$36,MATCH($B11,Setup!$A$25:$A$36,0))),"—")) -> 9 | P11: =IF(OR($B11="",$G11="",$D11="Cancelled",$D11="Owner block"),"—",IF(IFERROR(INDEX(Setup!$G$25:$G$36,MATCH($B11,Setup!$A$25:$A$36,0)),0)+IFERROR(INDEX(Setup!$H$25:$H$36,MATCH($B11,Setup!$A$25:$A$36,0)),0)*IF(ISNUMBER($H11),$H11,0)=0,"—",ROUND(IFERROR(INDEX(Setup!$G$25:$G$36,MATCH($B11,Setup!$A$25:$A$36,0)),0)+IFERROR(INDEX(Setup!$H$25:$H$36,MATCH($B11,Setup!$A$25:$A$36,0)),0)*IF(ISNUMBER($H11),$H11,0),2))) -> 9.3 | Q11: =IF(OR($B11="",$D11="Cancelled"),"—",IF(AND(NOT(ISNUMBER($M11)),COUNT($N11:$P11)=0),"—",ROUND(IF(ISNUMBER($M11),$M11,0)-SUM($N11:$P11),2))) -> 234.7 | R11: =IF(OR(NOT(ISNUMBER($Q11)),NOT(ISNUMBER($H11)),$H11<=0),"—",ROUND($Q11/$H11,2)) -> 58.68 | S11: Fee override 3% — this one came in through a different channel. | T11: =IF(OR(NOT(ISNUMBER($F11)),NOT(ISNUMBER($G11)),NOT(ISNUMBER(Dashboard!$P$2)),NOT(ISNUMBER(Dashboard!$P$3)),$D11="Cancelled",$D11="Owner block"),"—",IF(MAX(0,MIN($G11,Dashboard!$P$3+1)-MAX($F11,Dashboard!$P$2))=0,"—",MAX(0,MIN($G11,Dashboard!$P$3+1)-MAX($F11,Dashboard!$P$2)))) -> 4 | U11: =IF(OR(NOT(ISNUMBER($F11)),NOT(ISNUMBER($G11)),NOT(ISNUMBER(Dashboard!$P$2)),NOT(ISNUMBER(Dashboard!$P$3)),$D11<>"Owner block"),"—",IF(MAX(0,MIN($G11,Dashboard!$P$3+1)-MAX($F11,Dashboard!$P$2))=0,"—",MAX(0,MIN($G11,Dashboard!$P$3+1)-MAX($F11,Dashboard!$P$2)))) -> — | V11: =IF($B11="",IF(COUNTA($C11:$G11,$I11:$K11,$S11)=0,"","⚠ no property — not counted"),IF(COUNTIF(Setup!$A$25:$A$36,$B11)=0,"⚠ property not in Setup",IF(AND($F11<>"",NOT(ISNUMBER($F11))),"⚠ check-in is not a real date",IF(AND($G11<>"",NOT(ISNUMBER($G11))),"⚠ check-out is not a real date",IF(AND($J11<>"",NOT(ISNUMBER($J11))),"⚠ booking value is not a number","OK"))))) -> OK | W11: =IF(OR($B11="",NOT(ISNUMBER($J11)),$D11="Cancelled",$D11="Owner block"),"—",$J11) -> 300
A12: 8 | B12: Harbour Studio | C12: Booking.com | D12: Cancelled | E12: EXAMPLE — cancelled stay | F12: =IFERROR(DATE(YEAR(TODAY()),MONTH(TODAY()),21),"") -> 46224 | G12: =IFERROR(DATE(YEAR(TODAY()),MONTH(TODAY()),24),"") -> 46227 | H12: =IF(OR(NOT(ISNUMBER($F12)),NOT(ISNUMBER($G12))),"—",IF($G12<=$F12,"⚠ check dates",$G12-$F12)) -> 3 | I12: 2 | J12: 280 | L12: =IF(OR($B12="",NOT(ISNUMBER($J12)),$D12="Cancelled",$D12="Owner block"),"—",ROUND($J12*IF(ISNUMBER($K12),IF($K12>1,$K12/100,$K12),IF(IFERROR(INDEX(Setup!$D$25:$D$36,MATCH($B12,Setup!$A$25:$A$36,0)),0)>1,IFERROR(INDEX(Setup!$D$25:$D$36,MATCH($B12,Setup!$A$25:$A$36,0)),0)/100,IFERROR(INDEX(Setup!$D$25:$D$36,MATCH($B12,Setup!$A$25:$A$36,0)),0))),2)) -> — | M12: =IF(NOT(ISNUMBER($L12)),"—",ROUND($J12-$L12,2)) -> — | N12: =IF(OR($B12="",$G12="",$D12="Cancelled"),"—",IFERROR(IF(INDEX(Setup!$E$25:$E$36,MATCH($B12,Setup!$A$25:$A$36,0))=0,"—",INDEX(Setup!$E$25:$E$36,MATCH($B12,Setup!$A$25:$A$36,0))),"—")) -> — | O12: =IF(OR($B12="",$G12="",$D12="Cancelled"),"—",IFERROR(IF(INDEX(Setup!$F$25:$F$36,MATCH($B12,Setup!$A$25:$A$36,0))=0,"—",INDEX(Setup!$F$25:$F$36,MATCH($B12,Setup!$A$25:$A$36,0))),"—")) -> — | P12: =IF(OR($B12="",$G12="",$D12="Cancelled",$D12="Owner block"),"—",IF(IFERROR(INDEX(Setup!$G$25:$G$36,MATCH($B12,Setup!$A$25:$A$36,0)),0)+IFERROR(INDEX(Setup!$H$25:$H$36,MATCH($B12,Setup!$A$25:$A$36,0)),0)*IF(ISNUMBER($H12),$H12,0)=0,"—",ROUND(IFERROR(INDEX(Setup!$G$25:$G$36,MATCH($B12,Setup!$A$25:$A$36,0)),0)+IFERROR(INDEX(Setup!$H$25:$H$36,MATCH($B12,Setup!$A$25:$A$36,0)),0)*IF(ISNUMBER($H12),$H12,0),2))) -> — | Q12: =IF(OR($B12="",$D12="Cancelled"),"—",IF(AND(NOT(ISNUMBER($M12)),COUNT($N12:$P12)=0),"—",ROUND(IF(ISNUMBER($M12),$M12,0)-SUM($N12:$P12),2))) -> — | R12: =IF(OR(NOT(ISNUMBER($Q12)),NOT(ISNUMBER($H12)),$H12<=0),"—",ROUND($Q12/$H12,2)) -> — | S12: Cancelled: counted nowhere, every calculated column shows —. | T12: =IF(OR(NOT(ISNUMBER($F12)),NOT(ISNUMBER($G12)),NOT(ISNUMBER(Dashboard!$P$2)),NOT(ISNUMBER(Dashboard!$P$3)),$D12="Cancelled",$D12="Owner block"),"—",IF(MAX(0,MIN($G12,Dashboard!$P$3+1)-MAX($F12,Dashboard!$P$2))=0,"—",MAX(0,MIN($G12,Dashboard!$P$3+1)-MAX($F12,Dashboard!$P$2)))) -> — | U12: =IF(OR(NOT(ISNUMBER($F12)),NOT(ISNUMBER($G12)),NOT(ISNUMBER(Dashboard!$P$2)),NOT(ISNUMBER(Dashboard!$P$3)),$D12<>"Owner block"),"—",IF(MAX(0,MIN($G12,Dashboard!$P$3+1)-MAX($F12,Dashboard!$P$2))=0,"—",MAX(0,MIN($G12,Dashboard!$P$3+1)-MAX($F12,Dashboard!$P$2)))) -> — | V12: =IF($B12="",IF(COUNTA($C12:$G12,$I12:$K12,$S12)=0,"","⚠ no property — not counted"),IF(COUNTIF(Setup!$A$25:$A$36,$B12)=0,"⚠ property not in Setup",IF(AND($F12<>"",NOT(ISNUMBER($F12))),"⚠ check-in is not a real date",IF(AND($G12<>"",NOT(ISNUMBER($G12))),"⚠ check-out is not a real date",IF(AND($J12<>"",NOT(ISNUMBER($J12))),"⚠ booking value is not a number","OK"))))) -> OK | W12: =IF(OR($B12="",NOT(ISNUMBER($J12)),$D12="Cancelled",$D12="Owner block"),"—",$J12) -> —
A13: 9 | B13: Garden Cottage | C13: Vrbo | D13: Completed | E13: EXAMPLE — Family Duarte | F13: =IFERROR(DATE(YEAR(TODAY()),MONTH(TODAY()),3),"") -> 46206 | G13: =IFERROR(DATE(YEAR(TODAY()),MONTH(TODAY()),9),"") -> 46212 | H13: =IF(OR(NOT(ISNUMBER($F13)),NOT(ISNUMBER($G13))),"—",IF($G13<=$F13,"⚠ check dates",$G13-$F13)) -> 6 | I13: 6 | J13: 890 | L13: =IF(OR($B13="",NOT(ISNUMBER($J13)),$D13="Cancelled",$D13="Owner block"),"—",ROUND($J13*IF(ISNUMBER($K13),IF($K13>1,$K13/100,$K13),IF(IFERROR(INDEX(Setup!$D$25:$D$36,MATCH($B13,Setup!$A$25:$A$36,0)),0)>1,IFERROR(INDEX(Setup!$D$25:$D$36,MATCH($B13,Setup!$A$25:$A$36,0)),0)/100,IFERROR(INDEX(Setup!$D$25:$D$36,MATCH($B13,Setup!$A$25:$A$36,0)),0))),2)) -> 71.2 | M13: =IF(NOT(ISNUMBER($L13)),"—",ROUND($J13-$L13,2)) -> 818.8 | N13: =IF(OR($B13="",$G13="",$D13="Cancelled"),"—",IFERROR(IF(INDEX(Setup!$E$25:$E$36,MATCH($B13,Setup!$A$25:$A$36,0))=0,"—",INDEX(Setup!$E$25:$E$36,MATCH($B13,Setup!$A$25:$A$36,0))),"—")) -> 60 | O13: =IF(OR($B13="",$G13="",$D13="Cancelled"),"—",IFERROR(IF(INDEX(Setup!$F$25:$F$36,MATCH($B13,Setup!$A$25:$A$36,0))=0,"—",INDEX(Setup!$F$25:$F$36,MATCH($B13,Setup!$A$25:$A$36,0))),"—")) -> 18 | P13: =IF(OR($B13="",$G13="",$D13="Cancelled",$D13="Owner block"),"—",IF(IFERROR(INDEX(Setup!$G$25:$G$36,MATCH($B13,Setup!$A$25:$A$36,0)),0)+IFERROR(INDEX(Setup!$H$25:$H$36,MATCH($B13,Setup!$A$25:$A$36,0)),0)*IF(ISNUMBER($H13),$H13,0)=0,"—",ROUND(IFERROR(INDEX(Setup!$G$25:$G$36,MATCH($B13,Setup!$A$25:$A$36,0)),0)+IFERROR(INDEX(Setup!$H$25:$H$36,MATCH($B13,Setup!$A$25:$A$36,0)),0)*IF(ISNUMBER($H13),$H13,0),2))) -> 20 | Q13: =IF(OR($B13="",$D13="Cancelled"),"—",IF(AND(NOT(ISNUMBER($M13)),COUNT($N13:$P13)=0),"—",ROUND(IF(ISNUMBER($M13),$M13,0)-SUM($N13:$P13),2))) -> 720.8 | R13: =IF(OR(NOT(ISNUMBER($Q13)),NOT(ISNUMBER($H13)),$H13<=0),"—",ROUND($Q13/$H13,2)) -> 120.13 | T13: =IF(OR(NOT(ISNUMBER($F13)),NOT(ISNUMBER($G13)),NOT(ISNUMBER(Dashboard!$P$2)),NOT(ISNUMBER(Dashboard!$P$3)),$D13="Cancelled",$D13="Owner block"),"—",IF(MAX(0,MIN($G13,Dashboard!$P$3+1)-MAX($F13,Dashboard!$P$2))=0,"—",MAX(0,MIN($G13,Dashboard!$P$3+1)-MAX($F13,Dashboard!$P$2)))) -> 6 | U13: =IF(OR(NOT(ISNUMBER($F13)),NOT(ISNUMBER($G13)),NOT(ISNUMBER(Dashboard!$P$2)),NOT(ISNUMBER(Dashboard!$P$3)),$D13<>"Owner block"),"—",IF(MAX(0,MIN($G13,Dashboard!$P$3+1)-MAX($F13,Dashboard!$P$2))=0,"—",MAX(0,MIN($G13,Dashboard!$P$3+1)-MAX($F13,Dashboard!$P$2)))) -> — | V13: =IF($B13="",IF(COUNTA($C13:$G13,$I13:$K13,$S13)=0,"","⚠ no property — not counted"),IF(COUNTIF(Setup!$A$25:$A$36,$B13)=0,"⚠ property not in Setup",IF(AND($F13<>"",NOT(ISNUMBER($F13))),"⚠ check-in is not a real date",IF(AND($G13<>"",NOT(ISNUMBER($G13))),"⚠ check-out is not a real date",IF(AND($J13<>"",NOT(ISNUMBER($J13))),"⚠ booking value is not a number","OK"))))) -> OK | W13: =IF(OR($B13="",NOT(ISNUMBER($J13)),$D13="Cancelled",$D13="Owner block"),"—",$J13) -> 890
A14: 10 | B14: Garden Cottage | C14: Other | D14: Owner block | E14: EXAMPLE — own stay, no income | F14: =IFERROR(DATE(YEAR(TODAY()),MONTH(TODAY()),11),"") -> 46214 | G14: =IFERROR(DATE(YEAR(TODAY()),MONTH(TODAY()),14),"") -> 46217 | H14: =IF(OR(NOT(ISNUMBER($F14)),NOT(ISNUMBER($G14))),"—",IF($G14<=$F14,"⚠ check dates",$G14-$F14)) -> 3 | I14: 2 | L14: =IF(OR($B14="",NOT(ISNUMBER($J14)),$D14="Cancelled",$D14="Owner block"),"—",ROUND($J14*IF(ISNUMBER($K14),IF($K14>1,$K14/100,$K14),IF(IFERROR(INDEX(Setup!$D$25:$D$36,MATCH($B14,Setup!$A$25:$A$36,0)),0)>1,IFERROR(INDEX(Setup!$D$25:$D$36,MATCH($B14,Setup!$A$25:$A$36,0)),0)/100,IFERROR(INDEX(Setup!$D$25:$D$36,MATCH($B14,Setup!$A$25:$A$36,0)),0))),2)) -> — | M14: =IF(NOT(ISNUMBER($L14)),"—",ROUND($J14-$L14,2)) -> — | N14: =IF(OR($B14="",$G14="",$D14="Cancelled"),"—",IFERROR(IF(INDEX(Setup!$E$25:$E$36,MATCH($B14,Setup!$A$25:$A$36,0))=0,"—",INDEX(Setup!$E$25:$E$36,MATCH($B14,Setup!$A$25:$A$36,0))),"—")) -> 60 | O14: =IF(OR($B14="",$G14="",$D14="Cancelled"),"—",IFERROR(IF(INDEX(Setup!$F$25:$F$36,MATCH($B14,Setup!$A$25:$A$36,0))=0,"—",INDEX(Setup!$F$25:$F$36,MATCH($B14,Setup!$A$25:$A$36,0))),"—")) -> 18 | P14: =IF(OR($B14="",$G14="",$D14="Cancelled",$D14="Owner block"),"—",IF(IFERROR(INDEX(Setup!$G$25:$G$36,MATCH($B14,Setup!$A$25:$A$36,0)),0)+IFERROR(INDEX(Setup!$H$25:$H$36,MATCH($B14,Setup!$A$25:$A$36,0)),0)*IF(ISNUMBER($H14),$H14,0)=0,"—",ROUND(IFERROR(INDEX(Setup!$G$25:$G$36,MATCH($B14,Setup!$A$25:$A$36,0)),0)+IFERROR(INDEX(Setup!$H$25:$H$36,MATCH($B14,Setup!$A$25:$A$36,0)),0)*IF(ISNUMBER($H14),$H14,0),2))) -> — | Q14: =IF(OR($B14="",$D14="Cancelled"),"—",IF(AND(NOT(ISNUMBER($M14)),COUNT($N14:$P14)=0),"—",ROUND(IF(ISNUMBER($M14),$M14,0)-SUM($N14:$P14),2))) -> -78 | R14: =IF(OR(NOT(ISNUMBER($Q14)),NOT(ISNUMBER($H14)),$H14<=0),"—",ROUND($Q14/$H14,2)) -> -26 | S14: Owner block: no income, but the cleaner still comes — cleaning and laundry stay as costs. | T14: =IF(OR(NOT(ISNUMBER($F14)),NOT(ISNUMBER($G14)),NOT(ISNUMBER(Dashboard!$P$2)),NOT(ISNUMBER(Dashboard!$P$3)),$D14="Cancelled",$D14="Owner block"),"—",IF(MAX(0,MIN($G14,Dashboard!$P$3+1)-MAX($F14,Dashboard!$P$2))=0,"—",MAX(0,MIN($G14,Dashboard!$P$3+1)-MAX($F14,Dashboard!$P$2)))) -> — | U14: =IF(OR(NOT(ISNUMBER($F14)),NOT(ISNUMBER($G14)),NOT(ISNUMBER(Dashboard!$P$2)),NOT(ISNUMBER(Dashboard!$P$3)),$D14<>"Owner block"),"—",IF(MAX(0,MIN($G14,Dashboard!$P$3+1)-MAX($F14,Dashboard!$P$2))=0,"—",MAX(0,MIN($G14,Dashboard!$P$3+1)-MAX($F14,Dashboard!$P$2)))) -> 3 | V14: =IF($B14="",IF(COUNTA($C14:$G14,$I14:$K14,$S14)=0,"","⚠ no property — not counted"),IF(COUNTIF(Setup!$A$25:$A$36,$B14)=0,"⚠ property not in Setup",IF(AND($F14<>"",NOT(ISNUMBER($F14))),"⚠ check-in is not a real date",IF(AND($G14<>"",NOT(ISNUMBER($G14))),"⚠ check-out is not a real date",IF(AND($J14<>"",NOT(ISNUMBER($J14))),"⚠ booking value is not a number","OK"))))) -> OK | W14: =IF(OR($B14="",NOT(ISNUMBER($J14)),$D14="Cancelled",$D14="Owner block"),"—",$J14) -> —
A15: 11 | B15: Garden Cottage | C15: Vrbo | D15: Confirmed | E15: EXAMPLE — R. Lindqvist | F15: =IFERROR(TODAY()+5,"") -> 46237 | G15: =IFERROR(TODAY()+9,"") -> 46241 | H15: =IF(OR(NOT(ISNUMBER($F15)),NOT(ISNUMBER($G15))),"—",IF($G15<=$F15,"⚠ check dates",$G15-$F15)) -> 4 | I15: 5 | J15: 940 | L15: =IF(OR($B15="",NOT(ISNUMBER($J15)),$D15="Cancelled",$D15="Owner block"),"—",ROUND($J15*IF(ISNUMBER($K15),IF($K15>1,$K15/100,$K15),IF(IFERROR(INDEX(Setup!$D$25:$D$36,MATCH($B15,Setup!$A$25:$A$36,0)),0)>1,IFERROR(INDEX(Setup!$D$25:$D$36,MATCH($B15,Setup!$A$25:$A$36,0)),0)/100,IFERROR(INDEX(Setup!$D$25:$D$36,MATCH($B15,Setup!$A$25:$A$36,0)),0))),2)) -> 75.2 | M15: =IF(NOT(ISNUMBER($L15)),"—",ROUND($J15-$L15,2)) -> 864.8 | N15: =IF(OR($B15="",$G15="",$D15="Cancelled"),"—",IFERROR(IF(INDEX(Setup!$E$25:$E$36,MATCH($B15,Setup!$A$25:$A$36,0))=0,"—",INDEX(Setup!$E$25:$E$36,MATCH($B15,Setup!$A$25:$A$36,0))),"—")) -> 60 | O15: =IF(OR($B15="",$G15="",$D15="Cancelled"),"—",IFERROR(IF(INDEX(Setup!$F$25:$F$36,MATCH($B15,Setup!$A$25:$A$36,0))=0,"—",INDEX(Setup!$F$25:$F$36,MATCH($B15,Setup!$A$25:$A$36,0))),"—")) -> 18 | P15: =IF(OR($B15="",$G15="",$D15="Cancelled",$D15="Owner block"),"—",IF(IFERROR(INDEX(Setup!$G$25:$G$36,MATCH($B15,Setup!$A$25:$A$36,0)),0)+IFERROR(INDEX(Setup!$H$25:$H$36,MATCH($B15,Setup!$A$25:$A$36,0)),0)*IF(ISNUMBER($H15),$H15,0)=0,"—",ROUND(IFERROR(INDEX(Setup!$G$25:$G$36,MATCH($B15,Setup!$A$25:$A$36,0)),0)+IFERROR(INDEX(Setup!$H$25:$H$36,MATCH($B15,Setup!$A$25:$A$36,0)),0)*IF(ISNUMBER($H15),$H15,0),2))) -> 16 | Q15: =IF(OR($B15="",$D15="Cancelled"),"—",IF(AND(NOT(ISNUMBER($M15)),COUNT($N15:$P15)=0),"—",ROUND(IF(ISNUMBER($M15),$M15,0)-SUM($N15:$P15),2))) -> 770.8 | R15: =IF(OR(NOT(ISNUMBER($Q15)),NOT(ISNUMBER($H15)),$H15<=0),"—",ROUND($Q15/$H15,2)) -> 192.7 | T15: =IF(OR(NOT(ISNUMBER($F15)),NOT(ISNUMBER($G15)),NOT(ISNUMBER(Dashboard!$P$2)),NOT(ISNUMBER(Dashboard!$P$3)),$D15="Cancelled",$D15="Owner block"),"—",IF(MAX(0,MIN($G15,Dashboard!$P$3+1)-MAX($F15,Dashboard!$P$2))=0,"—",MAX(0,MIN($G15,Dashboard!$P$3+1)-MAX($F15,Dashboard!$P$2)))) -> — | U15: =IF(OR(NOT(ISNUMBER($F15)),NOT(ISNUMBER($G15)),NOT(ISNUMBER(Dashboard!$P$2)),NOT(ISNUMBER(Dashboard!$P$3)),$D15<>"Owner block"),"—",IF(MAX(0,MIN($G15,Dashboard!$P$3+1)-MAX($F15,Dashboard!$P$2))=0,"—",MAX(0,MIN($G15,Dashboard!$P$3+1)-MAX($F15,Dashboard!$P$2)))) -> — | V15: =IF($B15="",IF(COUNTA($C15:$G15,$I15:$K15,$S15)=0,"","⚠ no property — not counted"),IF(COUNTIF(Setup!$A$25:$A$36,$B15)=0,"⚠ property not in Setup",IF(AND($F15<>"",NOT(ISNUMBER($F15))),"⚠ check-in is not a real date",IF(AND($G15<>"",NOT(ISNUMBER($G15))),"⚠ check-out is not a real date",IF(AND($J15<>"",NOT(ISNUMBER($J15))),"⚠ booking value is not a number","OK"))))) -> OK | W15: =IF(OR($B15="",NOT(ISNUMBER($J15)),$D15="Cancelled",$D15="Owner block"),"—",$J15) -> 940
A16: 12 | B16: Riverside Loft | C16: Airbnb | D16: Completed | E16: EXAMPLE — stay across the month border | F16: =IFERROR(DATE(YEAR(TODAY()),MONTH(TODAY()),-2),"") -> 46201 | G16: =IFERROR(DATE(YEAR(TODAY()),MONTH(TODAY()),3),"") -> 46206 | H16: =IF(OR(NOT(ISNUMBER($F16)),NOT(ISNUMBER($G16))),"—",IF($G16<=$F16,"⚠ check dates",$G16-$F16)) -> 5 | I16: 2 | J16: 520 | L16: =IF(OR($B16="",NOT(ISNUMBER($J16)),$D16="Cancelled",$D16="Owner block"),"—",ROUND($J16*IF(ISNUMBER($K16),IF($K16>1,$K16/100,$K16),IF(IFERROR(INDEX(Setup!$D$25:$D$36,MATCH($B16,Setup!$A$25:$A$36,0)),0)>1,IFERROR(INDEX(Setup!$D$25:$D$36,MATCH($B16,Setup!$A$25:$A$36,0)),0)/100,IFERROR(INDEX(Setup!$D$25:$D$36,MATCH($B16,Setup!$A$25:$A$36,0)),0))),2)) -> 15.6 | M16: =IF(NOT(ISNUMBER($L16)),"—",ROUND($J16-$L16,2)) -> 504.4 | N16: =IF(OR($B16="",$G16="",$D16="Cancelled"),"—",IFERROR(IF(INDEX(Setup!$E$25:$E$36,MATCH($B16,Setup!$A$25:$A$36,0))=0,"—",INDEX(Setup!$E$25:$E$36,MATCH($B16,Setup!$A$25:$A$36,0))),"—")) -> 45 | O16: =IF(OR($B16="",$G16="",$D16="Cancelled"),"—",IFERROR(IF(INDEX(Setup!$F$25:$F$36,MATCH($B16,Setup!$A$25:$A$36,0))=0,"—",INDEX(Setup!$F$25:$F$36,MATCH($B16,Setup!$A$25:$A$36,0))),"—")) -> 12 | P16: =IF(OR($B16="",$G16="",$D16="Cancelled",$D16="Owner block"),"—",IF(IFERROR(INDEX(Setup!$G$25:$G$36,MATCH($B16,Setup!$A$25:$A$36,0)),0)+IFERROR(INDEX(Setup!$H$25:$H$36,MATCH($B16,Setup!$A$25:$A$36,0)),0)*IF(ISNUMBER($H16),$H16,0)=0,"—",ROUND(IFERROR(INDEX(Setup!$G$25:$G$36,MATCH($B16,Setup!$A$25:$A$36,0)),0)+IFERROR(INDEX(Setup!$H$25:$H$36,MATCH($B16,Setup!$A$25:$A$36,0)),0)*IF(ISNUMBER($H16),$H16,0),2))) -> 13.5 | Q16: =IF(OR($B16="",$D16="Cancelled"),"—",IF(AND(NOT(ISNUMBER($M16)),COUNT($N16:$P16)=0),"—",ROUND(IF(ISNUMBER($M16),$M16,0)-SUM($N16:$P16),2))) -> 433.9 | R16: =IF(OR(NOT(ISNUMBER($Q16)),NOT(ISNUMBER($H16)),$H16<=0),"—",ROUND($Q16/$H16,2)) -> 86.78 | S16: Checks out on the 3rd: money lands in this month, nights are split across both. | T16: =IF(OR(NOT(ISNUMBER($F16)),NOT(ISNUMBER($G16)),NOT(ISNUMBER(Dashboard!$P$2)),NOT(ISNUMBER(Dashboard!$P$3)),$D16="Cancelled",$D16="Owner block"),"—",IF(MAX(0,MIN($G16,Dashboard!$P$3+1)-MAX($F16,Dashboard!$P$2))=0,"—",MAX(0,MIN($G16,Dashboard!$P$3+1)-MAX($F16,Dashboard!$P$2)))) -> 2 | U16: =IF(OR(NOT(ISNUMBER($F16)),NOT(ISNUMBER($G16)),NOT(ISNUMBER(Dashboard!$P$2)),NOT(ISNUMBER(Dashboard!$P$3)),$D16<>"Owner block"),"—",IF(MAX(0,MIN($G16,Dashboard!$P$3+1)-MAX($F16,Dashboard!$P$2))=0,"—",MAX(0,MIN($G16,Dashboard!$P$3+1)-MAX($F16,Dashboard!$P$2)))) -> — | V16: =IF($B16="",IF(COUNTA($C16:$G16,$I16:$K16,$S16)=0,"","⚠ no property — not counted"),IF(COUNTIF(Setup!$A$25:$A$36,$B16)=0,"⚠ property not in Setup",IF(AND($F16<>"",NOT(ISNUMBER($F16))),"⚠ check-in is not a real date",IF(AND($G16<>"",NOT(ISNUMBER($G16))),"⚠ check-out is not a real date",IF(AND($J16<>"",NOT(ISNUMBER($J16))),"⚠ booking value is not a number","OK"))))) -> OK | W16: =IF(OR($B16="",NOT(ISNUMBER($J16)),$D16="Cancelled",$D16="Owner block"),"—",$J16) -> 520
A17: 13 | H17: =IF(OR(NOT(ISNUMBER($F17)),NOT(ISNUMBER($G17))),"—",IF($G17<=$F17,"⚠ check dates",$G17-$F17)) -> — | L17: =IF(OR($B17="",NOT(ISNUMBER($J17)),$D17="Cancelled",$D17="Owner block"),"—",ROUND($J17*IF(ISNUMBER($K17),IF($K17>1,$K17/100,$K17),IF(IFERROR(INDEX(Setup!$D$25:$D$36,MATCH($B17,Setup!$A$25:$A$36,0)),0)>1,IFERROR(INDEX(Setup!$D$25:$D$36,MATCH($B17,Setup!$A$25:$A$36,0)),0)/100,IFERROR(INDEX(Setup!$D$25:$D$36,MATCH($B17,Setup!$A$25:$A$36,0)),0))),2)) -> — | M17: =IF(NOT(ISNUMBER($L17)),"—",ROUND($J17-$L17,2)) -> — | N17: =IF(OR($B17="",$G17="",$D17="Cancelled"),"—",IFERROR(IF(INDEX(Setup!$E$25:$E$36,MATCH($B17,Setup!$A$25:$A$36,0))=0,"—",INDEX(Setup!$E$25:$E$36,MATCH($B17,Setup!$A$25:$A$36,0))),"—")) -> — | O17: =IF(OR($B17="",$G17="",$D17="Cancelled"),"—",IFERROR(IF(INDEX(Setup!$F$25:$F$36,MATCH($B17,Setup!$A$25:$A$36,0))=0,"—",INDEX(Setup!$F$25:$F$36,MATCH($B17,Setup!$A$25:$A$36,0))),"—")) -> — | P17: =IF(OR($B17="",$G17="",$D17="Cancelled",$D17="Owner block"),"—",IF(IFERROR(INDEX(Setup!$G$25:$G$36,MATCH($B17,Setup!$A$25:$A$36,0)),0)+IFERROR(INDEX(Setup!$H$25:$H$36,MATCH($B17,Setup!$A$25:$A$36,0)),0)*IF(ISNUMBER($H17),$H17,0)=0,"—",ROUND(IFERROR(INDEX(Setup!$G$25:$G$36,MATCH($B17,Setup!$A$25:$A$36,0)),0)+IFERROR(INDEX(Setup!$H$25:$H$36,MATCH($B17,Setup!$A$25:$A$36,0)),0)*IF(ISNUMBER($H17),$H17,0),2))) -> — | Q17: =IF(OR($B17="",$D17="Cancelled"),"—",IF(AND(NOT(ISNUMBER($M17)),COUNT($N17:$P17)=0),"—",ROUND(IF(ISNUMBER($M17),$M17,0)-SUM($N17:$P17),2))) -> — | R17: =IF(OR(NOT(ISNUMBER($Q17)),NOT(ISNUMBER($H17)),$H17<=0),"—",ROUND($Q17/$H17,2)) -> — | T17: =IF(OR(NOT(ISNUMBER($F17)),NOT(ISNUMBER($G17)),NOT(ISNUMBER(Dashboard!$P$2)),NOT(ISNUMBER(Dashboard!$P$3)),$D17="Cancelled",$D17="Owner block"),"—",IF(MAX(0,MIN($G17,Dashboard!$P$3+1)-MAX($F17,Dashboard!$P$2))=0,"—",MAX(0,MIN($G17,Dashboard!$P$3+1)-MAX($F17,Dashboard!$P$2)))) -> — | U17: =IF(OR(NOT(ISNUMBER($F17)),NOT(ISNUMBER($G17)),NOT(ISNUMBER(Dashboard!$P$2)),NOT(ISNUMBER(Dashboard!$P$3)),$D17<>"Owner block"),"—",IF(MAX(0,MIN($G17,Dashboard!$P$3+1)-MAX($F17,Dashboard!$P$2))=0,"—",MAX(0,MIN($G17,Dashboard!$P$3+1)-MAX($F17,Dashboard!$P$2)))) -> — | V17: =IF($B17="",IF(COUNTA($C17:$G17,$I17:$K17,$S17)=0,"","⚠ no property — not counted"),IF(COUNTIF(Setup!$A$25:$A$36,$B17)=0,"⚠ property not in Setup",IF(AND($F17<>"",NOT(ISNUMBER($F17))),"⚠ check-in is not a real date",IF(AND($G17<>"",NOT(ISNUMBER($G17))),"⚠ check-out is not a real date",IF(AND($J17<>"",NOT(ISNUMBER($J17))),"⚠ booking value is not a number","OK"))))) | W17: =IF(OR($B17="",NOT(ISNUMBER($J17)),$D17="Cancelled",$D17="Owner block"),"—",$J17) -> —
A18: 14 | H18: =IF(OR(NOT(ISNUMBER($F18)),NOT(ISNUMBER($G18))),"—",IF($G18<=$F18,"⚠ check dates",$G18-$F18)) -> — | L18: =IF(OR($B18="",NOT(ISNUMBER($J18)),$D18="Cancelled",$D18="Owner block"),"—",ROUND($J18*IF(ISNUMBER($K18),IF($K18>1,$K18/100,$K18),IF(IFERROR(INDEX(Setup!$D$25:$D$36,MATCH($B18,Setup!$A$25:$A$36,0)),0)>1,IFERROR(INDEX(Setup!$D$25:$D$36,MATCH($B18,Setup!$A$25:$A$36,0)),0)/100,IFERROR(INDEX(Setup!$D$25:$D$36,MATCH($B18,Setup!$A$25:$A$36,0)),0))),2)) -> — | M18: =IF(NOT(ISNUMBER($L18)),"—",ROUND($J18-$L18,2)) -> — | N18: =IF(OR($B18="",$G18="",$D18="Cancelled"),"—",IFERROR(IF(INDEX(Setup!$E$25:$E$36,MATCH($B18,Setup!$A$25:$A$36,0))=0,"—",INDEX(Setup!$E$25:$E$36,MATCH($B18,Setup!$A$25:$A$36,0))),"—")) -> — | O18: =IF(OR($B18="",$G18="",$D18="Cancelled"),"—",IFERROR(IF(INDEX(Setup!$F$25:$F$36,MATCH($B18,Setup!$A$25:$A$36,0))=0,"—",INDEX(Setup!$F$25:$F$36,MATCH($B18,Setup!$A$25:$A$36,0))),"—")) -> — | P18: =IF(OR($B18="",$G18="",$D18="Cancelled",$D18="Owner block"),"—",IF(IFERROR(INDEX(Setup!$G$25:$G$36,MATCH($B18,Setup!$A$25:$A$36,0)),0)+IFERROR(INDEX(Setup!$H$25:$H$36,MATCH($B18,Setup!$A$25:$A$36,0)),0)*IF(ISNUMBER($H18),$H18,0)=0,"—",ROUND(IFERROR(INDEX(Setup!$G$25:$G$36,MATCH($B18,Setup!$A$25:$A$36,0)),0)+IFERROR(INDEX(Setup!$H$25:$H$36,MATCH($B18,Setup!$A$25:$A$36,0)),0)*IF(ISNUMBER($H18),$H18,0),2))) -> — | Q18: =IF(OR($B18="",$D18="Cancelled"),"—",IF(AND(NOT(ISNUMBER($M18)),COUNT($N18:$P18)=0),"—",ROUND(IF(ISNUMBER($M18),$M18,0)-SUM($N18:$P18),2))) -> — | R18: =IF(OR(NOT(ISNUMBER($Q18)),NOT(ISNUMBER($H18)),$H18<=0),"—",ROUND($Q18/$H18,2)) -> — | T18: =IF(OR(NOT(ISNUMBER($F18)),NOT(ISNUMBER($G18)),NOT(ISNUMBER(Dashboard!$P$2)),NOT(ISNUMBER(Dashboard!$P$3)),$D18="Cancelled",$D18="Owner block"),"—",IF(MAX(0,MIN($G18,Dashboard!$P$3+1)-MAX($F18,Dashboard!$P$2))=0,"—",MAX(0,MIN($G18,Dashboard!$P$3+1)-MAX($F18,Dashboard!$P$2)))) -> — | U18: =IF(OR(NOT(ISNUMBER($F18)),NOT(ISNUMBER($G18)),NOT(ISNUMBER(Dashboard!$P$2)),NOT(ISNUMBER(Dashboard!$P$3)),$D18<>"Owner block"),"—",IF(MAX(0,MIN($G18,Dashboard!$P$3+1)-MAX($F18,Dashboard!$P$2))=0,"—",MAX(0,MIN($G18,Dashboard!$P$3+1)-MAX($F18,Dashboard!$P$2)))) -> — | V18: =IF($B18="",IF(COUNTA($C18:$G18,$I18:$K18,$S18)=0,"","⚠ no property — not counted"),IF(COUNTIF(Setup!$A$25:$A$36,$B18)=0,"⚠ property not in Setup",IF(AND($F18<>"",NOT(ISNUMBER($F18))),"⚠ check-in is not a real date",IF(AND($G18<>"",NOT(ISNUMBER($G18))),"⚠ check-out is not a real date",IF(AND($J18<>"",NOT(ISNUMBER($J18))),"⚠ booking value is not a number","OK"))))) | W18: =IF(OR($B18="",NOT(ISNUMBER($J18)),$D18="Cancelled",$D18="Owner block"),"—",$J18) -> —
A19: 15 | H19: =IF(OR(NOT(ISNUMBER($F19)),NOT(ISNUMBER($G19))),"—",IF($G19<=$F19,"⚠ check dates",$G19-$F19)) -> — | L19: =IF(OR($B19="",NOT(ISNUMBER($J19)),$D19="Cancelled",$D19="Owner block"),"—",ROUND($J19*IF(ISNUMBER($K19),IF($K19>1,$K19/100,$K19),IF(IFERROR(INDEX(Setup!$D$25:$D$36,MATCH($B19,Setup!$A$25:$A$36,0)),0)>1,IFERROR(INDEX(Setup!$D$25:$D$36,MATCH($B19,Setup!$A$25:$A$36,0)),0)/100,IFERROR(INDEX(Setup!$D$25:$D$36,MATCH($B19,Setup!$A$25:$A$36,0)),0))),2)) -> — | M19: =IF(NOT(ISNUMBER($L19)),"—",ROUND($J19-$L19,2)) -> — | N19: =IF(OR($B19="",$G19="",$D19="Cancelled"),"—",IFERROR(IF(INDEX(Setup!$E$25:$E$36,MATCH($B19,Setup!$A$25:$A$36,0))=0,"—",INDEX(Setup!$E$25:$E$36,MATCH($B19,Setup!$A$25:$A$36,0))),"—")) -> — | O19: =IF(OR($B19="",$G19="",$D19="Cancelled"),"—",IFERROR(IF(INDEX(Setup!$F$25:$F$36,MATCH($B19,Setup!$A$25:$A$36,0))=0,"—",INDEX(Setup!$F$25:$F$36,MATCH($B19,Setup!$A$25:$A$36,0))),"—")) -> — | P19: =IF(OR($B19="",$G19="",$D19="Cancelled",$D19="Owner block"),"—",IF(IFERROR(INDEX(Setup!$G$25:$G$36,MATCH($B19,Setup!$A$25:$A$36,0)),0)+IFERROR(INDEX(Setup!$H$25:$H$36,MATCH($B19,Setup!$A$25:$A$36,0)),0)*IF(ISNUMBER($H19),$H19,0)=0,"—",ROUND(IFERROR(INDEX(Setup!$G$25:$G$36,MATCH($B19,Setup!$A$25:$A$36,0)),0)+IFERROR(INDEX(Setup!$H$25:$H$36,MATCH($B19,Setup!$A$25:$A$36,0)),0)*IF(ISNUMBER($H19),$H19,0),2))) -> — | Q19: =IF(OR($B19="",$D19="Cancelled"),"—",IF(AND(NOT(ISNUMBER($M19)),COUNT($N19:$P19)=0),"—",ROUND(IF(ISNUMBER($M19),$M19,0)-SUM($N19:$P19),2))) -> — | R19: =IF(OR(NOT(ISNUMBER($Q19)),NOT(ISNUMBER($H19)),$H19<=0),"—",ROUND($Q19/$H19,2)) -> — | T19: =IF(OR(NOT(ISNUMBER($F19)),NOT(ISNUMBER($G19)),NOT(ISNUMBER(Dashboard!$P$2)),NOT(ISNUMBER(Dashboard!$P$3)),$D19="Cancelled",$D19="Owner block"),"—",IF(MAX(0,MIN($G19,Dashboard!$P$3+1)-MAX($F19,Dashboard!$P$2))=0,"—",MAX(0,MIN($G19,Dashboard!$P$3+1)-MAX($F19,Dashboard!$P$2)))) -> — | U19: =IF(OR(NOT(ISNUMBER($F19)),NOT(ISNUMBER($G19)),NOT(ISNUMBER(Dashboard!$P$2)),NOT(ISNUMBER(Dashboard!$P$3)),$D19<>"Owner block"),"—",IF(MAX(0,MIN($G19,Dashboard!$P$3+1)-MAX($F19,Dashboard!$P$2))=0,"—",MAX(0,MIN($G19,Dashboard!$P$3+1)-MAX($F19,Dashboard!$P$2)))) -> — | V19: =IF($B19="",IF(COUNTA($C19:$G19,$I19:$K19,$S19)=0,"","⚠ no property — not counted"),IF(COUNTIF(Setup!$A$25:$A$36,$B19)=0,"⚠ property not in Setup",IF(AND($F19<>"",NOT(ISNUMBER($F19))),"⚠ check-in is not a real date",IF(AND($G19<>"",NOT(ISNUMBER($G19))),"⚠ check-out is not a real date",IF(AND($J19<>"",NOT(ISNUMBER($J19))),"⚠ booking value is not a number","OK"))))) | W19: =IF(OR($B19="",NOT(ISNUMBER($J19)),$D19="Cancelled",$D19="Owner block"),"—",$J19) -> —
A20: 16 | H20: =IF(OR(NOT(ISNUMBER($F20)),NOT(ISNUMBER($G20))),"—",IF($G20<=$F20,"⚠ check dates",$G20-$F20)) -> — | L20: =IF(OR($B20="",NOT(ISNUMBER($J20)),$D20="Cancelled",$D20="Owner block"),"—",ROUND($J20*IF(ISNUMBER($K20),IF($K20>1,$K20/100,$K20),IF(IFERROR(INDEX(Setup!$D$25:$D$36,MATCH($B20,Setup!$A$25:$A$36,0)),0)>1,IFERROR(INDEX(Setup!$D$25:$D$36,MATCH($B20,Setup!$A$25:$A$36,0)),0)/100,IFERROR(INDEX(Setup!$D$25:$D$36,MATCH($B20,Setup!$A$25:$A$36,0)),0))),2)) -> — | M20: =IF(NOT(ISNUMBER($L20)),"—",ROUND($J20-$L20,2)) -> — | N20: =IF(OR($B20="",$G20="",$D20="Cancelled"),"—",IFERROR(IF(INDEX(Setup!$E$25:$E$36,MATCH($B20,Setup!$A$25:$A$36,0))=0,"—",INDEX(Setup!$E$25:$E$36,MATCH($B20,Setup!$A$25:$A$36,0))),"—")) -> — | O20: =IF(OR($B20="",$G20="",$D20="Cancelled"),"—",IFERROR(IF(INDEX(Setup!$F$25:$F$36,MATCH($B20,Setup!$A$25:$A$36,0))=0,"—",INDEX(Setup!$F$25:$F$36,MATCH($B20,Setup!$A$25:$A$36,0))),"—")) -> — | P20: =IF(OR($B20="",$G20="",$D20="Cancelled",$D20="Owner block"),"—",IF(IFERROR(INDEX(Setup!$G$25:$G$36,MATCH($B20,Setup!$A$25:$A$36,0)),0)+IFERROR(INDEX(Setup!$H$25:$H$36,MATCH($B20,Setup!$A$25:$A$36,0)),0)*IF(ISNUMBER($H20),$H20,0)=0,"—",ROUND(IFERROR(INDEX(Setup!$G$25:$G$36,MATCH($B20,Setup!$A$25:$A$36,0)),0)+IFERROR(INDEX(Setup!$H$25:$H$36,MATCH($B20,Setup!$A$25:$A$36,0)),0)*IF(ISNUMBER($H20),$H20,0),2))) -> — | Q20: =IF(OR($B20="",$D20="Cancelled"),"—",IF(AND(NOT(ISNUMBER($M20)),COUNT($N20:$P20)=0),"—",ROUND(IF(ISNUMBER($M20),$M20,0)-SUM($N20:$P20),2))) -> — | R20: =IF(OR(NOT(ISNUMBER($Q20)),NOT(ISNUMBER($H20)),$H20<=0),"—",ROUND($Q20/$H20,2)) -> — | T20: =IF(OR(NOT(ISNUMBER($F20)),NOT(ISNUMBER($G20)),NOT(ISNUMBER(Dashboard!$P$2)),NOT(ISNUMBER(Dashboard!$P$3)),$D20="Cancelled",$D20="Owner block"),"—",IF(MAX(0,MIN($G20,Dashboard!$P$3+1)-MAX($F20,Dashboard!$P$2))=0,"—",MAX(0,MIN($G20,Dashboard!$P$3+1)-MAX($F20,Dashboard!$P$2)))) -> — | U20: =IF(OR(NOT(ISNUMBER($F20)),NOT(ISNUMBER($G20)),NOT(ISNUMBER(Dashboard!$P$2)),NOT(ISNUMBER(Dashboard!$P$3)),$D20<>"Owner block"),"—",IF(MAX(0,MIN($G20,Dashboard!$P$3+1)-MAX($F20,Dashboard!$P$2))=0,"—",MAX(0,MIN($G20,Dashboard!$P$3+1)-MAX($F20,Dashboard!$P$2)))) -> — | V20: =IF($B20="",IF(COUNTA($C20:$G20,$I20:$K20,$S20)=0,"","⚠ no property — not counted"),IF(COUNTIF(Setup!$A$25:$A$36,$B20)=0,"⚠ property not in Setup",IF(AND($F20<>"",NOT(ISNUMBER($F20))),"⚠ check-in is not a real date",IF(AND($G20<>"",NOT(ISNUMBER($G20))),"⚠ check-out is not a real date",IF(AND($J20<>"",NOT(ISNUMBER($J20))),"⚠ booking value is not a number","OK"))))) | W20: =IF(OR($B20="",NOT(ISNUMBER($J20)),$D20="Cancelled",$D20="Owner block"),"—",$J20) -> —
A21: 17 | H21: =IF(OR(NOT(ISNUMBER($F21)),NOT(ISNUMBER($G21))),"—",IF($G21<=$F21,"⚠ check dates",$G21-$F21)) -> — | L21: =IF(OR($B21="",NOT(ISNUMBER($J21)),$D21="Cancelled",$D21="Owner block"),"—",ROUND($J21*IF(ISNUMBER($K21),IF($K21>1,$K21/100,$K21),IF(IFERROR(INDEX(Setup!$D$25:$D$36,MATCH($B21,Setup!$A$25:$A$36,0)),0)>1,IFERROR(INDEX(Setup!$D$25:$D$36,MATCH($B21,Setup!$A$25:$A$36,0)),0)/100,IFERROR(INDEX(Setup!$D$25:$D$36,MATCH($B21,Setup!$A$25:$A$36,0)),0))),2)) -> — | M21: =IF(NOT(ISNUMBER($L21)),"—",ROUND($J21-$L21,2)) -> — | N21: =IF(OR($B21="",$G21="",$D21="Cancelled"),"—",IFERROR(IF(INDEX(Setup!$E$25:$E$36,MATCH($B21,Setup!$A$25:$A$36,0))=0,"—",INDEX(Setup!$E$25:$E$36,MATCH($B21,Setup!$A$25:$A$36,0))),"—")) -> — | O21: =IF(OR($B21="",$G21="",$D21="Cancelled"),"—",IFERROR(IF(INDEX(Setup!$F$25:$F$36,MATCH($B21,Setup!$A$25:$A$36,0))=0,"—",INDEX(Setup!$F$25:$F$36,MATCH($B21,Setup!$A$25:$A$36,0))),"—")) -> — | P21: =IF(OR($B21="",$G21="",$D21="Cancelled",$D21="Owner block"),"—",IF(IFERROR(INDEX(Setup!$G$25:$G$36,MATCH($B21,Setup!$A$25:$A$36,0)),0)+IFERROR(INDEX(Setup!$H$25:$H$36,MATCH($B21,Setup!$A$25:$A$36,0)),0)*IF(ISNUMBER($H21),$H21,0)=0,"—",ROUND(IFERROR(INDEX(Setup!$G$25:$G$36,MATCH($B21,Setup!$A$25:$A$36,0)),0)+IFERROR(INDEX(Setup!$H$25:$H$36,MATCH($B21,Setup!$A$25:$A$36,0)),0)*IF(ISNUMBER($H21),$H21,0),2))) -> — | Q21: =IF(OR($B21="",$D21="Cancelled"),"—",IF(AND(NOT(ISNUMBER($M21)),COUNT($N21:$P21)=0),"—",ROUND(IF(ISNUMBER($M21),$M21,0)-SUM($N21:$P21),2))) -> — | R21: =IF(OR(NOT(ISNUMBER($Q21)),NOT(ISNUMBER($H21)),$H21<=0),"—",ROUND($Q21/$H21,2)) -> — | T21: =IF(OR(NOT(ISNUMBER($F21)),NOT(ISNUMBER($G21)),NOT(ISNUMBER(Dashboard!$P$2)),NOT(ISNUMBER(Dashboard!$P$3)),$D21="Cancelled",$D21="Owner block"),"—",IF(MAX(0,MIN($G21,Dashboard!$P$3+1)-MAX($F21,Dashboard!$P$2))=0,"—",MAX(0,MIN($G21,Dashboard!$P$3+1)-MAX($F21,Dashboard!$P$2)))) -> — | U21: =IF(OR(NOT(ISNUMBER($F21)),NOT(ISNUMBER($G21)),NOT(ISNUMBER(Dashboard!$P$2)),NOT(ISNUMBER(Dashboard!$P$3)),$D21<>"Owner block"),"—",IF(MAX(0,MIN($G21,Dashboard!$P$3+1)-MAX($F21,Dashboard!$P$2))=0,"—",MAX(0,MIN($G21,Dashboard!$P$3+1)-MAX($F21,Dashboard!$P$2)))) -> — | V21: =IF($B21="",IF(COUNTA($C21:$G21,$I21:$K21,$S21)=0,"","⚠ no property — not counted"),IF(COUNTIF(Setup!$A$25:$A$36,$B21)=0,"⚠ property not in Setup",IF(AND($F21<>"",NOT(ISNUMBER($F21))),"⚠ check-in is not a real date",IF(AND($G21<>"",NOT(ISNUMBER($G21))),"⚠ check-out is not a real date",IF(AND($J21<>"",NOT(ISNUMBER($J21))),"⚠ booking value is not a number","OK"))))) | W21: =IF(OR($B21="",NOT(ISNUMBER($J21)),$D21="Cancelled",$D21="Owner block"),"—",$J21) -> —
A22: 18 | H22: =IF(OR(NOT(ISNUMBER($F22)),NOT(ISNUMBER($G22))),"—",IF($G22<=$F22,"⚠ check dates",$G22-$F22)) -> — | L22: =IF(OR($B22="",NOT(ISNUMBER($J22)),$D22="Cancelled",$D22="Owner block"),"—",ROUND($J22*IF(ISNUMBER($K22),IF($K22>1,$K22/100,$K22),IF(IFERROR(INDEX(Setup!$D$25:$D$36,MATCH($B22,Setup!$A$25:$A$36,0)),0)>1,IFERROR(INDEX(Setup!$D$25:$D$36,MATCH($B22,Setup!$A$25:$A$36,0)),0)/100,IFERROR(INDEX(Setup!$D$25:$D$36,MATCH($B22,Setup!$A$25:$A$36,0)),0))),2)) -> — | M22: =IF(NOT(ISNUMBER($L22)),"—",ROUND($J22-$L22,2)) -> — | N22: =IF(OR($B22="",$G22="",$D22="Cancelled"),"—",IFERROR(IF(INDEX(Setup!$E$25:$E$36,MATCH($B22,Setup!$A$25:$A$36,0))=0,"—",INDEX(Setup!$E$25:$E$36,MATCH($B22,Setup!$A$25:$A$36,0))),"—")) -> — | O22: =IF(OR($B22="",$G22="",$D22="Cancelled"),"—",IFERROR(IF(INDEX(Setup!$F$25:$F$36,MATCH($B22,Setup!$A$25:$A$36,0))=0,"—",INDEX(Setup!$F$25:$F$36,MATCH($B22,Setup!$A$25:$A$36,0))),"—")) -> — | P22: =IF(OR($B22="",$G22="",$D22="Cancelled",$D22="Owner block"),"—",IF(IFERROR(INDEX(Setup!$G$25:$G$36,MATCH($B22,Setup!$A$25:$A$36,0)),0)+IFERROR(INDEX(Setup!$H$25:$H$36,MATCH($B22,Setup!$A$25:$A$36,0)),0)*IF(ISNUMBER($H22),$H22,0)=0,"—",ROUND(IFERROR(INDEX(Setup!$G$25:$G$36,MATCH($B22,Setup!$A$25:$A$36,0)),0)+IFERROR(INDEX(Setup!$H$25:$H$36,MATCH($B22,Setup!$A$25:$A$36,0)),0)*IF(ISNUMBER($H22),$H22,0),2))) -> — | Q22: =IF(OR($B22="",$D22="Cancelled"),"—",IF(AND(NOT(ISNUMBER($M22)),COUNT($N22:$P22)=0),"—",ROUND(IF(ISNUMBER($M22),$M22,0)-SUM($N22:$P22),2))) -> — | R22: =IF(OR(NOT(ISNUMBER($Q22)),NOT(ISNUMBER($H22)),$H22<=0),"—",ROUND($Q22/$H22,2)) -> — | T22: =IF(OR(NOT(ISNUMBER($F22)),NOT(ISNUMBER($G22)),NOT(ISNUMBER(Dashboard!$P$2)),NOT(ISNUMBER(Dashboard!$P$3)),$D22="Cancelled",$D22="Owner block"),"—",IF(MAX(0,MIN($G22,Dashboard!$P$3+1)-MAX($F22,Dashboard!$P$2))=0,"—",MAX(0,MIN($G22,Dashboard!$P$3+1)-MAX($F22,Dashboard!$P$2)))) -> — | U22: =IF(OR(NOT(ISNUMBER($F22)),NOT(ISNUMBER($G22)),NOT(ISNUMBER(Dashboard!$P$2)),NOT(ISNUMBER(Dashboard!$P$3)),$D22<>"Owner block"),"—",IF(MAX(0,MIN($G22,Dashboard!$P$3+1)-MAX($F22,Dashboard!$P$2))=0,"—",MAX(0,MIN($G22,Dashboard!$P$3+1)-MAX($F22,Dashboard!$P$2)))) -> — | V22: =IF($B22="",IF(COUNTA($C22:$G22,$I22:$K22,$S22)=0,"","⚠ no property — not counted"),IF(COUNTIF(Setup!$A$25:$A$36,$B22)=0,"⚠ property not in Setup",IF(AND($F22<>"",NOT(ISNUMBER($F22))),"⚠ check-in is not a real date",IF(AND($G22<>"",NOT(ISNUMBER($G22))),"⚠ check-out is not a real date",IF(AND($J22<>"",NOT(ISNUMBER($J22))),"⚠ booking value is not a number","OK"))))) | W22: =IF(OR($B22="",NOT(ISNUMBER($J22)),$D22="Cancelled",$D22="Owner block"),"—",$J22) -> —
A23: 19 | H23: =IF(OR(NOT(ISNUMBER($F23)),NOT(ISNUMBER($G23))),"—",IF($G23<=$F23,"⚠ check dates",$G23-$F23)) -> — | L23: =IF(OR($B23="",NOT(ISNUMBER($J23)),$D23="Cancelled",$D23="Owner block"),"—",ROUND($J23*IF(ISNUMBER($K23),IF($K23>1,$K23/100,$K23),IF(IFERROR(INDEX(Setup!$D$25:$D$36,MATCH($B23,Setup!$A$25:$A$36,0)),0)>1,IFERROR(INDEX(Setup!$D$25:$D$36,MATCH($B23,Setup!$A$25:$A$36,0)),0)/100,IFERROR(INDEX(Setup!$D$25:$D$36,MATCH($B23,Setup!$A$25:$A$36,0)),0))),2)) -> — | M23: =IF(NOT(ISNUMBER($L23)),"—",ROUND($J23-$L23,2)) -> — | N23: =IF(OR($B23="",$G23="",$D23="Cancelled"),"—",IFERROR(IF(INDEX(Setup!$E$25:$E$36,MATCH($B23,Setup!$A$25:$A$36,0))=0,"—",INDEX(Setup!$E$25:$E$36,MATCH($B23,Setup!$A$25:$A$36,0))),"—")) -> — | O23: =IF(OR($B23="",$G23="",$D23="Cancelled"),"—",IFERROR(IF(INDEX(Setup!$F$25:$F$36,MATCH($B23,Setup!$A$25:$A$36,0))=0,"—",INDEX(Setup!$F$25:$F$36,MATCH($B23,Setup!$A$25:$A$36,0))),"—")) -> — | P23: =IF(OR($B23="",$G23="",$D23="Cancelled",$D23="Owner block"),"—",IF(IFERROR(INDEX(Setup!$G$25:$G$36,MATCH($B23,Setup!$A$25:$A$36,0)),0)+IFERROR(INDEX(Setup!$H$25:$H$36,MATCH($B23,Setup!$A$25:$A$36,0)),0)*IF(ISNUMBER($H23),$H23,0)=0,"—",ROUND(IFERROR(INDEX(Setup!$G$25:$G$36,MATCH($B23,Setup!$A$25:$A$36,0)),0)+IFERROR(INDEX(Setup!$H$25:$H$36,MATCH($B23,Setup!$A$25:$A$36,0)),0)*IF(ISNUMBER($H23),$H23,0),2))) -> — | Q23: =IF(OR($B23="",$D23="Cancelled"),"—",IF(AND(NOT(ISNUMBER($M23)),COUNT($N23:$P23)=0),"—",ROUND(IF(ISNUMBER($M23),$M23,0)-SUM($N23:$P23),2))) -> — | R23: =IF(OR(NOT(ISNUMBER($Q23)),NOT(ISNUMBER($H23)),$H23<=0),"—",ROUND($Q23/$H23,2)) -> — | T23: =IF(OR(NOT(ISNUMBER($F23)),NOT(ISNUMBER($G23)),NOT(ISNUMBER(Dashboard!$P$2)),NOT(ISNUMBER(Dashboard!$P$3)),$D23="Cancelled",$D23="Owner block"),"—",IF(MAX(0,MIN($G23,Dashboard!$P$3+1)-MAX($F23,Dashboard!$P$2))=0,"—",MAX(0,MIN($G23,Dashboard!$P$3+1)-MAX($F23,Dashboard!$P$2)))) -> — | U23: =IF(OR(NOT(ISNUMBER($F23)),NOT(ISNUMBER($G23)),NOT(ISNUMBER(Dashboard!$P$2)),NOT(ISNUMBER(Dashboard!$P$3)),$D23<>"Owner block"),"—",IF(MAX(0,MIN($G23,Dashboard!$P$3+1)-MAX($F23,Dashboard!$P$2))=0,"—",MAX(0,MIN($G23,Dashboard!$P$3+1)-MAX($F23,Dashboard!$P$2)))) -> — | V23: =IF($B23="",IF(COUNTA($C23:$G23,$I23:$K23,$S23)=0,"","⚠ no property — not counted"),IF(COUNTIF(Setup!$A$25:$A$36,$B23)=0,"⚠ property not in Setup",IF(AND($F23<>"",NOT(ISNUMBER($F23))),"⚠ check-in is not a real date",IF(AND($G23<>"",NOT(ISNUMBER($G23))),"⚠ check-out is not a real date",IF(AND($J23<>"",NOT(ISNUMBER($J23))),"⚠ booking value is not a number","OK"))))) | W23: =IF(OR($B23="",NOT(ISNUMBER($J23)),$D23="Cancelled",$D23="Owner block"),"—",$J23) -> —
A24: 20 | H24: =IF(OR(NOT(ISNUMBER($F24)),NOT(ISNUMBER($G24))),"—",IF($G24<=$F24,"⚠ check dates",$G24-$F24)) -> — | L24: =IF(OR($B24="",NOT(ISNUMBER($J24)),$D24="Cancelled",$D24="Owner block"),"—",ROUND($J24*IF(ISNUMBER($K24),IF($K24>1,$K24/100,$K24),IF(IFERROR(INDEX(Setup!$D$25:$D$36,MATCH($B24,Setup!$A$25:$A$36,0)),0)>1,IFERROR(INDEX(Setup!$D$25:$D$36,MATCH($B24,Setup!$A$25:$A$36,0)),0)/100,IFERROR(INDEX(Setup!$D$25:$D$36,MATCH($B24,Setup!$A$25:$A$36,0)),0))),2)) -> — | M24: =IF(NOT(ISNUMBER($L24)),"—",ROUND($J24-$L24,2)) -> — | N24: =IF(OR($B24="",$G24="",$D24="Cancelled"),"—",IFERROR(IF(INDEX(Setup!$E$25:$E$36,MATCH($B24,Setup!$A$25:$A$36,0))=0,"—",INDEX(Setup!$E$25:$E$36,MATCH($B24,Setup!$A$25:$A$36,0))),"—")) -> — | O24: =IF(OR($B24="",$G24="",$D24="Cancelled"),"—",IFERROR(IF(INDEX(Setup!$F$25:$F$36,MATCH($B24,Setup!$A$25:$A$36,0))=0,"—",INDEX(Setup!$F$25:$F$36,MATCH($B24,Setup!$A$25:$A$36,0))),"—")) -> — | P24: =IF(OR($B24="",$G24="",$D24="Cancelled",$D24="Owner block"),"—",IF(IFERROR(INDEX(Setup!$G$25:$G$36,MATCH($B24,Setup!$A$25:$A$36,0)),0)+IFERROR(INDEX(Setup!$H$25:$H$36,MATCH($B24,Setup!$A$25:$A$36,0)),0)*IF(ISNUMBER($H24),$H24,0)=0,"—",ROUND(IFERROR(INDEX(Setup!$G$25:$G$36,MATCH($B24,Setup!$A$25:$A$36,0)),0)+IFERROR(INDEX(Setup!$H$25:$H$36,MATCH($B24,Setup!$A$25:$A$36,0)),0)*IF(ISNUMBER($H24),$H24,0),2))) -> — | Q24: =IF(OR($B24="",$D24="Cancelled"),"—",IF(AND(NOT(ISNUMBER($M24)),COUNT($N24:$P24)=0),"—",ROUND(IF(ISNUMBER($M24),$M24,0)-SUM($N24:$P24),2))) -> — | R24: =IF(OR(NOT(ISNUMBER($Q24)),NOT(ISNUMBER($H24)),$H24<=0),"—",ROUND($Q24/$H24,2)) -> — | T24: =IF(OR(NOT(ISNUMBER($F24)),NOT(ISNUMBER($G24)),NOT(ISNUMBER(Dashboard!$P$2)),NOT(ISNUMBER(Dashboard!$P$3)),$D24="Cancelled",$D24="Owner block"),"—",IF(MAX(0,MIN($G24,Dashboard!$P$3+1)-MAX($F24,Dashboard!$P$2))=0,"—",MAX(0,MIN($G24,Dashboard!$P$3+1)-MAX($F24,Dashboard!$P$2)))) -> — | U24: =IF(OR(NOT(ISNUMBER($F24)),NOT(ISNUMBER($G24)),NOT(ISNUMBER(Dashboard!$P$2)),NOT(ISNUMBER(Dashboard!$P$3)),$D24<>"Owner block"),"—",IF(MAX(0,MIN($G24,Dashboard!$P$3+1)-MAX($F24,Dashboard!$P$2))=0,"—",MAX(0,MIN($G24,Dashboard!$P$3+1)-MAX($F24,Dashboard!$P$2)))) -> — | V24: =IF($B24="",IF(COUNTA($C24:$G24,$I24:$K24,$S24)=0,"","⚠ no property — not counted"),IF(COUNTIF(Setup!$A$25:$A$36,$B24)=0,"⚠ property not in Setup",IF(AND($F24<>"",NOT(ISNUMBER($F24))),"⚠ check-in is not a real date",IF(AND($G24<>"",NOT(ISNUMBER($G24))),"⚠ check-out is not a real date",IF(AND($J24<>"",NOT(ISNUMBER($J24))),"⚠ booking value is not a number","OK"))))) | W24: =IF(OR($B24="",NOT(ISNUMBER($J24)),$D24="Cancelled",$D24="Owner block"),"—",$J24) -> —
A25: 21 | H25: =IF(OR(NOT(ISNUMBER($F25)),NOT(ISNUMBER($G25))),"—",IF($G25<=$F25,"⚠ check dates",$G25-$F25)) -> — | L25: =IF(OR($B25="",NOT(ISNUMBER($J25)),$D25="Cancelled",$D25="Owner block"),"—",ROUND($J25*IF(ISNUMBER($K25),IF($K25>1,$K25/100,$K25),IF(IFERROR(INDEX(Setup!$D$25:$D$36,MATCH($B25,Setup!$A$25:$A$36,0)),0)>1,IFERROR(INDEX(Setup!$D$25:$D$36,MATCH($B25,Setup!$A$25:$A$36,0)),0)/100,IFERROR(INDEX(Setup!$D$25:$D$36,MATCH($B25,Setup!$A$25:$A$36,0)),0))),2)) -> — | M25: =IF(NOT(ISNUMBER($L25)),"—",ROUND($J25-$L25,2)) -> — | N25: =IF(OR($B25="",$G25="",$D25="Cancelled"),"—",IFERROR(IF(INDEX(Setup!$E$25:$E$36,MATCH($B25,Setup!$A$25:$A$36,0))=0,"—",INDEX(Setup!$E$25:$E$36,MATCH($B25,Setup!$A$25:$A$36,0))),"—")) -> — | O25: =IF(OR($B25="",$G25="",$D25="Cancelled"),"—",IFERROR(IF(INDEX(Setup!$F$25:$F$36,MATCH($B25,Setup!$A$25:$A$36,0))=0,"—",INDEX(Setup!$F$25:$F$36,MATCH($B25,Setup!$A$25:$A$36,0))),"—")) -> — | P25: =IF(OR($B25="",$G25="",$D25="Cancelled",$D25="Owner block"),"—",IF(IFERROR(INDEX(Setup!$G$25:$G$36,MATCH($B25,Setup!$A$25:$A$36,0)),0)+IFERROR(INDEX(Setup!$H$25:$H$36,MATCH($B25,Setup!$A$25:$A$36,0)),0)*IF(ISNUMBER($H25),$H25,0)=0,"—",ROUND(IFERROR(INDEX(Setup!$G$25:$G$36,MATCH($B25,Setup!$A$25:$A$36,0)),0)+IFERROR(INDEX(Setup!$H$25:$H$36,MATCH($B25,Setup!$A$25:$A$36,0)),0)*IF(ISNUMBER($H25),$H25,0),2))) -> — | Q25: =IF(OR($B25="",$D25="Cancelled"),"—",IF(AND(NOT(ISNUMBER($M25)),COUNT($N25:$P25)=0),"—",ROUND(IF(ISNUMBER($M25),$M25,0)-SUM($N25:$P25),2))) -> — | R25: =IF(OR(NOT(ISNUMBER($Q25)),NOT(ISNUMBER($H25)),$H25<=0),"—",ROUND($Q25/$H25,2)) -> — | T25: =IF(OR(NOT(ISNUMBER($F25)),NOT(ISNUMBER($G25)),NOT(ISNUMBER(Dashboard!$P$2)),NOT(ISNUMBER(Dashboard!$P$3)),$D25="Cancelled",$D25="Owner block"),"—",IF(MAX(0,MIN($G25,Dashboard!$P$3+1)-MAX($F25,Dashboard!$P$2))=0,"—",MAX(0,MIN($G25,Dashboard!$P$3+1)-MAX($F25,Dashboard!$P$2)))) -> — | U25: =IF(OR(NOT(ISNUMBER($F25)),NOT(ISNUMBER($G25)),NOT(ISNUMBER(Dashboard!$P$2)),NOT(ISNUMBER(Dashboard!$P$3)),$D25<>"Owner block"),"—",IF(MAX(0,MIN($G25,Dashboard!$P$3+1)-MAX($F25,Dashboard!$P$2))=0,"—",MAX(0,MIN($G25,Dashboard!$P$3+1)-MAX($F25,Dashboard!$P$2)))) -> — | V25: =IF($B25="",IF(COUNTA($C25:$G25,$I25:$K25,$S25)=0,"","⚠ no property — not counted"),IF(COUNTIF(Setup!$A$25:$A$36,$B25)=0,"⚠ property not in Setup",IF(AND($F25<>"",NOT(ISNUMBER($F25))),"⚠ check-in is not a real date",IF(AND($G25<>"",NOT(ISNUMBER($G25))),"⚠ check-out is not a real date",IF(AND($J25<>"",NOT(ISNUMBER($J25))),"⚠ booking value is not a number","OK"))))) | W25: =IF(OR($B25="",NOT(ISNUMBER($J25)),$D25="Cancelled",$D25="Owner block"),"—",$J25) -> —
A26: 22 | H26: =IF(OR(NOT(ISNUMBER($F26)),NOT(ISNUMBER($G26))),"—",IF($G26<=$F26,"⚠ check dates",$G26-$F26)) -> — | L26: =IF(OR($B26="",NOT(ISNUMBER($J26)),$D26="Cancelled",$D26="Owner block"),"—",ROUND($J26*IF(ISNUMBER($K26),IF($K26>1,$K26/100,$K26),IF(IFERROR(INDEX(Setup!$D$25:$D$36,MATCH($B26,Setup!$A$25:$A$36,0)),0)>1,IFERROR(INDEX(Setup!$D$25:$D$36,MATCH($B26,Setup!$A$25:$A$36,0)),0)/100,IFERROR(INDEX(Setup!$D$25:$D$36,MATCH($B26,Setup!$A$25:$A$36,0)),0))),2)) -> — | M26: =IF(NOT(ISNUMBER($L26)),"—",ROUND($J26-$L26,2)) -> — | N26: =IF(OR($B26="",$G26="",$D26="Cancelled"),"—",IFERROR(IF(INDEX(Setup!$E$25:$E$36,MATCH($B26,Setup!$A$25:$A$36,0))=0,"—",INDEX(Setup!$E$25:$E$36,MATCH($B26,Setup!$A$25:$A$36,0))),"—")) -> — | O26: =IF(OR($B26="",$G26="",$D26="Cancelled"),"—",IFERROR(IF(INDEX(Setup!$F$25:$F$36,MATCH($B26,Setup!$A$25:$A$36,0))=0,"—",INDEX(Setup!$F$25:$F$36,MATCH($B26,Setup!$A$25:$A$36,0))),"—")) -> — | P26: =IF(OR($B26="",$G26="",$D26="Cancelled",$D26="Owner block"),"—",IF(IFERROR(INDEX(Setup!$G$25:$G$36,MATCH($B26,Setup!$A$25:$A$36,0)),0)+IFERROR(INDEX(Setup!$H$25:$H$36,MATCH($B26,Setup!$A$25:$A$36,0)),0)*IF(ISNUMBER($H26),$H26,0)=0,"—",ROUND(IFERROR(INDEX(Setup!$G$25:$G$36,MATCH($B26,Setup!$A$25:$A$36,0)),0)+IFERROR(INDEX(Setup!$H$25:$H$36,MATCH($B26,Setup!$A$25:$A$36,0)),0)*IF(ISNUMBER($H26),$H26,0),2))) -> — | Q26: =IF(OR($B26="",$D26="Cancelled"),"—",IF(AND(NOT(ISNUMBER($M26)),COUNT($N26:$P26)=0),"—",ROUND(IF(ISNUMBER($M26),$M26,0)-SUM($N26:$P26),2))) -> — | R26: =IF(OR(NOT(ISNUMBER($Q26)),NOT(ISNUMBER($H26)),$H26<=0),"—",ROUND($Q26/$H26,2)) -> — | T26: =IF(OR(NOT(ISNUMBER($F26)),NOT(ISNUMBER($G26)),NOT(ISNUMBER(Dashboard!$P$2)),NOT(ISNUMBER(Dashboard!$P$3)),$D26="Cancelled",$D26="Owner block"),"—",IF(MAX(0,MIN($G26,Dashboard!$P$3+1)-MAX($F26,Dashboard!$P$2))=0,"—",MAX(0,MIN($G26,Dashboard!$P$3+1)-MAX($F26,Dashboard!$P$2)))) -> — | U26: =IF(OR(NOT(ISNUMBER($F26)),NOT(ISNUMBER($G26)),NOT(ISNUMBER(Dashboard!$P$2)),NOT(ISNUMBER(Dashboard!$P$3)),$D26<>"Owner block"),"—",IF(MAX(0,MIN($G26,Dashboard!$P$3+1)-MAX($F26,Dashboard!$P$2))=0,"—",MAX(0,MIN($G26,Dashboard!$P$3+1)-MAX($F26,Dashboard!$P$2)))) -> — | V26: =IF($B26="",IF(COUNTA($C26:$G26,$I26:$K26,$S26)=0,"","⚠ no property — not counted"),IF(COUNTIF(Setup!$A$25:$A$36,$B26)=0,"⚠ property not in Setup",IF(AND($F26<>"",NOT(ISNUMBER($F26))),"⚠ check-in is not a real date",IF(AND($G26<>"",NOT(ISNUMBER($G26))),"⚠ check-out is not a real date",IF(AND($J26<>"",NOT(ISNUMBER($J26))),"⚠ booking value is not a number","OK"))))) | W26: =IF(OR($B26="",NOT(ISNUMBER($J26)),$D26="Cancelled",$D26="Owner block"),"—",$J26) -> —
A27: 23 | H27: =IF(OR(NOT(ISNUMBER($F27)),NOT(ISNUMBER($G27))),"—",IF($G27<=$F27,"⚠ check dates",$G27-$F27)) -> — | L27: =IF(OR($B27="",NOT(ISNUMBER($J27)),$D27="Cancelled",$D27="Owner block"),"—",ROUND($J27*IF(ISNUMBER($K27),IF($K27>1,$K27/100,$K27),IF(IFERROR(INDEX(Setup!$D$25:$D$36,MATCH($B27,Setup!$A$25:$A$36,0)),0)>1,IFERROR(INDEX(Setup!$D$25:$D$36,MATCH($B27,Setup!$A$25:$A$36,0)),0)/100,IFERROR(INDEX(Setup!$D$25:$D$36,MATCH($B27,Setup!$A$25:$A$36,0)),0))),2)) -> — | M27: =IF(NOT(ISNUMBER($L27)),"—",ROUND($J27-$L27,2)) -> — | N27: =IF(OR($B27="",$G27="",$D27="Cancelled"),"—",IFERROR(IF(INDEX(Setup!$E$25:$E$36,MATCH($B27,Setup!$A$25:$A$36,0))=0,"—",INDEX(Setup!$E$25:$E$36,MATCH($B27,Setup!$A$25:$A$36,0))),"—")) -> — | O27: =IF(OR($B27="",$G27="",$D27="Cancelled"),"—",IFERROR(IF(INDEX(Setup!$F$25:$F$36,MATCH($B27,Setup!$A$25:$A$36,0))=0,"—",INDEX(Setup!$F$25:$F$36,MATCH($B27,Setup!$A$25:$A$36,0))),"—")) -> — | P27: =IF(OR($B27="",$G27="",$D27="Cancelled",$D27="Owner block"),"—",IF(IFERROR(INDEX(Setup!$G$25:$G$36,MATCH($B27,Setup!$A$25:$A$36,0)),0)+IFERROR(INDEX(Setup!$H$25:$H$36,MATCH($B27,Setup!$A$25:$A$36,0)),0)*IF(ISNUMBER($H27),$H27,0)=0,"—",ROUND(IFERROR(INDEX(Setup!$G$25:$G$36,MATCH($B27,Setup!$A$25:$A$36,0)),0)+IFERROR(INDEX(Setup!$H$25:$H$36,MATCH($B27,Setup!$A$25:$A$36,0)),0)*IF(ISNUMBER($H27),$H27,0),2))) -> — | Q27: =IF(OR($B27="",$D27="Cancelled"),"—",IF(AND(NOT(ISNUMBER($M27)),COUNT($N27:$P27)=0),"—",ROUND(IF(ISNUMBER($M27),$M27,0)-SUM($N27:$P27),2))) -> — | R27: =IF(OR(NOT(ISNUMBER($Q27)),NOT(ISNUMBER($H27)),$H27<=0),"—",ROUND($Q27/$H27,2)) -> — | T27: =IF(OR(NOT(ISNUMBER($F27)),NOT(ISNUMBER($G27)),NOT(ISNUMBER(Dashboard!$P$2)),NOT(ISNUMBER(Dashboard!$P$3)),$D27="Cancelled",$D27="Owner block"),"—",IF(MAX(0,MIN($G27,Dashboard!$P$3+1)-MAX($F27,Dashboard!$P$2))=0,"—",MAX(0,MIN($G27,Dashboard!$P$3+1)-MAX($F27,Dashboard!$P$2)))) -> — | U27: =IF(OR(NOT(ISNUMBER($F27)),NOT(ISNUMBER($G27)),NOT(ISNUMBER(Dashboard!$P$2)),NOT(ISNUMBER(Dashboard!$P$3)),$D27<>"Owner block"),"—",IF(MAX(0,MIN($G27,Dashboard!$P$3+1)-MAX($F27,Dashboard!$P$2))=0,"—",MAX(0,MIN($G27,Dashboard!$P$3+1)-MAX($F27,Dashboard!$P$2)))) -> — | V27: =IF($B27="",IF(COUNTA($C27:$G27,$I27:$K27,$S27)=0,"","⚠ no property — not counted"),IF(COUNTIF(Setup!$A$25:$A$36,$B27)=0,"⚠ property not in Setup",IF(AND($F27<>"",NOT(ISNUMBER($F27))),"⚠ check-in is not a real date",IF(AND($G27<>"",NOT(ISNUMBER($G27))),"⚠ check-out is not a real date",IF(AND($J27<>"",NOT(ISNUMBER($J27))),"⚠ booking value is not a number","OK"))))) | W27: =IF(OR($B27="",NOT(ISNUMBER($J27)),$D27="Cancelled",$D27="Owner block"),"—",$J27) -> —
A28: 24 | H28: =IF(OR(NOT(ISNUMBER($F28)),NOT(ISNUMBER($G28))),"—",IF($G28<=$F28,"⚠ check dates",$G28-$F28)) -> — | L28: =IF(OR($B28="",NOT(ISNUMBER($J28)),$D28="Cancelled",$D28="Owner block"),"—",ROUND($J28*IF(ISNUMBER($K28),IF($K28>1,$K28/100,$K28),IF(IFERROR(INDEX(Setup!$D$25:$D$36,MATCH($B28,Setup!$A$25:$A$36,0)),0)>1,IFERROR(INDEX(Setup!$D$25:$D$36,MATCH($B28,Setup!$A$25:$A$36,0)),0)/100,IFERROR(INDEX(Setup!$D$25:$D$36,MATCH($B28,Setup!$A$25:$A$36,0)),0))),2)) -> — | M28: =IF(NOT(ISNUMBER($L28)),"—",ROUND($J28-$L28,2)) -> — | N28: =IF(OR($B28="",$G28="",$D28="Cancelled"),"—",IFERROR(IF(INDEX(Setup!$E$25:$E$36,MATCH($B28,Setup!$A$25:$A$36,0))=0,"—",INDEX(Setup!$E$25:$E$36,MATCH($B28,Setup!$A$25:$A$36,0))),"—")) -> — | O28: =IF(OR($B28="",$G28="",$D28="Cancelled"),"—",IFERROR(IF(INDEX(Setup!$F$25:$F$36,MATCH($B28,Setup!$A$25:$A$36,0))=0,"—",INDEX(Setup!$F$25:$F$36,MATCH($B28,Setup!$A$25:$A$36,0))),"—")) -> — | P28: =IF(OR($B28="",$G28="",$D28="Cancelled",$D28="Owner block"),"—",IF(IFERROR(INDEX(Setup!$G$25:$G$36,MATCH($B28,Setup!$A$25:$A$36,0)),0)+IFERROR(INDEX(Setup!$H$25:$H$36,MATCH($B28,Setup!$A$25:$A$36,0)),0)*IF(ISNUMBER($H28),$H28,0)=0,"—",ROUND(IFERROR(INDEX(Setup!$G$25:$G$36,MATCH($B28,Setup!$A$25:$A$36,0)),0)+IFERROR(INDEX(Setup!$H$25:$H$36,MATCH($B28,Setup!$A$25:$A$36,0)),0)*IF(ISNUMBER($H28),$H28,0),2))) -> — | Q28: =IF(OR($B28="",$D28="Cancelled"),"—",IF(AND(NOT(ISNUMBER($M28)),COUNT($N28:$P28)=0),"—",ROUND(IF(ISNUMBER($M28),$M28,0)-SUM($N28:$P28),2))) -> — | R28: =IF(OR(NOT(ISNUMBER($Q28)),NOT(ISNUMBER($H28)),$H28<=0),"—",ROUND($Q28/$H28,2)) -> — | T28: =IF(OR(NOT(ISNUMBER($F28)),NOT(ISNUMBER($G28)),NOT(ISNUMBER(Dashboard!$P$2)),NOT(ISNUMBER(Dashboard!$P$3)),$D28="Cancelled",$D28="Owner block"),"—",IF(MAX(0,MIN($G28,Dashboard!$P$3+1)-MAX($F28,Dashboard!$P$2))=0,"—",MAX(0,MIN($G28,Dashboard!$P$3+1)-MAX($F28,Dashboard!$P$2)))) -> — | U28: =IF(OR(NOT(ISNUMBER($F28)),NOT(ISNUMBER($G28)),NOT(ISNUMBER(Dashboard!$P$2)),NOT(ISNUMBER(Dashboard!$P$3)),$D28<>"Owner block"),"—",IF(MAX(0,MIN($G28,Dashboard!$P$3+1)-MAX($F28,Dashboard!$P$2))=0,"—",MAX(0,MIN($G28,Dashboard!$P$3+1)-MAX($F28,Dashboard!$P$2)))) -> — | V28: =IF($B28="",IF(COUNTA($C28:$G28,$I28:$K28,$S28)=0,"","⚠ no property — not counted"),IF(COUNTIF(Setup!$A$25:$A$36,$B28)=0,"⚠ property not in Setup",IF(AND($F28<>"",NOT(ISNUMBER($F28))),"⚠ check-in is not a real date",IF(AND($G28<>"",NOT(ISNUMBER($G28))),"⚠ check-out is not a real date",IF(AND($J28<>"",NOT(ISNUMBER($J28))),"⚠ booking value is not a number","OK"))))) | W28: =IF(OR($B28="",NOT(ISNUMBER($J28)),$D28="Cancelled",$D28="Owner block"),"—",$J28) -> —
... A304: 300 | H304: =IF(OR(NOT(ISNUMBER($F304)),NOT(ISNUMBER($G304))),"—",IF($G304<=$F304,"⚠ check dates",$G304-$F304)) -> — | L304: =IF(OR($B304="",NOT(ISNUMBER($J304)),$D304="Cancelled",$D304="Owner block"),"—",ROUND($J304*IF(ISNUMBER($K304),IF($K304>1,$K304/100,$K304),IF(IFERROR(INDEX(Setup!$D$25:$D$36,MATCH($B304,Setup!$A$25:$A$36,0)),0)>1,IFERROR(INDEX(Setup!$D$25:$D$36,MATCH($B304,Setup!$A$25:$A$36,0)),0)/100,IFERROR(INDEX(Setup!$D$25:$D$36,MATCH($B304,Setup!$A$25:$A$36,0)),0))),2)) -> — | M304: =IF(NOT(ISNUMBER($L304)),"—",ROUND($J304-$L304,2)) -> — | N304: =IF(OR($B304="",$G304="",$D304="Cancelled"),"—",IFERROR(IF(INDEX(Setup!$E$25:$E$36,MATCH($B304,Setup!$A$25:$A$36,0))=0,"—",INDEX(Setup!$E$25:$E$36,MATCH($B304,Setup!$A$25:$A$36,0))),"—")) -> — | O304: =IF(OR($B304="",$G304="",$D304="Cancelled"),"—",IFERROR(IF(INDEX(Setup!$F$25:$F$36,MATCH($B304,Setup!$A$25:$A$36,0))=0,"—",INDEX(Setup!$F$25:$F$36,MATCH($B304,Setup!$A$25:$A$36,0))),"—")) -> — | P304: =IF(OR($B304="",$G304="",$D304="Cancelled",$D304="Owner block"),"—",IF(IFERROR(INDEX(Setup!$G$25:$G$36,MATCH($B304,Setup!$A$25:$A$36,0)),0)+IFERROR(INDEX(Setup!$H$25:$H$36,MATCH($B304,Setup!$A$25:$A$36,0)),0)*IF(ISNUMBER($H304),$H304,0)=0,"—",ROUND(IFERROR(INDEX(Setup!$G$25:$G$36,MATCH($B304,Setup!$A$25:$A$36,0)),0)+IFERROR(INDEX(Setup!$H$25:$H$36,MATCH($B304,Setup!$A$25:$A$36,0)),0)*IF(ISNUMBER($H304),$H304,0),2))) -> — | Q304: =IF(OR($B304="",$D304="Cancelled"),"—",IF(AND(NOT(ISNUMBER($M304)),COUNT($N304:$P304)=0),"—",ROUND(IF(ISNUMBER($M304),$M304,0)-SUM($N304:$P304),2))) -> — | R304: =IF(OR(NOT(ISNUMBER($Q304)),NOT(ISNUMBER($H304)),$H304<=0),"—",ROUND($Q304/$H304,2)) -> — | T304: =IF(OR(NOT(ISNUMBER($F304)),NOT(ISNUMBER($G304)),NOT(ISNUMBER(Dashboard!$P$2)),NOT(ISNUMBER(Dashboard!$P$3)),$D304="Cancelled",$D304="Owner block"),"—",IF(MAX(0,MIN($G304,Dashboard!$P$3+1)-MAX($F304,Dashboard!$P$2))=0,"—",MAX(0,MIN($G304,Dashboard!$P$3+1)-MAX($F304,Dashboard!$P$2)))) -> — | U304: =IF(OR(NOT(ISNUMBER($F304)),NOT(ISNUMBER($G304)),NOT(ISNUMBER(Dashboard!$P$2)),NOT(ISNUMBER(Dashboard!$P$3)),$D304<>"Owner block"),"—",IF(MAX(0,MIN($G304,Dashboard!$P$3+1)-MAX($F304,Dashboard!$P$2))=0,"—",MAX(0,MIN($G304,Dashboard!$P$3+1)-MAX($F304,Dashboard!$P$2)))) -> — | V304: =IF($B304="",IF(COUNTA($C304:$G304,$I304:$K304,$S304)=0,"","⚠ no property — not counted"),IF(COUNTIF(Setup!$A$25:$A$36,$B304)=0,"⚠ property not in Setup",IF(AND($F304<>"",NOT(ISNUMBER($F304))),"⚠ check-in is not a real date",IF(AND($G304<>"",NOT(ISNUMBER($G304))),"⚠ check-out is not a real date",IF(AND($J304<>"",NOT(ISNUMBER($J304))),"⚠ booking value is not a number","OK"))))) | W304: =IF(OR($B304="",NOT(ISNUMBER($J304)),$D304="Cancelled",$D304="Owner block"),"—",$J304) -> —

Sheet Cleaning
A1: Cleaning & turnover plan
A2: Fills itself from Bookings through the # column. Type only Cleaner, Status and Notes. Column I shows what you pay per turnover — delete it before you hand this list to anyone.
A4: # | B4: Property | C4: Guest / reference | D4: Turnover date = check-out | E4: Days until turnover | F4: Next guest same day? | G4: Guests | H4: Linen sets due | I4: Cleaning cost | J4: Cleaner | K4: Cleaning status | L4: Notes / access info
A5: 1 | B5: =IFERROR(IF(INDEX(Bookings!$D$5:$D$304,MATCH($A5,Bookings!$A$5:$A$304,0))="Cancelled","—",IF(INDEX(Bookings!$B$5:$B$304,MATCH($A5,Bookings!$A$5:$A$304,0))="","—",INDEX(Bookings!$B$5:$B$304,MATCH($A5,Bookings!$A$5:$A$304,0)))),"—") -> Riverside Loft | C5: =IFERROR(IF(INDEX(Bookings!$D$5:$D$304,MATCH($A5,Bookings!$A$5:$A$304,0))="Cancelled","—",IF(INDEX(Bookings!$E$5:$E$304,MATCH($A5,Bookings!$A$5:$A$304,0))="","—",INDEX(Bookings!$E$5:$E$304,MATCH($A5,Bookings!$A$5:$A$304,0)))),"—") -> EXAMPLE — A. Pereira | D5: =IFERROR(IF(INDEX(Bookings!$D$5:$D$304,MATCH($A5,Bookings!$A$5:$A$304,0))="Cancelled","—",IF(INDEX(Bookings!$G$5:$G$304,MATCH($A5,Bookings!$A$5:$A$304,0))="","—",INDEX(Bookings!$G$5:$G$304,MATCH($A5,Bookings!$A$5:$A$304,0)))),"—") -> 46208 | E5: =IF(NOT(ISNUMBER($D5)),"—",IF($D5<TODAY(),"Past",IF($D5=TODAY(),"TODAY",$D5-TODAY()))) -> Past | F5: =IF(OR(NOT(ISNUMBER($D5)),$B5="—",$B5=""),"—",IF(COUNTIFS(Bookings!$B$5:$B$304,$B5,Bookings!$F$5:$F$304,$D5)-COUNTIFS(Bookings!$B$5:$B$304,$B5,Bookings!$F$5:$F$304,$D5,Bookings!$D$5:$D$304,"Cancelled")-COUNTIFS(Bookings!$B$5:$B$304,$B5,Bookings!$F$5:$F$304,$D5,Bookings!$D$5:$D$304,"Owner block")>0,"SAME-DAY TURN","No same-day guest")) -> No same-day guest | G5: =IFERROR(IF(INDEX(Bookings!$D$5:$D$304,MATCH($A5,Bookings!$A$5:$A$304,0))="Cancelled","—",IF(INDEX(Bookings!$I$5:$I$304,MATCH($A5,Bookings!$A$5:$A$304,0))="","—",INDEX(Bookings!$I$5:$I$304,MATCH($A5,Bookings!$A$5:$A$304,0)))),"—") -> 2 | H5: =IFERROR(IF(INDEX(Setup!$I$25:$I$36,MATCH($B5,Setup!$A$25:$A$36,0))=0,"—",INDEX(Setup!$I$25:$I$36,MATCH($B5,Setup!$A$25:$A$36,0))),"—") -> 2 | I5: =IFERROR(IF(INDEX(Setup!$E$25:$E$36,MATCH($B5,Setup!$A$25:$A$36,0))=0,"—",INDEX(Setup!$E$25:$E$36,MATCH($B5,Setup!$A$25:$A$36,0))),"—") -> 45 | J5: Ana | K5: Done | L5: EXAMPLE — key box code 1234, bins out on Tuesday.
A6: 2 | B6: =IFERROR(IF(INDEX(Bookings!$D$5:$D$304,MATCH($A6,Bookings!$A$5:$A$304,0))="Cancelled","—",IF(INDEX(Bookings!$B$5:$B$304,MATCH($A6,Bookings!$A$5:$A$304,0))="","—",INDEX(Bookings!$B$5:$B$304,MATCH($A6,Bookings!$A$5:$A$304,0)))),"—") -> Riverside Loft | C6: =IFERROR(IF(INDEX(Bookings!$D$5:$D$304,MATCH($A6,Bookings!$A$5:$A$304,0))="Cancelled","—",IF(INDEX(Bookings!$E$5:$E$304,MATCH($A6,Bookings!$A$5:$A$304,0))="","—",INDEX(Bookings!$E$5:$E$304,MATCH($A6,Bookings!$A$5:$A$304,0)))),"—") -> EXAMPLE — J. Meyer | D6: =IFERROR(IF(INDEX(Bookings!$D$5:$D$304,MATCH($A6,Bookings!$A$5:$A$304,0))="Cancelled","—",IF(INDEX(Bookings!$G$5:$G$304,MATCH($A6,Bookings!$A$5:$A$304,0))="","—",INDEX(Bookings!$G$5:$G$304,MATCH($A6,Bookings!$A$5:$A$304,0)))),"—") -> 46214 | E6: =IF(NOT(ISNUMBER($D6)),"—",IF($D6<TODAY(),"Past",IF($D6=TODAY(),"TODAY",$D6-TODAY()))) -> Past | F6: =IF(OR(NOT(ISNUMBER($D6)),$B6="—",$B6=""),"—",IF(COUNTIFS(Bookings!$B$5:$B$304,$B6,Bookings!$F$5:$F$304,$D6)-COUNTIFS(Bookings!$B$5:$B$304,$B6,Bookings!$F$5:$F$304,$D6,Bookings!$D$5:$D$304,"Cancelled")-COUNTIFS(Bookings!$B$5:$B$304,$B6,Bookings!$F$5:$F$304,$D6,Bookings!$D$5:$D$304,"Owner block")>0,"SAME-DAY TURN","No same-day guest")) -> No same-day guest | G6: =IFERROR(IF(INDEX(Bookings!$D$5:$D$304,MATCH($A6,Bookings!$A$5:$A$304,0))="Cancelled","—",IF(INDEX(Bookings!$I$5:$I$304,MATCH($A6,Bookings!$A$5:$A$304,0))="","—",INDEX(Bookings!$I$5:$I$304,MATCH($A6,Bookings!$A$5:$A$304,0)))),"—") -> 2 | H6: =IFERROR(IF(INDEX(Setup!$I$25:$I$36,MATCH($B6,Setup!$A$25:$A$36,0))=0,"—",INDEX(Setup!$I$25:$I$36,MATCH($B6,Setup!$A$25:$A$36,0))),"—") -> 2 | I6: =IFERROR(IF(INDEX(Setup!$E$25:$E$36,MATCH($B6,Setup!$A$25:$A$36,0))=0,"—",INDEX(Setup!$E$25:$E$36,MATCH($B6,Setup!$A$25:$A$36,0))),"—") -> 45 | J6: Ana | K6: Done
A7: 3 | B7: =IFERROR(IF(INDEX(Bookings!$D$5:$D$304,MATCH($A7,Bookings!$A$5:$A$304,0))="Cancelled","—",IF(INDEX(Bookings!$B$5:$B$304,MATCH($A7,Bookings!$A$5:$A$304,0))="","—",INDEX(Bookings!$B$5:$B$304,MATCH($A7,Bookings!$A$5:$A$304,0)))),"—") -> Riverside Loft | C7: =IFERROR(IF(INDEX(Bookings!$D$5:$D$304,MATCH($A7,Bookings!$A$5:$A$304,0))="Cancelled","—",IF(INDEX(Bookings!$E$5:$E$304,MATCH($A7,Bookings!$A$5:$A$304,0))="","—",INDEX(Bookings!$E$5:$E$304,MATCH($A7,Bookings!$A$5:$A$304,0)))),"—") -> EXAMPLE — L. Rossi | D7: =IFERROR(IF(INDEX(Bookings!$D$5:$D$304,MATCH($A7,Bookings!$A$5:$A$304,0))="Cancelled","—",IF(INDEX(Bookings!$G$5:$G$304,MATCH($A7,Bookings!$A$5:$A$304,0))="","—",INDEX(Bookings!$G$5:$G$304,MATCH($A7,Bookings!$A$5:$A$304,0)))),"—") -> 46219 | E7: =IF(NOT(ISNUMBER($D7)),"—",IF($D7<TODAY(),"Past",IF($D7=TODAY(),"TODAY",$D7-TODAY()))) -> Past | F7: =IF(OR(NOT(ISNUMBER($D7)),$B7="—",$B7=""),"—",IF(COUNTIFS(Bookings!$B$5:$B$304,$B7,Bookings!$F$5:$F$304,$D7)-COUNTIFS(Bookings!$B$5:$B$304,$B7,Bookings!$F$5:$F$304,$D7,Bookings!$D$5:$D$304,"Cancelled")-COUNTIFS(Bookings!$B$5:$B$304,$B7,Bookings!$F$5:$F$304,$D7,Bookings!$D$5:$D$304,"Owner block")>0,"SAME-DAY TURN","No same-day guest")) -> No same-day guest | G7: =IFERROR(IF(INDEX(Bookings!$D$5:$D$304,MATCH($A7,Bookings!$A$5:$A$304,0))="Cancelled","—",IF(INDEX(Bookings!$I$5:$I$304,MATCH($A7,Bookings!$A$5:$A$304,0))="","—",INDEX(Bookings!$I$5:$I$304,MATCH($A7,Bookings!$A$5:$A$304,0)))),"—") -> 3 | H7: =IFERROR(IF(INDEX(Setup!$I$25:$I$36,MATCH($B7,Setup!$A$25:$A$36,0))=0,"—",INDEX(Setup!$I$25:$I$36,MATCH($B7,Setup!$A$25:$A$36,0))),"—") -> 2 | I7: =IFERROR(IF(INDEX(Setup!$E$25:$E$36,MATCH($B7,Setup!$A$25:$A$36,0))=0,"—",INDEX(Setup!$E$25:$E$36,MATCH($B7,Setup!$A$25:$A$36,0))),"—") -> 45 | J7: Marco | K7: Done
A8: 4 | B8: =IFERROR(IF(INDEX(Bookings!$D$5:$D$304,MATCH($A8,Bookings!$A$5:$A$304,0))="Cancelled","—",IF(INDEX(Bookings!$B$5:$B$304,MATCH($A8,Bookings!$A$5:$A$304,0))="","—",INDEX(Bookings!$B$5:$B$304,MATCH($A8,Bookings!$A$5:$A$304,0)))),"—") -> Riverside Loft | C8: =IFERROR(IF(INDEX(Bookings!$D$5:$D$304,MATCH($A8,Bookings!$A$5:$A$304,0))="Cancelled","—",IF(INDEX(Bookings!$E$5:$E$304,MATCH($A8,Bookings!$A$5:$A$304,0))="","—",INDEX(Bookings!$E$5:$E$304,MATCH($A8,Bookings!$A$5:$A$304,0)))),"—") -> EXAMPLE — S. Novak | D8: =IFERROR(IF(INDEX(Bookings!$D$5:$D$304,MATCH($A8,Bookings!$A$5:$A$304,0))="Cancelled","—",IF(INDEX(Bookings!$G$5:$G$304,MATCH($A8,Bookings!$A$5:$A$304,0))="","—",INDEX(Bookings!$G$5:$G$304,MATCH($A8,Bookings!$A$5:$A$304,0)))),"—") -> 46235 | E8: =IF(NOT(ISNUMBER($D8)),"—",IF($D8<TODAY(),"Past",IF($D8=TODAY(),"TODAY",$D8-TODAY()))) -> 3 | F8: =IF(OR(NOT(ISNUMBER($D8)),$B8="—",$B8=""),"—",IF(COUNTIFS(Bookings!$B$5:$B$304,$B8,Bookings!$F$5:$F$304,$D8)-COUNTIFS(Bookings!$B$5:$B$304,$B8,Bookings!$F$5:$F$304,$D8,Bookings!$D$5:$D$304,"Cancelled")-COUNTIFS(Bookings!$B$5:$B$304,$B8,Bookings!$F$5:$F$304,$D8,Bookings!$D$5:$D$304,"Owner block")>0,"SAME-DAY TURN","No same-day guest")) -> No same-day guest | G8: =IFERROR(IF(INDEX(Bookings!$D$5:$D$304,MATCH($A8,Bookings!$A$5:$A$304,0))="Cancelled","—",IF(INDEX(Bookings!$I$5:$I$304,MATCH($A8,Bookings!$A$5:$A$304,0))="","—",INDEX(Bookings!$I$5:$I$304,MATCH($A8,Bookings!$A$5:$A$304,0)))),"—") -> 2 | H8: =IFERROR(IF(INDEX(Setup!$I$25:$I$36,MATCH($B8,Setup!$A$25:$A$36,0))=0,"—",INDEX(Setup!$I$25:$I$36,MATCH($B8,Setup!$A$25:$A$36,0))),"—") -> 2 | I8: =IFERROR(IF(INDEX(Setup!$E$25:$E$36,MATCH($B8,Setup!$A$25:$A$36,0))=0,"—",INDEX(Setup!$E$25:$E$36,MATCH($B8,Setup!$A$25:$A$36,0))),"—") -> 45 | J8: Ana | K8: Scheduled
A9: 5 | B9: =IFERROR(IF(INDEX(Bookings!$D$5:$D$304,MATCH($A9,Bookings!$A$5:$A$304,0))="Cancelled","—",IF(INDEX(Bookings!$B$5:$B$304,MATCH($A9,Bookings!$A$5:$A$304,0))="","—",INDEX(Bookings!$B$5:$B$304,MATCH($A9,Bookings!$A$5:$A$304,0)))),"—") -> Harbour Studio | C9: =IFERROR(IF(INDEX(Bookings!$D$5:$D$304,MATCH($A9,Bookings!$A$5:$A$304,0))="Cancelled","—",IF(INDEX(Bookings!$E$5:$E$304,MATCH($A9,Bookings!$A$5:$A$304,0))="","—",INDEX(Bookings!$E$5:$E$304,MATCH($A9,Bookings!$A$5:$A$304,0)))),"—") -> EXAMPLE — T. Brandt | D9: =IFERROR(IF(INDEX(Bookings!$D$5:$D$304,MATCH($A9,Bookings!$A$5:$A$304,0))="Cancelled","—",IF(INDEX(Bookings!$G$5:$G$304,MATCH($A9,Bookings!$A$5:$A$304,0))="","—",INDEX(Bookings!$G$5:$G$304,MATCH($A9,Bookings!$A$5:$A$304,0)))),"—") -> 46209 | E9: =IF(NOT(ISNUMBER($D9)),"—",IF($D9<TODAY(),"Past",IF($D9=TODAY(),"TODAY",$D9-TODAY()))) -> Past | F9: =IF(OR(NOT(ISNUMBER($D9)),$B9="—",$B9=""),"—",IF(COUNTIFS(Bookings!$B$5:$B$304,$B9,Bookings!$F$5:$F$304,$D9)-COUNTIFS(Bookings!$B$5:$B$304,$B9,Bookings!$F$5:$F$304,$D9,Bookings!$D$5:$D$304,"Cancelled")-COUNTIFS(Bookings!$B$5:$B$304,$B9,Bookings!$F$5:$F$304,$D9,Bookings!$D$5:$D$304,"Owner block")>0,"SAME-DAY TURN","No same-day guest")) -> No same-day guest | G9: =IFERROR(IF(INDEX(Bookings!$D$5:$D$304,MATCH($A9,Bookings!$A$5:$A$304,0))="Cancelled","—",IF(INDEX(Bookings!$I$5:$I$304,MATCH($A9,Bookings!$A$5:$A$304,0))="","—",INDEX(Bookings!$I$5:$I$304,MATCH($A9,Bookings!$A$5:$A$304,0)))),"—") -> 2 | H9: =IFERROR(IF(INDEX(Setup!$I$25:$I$36,MATCH($B9,Setup!$A$25:$A$36,0))=0,"—",INDEX(Setup!$I$25:$I$36,MATCH($B9,Setup!$A$25:$A$36,0))),"—") -> 1 | I9: =IFERROR(IF(INDEX(Setup!$E$25:$E$36,MATCH($B9,Setup!$A$25:$A$36,0))=0,"—",INDEX(Setup!$E$25:$E$36,MATCH($B9,Setup!$A$25:$A$36,0))),"—") -> 38 | J9: CleanCo (agency) | K9: Done | L9: EXAMPLE — agency invoices monthly.
A10: 6 | B10: =IFERROR(IF(INDEX(Bookings!$D$5:$D$304,MATCH($A10,Bookings!$A$5:$A$304,0))="Cancelled","—",IF(INDEX(Bookings!$B$5:$B$304,MATCH($A10,Bookings!$A$5:$A$304,0))="","—",INDEX(Bookings!$B$5:$B$304,MATCH($A10,Bookings!$A$5:$A$304,0)))),"—") -> Harbour Studio | C10: =IFERROR(IF(INDEX(Bookings!$D$5:$D$304,MATCH($A10,Bookings!$A$5:$A$304,0))="Cancelled","—",IF(INDEX(Bookings!$E$5:$E$304,MATCH($A10,Bookings!$A$5:$A$304,0))="","—",INDEX(Bookings!$E$5:$E$304,MATCH($A10,Bookings!$A$5:$A$304,0)))),"—") -> EXAMPLE — M. Silva | D10: =IFERROR(IF(INDEX(Bookings!$D$5:$D$304,MATCH($A10,Bookings!$A$5:$A$304,0))="Cancelled","—",IF(INDEX(Bookings!$G$5:$G$304,MATCH($A10,Bookings!$A$5:$A$304,0))="","—",INDEX(Bookings!$G$5:$G$304,MATCH($A10,Bookings!$A$5:$A$304,0)))),"—") -> 46217 | E10: =IF(NOT(ISNUMBER($D10)),"—",IF($D10<TODAY(),"Past",IF($D10=TODAY(),"TODAY",$D10-TODAY()))) -> Past | F10: =IF(OR(NOT(ISNUMBER($D10)),$B10="—",$B10=""),"—",IF(COUNTIFS(Bookings!$B$5:$B$304,$B10,Bookings!$F$5:$F$304,$D10)-COUNTIFS(Bookings!$B$5:$B$304,$B10,Bookings!$F$5:$F$304,$D10,Bookings!$D$5:$D$304,"Cancelled")-COUNTIFS(Bookings!$B$5:$B$304,$B10,Bookings!$F$5:$F$304,$D10,Bookings!$D$5:$D$304,"Owner block")>0,"SAME-DAY TURN","No same-day guest")) -> SAME-DAY TURN | G10: =IFERROR(IF(INDEX(Bookings!$D$5:$D$304,MATCH($A10,Bookings!$A$5:$A$304,0))="Cancelled","—",IF(INDEX(Bookings!$I$5:$I$304,MATCH($A10,Bookings!$A$5:$A$304,0))="","—",INDEX(Bookings!$I$5:$I$304,MATCH($A10,Bookings!$A$5:$A$304,0)))),"—") -> 2 | H10: =IFERROR(IF(INDEX(Setup!$I$25:$I$36,MATCH($B10,Setup!$A$25:$A$36,0))=0,"—",INDEX(Setup!$I$25:$I$36,MATCH($B10,Setup!$A$25:$A$36,0))),"—") -> 1 | I10: =IFERROR(IF(INDEX(Setup!$E$25:$E$36,MATCH($B10,Setup!$A$25:$A$36,0))=0,"—",INDEX(Setup!$E$25:$E$36,MATCH($B10,Setup!$A$25:$A$36,0))),"—") -> 38 | J10: CleanCo (agency) | K10: Done | L10: EXAMPLE — tight turn, next guest arrives 15:00.
A11: 7 | B11: =IFERROR(IF(INDEX(Bookings!$D$5:$D$304,MATCH($A11,Bookings!$A$5:$A$304,0))="Cancelled","—",IF(INDEX(Bookings!$B$5:$B$304,MATCH($A11,Bookings!$A$5:$A$304,0))="","—",INDEX(Bookings!$B$5:$B$304,MATCH($A11,Bookings!$A$5:$A$304,0)))),"—") -> Harbour Studio | C11: =IFERROR(IF(INDEX(Bookings!$D$5:$D$304,MATCH($A11,Bookings!$A$5:$A$304,0))="Cancelled","—",IF(INDEX(Bookings!$E$5:$E$304,MATCH($A11,Bookings!$A$5:$A$304,0))="","—",INDEX(Bookings!$E$5:$E$304,MATCH($A11,Bookings!$A$5:$A$304,0)))),"—") -> EXAMPLE — K. Owusu | D11: =IFERROR(IF(INDEX(Bookings!$D$5:$D$304,MATCH($A11,Bookings!$A$5:$A$304,0))="Cancelled","—",IF(INDEX(Bookings!$G$5:$G$304,MATCH($A11,Bookings!$A$5:$A$304,0))="","—",INDEX(Bookings!$G$5:$G$304,MATCH($A11,Bookings!$A$5:$A$304,0)))),"—") -> 46221 | E11: =IF(NOT(ISNUMBER($D11)),"—",IF($D11<TODAY(),"Past",IF($D11=TODAY(),"TODAY",$D11-TODAY()))) -> Past | F11: =IF(OR(NOT(ISNUMBER($D11)),$B11="—",$B11=""),"—",IF(COUNTIFS(Bookings!$B$5:$B$304,$B11,Bookings!$F$5:$F$304,$D11)-COUNTIFS(Bookings!$B$5:$B$304,$B11,Bookings!$F$5:$F$304,$D11,Bookings!$D$5:$D$304,"Cancelled")-COUNTIFS(Bookings!$B$5:$B$304,$B11,Bookings!$F$5:$F$304,$D11,Bookings!$D$5:$D$304,"Owner block")>0,"SAME-DAY TURN","No same-day guest")) -> No same-day guest | G11: =IFERROR(IF(INDEX(Bookings!$D$5:$D$304,MATCH($A11,Bookings!$A$5:$A$304,0))="Cancelled","—",IF(INDEX(Bookings!$I$5:$I$304,MATCH($A11,Bookings!$A$5:$A$304,0))="","—",INDEX(Bookings!$I$5:$I$304,MATCH($A11,Bookings!$A$5:$A$304,0)))),"—") -> 1 | H11: =IFERROR(IF(INDEX(Setup!$I$25:$I$36,MATCH($B11,Setup!$A$25:$A$36,0))=0,"—",INDEX(Setup!$I$25:$I$36,MATCH($B11,Setup!$A$25:$A$36,0))),"—") -> 1 | I11: =IFERROR(IF(INDEX(Setup!$E$25:$E$36,MATCH($B11,Setup!$A$25:$A$36,0))=0,"—",INDEX(Setup!$E$25:$E$36,MATCH($B11,Setup!$A$25:$A$36,0))),"—") -> 38 | J11: CleanCo (agency) | K11: Done
A12: 8 | B12: =IFERROR(IF(INDEX(Bookings!$D$5:$D$304,MATCH($A12,Bookings!$A$5:$A$304,0))="Cancelled","—",IF(INDEX(Bookings!$B$5:$B$304,MATCH($A12,Bookings!$A$5:$A$304,0))="","—",INDEX(Bookings!$B$5:$B$304,MATCH($A12,Bookings!$A$5:$A$304,0)))),"—") -> — | C12: =IFERROR(IF(INDEX(Bookings!$D$5:$D$304,MATCH($A12,Bookings!$A$5:$A$304,0))="Cancelled","—",IF(INDEX(Bookings!$E$5:$E$304,MATCH($A12,Bookings!$A$5:$A$304,0))="","—",INDEX(Bookings!$E$5:$E$304,MATCH($A12,Bookings!$A$5:$A$304,0)))),"—") -> — | D12: =IFERROR(IF(INDEX(Bookings!$D$5:$D$304,MATCH($A12,Bookings!$A$5:$A$304,0))="Cancelled","—",IF(INDEX(Bookings!$G$5:$G$304,MATCH($A12,Bookings!$A$5:$A$304,0))="","—",INDEX(Bookings!$G$5:$G$304,MATCH($A12,Bookings!$A$5:$A$304,0)))),"—") -> — | E12: =IF(NOT(ISNUMBER($D12)),"—",IF($D12<TODAY(),"Past",IF($D12=TODAY(),"TODAY",$D12-TODAY()))) -> — | F12: =IF(OR(NOT(ISNUMBER($D12)),$B12="—",$B12=""),"—",IF(COUNTIFS(Bookings!$B$5:$B$304,$B12,Bookings!$F$5:$F$304,$D12)-COUNTIFS(Bookings!$B$5:$B$304,$B12,Bookings!$F$5:$F$304,$D12,Bookings!$D$5:$D$304,"Cancelled")-COUNTIFS(Bookings!$B$5:$B$304,$B12,Bookings!$F$5:$F$304,$D12,Bookings!$D$5:$D$304,"Owner block")>0,"SAME-DAY TURN","No same-day guest")) -> — | G12: =IFERROR(IF(INDEX(Bookings!$D$5:$D$304,MATCH($A12,Bookings!$A$5:$A$304,0))="Cancelled","—",IF(INDEX(Bookings!$I$5:$I$304,MATCH($A12,Bookings!$A$5:$A$304,0))="","—",INDEX(Bookings!$I$5:$I$304,MATCH($A12,Bookings!$A$5:$A$304,0)))),"—") -> — | H12: =IFERROR(IF(INDEX(Setup!$I$25:$I$36,MATCH($B12,Setup!$A$25:$A$36,0))=0,"—",INDEX(Setup!$I$25:$I$36,MATCH($B12,Setup!$A$25:$A$36,0))),"—") -> — | I12: =IFERROR(IF(INDEX(Setup!$E$25:$E$36,MATCH($B12,Setup!$A$25:$A$36,0))=0,"—",INDEX(Setup!$E$25:$E$36,MATCH($B12,Setup!$A$25:$A$36,0))),"—") -> — | K12: Not scheduled
A13: 9 | B13: =IFERROR(IF(INDEX(Bookings!$D$5:$D$304,MATCH($A13,Bookings!$A$5:$A$304,0))="Cancelled","—",IF(INDEX(Bookings!$B$5:$B$304,MATCH($A13,Bookings!$A$5:$A$304,0))="","—",INDEX(Bookings!$B$5:$B$304,MATCH($A13,Bookings!$A$5:$A$304,0)))),"—") -> Garden Cottage | C13: =IFERROR(IF(INDEX(Bookings!$D$5:$D$304,MATCH($A13,Bookings!$A$5:$A$304,0))="Cancelled","—",IF(INDEX(Bookings!$E$5:$E$304,MATCH($A13,Bookings!$A$5:$A$304,0))="","—",INDEX(Bookings!$E$5:$E$304,MATCH($A13,Bookings!$A$5:$A$304,0)))),"—") -> EXAMPLE — Family Duarte | D13: =IFERROR(IF(INDEX(Bookings!$D$5:$D$304,MATCH($A13,Bookings!$A$5:$A$304,0))="Cancelled","—",IF(INDEX(Bookings!$G$5:$G$304,MATCH($A13,Bookings!$A$5:$A$304,0))="","—",INDEX(Bookings!$G$5:$G$304,MATCH($A13,Bookings!$A$5:$A$304,0)))),"—") -> 46212 | E13: =IF(NOT(ISNUMBER($D13)),"—",IF($D13<TODAY(),"Past",IF($D13=TODAY(),"TODAY",$D13-TODAY()))) -> Past | F13: =IF(OR(NOT(ISNUMBER($D13)),$B13="—",$B13=""),"—",IF(COUNTIFS(Bookings!$B$5:$B$304,$B13,Bookings!$F$5:$F$304,$D13)-COUNTIFS(Bookings!$B$5:$B$304,$B13,Bookings!$F$5:$F$304,$D13,Bookings!$D$5:$D$304,"Cancelled")-COUNTIFS(Bookings!$B$5:$B$304,$B13,Bookings!$F$5:$F$304,$D13,Bookings!$D$5:$D$304,"Owner block")>0,"SAME-DAY TURN","No same-day guest")) -> No same-day guest | G13: =IFERROR(IF(INDEX(Bookings!$D$5:$D$304,MATCH($A13,Bookings!$A$5:$A$304,0))="Cancelled","—",IF(INDEX(Bookings!$I$5:$I$304,MATCH($A13,Bookings!$A$5:$A$304,0))="","—",INDEX(Bookings!$I$5:$I$304,MATCH($A13,Bookings!$A$5:$A$304,0)))),"—") -> 6 | H13: =IFERROR(IF(INDEX(Setup!$I$25:$I$36,MATCH($B13,Setup!$A$25:$A$36,0))=0,"—",INDEX(Setup!$I$25:$I$36,MATCH($B13,Setup!$A$25:$A$36,0))),"—") -> 3 | I13: =IFERROR(IF(INDEX(Setup!$E$25:$E$36,MATCH($B13,Setup!$A$25:$A$36,0))=0,"—",INDEX(Setup!$E$25:$E$36,MATCH($B13,Setup!$A$25:$A$36,0))),"—") -> 60 | J13: Marco | K13: Done
A14: 10 | B14: =IFERROR(IF(INDEX(Bookings!$D$5:$D$304,MATCH($A14,Bookings!$A$5:$A$304,0))="Cancelled","—",IF(INDEX(Bookings!$B$5:$B$304,MATCH($A14,Bookings!$A$5:$A$304,0))="","—",INDEX(Bookings!$B$5:$B$304,MATCH($A14,Bookings!$A$5:$A$304,0)))),"—") -> Garden Cottage | C14: =IFERROR(IF(INDEX(Bookings!$D$5:$D$304,MATCH($A14,Bookings!$A$5:$A$304,0))="Cancelled","—",IF(INDEX(Bookings!$E$5:$E$304,MATCH($A14,Bookings!$A$5:$A$304,0))="","—",INDEX(Bookings!$E$5:$E$304,MATCH($A14,Bookings!$A$5:$A$304,0)))),"—") -> EXAMPLE — own stay, no income | D14: =IFERROR(IF(INDEX(Bookings!$D$5:$D$304,MATCH($A14,Bookings!$A$5:$A$304,0))="Cancelled","—",IF(INDEX(Bookings!$G$5:$G$304,MATCH($A14,Bookings!$A$5:$A$304,0))="","—",INDEX(Bookings!$G$5:$G$304,MATCH($A14,Bookings!$A$5:$A$304,0)))),"—") -> 46217 | E14: =IF(NOT(ISNUMBER($D14)),"—",IF($D14<TODAY(),"Past",IF($D14=TODAY(),"TODAY",$D14-TODAY()))) -> Past | F14: =IF(OR(NOT(ISNUMBER($D14)),$B14="—",$B14=""),"—",IF(COUNTIFS(Bookings!$B$5:$B$304,$B14,Bookings!$F$5:$F$304,$D14)-COUNTIFS(Bookings!$B$5:$B$304,$B14,Bookings!$F$5:$F$304,$D14,Bookings!$D$5:$D$304,"Cancelled")-COUNTIFS(Bookings!$B$5:$B$304,$B14,Bookings!$F$5:$F$304,$D14,Bookings!$D$5:$D$304,"Owner block")>0,"SAME-DAY TURN","No same-day guest")) -> No same-day guest | G14: =IFERROR(IF(INDEX(Bookings!$D$5:$D$304,MATCH($A14,Bookings!$A$5:$A$304,0))="Cancelled","—",IF(INDEX(Bookings!$I$5:$I$304,MATCH($A14,Bookings!$A$5:$A$304,0))="","—",INDEX(Bookings!$I$5:$I$304,MATCH($A14,Bookings!$A$5:$A$304,0)))),"—") -> 2 | H14: =IFERROR(IF(INDEX(Setup!$I$25:$I$36,MATCH($B14,Setup!$A$25:$A$36,0))=0,"—",INDEX(Setup!$I$25:$I$36,MATCH($B14,Setup!$A$25:$A$36,0))),"—") -> 3 | I14: =IFERROR(IF(INDEX(Setup!$E$25:$E$36,MATCH($B14,Setup!$A$25:$A$36,0))=0,"—",INDEX(Setup!$E$25:$E$36,MATCH($B14,Setup!$A$25:$A$36,0))),"—") -> 60 | J14: Me (owner) | K14: Issue | L14: EXAMPLE — shower drain blocked, plumber called.
A15: 11 | B15: =IFERROR(IF(INDEX(Bookings!$D$5:$D$304,MATCH($A15,Bookings!$A$5:$A$304,0))="Cancelled","—",IF(INDEX(Bookings!$B$5:$B$304,MATCH($A15,Bookings!$A$5:$A$304,0))="","—",INDEX(Bookings!$B$5:$B$304,MATCH($A15,Bookings!$A$5:$A$304,0)))),"—") -> Garden Cottage | C15: =IFERROR(IF(INDEX(Bookings!$D$5:$D$304,MATCH($A15,Bookings!$A$5:$A$304,0))="Cancelled","—",IF(INDEX(Bookings!$E$5:$E$304,MATCH($A15,Bookings!$A$5:$A$304,0))="","—",INDEX(Bookings!$E$5:$E$304,MATCH($A15,Bookings!$A$5:$A$304,0)))),"—") -> EXAMPLE — R. Lindqvist | D15: =IFERROR(IF(INDEX(Bookings!$D$5:$D$304,MATCH($A15,Bookings!$A$5:$A$304,0))="Cancelled","—",IF(INDEX(Bookings!$G$5:$G$304,MATCH($A15,Bookings!$A$5:$A$304,0))="","—",INDEX(Bookings!$G$5:$G$304,MATCH($A15,Bookings!$A$5:$A$304,0)))),"—") -> 46241 | E15: =IF(NOT(ISNUMBER($D15)),"—",IF($D15<TODAY(),"Past",IF($D15=TODAY(),"TODAY",$D15-TODAY()))) -> 9 | F15: =IF(OR(NOT(ISNUMBER($D15)),$B15="—",$B15=""),"—",IF(COUNTIFS(Bookings!$B$5:$B$304,$B15,Bookings!$F$5:$F$304,$D15)-COUNTIFS(Bookings!$B$5:$B$304,$B15,Bookings!$F$5:$F$304,$D15,Bookings!$D$5:$D$304,"Cancelled")-COUNTIFS(Bookings!$B$5:$B$304,$B15,Bookings!$F$5:$F$304,$D15,Bookings!$D$5:$D$304,"Owner block")>0,"SAME-DAY TURN","No same-day guest")) -> No same-day guest | G15: =IFERROR(IF(INDEX(Bookings!$D$5:$D$304,MATCH($A15,Bookings!$A$5:$A$304,0))="Cancelled","—",IF(INDEX(Bookings!$I$5:$I$304,MATCH($A15,Bookings!$A$5:$A$304,0))="","—",INDEX(Bookings!$I$5:$I$304,MATCH($A15,Bookings!$A$5:$A$304,0)))),"—") -> 5 | H15: =IFERROR(IF(INDEX(Setup!$I$25:$I$36,MATCH($B15,Setup!$A$25:$A$36,0))=0,"—",INDEX(Setup!$I$25:$I$36,MATCH($B15,Setup!$A$25:$A$36,0))),"—") -> 3 | I15: =IFERROR(IF(INDEX(Setup!$E$25:$E$36,MATCH($B15,Setup!$A$25:$A$36,0))=0,"—",INDEX(Setup!$E$25:$E$36,MATCH($B15,Setup!$A$25:$A$36,0))),"—") -> 60 | J15: Marco | K15: Scheduled
A16: 12 | B16: =IFERROR(IF(INDEX(Bookings!$D$5:$D$304,MATCH($A16,Bookings!$A$5:$A$304,0))="Cancelled","—",IF(INDEX(Bookings!$B$5:$B$304,MATCH($A16,Bookings!$A$5:$A$304,0))="","—",INDEX(Bookings!$B$5:$B$304,MATCH($A16,Bookings!$A$5:$A$304,0)))),"—") -> Riverside Loft | C16: =IFERROR(IF(INDEX(Bookings!$D$5:$D$304,MATCH($A16,Bookings!$A$5:$A$304,0))="Cancelled","—",IF(INDEX(Bookings!$E$5:$E$304,MATCH($A16,Bookings!$A$5:$A$304,0))="","—",INDEX(Bookings!$E$5:$E$304,MATCH($A16,Bookings!$A$5:$A$304,0)))),"—") -> EXAMPLE — stay across the month border | D16: =IFERROR(IF(INDEX(Bookings!$D$5:$D$304,MATCH($A16,Bookings!$A$5:$A$304,0))="Cancelled","—",IF(INDEX(Bookings!$G$5:$G$304,MATCH($A16,Bookings!$A$5:$A$304,0))="","—",INDEX(Bookings!$G$5:$G$304,MATCH($A16,Bookings!$A$5:$A$304,0)))),"—") -> 46206 | E16: =IF(NOT(ISNUMBER($D16)),"—",IF($D16<TODAY(),"Past",IF($D16=TODAY(),"TODAY",$D16-TODAY()))) -> Past | F16: =IF(OR(NOT(ISNUMBER($D16)),$B16="—",$B16=""),"—",IF(COUNTIFS(Bookings!$B$5:$B$304,$B16,Bookings!$F$5:$F$304,$D16)-COUNTIFS(Bookings!$B$5:$B$304,$B16,Bookings!$F$5:$F$304,$D16,Bookings!$D$5:$D$304,"Cancelled")-COUNTIFS(Bookings!$B$5:$B$304,$B16,Bookings!$F$5:$F$304,$D16,Bookings!$D$5:$D$304,"Owner block")>0,"SAME-DAY TURN","No same-day guest")) -> No same-day guest | G16: =IFERROR(IF(INDEX(Bookings!$D$5:$D$304,MATCH($A16,Bookings!$A$5:$A$304,0))="Cancelled","—",IF(INDEX(Bookings!$I$5:$I$304,MATCH($A16,Bookings!$A$5:$A$304,0))="","—",INDEX(Bookings!$I$5:$I$304,MATCH($A16,Bookings!$A$5:$A$304,0)))),"—") -> 2 | H16: =IFERROR(IF(INDEX(Setup!$I$25:$I$36,MATCH($B16,Setup!$A$25:$A$36,0))=0,"—",INDEX(Setup!$I$25:$I$36,MATCH($B16,Setup!$A$25:$A$36,0))),"—") -> 2 | I16: =IFERROR(IF(INDEX(Setup!$E$25:$E$36,MATCH($B16,Setup!$A$25:$A$36,0))=0,"—",INDEX(Setup!$E$25:$E$36,MATCH($B16,Setup!$A$25:$A$36,0))),"—") -> 45 | J16: Ana | K16: Done | L16: EXAMPLE — delete rows 5–16 (columns J to L) when you start with your own data.
A17: 13 | B17: =IFERROR(IF(INDEX(Bookings!$D$5:$D$304,MATCH($A17,Bookings!$A$5:$A$304,0))="Cancelled","—",IF(INDEX(Bookings!$B$5:$B$304,MATCH($A17,Bookings!$A$5:$A$304,0))="","—",INDEX(Bookings!$B$5:$B$304,MATCH($A17,Bookings!$A$5:$A$304,0)))),"—") -> — | C17: =IFERROR(IF(INDEX(Bookings!$D$5:$D$304,MATCH($A17,Bookings!$A$5:$A$304,0))="Cancelled","—",IF(INDEX(Bookings!$E$5:$E$304,MATCH($A17,Bookings!$A$5:$A$304,0))="","—",INDEX(Bookings!$E$5:$E$304,MATCH($A17,Bookings!$A$5:$A$304,0)))),"—") -> — | D17: =IFERROR(IF(INDEX(Bookings!$D$5:$D$304,MATCH($A17,Bookings!$A$5:$A$304,0))="Cancelled","—",IF(INDEX(Bookings!$G$5:$G$304,MATCH($A17,Bookings!$A$5:$A$304,0))="","—",INDEX(Bookings!$G$5:$G$304,MATCH($A17,Bookings!$A$5:$A$304,0)))),"—") -> — | E17: =IF(NOT(ISNUMBER($D17)),"—",IF($D17<TODAY(),"Past",IF($D17=TODAY(),"TODAY",$D17-TODAY()))) -> — | F17: =IF(OR(NOT(ISNUMBER($D17)),$B17="—",$B17=""),"—",IF(COUNTIFS(Bookings!$B$5:$B$304,$B17,Bookings!$F$5:$F$304,$D17)-COUNTIFS(Bookings!$B$5:$B$304,$B17,Bookings!$F$5:$F$304,$D17,Bookings!$D$5:$D$304,"Cancelled")-COUNTIFS(Bookings!$B$5:$B$304,$B17,Bookings!$F$5:$F$304,$D17,Bookings!$D$5:$D$304,"Owner block")>0,"SAME-DAY TURN","No same-day guest")) -> — | G17: =IFERROR(IF(INDEX(Bookings!$D$5:$D$304,MATCH($A17,Bookings!$A$5:$A$304,0))="Cancelled","—",IF(INDEX(Bookings!$I$5:$I$304,MATCH($A17,Bookings!$A$5:$A$304,0))="","—",INDEX(Bookings!$I$5:$I$304,MATCH($A17,Bookings!$A$5:$A$304,0)))),"—") -> — | H17: =IFERROR(IF(INDEX(Setup!$I$25:$I$36,MATCH($B17,Setup!$A$25:$A$36,0))=0,"—",INDEX(Setup!$I$25:$I$36,MATCH($B17,Setup!$A$25:$A$36,0))),"—") -> — | I17: =IFERROR(IF(INDEX(Setup!$E$25:$E$36,MATCH($B17,Setup!$A$25:$A$36,0))=0,"—",INDEX(Setup!$E$25:$E$36,MATCH($B17,Setup!$A$25:$A$36,0))),"—") -> —
A18: 14 | B18: =IFERROR(IF(INDEX(Bookings!$D$5:$D$304,MATCH($A18,Bookings!$A$5:$A$304,0))="Cancelled","—",IF(INDEX(Bookings!$B$5:$B$304,MATCH($A18,Bookings!$A$5:$A$304,0))="","—",INDEX(Bookings!$B$5:$B$304,MATCH($A18,Bookings!$A$5:$A$304,0)))),"—") -> — | C18: =IFERROR(IF(INDEX(Bookings!$D$5:$D$304,MATCH($A18,Bookings!$A$5:$A$304,0))="Cancelled","—",IF(INDEX(Bookings!$E$5:$E$304,MATCH($A18,Bookings!$A$5:$A$304,0))="","—",INDEX(Bookings!$E$5:$E$304,MATCH($A18,Bookings!$A$5:$A$304,0)))),"—") -> — | D18: =IFERROR(IF(INDEX(Bookings!$D$5:$D$304,MATCH($A18,Bookings!$A$5:$A$304,0))="Cancelled","—",IF(INDEX(Bookings!$G$5:$G$304,MATCH($A18,Bookings!$A$5:$A$304,0))="","—",INDEX(Bookings!$G$5:$G$304,MATCH($A18,Bookings!$A$5:$A$304,0)))),"—") -> — | E18: =IF(NOT(ISNUMBER($D18)),"—",IF($D18<TODAY(),"Past",IF($D18=TODAY(),"TODAY",$D18-TODAY()))) -> — | F18: =IF(OR(NOT(ISNUMBER($D18)),$B18="—",$B18=""),"—",IF(COUNTIFS(Bookings!$B$5:$B$304,$B18,Bookings!$F$5:$F$304,$D18)-COUNTIFS(Bookings!$B$5:$B$304,$B18,Bookings!$F$5:$F$304,$D18,Bookings!$D$5:$D$304,"Cancelled")-COUNTIFS(Bookings!$B$5:$B$304,$B18,Bookings!$F$5:$F$304,$D18,Bookings!$D$5:$D$304,"Owner block")>0,"SAME-DAY TURN","No same-day guest")) -> — | G18: =IFERROR(IF(INDEX(Bookings!$D$5:$D$304,MATCH($A18,Bookings!$A$5:$A$304,0))="Cancelled","—",IF(INDEX(Bookings!$I$5:$I$304,MATCH($A18,Bookings!$A$5:$A$304,0))="","—",INDEX(Bookings!$I$5:$I$304,MATCH($A18,Bookings!$A$5:$A$304,0)))),"—") -> — | H18: =IFERROR(IF(INDEX(Setup!$I$25:$I$36,MATCH($B18,Setup!$A$25:$A$36,0))=0,"—",INDEX(Setup!$I$25:$I$36,MATCH($B18,Setup!$A$25:$A$36,0))),"—") -> — | I18: =IFERROR(IF(INDEX(Setup!$E$25:$E$36,MATCH($B18,Setup!$A$25:$A$36,0))=0,"—",INDEX(Setup!$E$25:$E$36,MATCH($B18,Setup!$A$25:$A$36,0))),"—") -> —
A19: 15 | B19: =IFERROR(IF(INDEX(Bookings!$D$5:$D$304,MATCH($A19,Bookings!$A$5:$A$304,0))="Cancelled","—",IF(INDEX(Bookings!$B$5:$B$304,MATCH($A19,Bookings!$A$5:$A$304,0))="","—",INDEX(Bookings!$B$5:$B$304,MATCH($A19,Bookings!$A$5:$A$304,0)))),"—") -> — | C19: =IFERROR(IF(INDEX(Bookings!$D$5:$D$304,MATCH($A19,Bookings!$A$5:$A$304,0))="Cancelled","—",IF(INDEX(Bookings!$E$5:$E$304,MATCH($A19,Bookings!$A$5:$A$304,0))="","—",INDEX(Bookings!$E$5:$E$304,MATCH($A19,Bookings!$A$5:$A$304,0)))),"—") -> — | D19: =IFERROR(IF(INDEX(Bookings!$D$5:$D$304,MATCH($A19,Bookings!$A$5:$A$304,0))="Cancelled","—",IF(INDEX(Bookings!$G$5:$G$304,MATCH($A19,Bookings!$A$5:$A$304,0))="","—",INDEX(Bookings!$G$5:$G$304,MATCH($A19,Bookings!$A$5:$A$304,0)))),"—") -> — | E19: =IF(NOT(ISNUMBER($D19)),"—",IF($D19<TODAY(),"Past",IF($D19=TODAY(),"TODAY",$D19-TODAY()))) -> — | F19: =IF(OR(NOT(ISNUMBER($D19)),$B19="—",$B19=""),"—",IF(COUNTIFS(Bookings!$B$5:$B$304,$B19,Bookings!$F$5:$F$304,$D19)-COUNTIFS(Bookings!$B$5:$B$304,$B19,Bookings!$F$5:$F$304,$D19,Bookings!$D$5:$D$304,"Cancelled")-COUNTIFS(Bookings!$B$5:$B$304,$B19,Bookings!$F$5:$F$304,$D19,Bookings!$D$5:$D$304,"Owner block")>0,"SAME-DAY TURN","No same-day guest")) -> — | G19: =IFERROR(IF(INDEX(Bookings!$D$5:$D$304,MATCH($A19,Bookings!$A$5:$A$304,0))="Cancelled","—",IF(INDEX(Bookings!$I$5:$I$304,MATCH($A19,Bookings!$A$5:$A$304,0))="","—",INDEX(Bookings!$I$5:$I$304,MATCH($A19,Bookings!$A$5:$A$304,0)))),"—") -> — | H19: =IFERROR(IF(INDEX(Setup!$I$25:$I$36,MATCH($B19,Setup!$A$25:$A$36,0))=0,"—",INDEX(Setup!$I$25:$I$36,MATCH($B19,Setup!$A$25:$A$36,0))),"—") -> — | I19: =IFERROR(IF(INDEX(Setup!$E$25:$E$36,MATCH($B19,Setup!$A$25:$A$36,0))=0,"—",INDEX(Setup!$E$25:$E$36,MATCH($B19,Setup!$A$25:$A$36,0))),"—") -> —
A20: 16 | B20: =IFERROR(IF(INDEX(Bookings!$D$5:$D$304,MATCH($A20,Bookings!$A$5:$A$304,0))="Cancelled","—",IF(INDEX(Bookings!$B$5:$B$304,MATCH($A20,Bookings!$A$5:$A$304,0))="","—",INDEX(Bookings!$B$5:$B$304,MATCH($A20,Bookings!$A$5:$A$304,0)))),"—") -> — | C20: =IFERROR(IF(INDEX(Bookings!$D$5:$D$304,MATCH($A20,Bookings!$A$5:$A$304,0))="Cancelled","—",IF(INDEX(Bookings!$E$5:$E$304,MATCH($A20,Bookings!$A$5:$A$304,0))="","—",INDEX(Bookings!$E$5:$E$304,MATCH($A20,Bookings!$A$5:$A$304,0)))),"—") -> — | D20: =IFERROR(IF(INDEX(Bookings!$D$5:$D$304,MATCH($A20,Bookings!$A$5:$A$304,0))="Cancelled","—",IF(INDEX(Bookings!$G$5:$G$304,MATCH($A20,Bookings!$A$5:$A$304,0))="","—",INDEX(Bookings!$G$5:$G$304,MATCH($A20,Bookings!$A$5:$A$304,0)))),"—") -> — | E20: =IF(NOT(ISNUMBER($D20)),"—",IF($D20<TODAY(),"Past",IF($D20=TODAY(),"TODAY",$D20-TODAY()))) -> — | F20: =IF(OR(NOT(ISNUMBER($D20)),$B20="—",$B20=""),"—",IF(COUNTIFS(Bookings!$B$5:$B$304,$B20,Bookings!$F$5:$F$304,$D20)-COUNTIFS(Bookings!$B$5:$B$304,$B20,Bookings!$F$5:$F$304,$D20,Bookings!$D$5:$D$304,"Cancelled")-COUNTIFS(Bookings!$B$5:$B$304,$B20,Bookings!$F$5:$F$304,$D20,Bookings!$D$5:$D$304,"Owner block")>0,"SAME-DAY TURN","No same-day guest")) -> — | G20: =IFERROR(IF(INDEX(Bookings!$D$5:$D$304,MATCH($A20,Bookings!$A$5:$A$304,0))="Cancelled","—",IF(INDEX(Bookings!$I$5:$I$304,MATCH($A20,Bookings!$A$5:$A$304,0))="","—",INDEX(Bookings!$I$5:$I$304,MATCH($A20,Bookings!$A$5:$A$304,0)))),"—") -> — | H20: =IFERROR(IF(INDEX(Setup!$I$25:$I$36,MATCH($B20,Setup!$A$25:$A$36,0))=0,"—",INDEX(Setup!$I$25:$I$36,MATCH($B20,Setup!$A$25:$A$36,0))),"—") -> — | I20: =IFERROR(IF(INDEX(Setup!$E$25:$E$36,MATCH($B20,Setup!$A$25:$A$36,0))=0,"—",INDEX(Setup!$E$25:$E$36,MATCH($B20,Setup!$A$25:$A$36,0))),"—") -> —
A21: 17 | B21: =IFERROR(IF(INDEX(Bookings!$D$5:$D$304,MATCH($A21,Bookings!$A$5:$A$304,0))="Cancelled","—",IF(INDEX(Bookings!$B$5:$B$304,MATCH($A21,Bookings!$A$5:$A$304,0))="","—",INDEX(Bookings!$B$5:$B$304,MATCH($A21,Bookings!$A$5:$A$304,0)))),"—") -> — | C21: =IFERROR(IF(INDEX(Bookings!$D$5:$D$304,MATCH($A21,Bookings!$A$5:$A$304,0))="Cancelled","—",IF(INDEX(Bookings!$E$5:$E$304,MATCH($A21,Bookings!$A$5:$A$304,0))="","—",INDEX(Bookings!$E$5:$E$304,MATCH($A21,Bookings!$A$5:$A$304,0)))),"—") -> — | D21: =IFERROR(IF(INDEX(Bookings!$D$5:$D$304,MATCH($A21,Bookings!$A$5:$A$304,0))="Cancelled","—",IF(INDEX(Bookings!$G$5:$G$304,MATCH($A21,Bookings!$A$5:$A$304,0))="","—",INDEX(Bookings!$G$5:$G$304,MATCH($A21,Bookings!$A$5:$A$304,0)))),"—") -> — | E21: =IF(NOT(ISNUMBER($D21)),"—",IF($D21<TODAY(),"Past",IF($D21=TODAY(),"TODAY",$D21-TODAY()))) -> — | F21: =IF(OR(NOT(ISNUMBER($D21)),$B21="—",$B21=""),"—",IF(COUNTIFS(Bookings!$B$5:$B$304,$B21,Bookings!$F$5:$F$304,$D21)-COUNTIFS(Bookings!$B$5:$B$304,$B21,Bookings!$F$5:$F$304,$D21,Bookings!$D$5:$D$304,"Cancelled")-COUNTIFS(Bookings!$B$5:$B$304,$B21,Bookings!$F$5:$F$304,$D21,Bookings!$D$5:$D$304,"Owner block")>0,"SAME-DAY TURN","No same-day guest")) -> — | G21: =IFERROR(IF(INDEX(Bookings!$D$5:$D$304,MATCH($A21,Bookings!$A$5:$A$304,0))="Cancelled","—",IF(INDEX(Bookings!$I$5:$I$304,MATCH($A21,Bookings!$A$5:$A$304,0))="","—",INDEX(Bookings!$I$5:$I$304,MATCH($A21,Bookings!$A$5:$A$304,0)))),"—") -> — | H21: =IFERROR(IF(INDEX(Setup!$I$25:$I$36,MATCH($B21,Setup!$A$25:$A$36,0))=0,"—",INDEX(Setup!$I$25:$I$36,MATCH($B21,Setup!$A$25:$A$36,0))),"—") -> — | I21: =IFERROR(IF(INDEX(Setup!$E$25:$E$36,MATCH($B21,Setup!$A$25:$A$36,0))=0,"—",INDEX(Setup!$E$25:$E$36,MATCH($B21,Setup!$A$25:$A$36,0))),"—") -> —
A22: 18 | B22: =IFERROR(IF(INDEX(Bookings!$D$5:$D$304,MATCH($A22,Bookings!$A$5:$A$304,0))="Cancelled","—",IF(INDEX(Bookings!$B$5:$B$304,MATCH($A22,Bookings!$A$5:$A$304,0))="","—",INDEX(Bookings!$B$5:$B$304,MATCH($A22,Bookings!$A$5:$A$304,0)))),"—") -> — | C22: =IFERROR(IF(INDEX(Bookings!$D$5:$D$304,MATCH($A22,Bookings!$A$5:$A$304,0))="Cancelled","—",IF(INDEX(Bookings!$E$5:$E$304,MATCH($A22,Bookings!$A$5:$A$304,0))="","—",INDEX(Bookings!$E$5:$E$304,MATCH($A22,Bookings!$A$5:$A$304,0)))),"—") -> — | D22: =IFERROR(IF(INDEX(Bookings!$D$5:$D$304,MATCH($A22,Bookings!$A$5:$A$304,0))="Cancelled","—",IF(INDEX(Bookings!$G$5:$G$304,MATCH($A22,Bookings!$A$5:$A$304,0))="","—",INDEX(Bookings!$G$5:$G$304,MATCH($A22,Bookings!$A$5:$A$304,0)))),"—") -> — | E22: =IF(NOT(ISNUMBER($D22)),"—",IF($D22<TODAY(),"Past",IF($D22=TODAY(),"TODAY",$D22-TODAY()))) -> — | F22: =IF(OR(NOT(ISNUMBER($D22)),$B22="—",$B22=""),"—",IF(COUNTIFS(Bookings!$B$5:$B$304,$B22,Bookings!$F$5:$F$304,$D22)-COUNTIFS(Bookings!$B$5:$B$304,$B22,Bookings!$F$5:$F$304,$D22,Bookings!$D$5:$D$304,"Cancelled")-COUNTIFS(Bookings!$B$5:$B$304,$B22,Bookings!$F$5:$F$304,$D22,Bookings!$D$5:$D$304,"Owner block")>0,"SAME-DAY TURN","No same-day guest")) -> — | G22: =IFERROR(IF(INDEX(Bookings!$D$5:$D$304,MATCH($A22,Bookings!$A$5:$A$304,0))="Cancelled","—",IF(INDEX(Bookings!$I$5:$I$304,MATCH($A22,Bookings!$A$5:$A$304,0))="","—",INDEX(Bookings!$I$5:$I$304,MATCH($A22,Bookings!$A$5:$A$304,0)))),"—") -> — | H22: =IFERROR(IF(INDEX(Setup!$I$25:$I$36,MATCH($B22,Setup!$A$25:$A$36,0))=0,"—",INDEX(Setup!$I$25:$I$36,MATCH($B22,Setup!$A$25:$A$36,0))),"—") -> — | I22: =IFERROR(IF(INDEX(Setup!$E$25:$E$36,MATCH($B22,Setup!$A$25:$A$36,0))=0,"—",INDEX(Setup!$E$25:$E$36,MATCH($B22,Setup!$A$25:$A$36,0))),"—") -> —
A23: 19 | B23: =IFERROR(IF(INDEX(Bookings!$D$5:$D$304,MATCH($A23,Bookings!$A$5:$A$304,0))="Cancelled","—",IF(INDEX(Bookings!$B$5:$B$304,MATCH($A23,Bookings!$A$5:$A$304,0))="","—",INDEX(Bookings!$B$5:$B$304,MATCH($A23,Bookings!$A$5:$A$304,0)))),"—") -> — | C23: =IFERROR(IF(INDEX(Bookings!$D$5:$D$304,MATCH($A23,Bookings!$A$5:$A$304,0))="Cancelled","—",IF(INDEX(Bookings!$E$5:$E$304,MATCH($A23,Bookings!$A$5:$A$304,0))="","—",INDEX(Bookings!$E$5:$E$304,MATCH($A23,Bookings!$A$5:$A$304,0)))),"—") -> — | D23: =IFERROR(IF(INDEX(Bookings!$D$5:$D$304,MATCH($A23,Bookings!$A$5:$A$304,0))="Cancelled","—",IF(INDEX(Bookings!$G$5:$G$304,MATCH($A23,Bookings!$A$5:$A$304,0))="","—",INDEX(Bookings!$G$5:$G$304,MATCH($A23,Bookings!$A$5:$A$304,0)))),"—") -> — | E23: =IF(NOT(ISNUMBER($D23)),"—",IF($D23<TODAY(),"Past",IF($D23=TODAY(),"TODAY",$D23-TODAY()))) -> — | F23: =IF(OR(NOT(ISNUMBER($D23)),$B23="—",$B23=""),"—",IF(COUNTIFS(Bookings!$B$5:$B$304,$B23,Bookings!$F$5:$F$304,$D23)-COUNTIFS(Bookings!$B$5:$B$304,$B23,Bookings!$F$5:$F$304,$D23,Bookings!$D$5:$D$304,"Cancelled")-COUNTIFS(Bookings!$B$5:$B$304,$B23,Bookings!$F$5:$F$304,$D23,Bookings!$D$5:$D$304,"Owner block")>0,"SAME-DAY TURN","No same-day guest")) -> — | G23: =IFERROR(IF(INDEX(Bookings!$D$5:$D$304,MATCH($A23,Bookings!$A$5:$A$304,0))="Cancelled","—",IF(INDEX(Bookings!$I$5:$I$304,MATCH($A23,Bookings!$A$5:$A$304,0))="","—",INDEX(Bookings!$I$5:$I$304,MATCH($A23,Bookings!$A$5:$A$304,0)))),"—") -> — | H23: =IFERROR(IF(INDEX(Setup!$I$25:$I$36,MATCH($B23,Setup!$A$25:$A$36,0))=0,"—",INDEX(Setup!$I$25:$I$36,MATCH($B23,Setup!$A$25:$A$36,0))),"—") -> — | I23: =IFERROR(IF(INDEX(Setup!$E$25:$E$36,MATCH($B23,Setup!$A$25:$A$36,0))=0,"—",INDEX(Setup!$E$25:$E$36,MATCH($B23,Setup!$A$25:$A$36,0))),"—") -> —
A24: 20 | B24: =IFERROR(IF(INDEX(Bookings!$D$5:$D$304,MATCH($A24,Bookings!$A$5:$A$304,0))="Cancelled","—",IF(INDEX(Bookings!$B$5:$B$304,MATCH($A24,Bookings!$A$5:$A$304,0))="","—",INDEX(Bookings!$B$5:$B$304,MATCH($A24,Bookings!$A$5:$A$304,0)))),"—") -> — | C24: =IFERROR(IF(INDEX(Bookings!$D$5:$D$304,MATCH($A24,Bookings!$A$5:$A$304,0))="Cancelled","—",IF(INDEX(Bookings!$E$5:$E$304,MATCH($A24,Bookings!$A$5:$A$304,0))="","—",INDEX(Bookings!$E$5:$E$304,MATCH($A24,Bookings!$A$5:$A$304,0)))),"—") -> — | D24: =IFERROR(IF(INDEX(Bookings!$D$5:$D$304,MATCH($A24,Bookings!$A$5:$A$304,0))="Cancelled","—",IF(INDEX(Bookings!$G$5:$G$304,MATCH($A24,Bookings!$A$5:$A$304,0))="","—",INDEX(Bookings!$G$5:$G$304,MATCH($A24,Bookings!$A$5:$A$304,0)))),"—") -> — | E24: =IF(NOT(ISNUMBER($D24)),"—",IF($D24<TODAY(),"Past",IF($D24=TODAY(),"TODAY",$D24-TODAY()))) -> — | F24: =IF(OR(NOT(ISNUMBER($D24)),$B24="—",$B24=""),"—",IF(COUNTIFS(Bookings!$B$5:$B$304,$B24,Bookings!$F$5:$F$304,$D24)-COUNTIFS(Bookings!$B$5:$B$304,$B24,Bookings!$F$5:$F$304,$D24,Bookings!$D$5:$D$304,"Cancelled")-COUNTIFS(Bookings!$B$5:$B$304,$B24,Bookings!$F$5:$F$304,$D24,Bookings!$D$5:$D$304,"Owner block")>0,"SAME-DAY TURN","No same-day guest")) -> — | G24: =IFERROR(IF(INDEX(Bookings!$D$5:$D$304,MATCH($A24,Bookings!$A$5:$A$304,0))="Cancelled","—",IF(INDEX(Bookings!$I$5:$I$304,MATCH($A24,Bookings!$A$5:$A$304,0))="","—",INDEX(Bookings!$I$5:$I$304,MATCH($A24,Bookings!$A$5:$A$304,0)))),"—") -> — | H24: =IFERROR(IF(INDEX(Setup!$I$25:$I$36,MATCH($B24,Setup!$A$25:$A$36,0))=0,"—",INDEX(Setup!$I$25:$I$36,MATCH($B24,Setup!$A$25:$A$36,0))),"—") -> — | I24: =IFERROR(IF(INDEX(Setup!$E$25:$E$36,MATCH($B24,Setup!$A$25:$A$36,0))=0,"—",INDEX(Setup!$E$25:$E$36,MATCH($B24,Setup!$A$25:$A$36,0))),"—") -> —
A25: 21 | B25: =IFERROR(IF(INDEX(Bookings!$D$5:$D$304,MATCH($A25,Bookings!$A$5:$A$304,0))="Cancelled","—",IF(INDEX(Bookings!$B$5:$B$304,MATCH($A25,Bookings!$A$5:$A$304,0))="","—",INDEX(Bookings!$B$5:$B$304,MATCH($A25,Bookings!$A$5:$A$304,0)))),"—") -> — | C25: =IFERROR(IF(INDEX(Bookings!$D$5:$D$304,MATCH($A25,Bookings!$A$5:$A$304,0))="Cancelled","—",IF(INDEX(Bookings!$E$5:$E$304,MATCH($A25,Bookings!$A$5:$A$304,0))="","—",INDEX(Bookings!$E$5:$E$304,MATCH($A25,Bookings!$A$5:$A$304,0)))),"—") -> — | D25: =IFERROR(IF(INDEX(Bookings!$D$5:$D$304,MATCH($A25,Bookings!$A$5:$A$304,0))="Cancelled","—",IF(INDEX(Bookings!$G$5:$G$304,MATCH($A25,Bookings!$A$5:$A$304,0))="","—",INDEX(Bookings!$G$5:$G$304,MATCH($A25,Bookings!$A$5:$A$304,0)))),"—") -> — | E25: =IF(NOT(ISNUMBER($D25)),"—",IF($D25<TODAY(),"Past",IF($D25=TODAY(),"TODAY",$D25-TODAY()))) -> — | F25: =IF(OR(NOT(ISNUMBER($D25)),$B25="—",$B25=""),"—",IF(COUNTIFS(Bookings!$B$5:$B$304,$B25,Bookings!$F$5:$F$304,$D25)-COUNTIFS(Bookings!$B$5:$B$304,$B25,Bookings!$F$5:$F$304,$D25,Bookings!$D$5:$D$304,"Cancelled")-COUNTIFS(Bookings!$B$5:$B$304,$B25,Bookings!$F$5:$F$304,$D25,Bookings!$D$5:$D$304,"Owner block")>0,"SAME-DAY TURN","No same-day guest")) -> — | G25: =IFERROR(IF(INDEX(Bookings!$D$5:$D$304,MATCH($A25,Bookings!$A$5:$A$304,0))="Cancelled","—",IF(INDEX(Bookings!$I$5:$I$304,MATCH($A25,Bookings!$A$5:$A$304,0))="","—",INDEX(Bookings!$I$5:$I$304,MATCH($A25,Bookings!$A$5:$A$304,0)))),"—") -> — | H25: =IFERROR(IF(INDEX(Setup!$I$25:$I$36,MATCH($B25,Setup!$A$25:$A$36,0))=0,"—",INDEX(Setup!$I$25:$I$36,MATCH($B25,Setup!$A$25:$A$36,0))),"—") -> — | I25: =IFERROR(IF(INDEX(Setup!$E$25:$E$36,MATCH($B25,Setup!$A$25:$A$36,0))=0,"—",INDEX(Setup!$E$25:$E$36,MATCH($B25,Setup!$A$25:$A$36,0))),"—") -> —
A26: 22 | B26: =IFERROR(IF(INDEX(Bookings!$D$5:$D$304,MATCH($A26,Bookings!$A$5:$A$304,0))="Cancelled","—",IF(INDEX(Bookings!$B$5:$B$304,MATCH($A26,Bookings!$A$5:$A$304,0))="","—",INDEX(Bookings!$B$5:$B$304,MATCH($A26,Bookings!$A$5:$A$304,0)))),"—") -> — | C26: =IFERROR(IF(INDEX(Bookings!$D$5:$D$304,MATCH($A26,Bookings!$A$5:$A$304,0))="Cancelled","—",IF(INDEX(Bookings!$E$5:$E$304,MATCH($A26,Bookings!$A$5:$A$304,0))="","—",INDEX(Bookings!$E$5:$E$304,MATCH($A26,Bookings!$A$5:$A$304,0)))),"—") -> — | D26: =IFERROR(IF(INDEX(Bookings!$D$5:$D$304,MATCH($A26,Bookings!$A$5:$A$304,0))="Cancelled","—",IF(INDEX(Bookings!$G$5:$G$304,MATCH($A26,Bookings!$A$5:$A$304,0))="","—",INDEX(Bookings!$G$5:$G$304,MATCH($A26,Bookings!$A$5:$A$304,0)))),"—") -> — | E26: =IF(NOT(ISNUMBER($D26)),"—",IF($D26<TODAY(),"Past",IF($D26=TODAY(),"TODAY",$D26-TODAY()))) -> — | F26: =IF(OR(NOT(ISNUMBER($D26)),$B26="—",$B26=""),"—",IF(COUNTIFS(Bookings!$B$5:$B$304,$B26,Bookings!$F$5:$F$304,$D26)-COUNTIFS(Bookings!$B$5:$B$304,$B26,Bookings!$F$5:$F$304,$D26,Bookings!$D$5:$D$304,"Cancelled")-COUNTIFS(Bookings!$B$5:$B$304,$B26,Bookings!$F$5:$F$304,$D26,Bookings!$D$5:$D$304,"Owner block")>0,"SAME-DAY TURN","No same-day guest")) -> — | G26: =IFERROR(IF(INDEX(Bookings!$D$5:$D$304,MATCH($A26,Bookings!$A$5:$A$304,0))="Cancelled","—",IF(INDEX(Bookings!$I$5:$I$304,MATCH($A26,Bookings!$A$5:$A$304,0))="","—",INDEX(Bookings!$I$5:$I$304,MATCH($A26,Bookings!$A$5:$A$304,0)))),"—") -> — | H26: =IFERROR(IF(INDEX(Setup!$I$25:$I$36,MATCH($B26,Setup!$A$25:$A$36,0))=0,"—",INDEX(Setup!$I$25:$I$36,MATCH($B26,Setup!$A$25:$A$36,0))),"—") -> — | I26: =IFERROR(IF(INDEX(Setup!$E$25:$E$36,MATCH($B26,Setup!$A$25:$A$36,0))=0,"—",INDEX(Setup!$E$25:$E$36,MATCH($B26,Setup!$A$25:$A$36,0))),"—") -> —
A27: 23 | B27: =IFERROR(IF(INDEX(Bookings!$D$5:$D$304,MATCH($A27,Bookings!$A$5:$A$304,0))="Cancelled","—",IF(INDEX(Bookings!$B$5:$B$304,MATCH($A27,Bookings!$A$5:$A$304,0))="","—",INDEX(Bookings!$B$5:$B$304,MATCH($A27,Bookings!$A$5:$A$304,0)))),"—") -> — | C27: =IFERROR(IF(INDEX(Bookings!$D$5:$D$304,MATCH($A27,Bookings!$A$5:$A$304,0))="Cancelled","—",IF(INDEX(Bookings!$E$5:$E$304,MATCH($A27,Bookings!$A$5:$A$304,0))="","—",INDEX(Bookings!$E$5:$E$304,MATCH($A27,Bookings!$A$5:$A$304,0)))),"—") -> — | D27: =IFERROR(IF(INDEX(Bookings!$D$5:$D$304,MATCH($A27,Bookings!$A$5:$A$304,0))="Cancelled","—",IF(INDEX(Bookings!$G$5:$G$304,MATCH($A27,Bookings!$A$5:$A$304,0))="","—",INDEX(Bookings!$G$5:$G$304,MATCH($A27,Bookings!$A$5:$A$304,0)))),"—") -> — | E27: =IF(NOT(ISNUMBER($D27)),"—",IF($D27<TODAY(),"Past",IF($D27=TODAY(),"TODAY",$D27-TODAY()))) -> — | F27: =IF(OR(NOT(ISNUMBER($D27)),$B27="—",$B27=""),"—",IF(COUNTIFS(Bookings!$B$5:$B$304,$B27,Bookings!$F$5:$F$304,$D27)-COUNTIFS(Bookings!$B$5:$B$304,$B27,Bookings!$F$5:$F$304,$D27,Bookings!$D$5:$D$304,"Cancelled")-COUNTIFS(Bookings!$B$5:$B$304,$B27,Bookings!$F$5:$F$304,$D27,Bookings!$D$5:$D$304,"Owner block")>0,"SAME-DAY TURN","No same-day guest")) -> — | G27: =IFERROR(IF(INDEX(Bookings!$D$5:$D$304,MATCH($A27,Bookings!$A$5:$A$304,0))="Cancelled","—",IF(INDEX(Bookings!$I$5:$I$304,MATCH($A27,Bookings!$A$5:$A$304,0))="","—",INDEX(Bookings!$I$5:$I$304,MATCH($A27,Bookings!$A$5:$A$304,0)))),"—") -> — | H27: =IFERROR(IF(INDEX(Setup!$I$25:$I$36,MATCH($B27,Setup!$A$25:$A$36,0))=0,"—",INDEX(Setup!$I$25:$I$36,MATCH($B27,Setup!$A$25:$A$36,0))),"—") -> — | I27: =IFERROR(IF(INDEX(Setup!$E$25:$E$36,MATCH($B27,Setup!$A$25:$A$36,0))=0,"—",INDEX(Setup!$E$25:$E$36,MATCH($B27,Setup!$A$25:$A$36,0))),"—") -> —
A28: 24 | B28: =IFERROR(IF(INDEX(Bookings!$D$5:$D$304,MATCH($A28,Bookings!$A$5:$A$304,0))="Cancelled","—",IF(INDEX(Bookings!$B$5:$B$304,MATCH($A28,Bookings!$A$5:$A$304,0))="","—",INDEX(Bookings!$B$5:$B$304,MATCH($A28,Bookings!$A$5:$A$304,0)))),"—") -> — | C28: =IFERROR(IF(INDEX(Bookings!$D$5:$D$304,MATCH($A28,Bookings!$A$5:$A$304,0))="Cancelled","—",IF(INDEX(Bookings!$E$5:$E$304,MATCH($A28,Bookings!$A$5:$A$304,0))="","—",INDEX(Bookings!$E$5:$E$304,MATCH($A28,Bookings!$A$5:$A$304,0)))),"—") -> — | D28: =IFERROR(IF(INDEX(Bookings!$D$5:$D$304,MATCH($A28,Bookings!$A$5:$A$304,0))="Cancelled","—",IF(INDEX(Bookings!$G$5:$G$304,MATCH($A28,Bookings!$A$5:$A$304,0))="","—",INDEX(Bookings!$G$5:$G$304,MATCH($A28,Bookings!$A$5:$A$304,0)))),"—") -> — | E28: =IF(NOT(ISNUMBER($D28)),"—",IF($D28<TODAY(),"Past",IF($D28=TODAY(),"TODAY",$D28-TODAY()))) -> — | F28: =IF(OR(NOT(ISNUMBER($D28)),$B28="—",$B28=""),"—",IF(COUNTIFS(Bookings!$B$5:$B$304,$B28,Bookings!$F$5:$F$304,$D28)-COUNTIFS(Bookings!$B$5:$B$304,$B28,Bookings!$F$5:$F$304,$D28,Bookings!$D$5:$D$304,"Cancelled")-COUNTIFS(Bookings!$B$5:$B$304,$B28,Bookings!$F$5:$F$304,$D28,Bookings!$D$5:$D$304,"Owner block")>0,"SAME-DAY TURN","No same-day guest")) -> — | G28: =IFERROR(IF(INDEX(Bookings!$D$5:$D$304,MATCH($A28,Bookings!$A$5:$A$304,0))="Cancelled","—",IF(INDEX(Bookings!$I$5:$I$304,MATCH($A28,Bookings!$A$5:$A$304,0))="","—",INDEX(Bookings!$I$5:$I$304,MATCH($A28,Bookings!$A$5:$A$304,0)))),"—") -> — | H28: =IFERROR(IF(INDEX(Setup!$I$25:$I$36,MATCH($B28,Setup!$A$25:$A$36,0))=0,"—",INDEX(Setup!$I$25:$I$36,MATCH($B28,Setup!$A$25:$A$36,0))),"—") -> — | I28: =IFERROR(IF(INDEX(Setup!$E$25:$E$36,MATCH($B28,Setup!$A$25:$A$36,0))=0,"—",INDEX(Setup!$E$25:$E$36,MATCH($B28,Setup!$A$25:$A$36,0))),"—") -> —
... A304: 300 | B304: =IFERROR(IF(INDEX(Bookings!$D$5:$D$304,MATCH($A304,Bookings!$A$5:$A$304,0))="Cancelled","—",IF(INDEX(Bookings!$B$5:$B$304,MATCH($A304,Bookings!$A$5:$A$304,0))="","—",INDEX(Bookings!$B$5:$B$304,MATCH($A304,Bookings!$A$5:$A$304,0)))),"—") -> — | C304: =IFERROR(IF(INDEX(Bookings!$D$5:$D$304,MATCH($A304,Bookings!$A$5:$A$304,0))="Cancelled","—",IF(INDEX(Bookings!$E$5:$E$304,MATCH($A304,Bookings!$A$5:$A$304,0))="","—",INDEX(Bookings!$E$5:$E$304,MATCH($A304,Bookings!$A$5:$A$304,0)))),"—") -> — | D304: =IFERROR(IF(INDEX(Bookings!$D$5:$D$304,MATCH($A304,Bookings!$A$5:$A$304,0))="Cancelled","—",IF(INDEX(Bookings!$G$5:$G$304,MATCH($A304,Bookings!$A$5:$A$304,0))="","—",INDEX(Bookings!$G$5:$G$304,MATCH($A304,Bookings!$A$5:$A$304,0)))),"—") -> — | E304: =IF(NOT(ISNUMBER($D304)),"—",IF($D304<TODAY(),"Past",IF($D304=TODAY(),"TODAY",$D304-TODAY()))) -> — | F304: =IF(OR(NOT(ISNUMBER($D304)),$B304="—",$B304=""),"—",IF(COUNTIFS(Bookings!$B$5:$B$304,$B304,Bookings!$F$5:$F$304,$D304)-COUNTIFS(Bookings!$B$5:$B$304,$B304,Bookings!$F$5:$F$304,$D304,Bookings!$D$5:$D$304,"Cancelled")-COUNTIFS(Bookings!$B$5:$B$304,$B304,Bookings!$F$5:$F$304,$D304,Bookings!$D$5:$D$304,"Owner block")>0,"SAME-DAY TURN","No same-day guest")) -> — | G304: =IFERROR(IF(INDEX(Bookings!$D$5:$D$304,MATCH($A304,Bookings!$A$5:$A$304,0))="Cancelled","—",IF(INDEX(Bookings!$I$5:$I$304,MATCH($A304,Bookings!$A$5:$A$304,0))="","—",INDEX(Bookings!$I$5:$I$304,MATCH($A304,Bookings!$A$5:$A$304,0)))),"—") -> — | H304: =IFERROR(IF(INDEX(Setup!$I$25:$I$36,MATCH($B304,Setup!$A$25:$A$36,0))=0,"—",INDEX(Setup!$I$25:$I$36,MATCH($B304,Setup!$A$25:$A$36,0))),"—") -> — | I304: =IFERROR(IF(INDEX(Setup!$E$25:$E$36,MATCH($B304,Setup!$A$25:$A$36,0))=0,"—",INDEX(Setup!$E$25:$E$36,MATCH($B304,Setup!$A$25:$A$36,0))),"—") -> —

Sheet Costs
A1: Costs — everything that does not hang on a booking
A2: One-off and variable costs only — anything already entered as Fixed monthly costs in Setup must NOT be logged here, or you count it twice.
A4: # | B4: Date | C4: Property | D4: Category | E4: Description | F4: Amount | G4: Paid by | H4: Receipt / note | I4: Check
A5: =IF($F5="","",ROW()-4) -> 1 | B5: =IFERROR(DATE(YEAR(TODAY()),MONTH(TODAY()),4),"") -> 46207 | C5: Riverside Loft | D5: Maintenance & repair | E5: EXAMPLE — boiler service | F5: 120 | G5: Owner | H5: Invoice in the folder | I5: =IF($F5="","",IF($C5="","⚠ no property — not counted",IF(COUNTIF(Setup!$A$25:$A$36,$C5)=0,"⚠ unknown property","OK"))) -> OK
A6: =IF($F6="","",ROW()-4) -> 2 | B6: =IFERROR(DATE(YEAR(TODAY()),MONTH(TODAY()),6),"") -> 46209 | C6: Harbour Studio | D6: Supplies restock | E6: EXAMPLE — coffee, soap, paper | F6: 34.9 | G6: Owner | H6: Supermarket receipt | I6: =IF($F6="","",IF($C6="","⚠ no property — not counted",IF(COUNTIF(Setup!$A$25:$A$36,$C6)=0,"⚠ unknown property","OK"))) -> OK
A7: =IF($F7="","",ROW()-4) -> 3 | B7: =IFERROR(DATE(YEAR(TODAY()),MONTH(TODAY()),10),"") -> 46213 | C7: Garden Cottage | D7: Furnishings & replacement | E7: EXAMPLE — replaced broken lamp | F7: 42 | G7: Co-host | H7: Photo in the shared album | I7: =IF($F7="","",IF($C7="","⚠ no property — not counted",IF(COUNTIF(Setup!$A$25:$A$36,$C7)=0,"⚠ unknown property","OK"))) -> OK
A8: =IF($F8="","",ROW()-4) -> 4 | B8: =IFERROR(DATE(YEAR(TODAY()),MONTH(TODAY()),13),"") -> 46216 | C8: Riverside Loft | D8: Supplies restock | E8: EXAMPLE — extra bed linen set | F8: 28.5 | G8: Owner | H8: Online order | I8: =IF($F8="","",IF($C8="","⚠ no property — not counted",IF(COUNTIF(Setup!$A$25:$A$36,$C8)=0,"⚠ unknown property","OK"))) -> OK
A9: =IF($F9="","",ROW()-4) -> 5 | B9: =IFERROR(DATE(YEAR(TODAY()),MONTH(TODAY()),18),"") -> 46221 | C9: Garden Cottage | D9: Extra cleaning | E9: EXAMPLE — deep clean after a 6-guest stay | F9: 45 | G9: Cleaner | H9: Paid in cash — delete rows 5–9 when you start | I9: =IF($F9="","",IF($C9="","⚠ no property — not counted",IF(COUNTIF(Setup!$A$25:$A$36,$C9)=0,"⚠ unknown property","OK"))) -> OK
A10: =IF($F10="","",ROW()-4) | I10: =IF($F10="","",IF($C10="","⚠ no property — not counted",IF(COUNTIF(Setup!$A$25:$A$36,$C10)=0,"⚠ unknown property","OK")))
A11: =IF($F11="","",ROW()-4) | I11: =IF($F11="","",IF($C11="","⚠ no property — not counted",IF(COUNTIF(Setup!$A$25:$A$36,$C11)=0,"⚠ unknown property","OK")))
A12: =IF($F12="","",ROW()-4) | I12: =IF($F12="","",IF($C12="","⚠ no property — not counted",IF(COUNTIF(Setup!$A$25:$A$36,$C12)=0,"⚠ unknown property","OK")))
A13: =IF($F13="","",ROW()-4) | I13: =IF($F13="","",IF($C13="","⚠ no property — not counted",IF(COUNTIF(Setup!$A$25:$A$36,$C13)=0,"⚠ unknown property","OK")))
A14: =IF($F14="","",ROW()-4) | I14: =IF($F14="","",IF($C14="","⚠ no property — not counted",IF(COUNTIF(Setup!$A$25:$A$36,$C14)=0,"⚠ unknown property","OK")))
A15: =IF($F15="","",ROW()-4) | I15: =IF($F15="","",IF($C15="","⚠ no property — not counted",IF(COUNTIF(Setup!$A$25:$A$36,$C15)=0,"⚠ unknown property","OK")))
A16: =IF($F16="","",ROW()-4) | I16: =IF($F16="","",IF($C16="","⚠ no property — not counted",IF(COUNTIF(Setup!$A$25:$A$36,$C16)=0,"⚠ unknown property","OK")))
A17: =IF($F17="","",ROW()-4) | I17: =IF($F17="","",IF($C17="","⚠ no property — not counted",IF(COUNTIF(Setup!$A$25:$A$36,$C17)=0,"⚠ unknown property","OK")))
A18: =IF($F18="","",ROW()-4) | I18: =IF($F18="","",IF($C18="","⚠ no property — not counted",IF(COUNTIF(Setup!$A$25:$A$36,$C18)=0,"⚠ unknown property","OK")))
A19: =IF($F19="","",ROW()-4) | I19: =IF($F19="","",IF($C19="","⚠ no property — not counted",IF(COUNTIF(Setup!$A$25:$A$36,$C19)=0,"⚠ unknown property","OK")))
A20: =IF($F20="","",ROW()-4) | I20: =IF($F20="","",IF($C20="","⚠ no property — not counted",IF(COUNTIF(Setup!$A$25:$A$36,$C20)=0,"⚠ unknown property","OK")))
A21: =IF($F21="","",ROW()-4) | I21: =IF($F21="","",IF($C21="","⚠ no property — not counted",IF(COUNTIF(Setup!$A$25:$A$36,$C21)=0,"⚠ unknown property","OK")))
... A254: =IF($F254="","",ROW()-4) | I254: =IF($F254="","",IF($C254="","⚠ no property — not counted",IF(COUNTIF(Setup!$A$25:$A$36,$C254)=0,"⚠ unknown property","OK")))

Sheet Lists
A1: Airbnb | B1: Confirmed | C1: Not scheduled | D1: Maintenance & repair | E1: Owner | F1: 2025 | G1: January | H1: 1
A2: Vrbo | B2: Completed | C2: Scheduled | D2: Supplies restock | E2: Co-host | F2: 2026 | G2: February | H2: 2
A3: Booking.com | B3: Cancelled | C3: In progress | D3: Laundry service | E3: Cleaner | F3: 2027 | G3: March | H3: 3
A4: Direct booking | B4: Owner block | C4: Done | D4: Utilities | E4: Platform | F4: 2028 | G4: April | H4: 4
A5: Other | C5: Issue | D5: Internet & TV | F5: 2029 | G5: May | H5: 5
D6: Insurance | F6: 2030 | G6: June | H6: 6
D7: Software & tools | F7: 2031 | G7: July | H7: 7
D8: Furnishings & replacement | F8: 2032 | G8: August | H8: 8
D9: Extra cleaning | F9: 2033 | G9: September | H9: 9
D10: Guest damage | F10: 2034 | G10: October | H10: 10
D11: Co-host / management fee | G11: November | H11: 11
D12: Other | G12: December | H12: 12
A14: Do not sort or renumber these columns — the Dashboard month picker matches on the order in column G.
