Workbook

Sheet Setup
A1: Shared Expense Splitter — start here
A2: Enter each shared expense once — the workbook shows every person's fair share (equal, by weight such as room size, by nights present, by your own custom units, or exact amounts), each person's balance, and a payback plan of at most 9 transfers for 10 people. Up to 10 people and 300 expenses, in Excel and Google Sheets without macros. One currency per workbook — the currency label is a text label, there is no exchange-rate conversion.
B4: HOW TO USE — 5 STEPS
B5: STEP 1 · Name your group (C15), pick a currency label (C16) and a default split method (C17).
B6: STEP 2 · Type your people into B21:B30 — up to 10. Weight = room m2 / headcount / any number. Nights = nights or days present.
B7: STEP 3 · Expenses sheet: one row per expense — date, what it was, who paid, how much, category, how it is split.
B8: STEP 4 · Fine-tune a single row in the person columns H–Q: blank = normal share · 0 = not part of this expense · a number = custom units (or the exact amount in 'Exact amounts' mode). In 'Custom units' and 'Exact amounts' rows a blank cell counts as 0 — only the numbers you type share the row.
B9: STEP 5 · 'Who Owes What' shows every balance, 'Settle Up' shows the transfers that clear them. Tick each one off in 'Done?'.
B10: GOOGLE SHEETS: File → Import → Upload this file. Formulas, dropdowns, colours, frozen rows, tab colours and hidden columns survive the trip. Print setup (Letter / fit-to-width) does not — pick 'Fit to width' once in the Google Sheets print dialog.
B11: LIMITS — up to 10 people · up to 300 expenses · ONE currency per workbook: the currency label is a text label, there is no exchange-rate conversion · grey and hidden columns calculate themselves, never type in them.
B12: LICENSE — Personal use. One buyer, unlimited own projects & devices. Please don't resell or redistribute. · Questions or a broken formula? Message us on Etsy — we reply within 2 business days.
B13: For personal and household use. This is a calculation sheet, not accounting software: no VAT or tax calculation, no currency conversion, no legal or financial advice.
B15: Group name | C15: Flat share + Lisbon trip | F15: =IF($C$16="","Tip: type your currency symbol in C16 — it appears in every money heading.","")
B16: Currency label | C16: € | F16: Text label only. One currency per workbook — there is no exchange-rate conversion.
B17: Default split method | C17: Equal | F17: Used for every Expenses row that has no 'Split by' of its own.
A20: # | B20: Member | C20: Active? | D20: Weight (room m2, headcount, any number) | E20: Nights / days | F20: Note | G20: Check | H20: Categories (edit freely) | J20: Split methods (fixed) | L20: Yes/No | N20: Currency examples
A21: 1 | B21: Anna | C21: Yes | D21: 18 | E21: 7 | F21: Big room · flat + trip | G21: =IF($B21="","",IF(SUMPRODUCT(($B$21:$B$30=$B21)*1)>1,"⚠ duplicate name — every member needs a unique name","")) | H21: Groceries | J21: Equal | L21: Yes | N21: €
A22: 2 | B22: Ben | C22: Yes | D22: 16 | E22: 7 | F22: Flat + trip | G22: =IF($B22="","",IF(SUMPRODUCT(($B$21:$B$30=$B22)*1)>1,"⚠ duplicate name — every member needs a unique name","")) | H22: Rent | J22: Weights | L22: No | N22: $
A23: 3 | B23: Chris | C23: Yes | D23: 14 | E23: 3 | F23: Joined the trip on day 5 | G23: =IF($B23="","",IF(SUMPRODUCT(($B$21:$B$30=$B23)*1)>1,"⚠ duplicate name — every member needs a unique name","")) | H23: Utilities & internet | J23: Nights | N23: £
A24: 4 | B24: Dana | C24: Yes | D24: 12 | E24: 4 | F24: Flat + trip | G24: =IF($B24="","",IF(SUMPRODUCT(($B$21:$B$30=$B24)*1)>1,"⚠ duplicate name — every member needs a unique name","")) | H24: Household & repairs | J24: Custom units | N24: CHF
A25: 5 | B25: Eli | C25: Yes | E25: 7 | F25: Trip only — no room in the flat | G25: =IF($B25="","",IF(SUMPRODUCT(($B$21:$B$30=$B25)*1)>1,"⚠ duplicate name — every member needs a unique name","")) | H25: Eating out | J25: Exact amounts | N25: kr
A26: 6 | C26: No | G26: =IF($B26="","",IF(SUMPRODUCT(($B$21:$B$30=$B26)*1)>1,"⚠ duplicate name — every member needs a unique name","")) | H26: Drinks & nightlife | N26: zł
A27: 7 | C27: No | G27: =IF($B27="","",IF(SUMPRODUCT(($B$21:$B$30=$B27)*1)>1,"⚠ duplicate name — every member needs a unique name","")) | H27: Travel & transport | N27: C$
A28: 8 | C28: No | G28: =IF($B28="","",IF(SUMPRODUCT(($B$21:$B$30=$B28)*1)>1,"⚠ duplicate name — every member needs a unique name","")) | H28: Accommodation | N28: A$
A29: 9 | C29: No | G29: =IF($B29="","",IF(SUMPRODUCT(($B$21:$B$30=$B29)*1)>1,"⚠ duplicate name — every member needs a unique name","")) | H29: Activities & tickets | N29: ₹
A30: 10 | C30: No | G30: =IF($B30="","",IF(SUMPRODUCT(($B$21:$B$30=$B30)*1)>1,"⚠ duplicate name — every member needs a unique name","")) | H30: Gifts & celebration | N30: R$
H31: Payback / cash to a person
H32: Other
B33: REMEMBER · In Equal / Weights / Nights rows: blank = normal share, 0 = not part of that expense, any number = custom share. In 'Custom units' and 'Exact amounts' rows only the numbers you type count — blank means 0. Set Active = No only for people who never joined.
B34: CASH PAYBACK · Ben hands Anna 50 in cash? Add a normal row: Paid by = Ben, Amount = 50, Split by = 'Exact amounts', type 50 in Anna's column, leave everyone else blank. The category 'Payback / cash to a person' is only a label — the split mode does the maths.
B35: SPLIT MODES · Equal = same share for everyone active · Weights = by the Weight column · Nights = by the Nights column · Custom units = ONLY the people you type a number for share that row, a blank cell counts as 0 · Exact amounts = you type each person's exact amount (they must add up to the total). Type numbers for everyone who should share a 'Custom units' row — if you leave the whole row blank, the Check column says so instead of splitting it silently.
B36: MAKE IT YOURS · The example (flat share + Lisbon trip) is here so you can see every split mode working. To start your own: on the Expenses sheet select B8:Q31 and press Delete, then overwrite the names in B21:B30 above. Never delete whole rows — column A, the Check column R, the 'Share of' column S and the hidden columns T:AG hold the formulas.

Sheet Expenses
A1: Expenses — one row per expense
A2: Grey and hidden columns calculate themselves. Blank in a person's column = normal share · 0 = not part of this expense · a number = custom units (or the exact amount in 'Exact amounts' mode). In 'Custom units' and 'Exact amounts' rows a blank cell counts as 0 — only the numbers you type share the row.
B4: Show each person's share for: | C4: Anna | E4: ← pick a name; column S then shows that person's share of every row.
R6: The engine columns T:AG are hidden. Unhide them if you want to see the maths — never type in them. | T6: ▼ calculates itself — never type here
A7: # | B7: Date | C7: What was it? | D7: Paid by | E7: =IF(Setup!$C$16="","Amount","Amount ("&Setup!$C$16&")") -> Amount (€) | F7: Category | G7: Split by | H7: =IF(Setup!$B$21="","(person 1)",Setup!$B$21) -> Anna | I7: =IF(Setup!$B$22="","(person 2)",Setup!$B$22) -> Ben | J7: =IF(Setup!$B$23="","(person 3)",Setup!$B$23) -> Chris | K7: =IF(Setup!$B$24="","(person 4)",Setup!$B$24) -> Dana | L7: =IF(Setup!$B$25="","(person 5)",Setup!$B$25) -> Eli | M7: =IF(Setup!$B$26="","(person 6)",Setup!$B$26) -> (person 6) | N7: =IF(Setup!$B$27="","(person 7)",Setup!$B$27) -> (person 7) | O7: =IF(Setup!$B$28="","(person 8)",Setup!$B$28) -> (person 8) | P7: =IF(Setup!$B$29="","(person 9)",Setup!$B$29) -> (person 9) | Q7: =IF(Setup!$B$30="","(person 10)",Setup!$B$30) -> (person 10) | R7: Check | S7: =IF($C$4="","Share of … (pick a name in C4)","Share of "&$C$4) -> Share of Anna | T7: Split used | U7: =IF(Setup!$B$21="","units — person 1","units — "&Setup!$B$21) -> units — Anna | V7: =IF(Setup!$B$22="","units — person 2","units — "&Setup!$B$22) -> units — Ben | W7: =IF(Setup!$B$23="","units — person 3","units — "&Setup!$B$23) -> units — Chris | X7: =IF(Setup!$B$24="","units — person 4","units — "&Setup!$B$24) -> units — Dana | Y7: =IF(Setup!$B$25="","units — person 5","units — "&Setup!$B$25) -> units — Eli | Z7: =IF(Setup!$B$26="","units — person 6","units — "&Setup!$B$26) -> units — person 6 | AA7: =IF(Setup!$B$27="","units — person 7","units — "&Setup!$B$27) -> units — person 7 | AB7: =IF(Setup!$B$28="","units — person 8","units — "&Setup!$B$28) -> units — person 8 | AC7: =IF(Setup!$B$29="","units — person 9","units — "&Setup!$B$29) -> units — person 9 | AD7: =IF(Setup!$B$30="","units — person 10","units — "&Setup!$B$30) -> units — person 10 | AE7: Total units | AF7: Divisor (never 0) | AG7: Amount (number)
A8: =IF($T8="","—",ROW()-7) -> 1 | B8: =TODAY()-45 -> 46187 | C8: Rent — this month | D8: Anna | E8: 1450 | F8: Rent | G8: Weights | R8: =IF($T8="","",IF($D8="","Who paid?",IF(SUMPRODUCT((Setup!$B$21:$B$30=$D8)*1)=0,"Payer is not in the member list on Setup",IF($E8="","Amount missing — type the number in column E",IF(NOT(ISNUMBER($E8)),"Amount must be a plain number — no currency symbol, no text",IF(AND($T8="Custom units",$AE8<=0),"Custom units: nobody has units on this row — type a number for at least one person",IF($AE8<=0,"Nobody shares this row — check the person columns H–Q, and the Weight / Nights columns on Setup",IF(AND($T8="Exact amounts",ABS($AE8-$AG8)>0.01),"Exact amounts do not add up to the amount","OK")))))))) -> OK | S8: =IFERROR(IF(OR($T8="",$C$4=""),"—",ROUND($AG8*INDEX($U8:$AD8,1,MATCH($C$4,Setup!$B$21:$B$30,0))/$AF8,2)),"—") -> 435 | T8: =IF(AND($C8="",$D8="",NOT(ISNUMBER($E8))),"",IF($G8="",IF(Setup!$C$17="","Equal",Setup!$C$17),$G8)) -> Weights | U8: =IF($T8="",0,IF(OR(Setup!$B$21="",Setup!$C$21="No"),0,IF(ISNUMBER(H8),H8,IF($T8="Weights",IF(ISNUMBER(Setup!$D$21),Setup!$D$21,0),IF($T8="Nights",IF(ISNUMBER(Setup!$E$21),Setup!$E$21,0),IF(OR($T8="Exact amounts",$T8="Custom units"),0,1)))))) -> 18 | V8: =IF($T8="",0,IF(OR(Setup!$B$22="",Setup!$C$22="No"),0,IF(ISNUMBER(I8),I8,IF($T8="Weights",IF(ISNUMBER(Setup!$D$22),Setup!$D$22,0),IF($T8="Nights",IF(ISNUMBER(Setup!$E$22),Setup!$E$22,0),IF(OR($T8="Exact amounts",$T8="Custom units"),0,1)))))) -> 16 | W8: =IF($T8="",0,IF(OR(Setup!$B$23="",Setup!$C$23="No"),0,IF(ISNUMBER(J8),J8,IF($T8="Weights",IF(ISNUMBER(Setup!$D$23),Setup!$D$23,0),IF($T8="Nights",IF(ISNUMBER(Setup!$E$23),Setup!$E$23,0),IF(OR($T8="Exact amounts",$T8="Custom units"),0,1)))))) -> 14 | X8: =IF($T8="",0,IF(OR(Setup!$B$24="",Setup!$C$24="No"),0,IF(ISNUMBER(K8),K8,IF($T8="Weights",IF(ISNUMBER(Setup!$D$24),Setup!$D$24,0),IF($T8="Nights",IF(ISNUMBER(Setup!$E$24),Setup!$E$24,0),IF(OR($T8="Exact amounts",$T8="Custom units"),0,1)))))) -> 12 | Y8: =IF($T8="",0,IF(OR(Setup!$B$25="",Setup!$C$25="No"),0,IF(ISNUMBER(L8),L8,IF($T8="Weights",IF(ISNUMBER(Setup!$D$25),Setup!$D$25,0),IF($T8="Nights",IF(ISNUMBER(Setup!$E$25),Setup!$E$25,0),IF(OR($T8="Exact amounts",$T8="Custom units"),0,1)))))) -> 0 | Z8: =IF($T8="",0,IF(OR(Setup!$B$26="",Setup!$C$26="No"),0,IF(ISNUMBER(M8),M8,IF($T8="Weights",IF(ISNUMBER(Setup!$D$26),Setup!$D$26,0),IF($T8="Nights",IF(ISNUMBER(Setup!$E$26),Setup!$E$26,0),IF(OR($T8="Exact amounts",$T8="Custom units"),0,1)))))) -> 0 | AA8: =IF($T8="",0,IF(OR(Setup!$B$27="",Setup!$C$27="No"),0,IF(ISNUMBER(N8),N8,IF($T8="Weights",IF(ISNUMBER(Setup!$D$27),Setup!$D$27,0),IF($T8="Nights",IF(ISNUMBER(Setup!$E$27),Setup!$E$27,0),IF(OR($T8="Exact amounts",$T8="Custom units"),0,1)))))) -> 0 | AB8: =IF($T8="",0,IF(OR(Setup!$B$28="",Setup!$C$28="No"),0,IF(ISNUMBER(O8),O8,IF($T8="Weights",IF(ISNUMBER(Setup!$D$28),Setup!$D$28,0),IF($T8="Nights",IF(ISNUMBER(Setup!$E$28),Setup!$E$28,0),IF(OR($T8="Exact amounts",$T8="Custom units"),0,1)))))) -> 0 | AC8: =IF($T8="",0,IF(OR(Setup!$B$29="",Setup!$C$29="No"),0,IF(ISNUMBER(P8),P8,IF($T8="Weights",IF(ISNUMBER(Setup!$D$29),Setup!$D$29,0),IF($T8="Nights",IF(ISNUMBER(Setup!$E$29),Setup!$E$29,0),IF(OR($T8="Exact amounts",$T8="Custom units"),0,1)))))) -> 0 | AD8: =IF($T8="",0,IF(OR(Setup!$B$30="",Setup!$C$30="No"),0,IF(ISNUMBER(Q8),Q8,IF($T8="Weights",IF(ISNUMBER(Setup!$D$30),Setup!$D$30,0),IF($T8="Nights",IF(ISNUMBER(Setup!$E$30),Setup!$E$30,0),IF(OR($T8="Exact amounts",$T8="Custom units"),0,1)))))) -> 0 | AE8: =IF($T8="",0,SUM($U8:$AD8)) -> 60 | AF8: =IF($AE8<=0,1,$AE8) -> 60 | AG8: =IF(ISNUMBER($E8),$E8,0) -> 1450
A9: =IF($T9="","—",ROW()-7) -> 2 | B9: =TODAY()-44 -> 46188 | C9: Electricity & internet | D9: Ben | E9: 186.4 | F9: Utilities & internet | G9: Equal | L9: 0 | R9: =IF($T9="","",IF($D9="","Who paid?",IF(SUMPRODUCT((Setup!$B$21:$B$30=$D9)*1)=0,"Payer is not in the member list on Setup",IF($E9="","Amount missing — type the number in column E",IF(NOT(ISNUMBER($E9)),"Amount must be a plain number — no currency symbol, no text",IF(AND($T9="Custom units",$AE9<=0),"Custom units: nobody has units on this row — type a number for at least one person",IF($AE9<=0,"Nobody shares this row — check the person columns H–Q, and the Weight / Nights columns on Setup",IF(AND($T9="Exact amounts",ABS($AE9-$AG9)>0.01),"Exact amounts do not add up to the amount","OK")))))))) -> OK | S9: =IFERROR(IF(OR($T9="",$C$4=""),"—",ROUND($AG9*INDEX($U9:$AD9,1,MATCH($C$4,Setup!$B$21:$B$30,0))/$AF9,2)),"—") -> 46.6 | T9: =IF(AND($C9="",$D9="",NOT(ISNUMBER($E9))),"",IF($G9="",IF(Setup!$C$17="","Equal",Setup!$C$17),$G9)) -> Equal | U9: =IF($T9="",0,IF(OR(Setup!$B$21="",Setup!$C$21="No"),0,IF(ISNUMBER(H9),H9,IF($T9="Weights",IF(ISNUMBER(Setup!$D$21),Setup!$D$21,0),IF($T9="Nights",IF(ISNUMBER(Setup!$E$21),Setup!$E$21,0),IF(OR($T9="Exact amounts",$T9="Custom units"),0,1)))))) -> 1 | V9: =IF($T9="",0,IF(OR(Setup!$B$22="",Setup!$C$22="No"),0,IF(ISNUMBER(I9),I9,IF($T9="Weights",IF(ISNUMBER(Setup!$D$22),Setup!$D$22,0),IF($T9="Nights",IF(ISNUMBER(Setup!$E$22),Setup!$E$22,0),IF(OR($T9="Exact amounts",$T9="Custom units"),0,1)))))) -> 1 | W9: =IF($T9="",0,IF(OR(Setup!$B$23="",Setup!$C$23="No"),0,IF(ISNUMBER(J9),J9,IF($T9="Weights",IF(ISNUMBER(Setup!$D$23),Setup!$D$23,0),IF($T9="Nights",IF(ISNUMBER(Setup!$E$23),Setup!$E$23,0),IF(OR($T9="Exact amounts",$T9="Custom units"),0,1)))))) -> 1 | X9: =IF($T9="",0,IF(OR(Setup!$B$24="",Setup!$C$24="No"),0,IF(ISNUMBER(K9),K9,IF($T9="Weights",IF(ISNUMBER(Setup!$D$24),Setup!$D$24,0),IF($T9="Nights",IF(ISNUMBER(Setup!$E$24),Setup!$E$24,0),IF(OR($T9="Exact amounts",$T9="Custom units"),0,1)))))) -> 1 | Y9: =IF($T9="",0,IF(OR(Setup!$B$25="",Setup!$C$25="No"),0,IF(ISNUMBER(L9),L9,IF($T9="Weights",IF(ISNUMBER(Setup!$D$25),Setup!$D$25,0),IF($T9="Nights",IF(ISNUMBER(Setup!$E$25),Setup!$E$25,0),IF(OR($T9="Exact amounts",$T9="Custom units"),0,1)))))) -> 0 | Z9: =IF($T9="",0,IF(OR(Setup!$B$26="",Setup!$C$26="No"),0,IF(ISNUMBER(M9),M9,IF($T9="Weights",IF(ISNUMBER(Setup!$D$26),Setup!$D$26,0),IF($T9="Nights",IF(ISNUMBER(Setup!$E$26),Setup!$E$26,0),IF(OR($T9="Exact amounts",$T9="Custom units"),0,1)))))) -> 0 | AA9: =IF($T9="",0,IF(OR(Setup!$B$27="",Setup!$C$27="No"),0,IF(ISNUMBER(N9),N9,IF($T9="Weights",IF(ISNUMBER(Setup!$D$27),Setup!$D$27,0),IF($T9="Nights",IF(ISNUMBER(Setup!$E$27),Setup!$E$27,0),IF(OR($T9="Exact amounts",$T9="Custom units"),0,1)))))) -> 0 | AB9: =IF($T9="",0,IF(OR(Setup!$B$28="",Setup!$C$28="No"),0,IF(ISNUMBER(O9),O9,IF($T9="Weights",IF(ISNUMBER(Setup!$D$28),Setup!$D$28,0),IF($T9="Nights",IF(ISNUMBER(Setup!$E$28),Setup!$E$28,0),IF(OR($T9="Exact amounts",$T9="Custom units"),0,1)))))) -> 0 | AC9: =IF($T9="",0,IF(OR(Setup!$B$29="",Setup!$C$29="No"),0,IF(ISNUMBER(P9),P9,IF($T9="Weights",IF(ISNUMBER(Setup!$D$29),Setup!$D$29,0),IF($T9="Nights",IF(ISNUMBER(Setup!$E$29),Setup!$E$29,0),IF(OR($T9="Exact amounts",$T9="Custom units"),0,1)))))) -> 0 | AD9: =IF($T9="",0,IF(OR(Setup!$B$30="",Setup!$C$30="No"),0,IF(ISNUMBER(Q9),Q9,IF($T9="Weights",IF(ISNUMBER(Setup!$D$30),Setup!$D$30,0),IF($T9="Nights",IF(ISNUMBER(Setup!$E$30),Setup!$E$30,0),IF(OR($T9="Exact amounts",$T9="Custom units"),0,1)))))) -> 0 | AE9: =IF($T9="",0,SUM($U9:$AD9)) -> 4 | AF9: =IF($AE9<=0,1,$AE9) -> 4 | AG9: =IF(ISNUMBER($E9),$E9,0) -> 186.4
A10: =IF($T10="","—",ROW()-7) -> 3 | B10: =TODAY()-42 -> 46190 | C10: Weekly groceries | D10: Chris | E10: 94.2 | F10: Groceries | G10: Equal | L10: 0 | R10: =IF($T10="","",IF($D10="","Who paid?",IF(SUMPRODUCT((Setup!$B$21:$B$30=$D10)*1)=0,"Payer is not in the member list on Setup",IF($E10="","Amount missing — type the number in column E",IF(NOT(ISNUMBER($E10)),"Amount must be a plain number — no currency symbol, no text",IF(AND($T10="Custom units",$AE10<=0),"Custom units: nobody has units on this row — type a number for at least one person",IF($AE10<=0,"Nobody shares this row — check the person columns H–Q, and the Weight / Nights columns on Setup",IF(AND($T10="Exact amounts",ABS($AE10-$AG10)>0.01),"Exact amounts do not add up to the amount","OK")))))))) -> OK | S10: =IFERROR(IF(OR($T10="",$C$4=""),"—",ROUND($AG10*INDEX($U10:$AD10,1,MATCH($C$4,Setup!$B$21:$B$30,0))/$AF10,2)),"—") -> 23.55 | T10: =IF(AND($C10="",$D10="",NOT(ISNUMBER($E10))),"",IF($G10="",IF(Setup!$C$17="","Equal",Setup!$C$17),$G10)) -> Equal | U10: =IF($T10="",0,IF(OR(Setup!$B$21="",Setup!$C$21="No"),0,IF(ISNUMBER(H10),H10,IF($T10="Weights",IF(ISNUMBER(Setup!$D$21),Setup!$D$21,0),IF($T10="Nights",IF(ISNUMBER(Setup!$E$21),Setup!$E$21,0),IF(OR($T10="Exact amounts",$T10="Custom units"),0,1)))))) -> 1 | V10: =IF($T10="",0,IF(OR(Setup!$B$22="",Setup!$C$22="No"),0,IF(ISNUMBER(I10),I10,IF($T10="Weights",IF(ISNUMBER(Setup!$D$22),Setup!$D$22,0),IF($T10="Nights",IF(ISNUMBER(Setup!$E$22),Setup!$E$22,0),IF(OR($T10="Exact amounts",$T10="Custom units"),0,1)))))) -> 1 | W10: =IF($T10="",0,IF(OR(Setup!$B$23="",Setup!$C$23="No"),0,IF(ISNUMBER(J10),J10,IF($T10="Weights",IF(ISNUMBER(Setup!$D$23),Setup!$D$23,0),IF($T10="Nights",IF(ISNUMBER(Setup!$E$23),Setup!$E$23,0),IF(OR($T10="Exact amounts",$T10="Custom units"),0,1)))))) -> 1 | X10: =IF($T10="",0,IF(OR(Setup!$B$24="",Setup!$C$24="No"),0,IF(ISNUMBER(K10),K10,IF($T10="Weights",IF(ISNUMBER(Setup!$D$24),Setup!$D$24,0),IF($T10="Nights",IF(ISNUMBER(Setup!$E$24),Setup!$E$24,0),IF(OR($T10="Exact amounts",$T10="Custom units"),0,1)))))) -> 1 | Y10: =IF($T10="",0,IF(OR(Setup!$B$25="",Setup!$C$25="No"),0,IF(ISNUMBER(L10),L10,IF($T10="Weights",IF(ISNUMBER(Setup!$D$25),Setup!$D$25,0),IF($T10="Nights",IF(ISNUMBER(Setup!$E$25),Setup!$E$25,0),IF(OR($T10="Exact amounts",$T10="Custom units"),0,1)))))) -> 0 | Z10: =IF($T10="",0,IF(OR(Setup!$B$26="",Setup!$C$26="No"),0,IF(ISNUMBER(M10),M10,IF($T10="Weights",IF(ISNUMBER(Setup!$D$26),Setup!$D$26,0),IF($T10="Nights",IF(ISNUMBER(Setup!$E$26),Setup!$E$26,0),IF(OR($T10="Exact amounts",$T10="Custom units"),0,1)))))) -> 0 | AA10: =IF($T10="",0,IF(OR(Setup!$B$27="",Setup!$C$27="No"),0,IF(ISNUMBER(N10),N10,IF($T10="Weights",IF(ISNUMBER(Setup!$D$27),Setup!$D$27,0),IF($T10="Nights",IF(ISNUMBER(Setup!$E$27),Setup!$E$27,0),IF(OR($T10="Exact amounts",$T10="Custom units"),0,1)))))) -> 0 | AB10: =IF($T10="",0,IF(OR(Setup!$B$28="",Setup!$C$28="No"),0,IF(ISNUMBER(O10),O10,IF($T10="Weights",IF(ISNUMBER(Setup!$D$28),Setup!$D$28,0),IF($T10="Nights",IF(ISNUMBER(Setup!$E$28),Setup!$E$28,0),IF(OR($T10="Exact amounts",$T10="Custom units"),0,1)))))) -> 0 | AC10: =IF($T10="",0,IF(OR(Setup!$B$29="",Setup!$C$29="No"),0,IF(ISNUMBER(P10),P10,IF($T10="Weights",IF(ISNUMBER(Setup!$D$29),Setup!$D$29,0),IF($T10="Nights",IF(ISNUMBER(Setup!$E$29),Setup!$E$29,0),IF(OR($T10="Exact amounts",$T10="Custom units"),0,1)))))) -> 0 | AD10: =IF($T10="",0,IF(OR(Setup!$B$30="",Setup!$C$30="No"),0,IF(ISNUMBER(Q10),Q10,IF($T10="Weights",IF(ISNUMBER(Setup!$D$30),Setup!$D$30,0),IF($T10="Nights",IF(ISNUMBER(Setup!$E$30),Setup!$E$30,0),IF(OR($T10="Exact amounts",$T10="Custom units"),0,1)))))) -> 0 | AE10: =IF($T10="",0,SUM($U10:$AD10)) -> 4 | AF10: =IF($AE10<=0,1,$AE10) -> 4 | AG10: =IF(ISNUMBER($E10),$E10,0) -> 94.2
A11: =IF($T11="","—",ROW()-7) -> 4 | B11: =TODAY()-40 -> 46192 | C11: Cleaning supplies + light bulbs | D11: Dana | E11: 38.75 | F11: Household & repairs | G11: Equal | L11: 0 | R11: =IF($T11="","",IF($D11="","Who paid?",IF(SUMPRODUCT((Setup!$B$21:$B$30=$D11)*1)=0,"Payer is not in the member list on Setup",IF($E11="","Amount missing — type the number in column E",IF(NOT(ISNUMBER($E11)),"Amount must be a plain number — no currency symbol, no text",IF(AND($T11="Custom units",$AE11<=0),"Custom units: nobody has units on this row — type a number for at least one person",IF($AE11<=0,"Nobody shares this row — check the person columns H–Q, and the Weight / Nights columns on Setup",IF(AND($T11="Exact amounts",ABS($AE11-$AG11)>0.01),"Exact amounts do not add up to the amount","OK")))))))) -> OK | S11: =IFERROR(IF(OR($T11="",$C$4=""),"—",ROUND($AG11*INDEX($U11:$AD11,1,MATCH($C$4,Setup!$B$21:$B$30,0))/$AF11,2)),"—") -> 9.69 | T11: =IF(AND($C11="",$D11="",NOT(ISNUMBER($E11))),"",IF($G11="",IF(Setup!$C$17="","Equal",Setup!$C$17),$G11)) -> Equal | U11: =IF($T11="",0,IF(OR(Setup!$B$21="",Setup!$C$21="No"),0,IF(ISNUMBER(H11),H11,IF($T11="Weights",IF(ISNUMBER(Setup!$D$21),Setup!$D$21,0),IF($T11="Nights",IF(ISNUMBER(Setup!$E$21),Setup!$E$21,0),IF(OR($T11="Exact amounts",$T11="Custom units"),0,1)))))) -> 1 | V11: =IF($T11="",0,IF(OR(Setup!$B$22="",Setup!$C$22="No"),0,IF(ISNUMBER(I11),I11,IF($T11="Weights",IF(ISNUMBER(Setup!$D$22),Setup!$D$22,0),IF($T11="Nights",IF(ISNUMBER(Setup!$E$22),Setup!$E$22,0),IF(OR($T11="Exact amounts",$T11="Custom units"),0,1)))))) -> 1 | W11: =IF($T11="",0,IF(OR(Setup!$B$23="",Setup!$C$23="No"),0,IF(ISNUMBER(J11),J11,IF($T11="Weights",IF(ISNUMBER(Setup!$D$23),Setup!$D$23,0),IF($T11="Nights",IF(ISNUMBER(Setup!$E$23),Setup!$E$23,0),IF(OR($T11="Exact amounts",$T11="Custom units"),0,1)))))) -> 1 | X11: =IF($T11="",0,IF(OR(Setup!$B$24="",Setup!$C$24="No"),0,IF(ISNUMBER(K11),K11,IF($T11="Weights",IF(ISNUMBER(Setup!$D$24),Setup!$D$24,0),IF($T11="Nights",IF(ISNUMBER(Setup!$E$24),Setup!$E$24,0),IF(OR($T11="Exact amounts",$T11="Custom units"),0,1)))))) -> 1 | Y11: =IF($T11="",0,IF(OR(Setup!$B$25="",Setup!$C$25="No"),0,IF(ISNUMBER(L11),L11,IF($T11="Weights",IF(ISNUMBER(Setup!$D$25),Setup!$D$25,0),IF($T11="Nights",IF(ISNUMBER(Setup!$E$25),Setup!$E$25,0),IF(OR($T11="Exact amounts",$T11="Custom units"),0,1)))))) -> 0 | Z11: =IF($T11="",0,IF(OR(Setup!$B$26="",Setup!$C$26="No"),0,IF(ISNUMBER(M11),M11,IF($T11="Weights",IF(ISNUMBER(Setup!$D$26),Setup!$D$26,0),IF($T11="Nights",IF(ISNUMBER(Setup!$E$26),Setup!$E$26,0),IF(OR($T11="Exact amounts",$T11="Custom units"),0,1)))))) -> 0 | AA11: =IF($T11="",0,IF(OR(Setup!$B$27="",Setup!$C$27="No"),0,IF(ISNUMBER(N11),N11,IF($T11="Weights",IF(ISNUMBER(Setup!$D$27),Setup!$D$27,0),IF($T11="Nights",IF(ISNUMBER(Setup!$E$27),Setup!$E$27,0),IF(OR($T11="Exact amounts",$T11="Custom units"),0,1)))))) -> 0 | AB11: =IF($T11="",0,IF(OR(Setup!$B$28="",Setup!$C$28="No"),0,IF(ISNUMBER(O11),O11,IF($T11="Weights",IF(ISNUMBER(Setup!$D$28),Setup!$D$28,0),IF($T11="Nights",IF(ISNUMBER(Setup!$E$28),Setup!$E$28,0),IF(OR($T11="Exact amounts",$T11="Custom units"),0,1)))))) -> 0 | AC11: =IF($T11="",0,IF(OR(Setup!$B$29="",Setup!$C$29="No"),0,IF(ISNUMBER(P11),P11,IF($T11="Weights",IF(ISNUMBER(Setup!$D$29),Setup!$D$29,0),IF($T11="Nights",IF(ISNUMBER(Setup!$E$29),Setup!$E$29,0),IF(OR($T11="Exact amounts",$T11="Custom units"),0,1)))))) -> 0 | AD11: =IF($T11="",0,IF(OR(Setup!$B$30="",Setup!$C$30="No"),0,IF(ISNUMBER(Q11),Q11,IF($T11="Weights",IF(ISNUMBER(Setup!$D$30),Setup!$D$30,0),IF($T11="Nights",IF(ISNUMBER(Setup!$E$30),Setup!$E$30,0),IF(OR($T11="Exact amounts",$T11="Custom units"),0,1)))))) -> 0 | AE11: =IF($T11="",0,SUM($U11:$AD11)) -> 4 | AF11: =IF($AE11<=0,1,$AE11) -> 4 | AG11: =IF(ISNUMBER($E11),$E11,0) -> 38.75
A12: =IF($T12="","—",ROW()-7) -> 5 | B12: =TODAY()-38 -> 46194 | C12: Plumber — kitchen sink | D12: Anna | E12: 210 | F12: Household & repairs | G12: Equal | L12: 0 | R12: =IF($T12="","",IF($D12="","Who paid?",IF(SUMPRODUCT((Setup!$B$21:$B$30=$D12)*1)=0,"Payer is not in the member list on Setup",IF($E12="","Amount missing — type the number in column E",IF(NOT(ISNUMBER($E12)),"Amount must be a plain number — no currency symbol, no text",IF(AND($T12="Custom units",$AE12<=0),"Custom units: nobody has units on this row — type a number for at least one person",IF($AE12<=0,"Nobody shares this row — check the person columns H–Q, and the Weight / Nights columns on Setup",IF(AND($T12="Exact amounts",ABS($AE12-$AG12)>0.01),"Exact amounts do not add up to the amount","OK")))))))) -> OK | S12: =IFERROR(IF(OR($T12="",$C$4=""),"—",ROUND($AG12*INDEX($U12:$AD12,1,MATCH($C$4,Setup!$B$21:$B$30,0))/$AF12,2)),"—") -> 52.5 | T12: =IF(AND($C12="",$D12="",NOT(ISNUMBER($E12))),"",IF($G12="",IF(Setup!$C$17="","Equal",Setup!$C$17),$G12)) -> Equal | U12: =IF($T12="",0,IF(OR(Setup!$B$21="",Setup!$C$21="No"),0,IF(ISNUMBER(H12),H12,IF($T12="Weights",IF(ISNUMBER(Setup!$D$21),Setup!$D$21,0),IF($T12="Nights",IF(ISNUMBER(Setup!$E$21),Setup!$E$21,0),IF(OR($T12="Exact amounts",$T12="Custom units"),0,1)))))) -> 1 | V12: =IF($T12="",0,IF(OR(Setup!$B$22="",Setup!$C$22="No"),0,IF(ISNUMBER(I12),I12,IF($T12="Weights",IF(ISNUMBER(Setup!$D$22),Setup!$D$22,0),IF($T12="Nights",IF(ISNUMBER(Setup!$E$22),Setup!$E$22,0),IF(OR($T12="Exact amounts",$T12="Custom units"),0,1)))))) -> 1 | W12: =IF($T12="",0,IF(OR(Setup!$B$23="",Setup!$C$23="No"),0,IF(ISNUMBER(J12),J12,IF($T12="Weights",IF(ISNUMBER(Setup!$D$23),Setup!$D$23,0),IF($T12="Nights",IF(ISNUMBER(Setup!$E$23),Setup!$E$23,0),IF(OR($T12="Exact amounts",$T12="Custom units"),0,1)))))) -> 1 | X12: =IF($T12="",0,IF(OR(Setup!$B$24="",Setup!$C$24="No"),0,IF(ISNUMBER(K12),K12,IF($T12="Weights",IF(ISNUMBER(Setup!$D$24),Setup!$D$24,0),IF($T12="Nights",IF(ISNUMBER(Setup!$E$24),Setup!$E$24,0),IF(OR($T12="Exact amounts",$T12="Custom units"),0,1)))))) -> 1 | Y12: =IF($T12="",0,IF(OR(Setup!$B$25="",Setup!$C$25="No"),0,IF(ISNUMBER(L12),L12,IF($T12="Weights",IF(ISNUMBER(Setup!$D$25),Setup!$D$25,0),IF($T12="Nights",IF(ISNUMBER(Setup!$E$25),Setup!$E$25,0),IF(OR($T12="Exact amounts",$T12="Custom units"),0,1)))))) -> 0 | Z12: =IF($T12="",0,IF(OR(Setup!$B$26="",Setup!$C$26="No"),0,IF(ISNUMBER(M12),M12,IF($T12="Weights",IF(ISNUMBER(Setup!$D$26),Setup!$D$26,0),IF($T12="Nights",IF(ISNUMBER(Setup!$E$26),Setup!$E$26,0),IF(OR($T12="Exact amounts",$T12="Custom units"),0,1)))))) -> 0 | AA12: =IF($T12="",0,IF(OR(Setup!$B$27="",Setup!$C$27="No"),0,IF(ISNUMBER(N12),N12,IF($T12="Weights",IF(ISNUMBER(Setup!$D$27),Setup!$D$27,0),IF($T12="Nights",IF(ISNUMBER(Setup!$E$27),Setup!$E$27,0),IF(OR($T12="Exact amounts",$T12="Custom units"),0,1)))))) -> 0 | AB12: =IF($T12="",0,IF(OR(Setup!$B$28="",Setup!$C$28="No"),0,IF(ISNUMBER(O12),O12,IF($T12="Weights",IF(ISNUMBER(Setup!$D$28),Setup!$D$28,0),IF($T12="Nights",IF(ISNUMBER(Setup!$E$28),Setup!$E$28,0),IF(OR($T12="Exact amounts",$T12="Custom units"),0,1)))))) -> 0 | AC12: =IF($T12="",0,IF(OR(Setup!$B$29="",Setup!$C$29="No"),0,IF(ISNUMBER(P12),P12,IF($T12="Weights",IF(ISNUMBER(Setup!$D$29),Setup!$D$29,0),IF($T12="Nights",IF(ISNUMBER(Setup!$E$29),Setup!$E$29,0),IF(OR($T12="Exact amounts",$T12="Custom units"),0,1)))))) -> 0 | AD12: =IF($T12="",0,IF(OR(Setup!$B$30="",Setup!$C$30="No"),0,IF(ISNUMBER(Q12),Q12,IF($T12="Weights",IF(ISNUMBER(Setup!$D$30),Setup!$D$30,0),IF($T12="Nights",IF(ISNUMBER(Setup!$E$30),Setup!$E$30,0),IF(OR($T12="Exact amounts",$T12="Custom units"),0,1)))))) -> 0 | AE12: =IF($T12="",0,SUM($U12:$AD12)) -> 4 | AF12: =IF($AE12<=0,1,$AE12) -> 4 | AG12: =IF(ISNUMBER($E12),$E12,0) -> 210
A13: =IF($T13="","—",ROW()-7) -> 6 | B13: =TODAY()-36 -> 46196 | C13: Weekly groceries | D13: Ben | E13: 112.6 | F13: Groceries | G13: Equal | L13: 0 | R13: =IF($T13="","",IF($D13="","Who paid?",IF(SUMPRODUCT((Setup!$B$21:$B$30=$D13)*1)=0,"Payer is not in the member list on Setup",IF($E13="","Amount missing — type the number in column E",IF(NOT(ISNUMBER($E13)),"Amount must be a plain number — no currency symbol, no text",IF(AND($T13="Custom units",$AE13<=0),"Custom units: nobody has units on this row — type a number for at least one person",IF($AE13<=0,"Nobody shares this row — check the person columns H–Q, and the Weight / Nights columns on Setup",IF(AND($T13="Exact amounts",ABS($AE13-$AG13)>0.01),"Exact amounts do not add up to the amount","OK")))))))) -> OK | S13: =IFERROR(IF(OR($T13="",$C$4=""),"—",ROUND($AG13*INDEX($U13:$AD13,1,MATCH($C$4,Setup!$B$21:$B$30,0))/$AF13,2)),"—") -> 28.15 | T13: =IF(AND($C13="",$D13="",NOT(ISNUMBER($E13))),"",IF($G13="",IF(Setup!$C$17="","Equal",Setup!$C$17),$G13)) -> Equal | U13: =IF($T13="",0,IF(OR(Setup!$B$21="",Setup!$C$21="No"),0,IF(ISNUMBER(H13),H13,IF($T13="Weights",IF(ISNUMBER(Setup!$D$21),Setup!$D$21,0),IF($T13="Nights",IF(ISNUMBER(Setup!$E$21),Setup!$E$21,0),IF(OR($T13="Exact amounts",$T13="Custom units"),0,1)))))) -> 1 | V13: =IF($T13="",0,IF(OR(Setup!$B$22="",Setup!$C$22="No"),0,IF(ISNUMBER(I13),I13,IF($T13="Weights",IF(ISNUMBER(Setup!$D$22),Setup!$D$22,0),IF($T13="Nights",IF(ISNUMBER(Setup!$E$22),Setup!$E$22,0),IF(OR($T13="Exact amounts",$T13="Custom units"),0,1)))))) -> 1 | W13: =IF($T13="",0,IF(OR(Setup!$B$23="",Setup!$C$23="No"),0,IF(ISNUMBER(J13),J13,IF($T13="Weights",IF(ISNUMBER(Setup!$D$23),Setup!$D$23,0),IF($T13="Nights",IF(ISNUMBER(Setup!$E$23),Setup!$E$23,0),IF(OR($T13="Exact amounts",$T13="Custom units"),0,1)))))) -> 1 | X13: =IF($T13="",0,IF(OR(Setup!$B$24="",Setup!$C$24="No"),0,IF(ISNUMBER(K13),K13,IF($T13="Weights",IF(ISNUMBER(Setup!$D$24),Setup!$D$24,0),IF($T13="Nights",IF(ISNUMBER(Setup!$E$24),Setup!$E$24,0),IF(OR($T13="Exact amounts",$T13="Custom units"),0,1)))))) -> 1 | Y13: =IF($T13="",0,IF(OR(Setup!$B$25="",Setup!$C$25="No"),0,IF(ISNUMBER(L13),L13,IF($T13="Weights",IF(ISNUMBER(Setup!$D$25),Setup!$D$25,0),IF($T13="Nights",IF(ISNUMBER(Setup!$E$25),Setup!$E$25,0),IF(OR($T13="Exact amounts",$T13="Custom units"),0,1)))))) -> 0 | Z13: =IF($T13="",0,IF(OR(Setup!$B$26="",Setup!$C$26="No"),0,IF(ISNUMBER(M13),M13,IF($T13="Weights",IF(ISNUMBER(Setup!$D$26),Setup!$D$26,0),IF($T13="Nights",IF(ISNUMBER(Setup!$E$26),Setup!$E$26,0),IF(OR($T13="Exact amounts",$T13="Custom units"),0,1)))))) -> 0 | AA13: =IF($T13="",0,IF(OR(Setup!$B$27="",Setup!$C$27="No"),0,IF(ISNUMBER(N13),N13,IF($T13="Weights",IF(ISNUMBER(Setup!$D$27),Setup!$D$27,0),IF($T13="Nights",IF(ISNUMBER(Setup!$E$27),Setup!$E$27,0),IF(OR($T13="Exact amounts",$T13="Custom units"),0,1)))))) -> 0 | AB13: =IF($T13="",0,IF(OR(Setup!$B$28="",Setup!$C$28="No"),0,IF(ISNUMBER(O13),O13,IF($T13="Weights",IF(ISNUMBER(Setup!$D$28),Setup!$D$28,0),IF($T13="Nights",IF(ISNUMBER(Setup!$E$28),Setup!$E$28,0),IF(OR($T13="Exact amounts",$T13="Custom units"),0,1)))))) -> 0 | AC13: =IF($T13="",0,IF(OR(Setup!$B$29="",Setup!$C$29="No"),0,IF(ISNUMBER(P13),P13,IF($T13="Weights",IF(ISNUMBER(Setup!$D$29),Setup!$D$29,0),IF($T13="Nights",IF(ISNUMBER(Setup!$E$29),Setup!$E$29,0),IF(OR($T13="Exact amounts",$T13="Custom units"),0,1)))))) -> 0 | AD13: =IF($T13="",0,IF(OR(Setup!$B$30="",Setup!$C$30="No"),0,IF(ISNUMBER(Q13),Q13,IF($T13="Weights",IF(ISNUMBER(Setup!$D$30),Setup!$D$30,0),IF($T13="Nights",IF(ISNUMBER(Setup!$E$30),Setup!$E$30,0),IF(OR($T13="Exact amounts",$T13="Custom units"),0,1)))))) -> 0 | AE13: =IF($T13="",0,SUM($U13:$AD13)) -> 4 | AF13: =IF($AE13<=0,1,$AE13) -> 4 | AG13: =IF(ISNUMBER($E13),$E13,0) -> 112.6
A14: =IF($T14="","—",ROW()-7) -> 7 | B14: =TODAY()-34 -> 46198 | C14: Pizza night at home | D14: Dana | E14: 61.5 | F14: Eating out | G14: Equal | L14: 0 | R14: =IF($T14="","",IF($D14="","Who paid?",IF(SUMPRODUCT((Setup!$B$21:$B$30=$D14)*1)=0,"Payer is not in the member list on Setup",IF($E14="","Amount missing — type the number in column E",IF(NOT(ISNUMBER($E14)),"Amount must be a plain number — no currency symbol, no text",IF(AND($T14="Custom units",$AE14<=0),"Custom units: nobody has units on this row — type a number for at least one person",IF($AE14<=0,"Nobody shares this row — check the person columns H–Q, and the Weight / Nights columns on Setup",IF(AND($T14="Exact amounts",ABS($AE14-$AG14)>0.01),"Exact amounts do not add up to the amount","OK")))))))) -> OK | S14: =IFERROR(IF(OR($T14="",$C$4=""),"—",ROUND($AG14*INDEX($U14:$AD14,1,MATCH($C$4,Setup!$B$21:$B$30,0))/$AF14,2)),"—") -> 15.38 | T14: =IF(AND($C14="",$D14="",NOT(ISNUMBER($E14))),"",IF($G14="",IF(Setup!$C$17="","Equal",Setup!$C$17),$G14)) -> Equal | U14: =IF($T14="",0,IF(OR(Setup!$B$21="",Setup!$C$21="No"),0,IF(ISNUMBER(H14),H14,IF($T14="Weights",IF(ISNUMBER(Setup!$D$21),Setup!$D$21,0),IF($T14="Nights",IF(ISNUMBER(Setup!$E$21),Setup!$E$21,0),IF(OR($T14="Exact amounts",$T14="Custom units"),0,1)))))) -> 1 | V14: =IF($T14="",0,IF(OR(Setup!$B$22="",Setup!$C$22="No"),0,IF(ISNUMBER(I14),I14,IF($T14="Weights",IF(ISNUMBER(Setup!$D$22),Setup!$D$22,0),IF($T14="Nights",IF(ISNUMBER(Setup!$E$22),Setup!$E$22,0),IF(OR($T14="Exact amounts",$T14="Custom units"),0,1)))))) -> 1 | W14: =IF($T14="",0,IF(OR(Setup!$B$23="",Setup!$C$23="No"),0,IF(ISNUMBER(J14),J14,IF($T14="Weights",IF(ISNUMBER(Setup!$D$23),Setup!$D$23,0),IF($T14="Nights",IF(ISNUMBER(Setup!$E$23),Setup!$E$23,0),IF(OR($T14="Exact amounts",$T14="Custom units"),0,1)))))) -> 1 | X14: =IF($T14="",0,IF(OR(Setup!$B$24="",Setup!$C$24="No"),0,IF(ISNUMBER(K14),K14,IF($T14="Weights",IF(ISNUMBER(Setup!$D$24),Setup!$D$24,0),IF($T14="Nights",IF(ISNUMBER(Setup!$E$24),Setup!$E$24,0),IF(OR($T14="Exact amounts",$T14="Custom units"),0,1)))))) -> 1 | Y14: =IF($T14="",0,IF(OR(Setup!$B$25="",Setup!$C$25="No"),0,IF(ISNUMBER(L14),L14,IF($T14="Weights",IF(ISNUMBER(Setup!$D$25),Setup!$D$25,0),IF($T14="Nights",IF(ISNUMBER(Setup!$E$25),Setup!$E$25,0),IF(OR($T14="Exact amounts",$T14="Custom units"),0,1)))))) -> 0 | Z14: =IF($T14="",0,IF(OR(Setup!$B$26="",Setup!$C$26="No"),0,IF(ISNUMBER(M14),M14,IF($T14="Weights",IF(ISNUMBER(Setup!$D$26),Setup!$D$26,0),IF($T14="Nights",IF(ISNUMBER(Setup!$E$26),Setup!$E$26,0),IF(OR($T14="Exact amounts",$T14="Custom units"),0,1)))))) -> 0 | AA14: =IF($T14="",0,IF(OR(Setup!$B$27="",Setup!$C$27="No"),0,IF(ISNUMBER(N14),N14,IF($T14="Weights",IF(ISNUMBER(Setup!$D$27),Setup!$D$27,0),IF($T14="Nights",IF(ISNUMBER(Setup!$E$27),Setup!$E$27,0),IF(OR($T14="Exact amounts",$T14="Custom units"),0,1)))))) -> 0 | AB14: =IF($T14="",0,IF(OR(Setup!$B$28="",Setup!$C$28="No"),0,IF(ISNUMBER(O14),O14,IF($T14="Weights",IF(ISNUMBER(Setup!$D$28),Setup!$D$28,0),IF($T14="Nights",IF(ISNUMBER(Setup!$E$28),Setup!$E$28,0),IF(OR($T14="Exact amounts",$T14="Custom units"),0,1)))))) -> 0 | AC14: =IF($T14="",0,IF(OR(Setup!$B$29="",Setup!$C$29="No"),0,IF(ISNUMBER(P14),P14,IF($T14="Weights",IF(ISNUMBER(Setup!$D$29),Setup!$D$29,0),IF($T14="Nights",IF(ISNUMBER(Setup!$E$29),Setup!$E$29,0),IF(OR($T14="Exact amounts",$T14="Custom units"),0,1)))))) -> 0 | AD14: =IF($T14="",0,IF(OR(Setup!$B$30="",Setup!$C$30="No"),0,IF(ISNUMBER(Q14),Q14,IF($T14="Weights",IF(ISNUMBER(Setup!$D$30),Setup!$D$30,0),IF($T14="Nights",IF(ISNUMBER(Setup!$E$30),Setup!$E$30,0),IF(OR($T14="Exact amounts",$T14="Custom units"),0,1)))))) -> 0 | AE14: =IF($T14="",0,SUM($U14:$AD14)) -> 4 | AF14: =IF($AE14<=0,1,$AE14) -> 4 | AG14: =IF(ISNUMBER($E14),$E14,0) -> 61.5
A15: =IF($T15="","—",ROW()-7) -> 8 | B15: =TODAY()-32 -> 46200 | C15: Weekly groceries | D15: Anna | E15: 88.9 | F15: Groceries | G15: Equal | L15: 0 | R15: =IF($T15="","",IF($D15="","Who paid?",IF(SUMPRODUCT((Setup!$B$21:$B$30=$D15)*1)=0,"Payer is not in the member list on Setup",IF($E15="","Amount missing — type the number in column E",IF(NOT(ISNUMBER($E15)),"Amount must be a plain number — no currency symbol, no text",IF(AND($T15="Custom units",$AE15<=0),"Custom units: nobody has units on this row — type a number for at least one person",IF($AE15<=0,"Nobody shares this row — check the person columns H–Q, and the Weight / Nights columns on Setup",IF(AND($T15="Exact amounts",ABS($AE15-$AG15)>0.01),"Exact amounts do not add up to the amount","OK")))))))) -> OK | S15: =IFERROR(IF(OR($T15="",$C$4=""),"—",ROUND($AG15*INDEX($U15:$AD15,1,MATCH($C$4,Setup!$B$21:$B$30,0))/$AF15,2)),"—") -> 22.23 | T15: =IF(AND($C15="",$D15="",NOT(ISNUMBER($E15))),"",IF($G15="",IF(Setup!$C$17="","Equal",Setup!$C$17),$G15)) -> Equal | U15: =IF($T15="",0,IF(OR(Setup!$B$21="",Setup!$C$21="No"),0,IF(ISNUMBER(H15),H15,IF($T15="Weights",IF(ISNUMBER(Setup!$D$21),Setup!$D$21,0),IF($T15="Nights",IF(ISNUMBER(Setup!$E$21),Setup!$E$21,0),IF(OR($T15="Exact amounts",$T15="Custom units"),0,1)))))) -> 1 | V15: =IF($T15="",0,IF(OR(Setup!$B$22="",Setup!$C$22="No"),0,IF(ISNUMBER(I15),I15,IF($T15="Weights",IF(ISNUMBER(Setup!$D$22),Setup!$D$22,0),IF($T15="Nights",IF(ISNUMBER(Setup!$E$22),Setup!$E$22,0),IF(OR($T15="Exact amounts",$T15="Custom units"),0,1)))))) -> 1 | W15: =IF($T15="",0,IF(OR(Setup!$B$23="",Setup!$C$23="No"),0,IF(ISNUMBER(J15),J15,IF($T15="Weights",IF(ISNUMBER(Setup!$D$23),Setup!$D$23,0),IF($T15="Nights",IF(ISNUMBER(Setup!$E$23),Setup!$E$23,0),IF(OR($T15="Exact amounts",$T15="Custom units"),0,1)))))) -> 1 | X15: =IF($T15="",0,IF(OR(Setup!$B$24="",Setup!$C$24="No"),0,IF(ISNUMBER(K15),K15,IF($T15="Weights",IF(ISNUMBER(Setup!$D$24),Setup!$D$24,0),IF($T15="Nights",IF(ISNUMBER(Setup!$E$24),Setup!$E$24,0),IF(OR($T15="Exact amounts",$T15="Custom units"),0,1)))))) -> 1 | Y15: =IF($T15="",0,IF(OR(Setup!$B$25="",Setup!$C$25="No"),0,IF(ISNUMBER(L15),L15,IF($T15="Weights",IF(ISNUMBER(Setup!$D$25),Setup!$D$25,0),IF($T15="Nights",IF(ISNUMBER(Setup!$E$25),Setup!$E$25,0),IF(OR($T15="Exact amounts",$T15="Custom units"),0,1)))))) -> 0 | Z15: =IF($T15="",0,IF(OR(Setup!$B$26="",Setup!$C$26="No"),0,IF(ISNUMBER(M15),M15,IF($T15="Weights",IF(ISNUMBER(Setup!$D$26),Setup!$D$26,0),IF($T15="Nights",IF(ISNUMBER(Setup!$E$26),Setup!$E$26,0),IF(OR($T15="Exact amounts",$T15="Custom units"),0,1)))))) -> 0 | AA15: =IF($T15="",0,IF(OR(Setup!$B$27="",Setup!$C$27="No"),0,IF(ISNUMBER(N15),N15,IF($T15="Weights",IF(ISNUMBER(Setup!$D$27),Setup!$D$27,0),IF($T15="Nights",IF(ISNUMBER(Setup!$E$27),Setup!$E$27,0),IF(OR($T15="Exact amounts",$T15="Custom units"),0,1)))))) -> 0 | AB15: =IF($T15="",0,IF(OR(Setup!$B$28="",Setup!$C$28="No"),0,IF(ISNUMBER(O15),O15,IF($T15="Weights",IF(ISNUMBER(Setup!$D$28),Setup!$D$28,0),IF($T15="Nights",IF(ISNUMBER(Setup!$E$28),Setup!$E$28,0),IF(OR($T15="Exact amounts",$T15="Custom units"),0,1)))))) -> 0 | AC15: =IF($T15="",0,IF(OR(Setup!$B$29="",Setup!$C$29="No"),0,IF(ISNUMBER(P15),P15,IF($T15="Weights",IF(ISNUMBER(Setup!$D$29),Setup!$D$29,0),IF($T15="Nights",IF(ISNUMBER(Setup!$E$29),Setup!$E$29,0),IF(OR($T15="Exact amounts",$T15="Custom units"),0,1)))))) -> 0 | AD15: =IF($T15="",0,IF(OR(Setup!$B$30="",Setup!$C$30="No"),0,IF(ISNUMBER(Q15),Q15,IF($T15="Weights",IF(ISNUMBER(Setup!$D$30),Setup!$D$30,0),IF($T15="Nights",IF(ISNUMBER(Setup!$E$30),Setup!$E$30,0),IF(OR($T15="Exact amounts",$T15="Custom units"),0,1)))))) -> 0 | AE15: =IF($T15="",0,SUM($U15:$AD15)) -> 4 | AF15: =IF($AE15<=0,1,$AE15) -> 4 | AG15: =IF(ISNUMBER($E15),$E15,0) -> 88.9
A16: =IF($T16="","—",ROW()-7) -> 9 | B16: =TODAY()-30 -> 46202 | C16: Supermarket — shared + 2 personal items | D16: Chris | E16: 76.4 | F16: Groceries | G16: Exact amounts | H16: 24.9 | I16: 15 | J16: 15 | K16: 21.5 | R16: =IF($T16="","",IF($D16="","Who paid?",IF(SUMPRODUCT((Setup!$B$21:$B$30=$D16)*1)=0,"Payer is not in the member list on Setup",IF($E16="","Amount missing — type the number in column E",IF(NOT(ISNUMBER($E16)),"Amount must be a plain number — no currency symbol, no text",IF(AND($T16="Custom units",$AE16<=0),"Custom units: nobody has units on this row — type a number for at least one person",IF($AE16<=0,"Nobody shares this row — check the person columns H–Q, and the Weight / Nights columns on Setup",IF(AND($T16="Exact amounts",ABS($AE16-$AG16)>0.01),"Exact amounts do not add up to the amount","OK")))))))) -> OK | S16: =IFERROR(IF(OR($T16="",$C$4=""),"—",ROUND($AG16*INDEX($U16:$AD16,1,MATCH($C$4,Setup!$B$21:$B$30,0))/$AF16,2)),"—") -> 24.9 | T16: =IF(AND($C16="",$D16="",NOT(ISNUMBER($E16))),"",IF($G16="",IF(Setup!$C$17="","Equal",Setup!$C$17),$G16)) -> Exact amounts | U16: =IF($T16="",0,IF(OR(Setup!$B$21="",Setup!$C$21="No"),0,IF(ISNUMBER(H16),H16,IF($T16="Weights",IF(ISNUMBER(Setup!$D$21),Setup!$D$21,0),IF($T16="Nights",IF(ISNUMBER(Setup!$E$21),Setup!$E$21,0),IF(OR($T16="Exact amounts",$T16="Custom units"),0,1)))))) -> 24.9 | V16: =IF($T16="",0,IF(OR(Setup!$B$22="",Setup!$C$22="No"),0,IF(ISNUMBER(I16),I16,IF($T16="Weights",IF(ISNUMBER(Setup!$D$22),Setup!$D$22,0),IF($T16="Nights",IF(ISNUMBER(Setup!$E$22),Setup!$E$22,0),IF(OR($T16="Exact amounts",$T16="Custom units"),0,1)))))) -> 15 | W16: =IF($T16="",0,IF(OR(Setup!$B$23="",Setup!$C$23="No"),0,IF(ISNUMBER(J16),J16,IF($T16="Weights",IF(ISNUMBER(Setup!$D$23),Setup!$D$23,0),IF($T16="Nights",IF(ISNUMBER(Setup!$E$23),Setup!$E$23,0),IF(OR($T16="Exact amounts",$T16="Custom units"),0,1)))))) -> 15 | X16: =IF($T16="",0,IF(OR(Setup!$B$24="",Setup!$C$24="No"),0,IF(ISNUMBER(K16),K16,IF($T16="Weights",IF(ISNUMBER(Setup!$D$24),Setup!$D$24,0),IF($T16="Nights",IF(ISNUMBER(Setup!$E$24),Setup!$E$24,0),IF(OR($T16="Exact amounts",$T16="Custom units"),0,1)))))) -> 21.5 | Y16: =IF($T16="",0,IF(OR(Setup!$B$25="",Setup!$C$25="No"),0,IF(ISNUMBER(L16),L16,IF($T16="Weights",IF(ISNUMBER(Setup!$D$25),Setup!$D$25,0),IF($T16="Nights",IF(ISNUMBER(Setup!$E$25),Setup!$E$25,0),IF(OR($T16="Exact amounts",$T16="Custom units"),0,1)))))) -> 0 | Z16: =IF($T16="",0,IF(OR(Setup!$B$26="",Setup!$C$26="No"),0,IF(ISNUMBER(M16),M16,IF($T16="Weights",IF(ISNUMBER(Setup!$D$26),Setup!$D$26,0),IF($T16="Nights",IF(ISNUMBER(Setup!$E$26),Setup!$E$26,0),IF(OR($T16="Exact amounts",$T16="Custom units"),0,1)))))) -> 0 | AA16: =IF($T16="",0,IF(OR(Setup!$B$27="",Setup!$C$27="No"),0,IF(ISNUMBER(N16),N16,IF($T16="Weights",IF(ISNUMBER(Setup!$D$27),Setup!$D$27,0),IF($T16="Nights",IF(ISNUMBER(Setup!$E$27),Setup!$E$27,0),IF(OR($T16="Exact amounts",$T16="Custom units"),0,1)))))) -> 0 | AB16: =IF($T16="",0,IF(OR(Setup!$B$28="",Setup!$C$28="No"),0,IF(ISNUMBER(O16),O16,IF($T16="Weights",IF(ISNUMBER(Setup!$D$28),Setup!$D$28,0),IF($T16="Nights",IF(ISNUMBER(Setup!$E$28),Setup!$E$28,0),IF(OR($T16="Exact amounts",$T16="Custom units"),0,1)))))) -> 0 | AC16: =IF($T16="",0,IF(OR(Setup!$B$29="",Setup!$C$29="No"),0,IF(ISNUMBER(P16),P16,IF($T16="Weights",IF(ISNUMBER(Setup!$D$29),Setup!$D$29,0),IF($T16="Nights",IF(ISNUMBER(Setup!$E$29),Setup!$E$29,0),IF(OR($T16="Exact amounts",$T16="Custom units"),0,1)))))) -> 0 | AD16: =IF($T16="",0,IF(OR(Setup!$B$30="",Setup!$C$30="No"),0,IF(ISNUMBER(Q16),Q16,IF($T16="Weights",IF(ISNUMBER(Setup!$D$30),Setup!$D$30,0),IF($T16="Nights",IF(ISNUMBER(Setup!$E$30),Setup!$E$30,0),IF(OR($T16="Exact amounts",$T16="Custom units"),0,1)))))) -> 0 | AE16: =IF($T16="",0,SUM($U16:$AD16)) -> 76.4 | AF16: =IF($AE16<=0,1,$AE16) -> 76.4 | AG16: =IF(ISNUMBER($E16),$E16,0) -> 76.4
A17: =IF($T17="","—",ROW()-7) -> 10 | B17: =TODAY()-28 -> 46204 | C17: New wifi router | D17: Ben | E17: 79 | F17: Household & repairs | G17: Equal | L17: 0 | R17: =IF($T17="","",IF($D17="","Who paid?",IF(SUMPRODUCT((Setup!$B$21:$B$30=$D17)*1)=0,"Payer is not in the member list on Setup",IF($E17="","Amount missing — type the number in column E",IF(NOT(ISNUMBER($E17)),"Amount must be a plain number — no currency symbol, no text",IF(AND($T17="Custom units",$AE17<=0),"Custom units: nobody has units on this row — type a number for at least one person",IF($AE17<=0,"Nobody shares this row — check the person columns H–Q, and the Weight / Nights columns on Setup",IF(AND($T17="Exact amounts",ABS($AE17-$AG17)>0.01),"Exact amounts do not add up to the amount","OK")))))))) -> OK | S17: =IFERROR(IF(OR($T17="",$C$4=""),"—",ROUND($AG17*INDEX($U17:$AD17,1,MATCH($C$4,Setup!$B$21:$B$30,0))/$AF17,2)),"—") -> 19.75 | T17: =IF(AND($C17="",$D17="",NOT(ISNUMBER($E17))),"",IF($G17="",IF(Setup!$C$17="","Equal",Setup!$C$17),$G17)) -> Equal | U17: =IF($T17="",0,IF(OR(Setup!$B$21="",Setup!$C$21="No"),0,IF(ISNUMBER(H17),H17,IF($T17="Weights",IF(ISNUMBER(Setup!$D$21),Setup!$D$21,0),IF($T17="Nights",IF(ISNUMBER(Setup!$E$21),Setup!$E$21,0),IF(OR($T17="Exact amounts",$T17="Custom units"),0,1)))))) -> 1 | V17: =IF($T17="",0,IF(OR(Setup!$B$22="",Setup!$C$22="No"),0,IF(ISNUMBER(I17),I17,IF($T17="Weights",IF(ISNUMBER(Setup!$D$22),Setup!$D$22,0),IF($T17="Nights",IF(ISNUMBER(Setup!$E$22),Setup!$E$22,0),IF(OR($T17="Exact amounts",$T17="Custom units"),0,1)))))) -> 1 | W17: =IF($T17="",0,IF(OR(Setup!$B$23="",Setup!$C$23="No"),0,IF(ISNUMBER(J17),J17,IF($T17="Weights",IF(ISNUMBER(Setup!$D$23),Setup!$D$23,0),IF($T17="Nights",IF(ISNUMBER(Setup!$E$23),Setup!$E$23,0),IF(OR($T17="Exact amounts",$T17="Custom units"),0,1)))))) -> 1 | X17: =IF($T17="",0,IF(OR(Setup!$B$24="",Setup!$C$24="No"),0,IF(ISNUMBER(K17),K17,IF($T17="Weights",IF(ISNUMBER(Setup!$D$24),Setup!$D$24,0),IF($T17="Nights",IF(ISNUMBER(Setup!$E$24),Setup!$E$24,0),IF(OR($T17="Exact amounts",$T17="Custom units"),0,1)))))) -> 1 | Y17: =IF($T17="",0,IF(OR(Setup!$B$25="",Setup!$C$25="No"),0,IF(ISNUMBER(L17),L17,IF($T17="Weights",IF(ISNUMBER(Setup!$D$25),Setup!$D$25,0),IF($T17="Nights",IF(ISNUMBER(Setup!$E$25),Setup!$E$25,0),IF(OR($T17="Exact amounts",$T17="Custom units"),0,1)))))) -> 0 | Z17: =IF($T17="",0,IF(OR(Setup!$B$26="",Setup!$C$26="No"),0,IF(ISNUMBER(M17),M17,IF($T17="Weights",IF(ISNUMBER(Setup!$D$26),Setup!$D$26,0),IF($T17="Nights",IF(ISNUMBER(Setup!$E$26),Setup!$E$26,0),IF(OR($T17="Exact amounts",$T17="Custom units"),0,1)))))) -> 0 | AA17: =IF($T17="",0,IF(OR(Setup!$B$27="",Setup!$C$27="No"),0,IF(ISNUMBER(N17),N17,IF($T17="Weights",IF(ISNUMBER(Setup!$D$27),Setup!$D$27,0),IF($T17="Nights",IF(ISNUMBER(Setup!$E$27),Setup!$E$27,0),IF(OR($T17="Exact amounts",$T17="Custom units"),0,1)))))) -> 0 | AB17: =IF($T17="",0,IF(OR(Setup!$B$28="",Setup!$C$28="No"),0,IF(ISNUMBER(O17),O17,IF($T17="Weights",IF(ISNUMBER(Setup!$D$28),Setup!$D$28,0),IF($T17="Nights",IF(ISNUMBER(Setup!$E$28),Setup!$E$28,0),IF(OR($T17="Exact amounts",$T17="Custom units"),0,1)))))) -> 0 | AC17: =IF($T17="",0,IF(OR(Setup!$B$29="",Setup!$C$29="No"),0,IF(ISNUMBER(P17),P17,IF($T17="Weights",IF(ISNUMBER(Setup!$D$29),Setup!$D$29,0),IF($T17="Nights",IF(ISNUMBER(Setup!$E$29),Setup!$E$29,0),IF(OR($T17="Exact amounts",$T17="Custom units"),0,1)))))) -> 0 | AD17: =IF($T17="",0,IF(OR(Setup!$B$30="",Setup!$C$30="No"),0,IF(ISNUMBER(Q17),Q17,IF($T17="Weights",IF(ISNUMBER(Setup!$D$30),Setup!$D$30,0),IF($T17="Nights",IF(ISNUMBER(Setup!$E$30),Setup!$E$30,0),IF(OR($T17="Exact amounts",$T17="Custom units"),0,1)))))) -> 0 | AE17: =IF($T17="",0,SUM($U17:$AD17)) -> 4 | AF17: =IF($AE17<=0,1,$AE17) -> 4 | AG17: =IF(ISNUMBER($E17),$E17,0) -> 79
A18: =IF($T18="","—",ROW()-7) -> 11 | B18: =TODAY()-21 -> 46211 | C18: Flights Munich → Lisbon (5 tickets) | D18: Anna | E18: 745 | F18: Travel & transport | G18: Equal | R18: =IF($T18="","",IF($D18="","Who paid?",IF(SUMPRODUCT((Setup!$B$21:$B$30=$D18)*1)=0,"Payer is not in the member list on Setup",IF($E18="","Amount missing — type the number in column E",IF(NOT(ISNUMBER($E18)),"Amount must be a plain number — no currency symbol, no text",IF(AND($T18="Custom units",$AE18<=0),"Custom units: nobody has units on this row — type a number for at least one person",IF($AE18<=0,"Nobody shares this row — check the person columns H–Q, and the Weight / Nights columns on Setup",IF(AND($T18="Exact amounts",ABS($AE18-$AG18)>0.01),"Exact amounts do not add up to the amount","OK")))))))) -> OK | S18: =IFERROR(IF(OR($T18="",$C$4=""),"—",ROUND($AG18*INDEX($U18:$AD18,1,MATCH($C$4,Setup!$B$21:$B$30,0))/$AF18,2)),"—") -> 149 | T18: =IF(AND($C18="",$D18="",NOT(ISNUMBER($E18))),"",IF($G18="",IF(Setup!$C$17="","Equal",Setup!$C$17),$G18)) -> Equal | U18: =IF($T18="",0,IF(OR(Setup!$B$21="",Setup!$C$21="No"),0,IF(ISNUMBER(H18),H18,IF($T18="Weights",IF(ISNUMBER(Setup!$D$21),Setup!$D$21,0),IF($T18="Nights",IF(ISNUMBER(Setup!$E$21),Setup!$E$21,0),IF(OR($T18="Exact amounts",$T18="Custom units"),0,1)))))) -> 1 | V18: =IF($T18="",0,IF(OR(Setup!$B$22="",Setup!$C$22="No"),0,IF(ISNUMBER(I18),I18,IF($T18="Weights",IF(ISNUMBER(Setup!$D$22),Setup!$D$22,0),IF($T18="Nights",IF(ISNUMBER(Setup!$E$22),Setup!$E$22,0),IF(OR($T18="Exact amounts",$T18="Custom units"),0,1)))))) -> 1 | W18: =IF($T18="",0,IF(OR(Setup!$B$23="",Setup!$C$23="No"),0,IF(ISNUMBER(J18),J18,IF($T18="Weights",IF(ISNUMBER(Setup!$D$23),Setup!$D$23,0),IF($T18="Nights",IF(ISNUMBER(Setup!$E$23),Setup!$E$23,0),IF(OR($T18="Exact amounts",$T18="Custom units"),0,1)))))) -> 1 | X18: =IF($T18="",0,IF(OR(Setup!$B$24="",Setup!$C$24="No"),0,IF(ISNUMBER(K18),K18,IF($T18="Weights",IF(ISNUMBER(Setup!$D$24),Setup!$D$24,0),IF($T18="Nights",IF(ISNUMBER(Setup!$E$24),Setup!$E$24,0),IF(OR($T18="Exact amounts",$T18="Custom units"),0,1)))))) -> 1 | Y18: =IF($T18="",0,IF(OR(Setup!$B$25="",Setup!$C$25="No"),0,IF(ISNUMBER(L18),L18,IF($T18="Weights",IF(ISNUMBER(Setup!$D$25),Setup!$D$25,0),IF($T18="Nights",IF(ISNUMBER(Setup!$E$25),Setup!$E$25,0),IF(OR($T18="Exact amounts",$T18="Custom units"),0,1)))))) -> 1 | Z18: =IF($T18="",0,IF(OR(Setup!$B$26="",Setup!$C$26="No"),0,IF(ISNUMBER(M18),M18,IF($T18="Weights",IF(ISNUMBER(Setup!$D$26),Setup!$D$26,0),IF($T18="Nights",IF(ISNUMBER(Setup!$E$26),Setup!$E$26,0),IF(OR($T18="Exact amounts",$T18="Custom units"),0,1)))))) -> 0 | AA18: =IF($T18="",0,IF(OR(Setup!$B$27="",Setup!$C$27="No"),0,IF(ISNUMBER(N18),N18,IF($T18="Weights",IF(ISNUMBER(Setup!$D$27),Setup!$D$27,0),IF($T18="Nights",IF(ISNUMBER(Setup!$E$27),Setup!$E$27,0),IF(OR($T18="Exact amounts",$T18="Custom units"),0,1)))))) -> 0 | AB18: =IF($T18="",0,IF(OR(Setup!$B$28="",Setup!$C$28="No"),0,IF(ISNUMBER(O18),O18,IF($T18="Weights",IF(ISNUMBER(Setup!$D$28),Setup!$D$28,0),IF($T18="Nights",IF(ISNUMBER(Setup!$E$28),Setup!$E$28,0),IF(OR($T18="Exact amounts",$T18="Custom units"),0,1)))))) -> 0 | AC18: =IF($T18="",0,IF(OR(Setup!$B$29="",Setup!$C$29="No"),0,IF(ISNUMBER(P18),P18,IF($T18="Weights",IF(ISNUMBER(Setup!$D$29),Setup!$D$29,0),IF($T18="Nights",IF(ISNUMBER(Setup!$E$29),Setup!$E$29,0),IF(OR($T18="Exact amounts",$T18="Custom units"),0,1)))))) -> 0 | AD18: =IF($T18="",0,IF(OR(Setup!$B$30="",Setup!$C$30="No"),0,IF(ISNUMBER(Q18),Q18,IF($T18="Weights",IF(ISNUMBER(Setup!$D$30),Setup!$D$30,0),IF($T18="Nights",IF(ISNUMBER(Setup!$E$30),Setup!$E$30,0),IF(OR($T18="Exact amounts",$T18="Custom units"),0,1)))))) -> 0 | AE18: =IF($T18="",0,SUM($U18:$AD18)) -> 5 | AF18: =IF($AE18<=0,1,$AE18) -> 5 | AG18: =IF(ISNUMBER($E18),$E18,0) -> 745
A19: =IF($T19="","—",ROW()-7) -> 12 | B19: =TODAY()-20 -> 46212 | C19: Lisbon apartment, 7 nights | D19: Ben | E19: 980 | F19: Accommodation | G19: Nights | R19: =IF($T19="","",IF($D19="","Who paid?",IF(SUMPRODUCT((Setup!$B$21:$B$30=$D19)*1)=0,"Payer is not in the member list on Setup",IF($E19="","Amount missing — type the number in column E",IF(NOT(ISNUMBER($E19)),"Amount must be a plain number — no currency symbol, no text",IF(AND($T19="Custom units",$AE19<=0),"Custom units: nobody has units on this row — type a number for at least one person",IF($AE19<=0,"Nobody shares this row — check the person columns H–Q, and the Weight / Nights columns on Setup",IF(AND($T19="Exact amounts",ABS($AE19-$AG19)>0.01),"Exact amounts do not add up to the amount","OK")))))))) -> OK | S19: =IFERROR(IF(OR($T19="",$C$4=""),"—",ROUND($AG19*INDEX($U19:$AD19,1,MATCH($C$4,Setup!$B$21:$B$30,0))/$AF19,2)),"—") -> 245 | T19: =IF(AND($C19="",$D19="",NOT(ISNUMBER($E19))),"",IF($G19="",IF(Setup!$C$17="","Equal",Setup!$C$17),$G19)) -> Nights | U19: =IF($T19="",0,IF(OR(Setup!$B$21="",Setup!$C$21="No"),0,IF(ISNUMBER(H19),H19,IF($T19="Weights",IF(ISNUMBER(Setup!$D$21),Setup!$D$21,0),IF($T19="Nights",IF(ISNUMBER(Setup!$E$21),Setup!$E$21,0),IF(OR($T19="Exact amounts",$T19="Custom units"),0,1)))))) -> 7 | V19: =IF($T19="",0,IF(OR(Setup!$B$22="",Setup!$C$22="No"),0,IF(ISNUMBER(I19),I19,IF($T19="Weights",IF(ISNUMBER(Setup!$D$22),Setup!$D$22,0),IF($T19="Nights",IF(ISNUMBER(Setup!$E$22),Setup!$E$22,0),IF(OR($T19="Exact amounts",$T19="Custom units"),0,1)))))) -> 7 | W19: =IF($T19="",0,IF(OR(Setup!$B$23="",Setup!$C$23="No"),0,IF(ISNUMBER(J19),J19,IF($T19="Weights",IF(ISNUMBER(Setup!$D$23),Setup!$D$23,0),IF($T19="Nights",IF(ISNUMBER(Setup!$E$23),Setup!$E$23,0),IF(OR($T19="Exact amounts",$T19="Custom units"),0,1)))))) -> 3 | X19: =IF($T19="",0,IF(OR(Setup!$B$24="",Setup!$C$24="No"),0,IF(ISNUMBER(K19),K19,IF($T19="Weights",IF(ISNUMBER(Setup!$D$24),Setup!$D$24,0),IF($T19="Nights",IF(ISNUMBER(Setup!$E$24),Setup!$E$24,0),IF(OR($T19="Exact amounts",$T19="Custom units"),0,1)))))) -> 4 | Y19: =IF($T19="",0,IF(OR(Setup!$B$25="",Setup!$C$25="No"),0,IF(ISNUMBER(L19),L19,IF($T19="Weights",IF(ISNUMBER(Setup!$D$25),Setup!$D$25,0),IF($T19="Nights",IF(ISNUMBER(Setup!$E$25),Setup!$E$25,0),IF(OR($T19="Exact amounts",$T19="Custom units"),0,1)))))) -> 7 | Z19: =IF($T19="",0,IF(OR(Setup!$B$26="",Setup!$C$26="No"),0,IF(ISNUMBER(M19),M19,IF($T19="Weights",IF(ISNUMBER(Setup!$D$26),Setup!$D$26,0),IF($T19="Nights",IF(ISNUMBER(Setup!$E$26),Setup!$E$26,0),IF(OR($T19="Exact amounts",$T19="Custom units"),0,1)))))) -> 0 | AA19: =IF($T19="",0,IF(OR(Setup!$B$27="",Setup!$C$27="No"),0,IF(ISNUMBER(N19),N19,IF($T19="Weights",IF(ISNUMBER(Setup!$D$27),Setup!$D$27,0),IF($T19="Nights",IF(ISNUMBER(Setup!$E$27),Setup!$E$27,0),IF(OR($T19="Exact amounts",$T19="Custom units"),0,1)))))) -> 0 | AB19: =IF($T19="",0,IF(OR(Setup!$B$28="",Setup!$C$28="No"),0,IF(ISNUMBER(O19),O19,IF($T19="Weights",IF(ISNUMBER(Setup!$D$28),Setup!$D$28,0),IF($T19="Nights",IF(ISNUMBER(Setup!$E$28),Setup!$E$28,0),IF(OR($T19="Exact amounts",$T19="Custom units"),0,1)))))) -> 0 | AC19: =IF($T19="",0,IF(OR(Setup!$B$29="",Setup!$C$29="No"),0,IF(ISNUMBER(P19),P19,IF($T19="Weights",IF(ISNUMBER(Setup!$D$29),Setup!$D$29,0),IF($T19="Nights",IF(ISNUMBER(Setup!$E$29),Setup!$E$29,0),IF(OR($T19="Exact amounts",$T19="Custom units"),0,1)))))) -> 0 | AD19: =IF($T19="",0,IF(OR(Setup!$B$30="",Setup!$C$30="No"),0,IF(ISNUMBER(Q19),Q19,IF($T19="Weights",IF(ISNUMBER(Setup!$D$30),Setup!$D$30,0),IF($T19="Nights",IF(ISNUMBER(Setup!$E$30),Setup!$E$30,0),IF(OR($T19="Exact amounts",$T19="Custom units"),0,1)))))) -> 0 | AE19: =IF($T19="",0,SUM($U19:$AD19)) -> 28 | AF19: =IF($AE19<=0,1,$AE19) -> 28 | AG19: =IF(ISNUMBER($E19),$E19,0) -> 980
A20: =IF($T20="","—",ROW()-7) -> 13 | B20: =TODAY()-19 -> 46213 | C20: Airport transfer | D20: Chris | E20: 48 | F20: Travel & transport | G20: Equal | R20: =IF($T20="","",IF($D20="","Who paid?",IF(SUMPRODUCT((Setup!$B$21:$B$30=$D20)*1)=0,"Payer is not in the member list on Setup",IF($E20="","Amount missing — type the number in column E",IF(NOT(ISNUMBER($E20)),"Amount must be a plain number — no currency symbol, no text",IF(AND($T20="Custom units",$AE20<=0),"Custom units: nobody has units on this row — type a number for at least one person",IF($AE20<=0,"Nobody shares this row — check the person columns H–Q, and the Weight / Nights columns on Setup",IF(AND($T20="Exact amounts",ABS($AE20-$AG20)>0.01),"Exact amounts do not add up to the amount","OK")))))))) -> OK | S20: =IFERROR(IF(OR($T20="",$C$4=""),"—",ROUND($AG20*INDEX($U20:$AD20,1,MATCH($C$4,Setup!$B$21:$B$30,0))/$AF20,2)),"—") -> 9.6 | T20: =IF(AND($C20="",$D20="",NOT(ISNUMBER($E20))),"",IF($G20="",IF(Setup!$C$17="","Equal",Setup!$C$17),$G20)) -> Equal | U20: =IF($T20="",0,IF(OR(Setup!$B$21="",Setup!$C$21="No"),0,IF(ISNUMBER(H20),H20,IF($T20="Weights",IF(ISNUMBER(Setup!$D$21),Setup!$D$21,0),IF($T20="Nights",IF(ISNUMBER(Setup!$E$21),Setup!$E$21,0),IF(OR($T20="Exact amounts",$T20="Custom units"),0,1)))))) -> 1 | V20: =IF($T20="",0,IF(OR(Setup!$B$22="",Setup!$C$22="No"),0,IF(ISNUMBER(I20),I20,IF($T20="Weights",IF(ISNUMBER(Setup!$D$22),Setup!$D$22,0),IF($T20="Nights",IF(ISNUMBER(Setup!$E$22),Setup!$E$22,0),IF(OR($T20="Exact amounts",$T20="Custom units"),0,1)))))) -> 1 | W20: =IF($T20="",0,IF(OR(Setup!$B$23="",Setup!$C$23="No"),0,IF(ISNUMBER(J20),J20,IF($T20="Weights",IF(ISNUMBER(Setup!$D$23),Setup!$D$23,0),IF($T20="Nights",IF(ISNUMBER(Setup!$E$23),Setup!$E$23,0),IF(OR($T20="Exact amounts",$T20="Custom units"),0,1)))))) -> 1 | X20: =IF($T20="",0,IF(OR(Setup!$B$24="",Setup!$C$24="No"),0,IF(ISNUMBER(K20),K20,IF($T20="Weights",IF(ISNUMBER(Setup!$D$24),Setup!$D$24,0),IF($T20="Nights",IF(ISNUMBER(Setup!$E$24),Setup!$E$24,0),IF(OR($T20="Exact amounts",$T20="Custom units"),0,1)))))) -> 1 | Y20: =IF($T20="",0,IF(OR(Setup!$B$25="",Setup!$C$25="No"),0,IF(ISNUMBER(L20),L20,IF($T20="Weights",IF(ISNUMBER(Setup!$D$25),Setup!$D$25,0),IF($T20="Nights",IF(ISNUMBER(Setup!$E$25),Setup!$E$25,0),IF(OR($T20="Exact amounts",$T20="Custom units"),0,1)))))) -> 1 | Z20: =IF($T20="",0,IF(OR(Setup!$B$26="",Setup!$C$26="No"),0,IF(ISNUMBER(M20),M20,IF($T20="Weights",IF(ISNUMBER(Setup!$D$26),Setup!$D$26,0),IF($T20="Nights",IF(ISNUMBER(Setup!$E$26),Setup!$E$26,0),IF(OR($T20="Exact amounts",$T20="Custom units"),0,1)))))) -> 0 | AA20: =IF($T20="",0,IF(OR(Setup!$B$27="",Setup!$C$27="No"),0,IF(ISNUMBER(N20),N20,IF($T20="Weights",IF(ISNUMBER(Setup!$D$27),Setup!$D$27,0),IF($T20="Nights",IF(ISNUMBER(Setup!$E$27),Setup!$E$27,0),IF(OR($T20="Exact amounts",$T20="Custom units"),0,1)))))) -> 0 | AB20: =IF($T20="",0,IF(OR(Setup!$B$28="",Setup!$C$28="No"),0,IF(ISNUMBER(O20),O20,IF($T20="Weights",IF(ISNUMBER(Setup!$D$28),Setup!$D$28,0),IF($T20="Nights",IF(ISNUMBER(Setup!$E$28),Setup!$E$28,0),IF(OR($T20="Exact amounts",$T20="Custom units"),0,1)))))) -> 0 | AC20: =IF($T20="",0,IF(OR(Setup!$B$29="",Setup!$C$29="No"),0,IF(ISNUMBER(P20),P20,IF($T20="Weights",IF(ISNUMBER(Setup!$D$29),Setup!$D$29,0),IF($T20="Nights",IF(ISNUMBER(Setup!$E$29),Setup!$E$29,0),IF(OR($T20="Exact amounts",$T20="Custom units"),0,1)))))) -> 0 | AD20: =IF($T20="",0,IF(OR(Setup!$B$30="",Setup!$C$30="No"),0,IF(ISNUMBER(Q20),Q20,IF($T20="Weights",IF(ISNUMBER(Setup!$D$30),Setup!$D$30,0),IF($T20="Nights",IF(ISNUMBER(Setup!$E$30),Setup!$E$30,0),IF(OR($T20="Exact amounts",$T20="Custom units"),0,1)))))) -> 0 | AE20: =IF($T20="",0,SUM($U20:$AD20)) -> 5 | AF20: =IF($AE20<=0,1,$AE20) -> 5 | AG20: =IF(ISNUMBER($E20),$E20,0) -> 48
A21: =IF($T21="","—",ROW()-7) -> 14 | B21: =TODAY()-19 -> 46213 | C21: Groceries for the apartment | D21: Dana | E21: 63.4 | F21: Groceries | G21: Equal | R21: =IF($T21="","",IF($D21="","Who paid?",IF(SUMPRODUCT((Setup!$B$21:$B$30=$D21)*1)=0,"Payer is not in the member list on Setup",IF($E21="","Amount missing — type the number in column E",IF(NOT(ISNUMBER($E21)),"Amount must be a plain number — no currency symbol, no text",IF(AND($T21="Custom units",$AE21<=0),"Custom units: nobody has units on this row — type a number for at least one person",IF($AE21<=0,"Nobody shares this row — check the person columns H–Q, and the Weight / Nights columns on Setup",IF(AND($T21="Exact amounts",ABS($AE21-$AG21)>0.01),"Exact amounts do not add up to the amount","OK")))))))) -> OK | S21: =IFERROR(IF(OR($T21="",$C$4=""),"—",ROUND($AG21*INDEX($U21:$AD21,1,MATCH($C$4,Setup!$B$21:$B$30,0))/$AF21,2)),"—") -> 12.68 | T21: =IF(AND($C21="",$D21="",NOT(ISNUMBER($E21))),"",IF($G21="",IF(Setup!$C$17="","Equal",Setup!$C$17),$G21)) -> Equal | U21: =IF($T21="",0,IF(OR(Setup!$B$21="",Setup!$C$21="No"),0,IF(ISNUMBER(H21),H21,IF($T21="Weights",IF(ISNUMBER(Setup!$D$21),Setup!$D$21,0),IF($T21="Nights",IF(ISNUMBER(Setup!$E$21),Setup!$E$21,0),IF(OR($T21="Exact amounts",$T21="Custom units"),0,1)))))) -> 1 | V21: =IF($T21="",0,IF(OR(Setup!$B$22="",Setup!$C$22="No"),0,IF(ISNUMBER(I21),I21,IF($T21="Weights",IF(ISNUMBER(Setup!$D$22),Setup!$D$22,0),IF($T21="Nights",IF(ISNUMBER(Setup!$E$22),Setup!$E$22,0),IF(OR($T21="Exact amounts",$T21="Custom units"),0,1)))))) -> 1 | W21: =IF($T21="",0,IF(OR(Setup!$B$23="",Setup!$C$23="No"),0,IF(ISNUMBER(J21),J21,IF($T21="Weights",IF(ISNUMBER(Setup!$D$23),Setup!$D$23,0),IF($T21="Nights",IF(ISNUMBER(Setup!$E$23),Setup!$E$23,0),IF(OR($T21="Exact amounts",$T21="Custom units"),0,1)))))) -> 1 | X21: =IF($T21="",0,IF(OR(Setup!$B$24="",Setup!$C$24="No"),0,IF(ISNUMBER(K21),K21,IF($T21="Weights",IF(ISNUMBER(Setup!$D$24),Setup!$D$24,0),IF($T21="Nights",IF(ISNUMBER(Setup!$E$24),Setup!$E$24,0),IF(OR($T21="Exact amounts",$T21="Custom units"),0,1)))))) -> 1 | Y21: =IF($T21="",0,IF(OR(Setup!$B$25="",Setup!$C$25="No"),0,IF(ISNUMBER(L21),L21,IF($T21="Weights",IF(ISNUMBER(Setup!$D$25),Setup!$D$25,0),IF($T21="Nights",IF(ISNUMBER(Setup!$E$25),Setup!$E$25,0),IF(OR($T21="Exact amounts",$T21="Custom units"),0,1)))))) -> 1 | Z21: =IF($T21="",0,IF(OR(Setup!$B$26="",Setup!$C$26="No"),0,IF(ISNUMBER(M21),M21,IF($T21="Weights",IF(ISNUMBER(Setup!$D$26),Setup!$D$26,0),IF($T21="Nights",IF(ISNUMBER(Setup!$E$26),Setup!$E$26,0),IF(OR($T21="Exact amounts",$T21="Custom units"),0,1)))))) -> 0 | AA21: =IF($T21="",0,IF(OR(Setup!$B$27="",Setup!$C$27="No"),0,IF(ISNUMBER(N21),N21,IF($T21="Weights",IF(ISNUMBER(Setup!$D$27),Setup!$D$27,0),IF($T21="Nights",IF(ISNUMBER(Setup!$E$27),Setup!$E$27,0),IF(OR($T21="Exact amounts",$T21="Custom units"),0,1)))))) -> 0 | AB21: =IF($T21="",0,IF(OR(Setup!$B$28="",Setup!$C$28="No"),0,IF(ISNUMBER(O21),O21,IF($T21="Weights",IF(ISNUMBER(Setup!$D$28),Setup!$D$28,0),IF($T21="Nights",IF(ISNUMBER(Setup!$E$28),Setup!$E$28,0),IF(OR($T21="Exact amounts",$T21="Custom units"),0,1)))))) -> 0 | AC21: =IF($T21="",0,IF(OR(Setup!$B$29="",Setup!$C$29="No"),0,IF(ISNUMBER(P21),P21,IF($T21="Weights",IF(ISNUMBER(Setup!$D$29),Setup!$D$29,0),IF($T21="Nights",IF(ISNUMBER(Setup!$E$29),Setup!$E$29,0),IF(OR($T21="Exact amounts",$T21="Custom units"),0,1)))))) -> 0 | AD21: =IF($T21="",0,IF(OR(Setup!$B$30="",Setup!$C$30="No"),0,IF(ISNUMBER(Q21),Q21,IF($T21="Weights",IF(ISNUMBER(Setup!$D$30),Setup!$D$30,0),IF($T21="Nights",IF(ISNUMBER(Setup!$E$30),Setup!$E$30,0),IF(OR($T21="Exact amounts",$T21="Custom units"),0,1)))))) -> 0 | AE21: =IF($T21="",0,SUM($U21:$AD21)) -> 5 | AF21: =IF($AE21<=0,1,$AE21) -> 5 | AG21: =IF(ISNUMBER($E21),$E21,0) -> 63.4
A22: =IF($T22="","—",ROW()-7) -> 15 | B22: =TODAY()-18 -> 46214 | C22: Dinner at the seafood place | D22: Eli | E22: 142.8 | F22: Eating out | G22: Equal | I22: 0 | R22: =IF($T22="","",IF($D22="","Who paid?",IF(SUMPRODUCT((Setup!$B$21:$B$30=$D22)*1)=0,"Payer is not in the member list on Setup",IF($E22="","Amount missing — type the number in column E",IF(NOT(ISNUMBER($E22)),"Amount must be a plain number — no currency symbol, no text",IF(AND($T22="Custom units",$AE22<=0),"Custom units: nobody has units on this row — type a number for at least one person",IF($AE22<=0,"Nobody shares this row — check the person columns H–Q, and the Weight / Nights columns on Setup",IF(AND($T22="Exact amounts",ABS($AE22-$AG22)>0.01),"Exact amounts do not add up to the amount","OK")))))))) -> OK | S22: =IFERROR(IF(OR($T22="",$C$4=""),"—",ROUND($AG22*INDEX($U22:$AD22,1,MATCH($C$4,Setup!$B$21:$B$30,0))/$AF22,2)),"—") -> 35.7 | T22: =IF(AND($C22="",$D22="",NOT(ISNUMBER($E22))),"",IF($G22="",IF(Setup!$C$17="","Equal",Setup!$C$17),$G22)) -> Equal | U22: =IF($T22="",0,IF(OR(Setup!$B$21="",Setup!$C$21="No"),0,IF(ISNUMBER(H22),H22,IF($T22="Weights",IF(ISNUMBER(Setup!$D$21),Setup!$D$21,0),IF($T22="Nights",IF(ISNUMBER(Setup!$E$21),Setup!$E$21,0),IF(OR($T22="Exact amounts",$T22="Custom units"),0,1)))))) -> 1 | V22: =IF($T22="",0,IF(OR(Setup!$B$22="",Setup!$C$22="No"),0,IF(ISNUMBER(I22),I22,IF($T22="Weights",IF(ISNUMBER(Setup!$D$22),Setup!$D$22,0),IF($T22="Nights",IF(ISNUMBER(Setup!$E$22),Setup!$E$22,0),IF(OR($T22="Exact amounts",$T22="Custom units"),0,1)))))) -> 0 | W22: =IF($T22="",0,IF(OR(Setup!$B$23="",Setup!$C$23="No"),0,IF(ISNUMBER(J22),J22,IF($T22="Weights",IF(ISNUMBER(Setup!$D$23),Setup!$D$23,0),IF($T22="Nights",IF(ISNUMBER(Setup!$E$23),Setup!$E$23,0),IF(OR($T22="Exact amounts",$T22="Custom units"),0,1)))))) -> 1 | X22: =IF($T22="",0,IF(OR(Setup!$B$24="",Setup!$C$24="No"),0,IF(ISNUMBER(K22),K22,IF($T22="Weights",IF(ISNUMBER(Setup!$D$24),Setup!$D$24,0),IF($T22="Nights",IF(ISNUMBER(Setup!$E$24),Setup!$E$24,0),IF(OR($T22="Exact amounts",$T22="Custom units"),0,1)))))) -> 1 | Y22: =IF($T22="",0,IF(OR(Setup!$B$25="",Setup!$C$25="No"),0,IF(ISNUMBER(L22),L22,IF($T22="Weights",IF(ISNUMBER(Setup!$D$25),Setup!$D$25,0),IF($T22="Nights",IF(ISNUMBER(Setup!$E$25),Setup!$E$25,0),IF(OR($T22="Exact amounts",$T22="Custom units"),0,1)))))) -> 1 | Z22: =IF($T22="",0,IF(OR(Setup!$B$26="",Setup!$C$26="No"),0,IF(ISNUMBER(M22),M22,IF($T22="Weights",IF(ISNUMBER(Setup!$D$26),Setup!$D$26,0),IF($T22="Nights",IF(ISNUMBER(Setup!$E$26),Setup!$E$26,0),IF(OR($T22="Exact amounts",$T22="Custom units"),0,1)))))) -> 0 | AA22: =IF($T22="",0,IF(OR(Setup!$B$27="",Setup!$C$27="No"),0,IF(ISNUMBER(N22),N22,IF($T22="Weights",IF(ISNUMBER(Setup!$D$27),Setup!$D$27,0),IF($T22="Nights",IF(ISNUMBER(Setup!$E$27),Setup!$E$27,0),IF(OR($T22="Exact amounts",$T22="Custom units"),0,1)))))) -> 0 | AB22: =IF($T22="",0,IF(OR(Setup!$B$28="",Setup!$C$28="No"),0,IF(ISNUMBER(O22),O22,IF($T22="Weights",IF(ISNUMBER(Setup!$D$28),Setup!$D$28,0),IF($T22="Nights",IF(ISNUMBER(Setup!$E$28),Setup!$E$28,0),IF(OR($T22="Exact amounts",$T22="Custom units"),0,1)))))) -> 0 | AC22: =IF($T22="",0,IF(OR(Setup!$B$29="",Setup!$C$29="No"),0,IF(ISNUMBER(P22),P22,IF($T22="Weights",IF(ISNUMBER(Setup!$D$29),Setup!$D$29,0),IF($T22="Nights",IF(ISNUMBER(Setup!$E$29),Setup!$E$29,0),IF(OR($T22="Exact amounts",$T22="Custom units"),0,1)))))) -> 0 | AD22: =IF($T22="",0,IF(OR(Setup!$B$30="",Setup!$C$30="No"),0,IF(ISNUMBER(Q22),Q22,IF($T22="Weights",IF(ISNUMBER(Setup!$D$30),Setup!$D$30,0),IF($T22="Nights",IF(ISNUMBER(Setup!$E$30),Setup!$E$30,0),IF(OR($T22="Exact amounts",$T22="Custom units"),0,1)))))) -> 0 | AE22: =IF($T22="",0,SUM($U22:$AD22)) -> 4 | AF22: =IF($AE22<=0,1,$AE22) -> 4 | AG22: =IF(ISNUMBER($E22),$E22,0) -> 142.8
A23: =IF($T23="","—",ROW()-7) -> 16 | B23: =TODAY()-17 -> 46215 | C23: Tram + metro tickets | D23: Anna | E23: 36 | F23: Travel & transport | G23: Equal | R23: =IF($T23="","",IF($D23="","Who paid?",IF(SUMPRODUCT((Setup!$B$21:$B$30=$D23)*1)=0,"Payer is not in the member list on Setup",IF($E23="","Amount missing — type the number in column E",IF(NOT(ISNUMBER($E23)),"Amount must be a plain number — no currency symbol, no text",IF(AND($T23="Custom units",$AE23<=0),"Custom units: nobody has units on this row — type a number for at least one person",IF($AE23<=0,"Nobody shares this row — check the person columns H–Q, and the Weight / Nights columns on Setup",IF(AND($T23="Exact amounts",ABS($AE23-$AG23)>0.01),"Exact amounts do not add up to the amount","OK")))))))) -> OK | S23: =IFERROR(IF(OR($T23="",$C$4=""),"—",ROUND($AG23*INDEX($U23:$AD23,1,MATCH($C$4,Setup!$B$21:$B$30,0))/$AF23,2)),"—") -> 7.2 | T23: =IF(AND($C23="",$D23="",NOT(ISNUMBER($E23))),"",IF($G23="",IF(Setup!$C$17="","Equal",Setup!$C$17),$G23)) -> Equal | U23: =IF($T23="",0,IF(OR(Setup!$B$21="",Setup!$C$21="No"),0,IF(ISNUMBER(H23),H23,IF($T23="Weights",IF(ISNUMBER(Setup!$D$21),Setup!$D$21,0),IF($T23="Nights",IF(ISNUMBER(Setup!$E$21),Setup!$E$21,0),IF(OR($T23="Exact amounts",$T23="Custom units"),0,1)))))) -> 1 | V23: =IF($T23="",0,IF(OR(Setup!$B$22="",Setup!$C$22="No"),0,IF(ISNUMBER(I23),I23,IF($T23="Weights",IF(ISNUMBER(Setup!$D$22),Setup!$D$22,0),IF($T23="Nights",IF(ISNUMBER(Setup!$E$22),Setup!$E$22,0),IF(OR($T23="Exact amounts",$T23="Custom units"),0,1)))))) -> 1 | W23: =IF($T23="",0,IF(OR(Setup!$B$23="",Setup!$C$23="No"),0,IF(ISNUMBER(J23),J23,IF($T23="Weights",IF(ISNUMBER(Setup!$D$23),Setup!$D$23,0),IF($T23="Nights",IF(ISNUMBER(Setup!$E$23),Setup!$E$23,0),IF(OR($T23="Exact amounts",$T23="Custom units"),0,1)))))) -> 1 | X23: =IF($T23="",0,IF(OR(Setup!$B$24="",Setup!$C$24="No"),0,IF(ISNUMBER(K23),K23,IF($T23="Weights",IF(ISNUMBER(Setup!$D$24),Setup!$D$24,0),IF($T23="Nights",IF(ISNUMBER(Setup!$E$24),Setup!$E$24,0),IF(OR($T23="Exact amounts",$T23="Custom units"),0,1)))))) -> 1 | Y23: =IF($T23="",0,IF(OR(Setup!$B$25="",Setup!$C$25="No"),0,IF(ISNUMBER(L23),L23,IF($T23="Weights",IF(ISNUMBER(Setup!$D$25),Setup!$D$25,0),IF($T23="Nights",IF(ISNUMBER(Setup!$E$25),Setup!$E$25,0),IF(OR($T23="Exact amounts",$T23="Custom units"),0,1)))))) -> 1 | Z23: =IF($T23="",0,IF(OR(Setup!$B$26="",Setup!$C$26="No"),0,IF(ISNUMBER(M23),M23,IF($T23="Weights",IF(ISNUMBER(Setup!$D$26),Setup!$D$26,0),IF($T23="Nights",IF(ISNUMBER(Setup!$E$26),Setup!$E$26,0),IF(OR($T23="Exact amounts",$T23="Custom units"),0,1)))))) -> 0 | AA23: =IF($T23="",0,IF(OR(Setup!$B$27="",Setup!$C$27="No"),0,IF(ISNUMBER(N23),N23,IF($T23="Weights",IF(ISNUMBER(Setup!$D$27),Setup!$D$27,0),IF($T23="Nights",IF(ISNUMBER(Setup!$E$27),Setup!$E$27,0),IF(OR($T23="Exact amounts",$T23="Custom units"),0,1)))))) -> 0 | AB23: =IF($T23="",0,IF(OR(Setup!$B$28="",Setup!$C$28="No"),0,IF(ISNUMBER(O23),O23,IF($T23="Weights",IF(ISNUMBER(Setup!$D$28),Setup!$D$28,0),IF($T23="Nights",IF(ISNUMBER(Setup!$E$28),Setup!$E$28,0),IF(OR($T23="Exact amounts",$T23="Custom units"),0,1)))))) -> 0 | AC23: =IF($T23="",0,IF(OR(Setup!$B$29="",Setup!$C$29="No"),0,IF(ISNUMBER(P23),P23,IF($T23="Weights",IF(ISNUMBER(Setup!$D$29),Setup!$D$29,0),IF($T23="Nights",IF(ISNUMBER(Setup!$E$29),Setup!$E$29,0),IF(OR($T23="Exact amounts",$T23="Custom units"),0,1)))))) -> 0 | AD23: =IF($T23="",0,IF(OR(Setup!$B$30="",Setup!$C$30="No"),0,IF(ISNUMBER(Q23),Q23,IF($T23="Weights",IF(ISNUMBER(Setup!$D$30),Setup!$D$30,0),IF($T23="Nights",IF(ISNUMBER(Setup!$E$30),Setup!$E$30,0),IF(OR($T23="Exact amounts",$T23="Custom units"),0,1)))))) -> 0 | AE23: =IF($T23="",0,SUM($U23:$AD23)) -> 5 | AF23: =IF($AE23<=0,1,$AE23) -> 5 | AG23: =IF(ISNUMBER($E23),$E23,0) -> 36
A24: =IF($T24="","—",ROW()-7) -> 17 | B24: =TODAY()-16 -> 46216 | C24: Surf lesson (3 of us) | D24: Chris | E24: 135 | F24: Activities & tickets | G24: Equal | I24: 0 | K24: 0 | R24: =IF($T24="","",IF($D24="","Who paid?",IF(SUMPRODUCT((Setup!$B$21:$B$30=$D24)*1)=0,"Payer is not in the member list on Setup",IF($E24="","Amount missing — type the number in column E",IF(NOT(ISNUMBER($E24)),"Amount must be a plain number — no currency symbol, no text",IF(AND($T24="Custom units",$AE24<=0),"Custom units: nobody has units on this row — type a number for at least one person",IF($AE24<=0,"Nobody shares this row — check the person columns H–Q, and the Weight / Nights columns on Setup",IF(AND($T24="Exact amounts",ABS($AE24-$AG24)>0.01),"Exact amounts do not add up to the amount","OK")))))))) -> OK | S24: =IFERROR(IF(OR($T24="",$C$4=""),"—",ROUND($AG24*INDEX($U24:$AD24,1,MATCH($C$4,Setup!$B$21:$B$30,0))/$AF24,2)),"—") -> 45 | T24: =IF(AND($C24="",$D24="",NOT(ISNUMBER($E24))),"",IF($G24="",IF(Setup!$C$17="","Equal",Setup!$C$17),$G24)) -> Equal | U24: =IF($T24="",0,IF(OR(Setup!$B$21="",Setup!$C$21="No"),0,IF(ISNUMBER(H24),H24,IF($T24="Weights",IF(ISNUMBER(Setup!$D$21),Setup!$D$21,0),IF($T24="Nights",IF(ISNUMBER(Setup!$E$21),Setup!$E$21,0),IF(OR($T24="Exact amounts",$T24="Custom units"),0,1)))))) -> 1 | V24: =IF($T24="",0,IF(OR(Setup!$B$22="",Setup!$C$22="No"),0,IF(ISNUMBER(I24),I24,IF($T24="Weights",IF(ISNUMBER(Setup!$D$22),Setup!$D$22,0),IF($T24="Nights",IF(ISNUMBER(Setup!$E$22),Setup!$E$22,0),IF(OR($T24="Exact amounts",$T24="Custom units"),0,1)))))) -> 0 | W24: =IF($T24="",0,IF(OR(Setup!$B$23="",Setup!$C$23="No"),0,IF(ISNUMBER(J24),J24,IF($T24="Weights",IF(ISNUMBER(Setup!$D$23),Setup!$D$23,0),IF($T24="Nights",IF(ISNUMBER(Setup!$E$23),Setup!$E$23,0),IF(OR($T24="Exact amounts",$T24="Custom units"),0,1)))))) -> 1 | X24: =IF($T24="",0,IF(OR(Setup!$B$24="",Setup!$C$24="No"),0,IF(ISNUMBER(K24),K24,IF($T24="Weights",IF(ISNUMBER(Setup!$D$24),Setup!$D$24,0),IF($T24="Nights",IF(ISNUMBER(Setup!$E$24),Setup!$E$24,0),IF(OR($T24="Exact amounts",$T24="Custom units"),0,1)))))) -> 0 | Y24: =IF($T24="",0,IF(OR(Setup!$B$25="",Setup!$C$25="No"),0,IF(ISNUMBER(L24),L24,IF($T24="Weights",IF(ISNUMBER(Setup!$D$25),Setup!$D$25,0),IF($T24="Nights",IF(ISNUMBER(Setup!$E$25),Setup!$E$25,0),IF(OR($T24="Exact amounts",$T24="Custom units"),0,1)))))) -> 1 | Z24: =IF($T24="",0,IF(OR(Setup!$B$26="",Setup!$C$26="No"),0,IF(ISNUMBER(M24),M24,IF($T24="Weights",IF(ISNUMBER(Setup!$D$26),Setup!$D$26,0),IF($T24="Nights",IF(ISNUMBER(Setup!$E$26),Setup!$E$26,0),IF(OR($T24="Exact amounts",$T24="Custom units"),0,1)))))) -> 0 | AA24: =IF($T24="",0,IF(OR(Setup!$B$27="",Setup!$C$27="No"),0,IF(ISNUMBER(N24),N24,IF($T24="Weights",IF(ISNUMBER(Setup!$D$27),Setup!$D$27,0),IF($T24="Nights",IF(ISNUMBER(Setup!$E$27),Setup!$E$27,0),IF(OR($T24="Exact amounts",$T24="Custom units"),0,1)))))) -> 0 | AB24: =IF($T24="",0,IF(OR(Setup!$B$28="",Setup!$C$28="No"),0,IF(ISNUMBER(O24),O24,IF($T24="Weights",IF(ISNUMBER(Setup!$D$28),Setup!$D$28,0),IF($T24="Nights",IF(ISNUMBER(Setup!$E$28),Setup!$E$28,0),IF(OR($T24="Exact amounts",$T24="Custom units"),0,1)))))) -> 0 | AC24: =IF($T24="",0,IF(OR(Setup!$B$29="",Setup!$C$29="No"),0,IF(ISNUMBER(P24),P24,IF($T24="Weights",IF(ISNUMBER(Setup!$D$29),Setup!$D$29,0),IF($T24="Nights",IF(ISNUMBER(Setup!$E$29),Setup!$E$29,0),IF(OR($T24="Exact amounts",$T24="Custom units"),0,1)))))) -> 0 | AD24: =IF($T24="",0,IF(OR(Setup!$B$30="",Setup!$C$30="No"),0,IF(ISNUMBER(Q24),Q24,IF($T24="Weights",IF(ISNUMBER(Setup!$D$30),Setup!$D$30,0),IF($T24="Nights",IF(ISNUMBER(Setup!$E$30),Setup!$E$30,0),IF(OR($T24="Exact amounts",$T24="Custom units"),0,1)))))) -> 0 | AE24: =IF($T24="",0,SUM($U24:$AD24)) -> 3 | AF24: =IF($AE24<=0,1,$AE24) -> 3 | AG24: =IF(ISNUMBER($E24),$E24,0) -> 135
A25: =IF($T25="","—",ROW()-7) -> 18 | B25: =TODAY()-15 -> 46217 | C25: Castle tickets | D25: Dana | E25: 52.5 | F25: Activities & tickets | G25: Equal | R25: =IF($T25="","",IF($D25="","Who paid?",IF(SUMPRODUCT((Setup!$B$21:$B$30=$D25)*1)=0,"Payer is not in the member list on Setup",IF($E25="","Amount missing — type the number in column E",IF(NOT(ISNUMBER($E25)),"Amount must be a plain number — no currency symbol, no text",IF(AND($T25="Custom units",$AE25<=0),"Custom units: nobody has units on this row — type a number for at least one person",IF($AE25<=0,"Nobody shares this row — check the person columns H–Q, and the Weight / Nights columns on Setup",IF(AND($T25="Exact amounts",ABS($AE25-$AG25)>0.01),"Exact amounts do not add up to the amount","OK")))))))) -> OK | S25: =IFERROR(IF(OR($T25="",$C$4=""),"—",ROUND($AG25*INDEX($U25:$AD25,1,MATCH($C$4,Setup!$B$21:$B$30,0))/$AF25,2)),"—") -> 10.5 | T25: =IF(AND($C25="",$D25="",NOT(ISNUMBER($E25))),"",IF($G25="",IF(Setup!$C$17="","Equal",Setup!$C$17),$G25)) -> Equal | U25: =IF($T25="",0,IF(OR(Setup!$B$21="",Setup!$C$21="No"),0,IF(ISNUMBER(H25),H25,IF($T25="Weights",IF(ISNUMBER(Setup!$D$21),Setup!$D$21,0),IF($T25="Nights",IF(ISNUMBER(Setup!$E$21),Setup!$E$21,0),IF(OR($T25="Exact amounts",$T25="Custom units"),0,1)))))) -> 1 | V25: =IF($T25="",0,IF(OR(Setup!$B$22="",Setup!$C$22="No"),0,IF(ISNUMBER(I25),I25,IF($T25="Weights",IF(ISNUMBER(Setup!$D$22),Setup!$D$22,0),IF($T25="Nights",IF(ISNUMBER(Setup!$E$22),Setup!$E$22,0),IF(OR($T25="Exact amounts",$T25="Custom units"),0,1)))))) -> 1 | W25: =IF($T25="",0,IF(OR(Setup!$B$23="",Setup!$C$23="No"),0,IF(ISNUMBER(J25),J25,IF($T25="Weights",IF(ISNUMBER(Setup!$D$23),Setup!$D$23,0),IF($T25="Nights",IF(ISNUMBER(Setup!$E$23),Setup!$E$23,0),IF(OR($T25="Exact amounts",$T25="Custom units"),0,1)))))) -> 1 | X25: =IF($T25="",0,IF(OR(Setup!$B$24="",Setup!$C$24="No"),0,IF(ISNUMBER(K25),K25,IF($T25="Weights",IF(ISNUMBER(Setup!$D$24),Setup!$D$24,0),IF($T25="Nights",IF(ISNUMBER(Setup!$E$24),Setup!$E$24,0),IF(OR($T25="Exact amounts",$T25="Custom units"),0,1)))))) -> 1 | Y25: =IF($T25="",0,IF(OR(Setup!$B$25="",Setup!$C$25="No"),0,IF(ISNUMBER(L25),L25,IF($T25="Weights",IF(ISNUMBER(Setup!$D$25),Setup!$D$25,0),IF($T25="Nights",IF(ISNUMBER(Setup!$E$25),Setup!$E$25,0),IF(OR($T25="Exact amounts",$T25="Custom units"),0,1)))))) -> 1 | Z25: =IF($T25="",0,IF(OR(Setup!$B$26="",Setup!$C$26="No"),0,IF(ISNUMBER(M25),M25,IF($T25="Weights",IF(ISNUMBER(Setup!$D$26),Setup!$D$26,0),IF($T25="Nights",IF(ISNUMBER(Setup!$E$26),Setup!$E$26,0),IF(OR($T25="Exact amounts",$T25="Custom units"),0,1)))))) -> 0 | AA25: =IF($T25="",0,IF(OR(Setup!$B$27="",Setup!$C$27="No"),0,IF(ISNUMBER(N25),N25,IF($T25="Weights",IF(ISNUMBER(Setup!$D$27),Setup!$D$27,0),IF($T25="Nights",IF(ISNUMBER(Setup!$E$27),Setup!$E$27,0),IF(OR($T25="Exact amounts",$T25="Custom units"),0,1)))))) -> 0 | AB25: =IF($T25="",0,IF(OR(Setup!$B$28="",Setup!$C$28="No"),0,IF(ISNUMBER(O25),O25,IF($T25="Weights",IF(ISNUMBER(Setup!$D$28),Setup!$D$28,0),IF($T25="Nights",IF(ISNUMBER(Setup!$E$28),Setup!$E$28,0),IF(OR($T25="Exact amounts",$T25="Custom units"),0,1)))))) -> 0 | AC25: =IF($T25="",0,IF(OR(Setup!$B$29="",Setup!$C$29="No"),0,IF(ISNUMBER(P25),P25,IF($T25="Weights",IF(ISNUMBER(Setup!$D$29),Setup!$D$29,0),IF($T25="Nights",IF(ISNUMBER(Setup!$E$29),Setup!$E$29,0),IF(OR($T25="Exact amounts",$T25="Custom units"),0,1)))))) -> 0 | AD25: =IF($T25="",0,IF(OR(Setup!$B$30="",Setup!$C$30="No"),0,IF(ISNUMBER(Q25),Q25,IF($T25="Weights",IF(ISNUMBER(Setup!$D$30),Setup!$D$30,0),IF($T25="Nights",IF(ISNUMBER(Setup!$E$30),Setup!$E$30,0),IF(OR($T25="Exact amounts",$T25="Custom units"),0,1)))))) -> 0 | AE25: =IF($T25="",0,SUM($U25:$AD25)) -> 5 | AF25: =IF($AE25<=0,1,$AE25) -> 5 | AG25: =IF(ISNUMBER($E25),$E25,0) -> 52.5
A26: =IF($T26="","—",ROW()-7) -> 19 | B26: =TODAY()-15 -> 46217 | C26: Drinks in Bairro Alto | D26: Ben | E26: 68.3 | F26: Drinks & nightlife | G26: Equal | R26: =IF($T26="","",IF($D26="","Who paid?",IF(SUMPRODUCT((Setup!$B$21:$B$30=$D26)*1)=0,"Payer is not in the member list on Setup",IF($E26="","Amount missing — type the number in column E",IF(NOT(ISNUMBER($E26)),"Amount must be a plain number — no currency symbol, no text",IF(AND($T26="Custom units",$AE26<=0),"Custom units: nobody has units on this row — type a number for at least one person",IF($AE26<=0,"Nobody shares this row — check the person columns H–Q, and the Weight / Nights columns on Setup",IF(AND($T26="Exact amounts",ABS($AE26-$AG26)>0.01),"Exact amounts do not add up to the amount","OK")))))))) -> OK | S26: =IFERROR(IF(OR($T26="",$C$4=""),"—",ROUND($AG26*INDEX($U26:$AD26,1,MATCH($C$4,Setup!$B$21:$B$30,0))/$AF26,2)),"—") -> 13.66 | T26: =IF(AND($C26="",$D26="",NOT(ISNUMBER($E26))),"",IF($G26="",IF(Setup!$C$17="","Equal",Setup!$C$17),$G26)) -> Equal | U26: =IF($T26="",0,IF(OR(Setup!$B$21="",Setup!$C$21="No"),0,IF(ISNUMBER(H26),H26,IF($T26="Weights",IF(ISNUMBER(Setup!$D$21),Setup!$D$21,0),IF($T26="Nights",IF(ISNUMBER(Setup!$E$21),Setup!$E$21,0),IF(OR($T26="Exact amounts",$T26="Custom units"),0,1)))))) -> 1 | V26: =IF($T26="",0,IF(OR(Setup!$B$22="",Setup!$C$22="No"),0,IF(ISNUMBER(I26),I26,IF($T26="Weights",IF(ISNUMBER(Setup!$D$22),Setup!$D$22,0),IF($T26="Nights",IF(ISNUMBER(Setup!$E$22),Setup!$E$22,0),IF(OR($T26="Exact amounts",$T26="Custom units"),0,1)))))) -> 1 | W26: =IF($T26="",0,IF(OR(Setup!$B$23="",Setup!$C$23="No"),0,IF(ISNUMBER(J26),J26,IF($T26="Weights",IF(ISNUMBER(Setup!$D$23),Setup!$D$23,0),IF($T26="Nights",IF(ISNUMBER(Setup!$E$23),Setup!$E$23,0),IF(OR($T26="Exact amounts",$T26="Custom units"),0,1)))))) -> 1 | X26: =IF($T26="",0,IF(OR(Setup!$B$24="",Setup!$C$24="No"),0,IF(ISNUMBER(K26),K26,IF($T26="Weights",IF(ISNUMBER(Setup!$D$24),Setup!$D$24,0),IF($T26="Nights",IF(ISNUMBER(Setup!$E$24),Setup!$E$24,0),IF(OR($T26="Exact amounts",$T26="Custom units"),0,1)))))) -> 1 | Y26: =IF($T26="",0,IF(OR(Setup!$B$25="",Setup!$C$25="No"),0,IF(ISNUMBER(L26),L26,IF($T26="Weights",IF(ISNUMBER(Setup!$D$25),Setup!$D$25,0),IF($T26="Nights",IF(ISNUMBER(Setup!$E$25),Setup!$E$25,0),IF(OR($T26="Exact amounts",$T26="Custom units"),0,1)))))) -> 1 | Z26: =IF($T26="",0,IF(OR(Setup!$B$26="",Setup!$C$26="No"),0,IF(ISNUMBER(M26),M26,IF($T26="Weights",IF(ISNUMBER(Setup!$D$26),Setup!$D$26,0),IF($T26="Nights",IF(ISNUMBER(Setup!$E$26),Setup!$E$26,0),IF(OR($T26="Exact amounts",$T26="Custom units"),0,1)))))) -> 0 | AA26: =IF($T26="",0,IF(OR(Setup!$B$27="",Setup!$C$27="No"),0,IF(ISNUMBER(N26),N26,IF($T26="Weights",IF(ISNUMBER(Setup!$D$27),Setup!$D$27,0),IF($T26="Nights",IF(ISNUMBER(Setup!$E$27),Setup!$E$27,0),IF(OR($T26="Exact amounts",$T26="Custom units"),0,1)))))) -> 0 | AB26: =IF($T26="",0,IF(OR(Setup!$B$28="",Setup!$C$28="No"),0,IF(ISNUMBER(O26),O26,IF($T26="Weights",IF(ISNUMBER(Setup!$D$28),Setup!$D$28,0),IF($T26="Nights",IF(ISNUMBER(Setup!$E$28),Setup!$E$28,0),IF(OR($T26="Exact amounts",$T26="Custom units"),0,1)))))) -> 0 | AC26: =IF($T26="",0,IF(OR(Setup!$B$29="",Setup!$C$29="No"),0,IF(ISNUMBER(P26),P26,IF($T26="Weights",IF(ISNUMBER(Setup!$D$29),Setup!$D$29,0),IF($T26="Nights",IF(ISNUMBER(Setup!$E$29),Setup!$E$29,0),IF(OR($T26="Exact amounts",$T26="Custom units"),0,1)))))) -> 0 | AD26: =IF($T26="",0,IF(OR(Setup!$B$30="",Setup!$C$30="No"),0,IF(ISNUMBER(Q26),Q26,IF($T26="Weights",IF(ISNUMBER(Setup!$D$30),Setup!$D$30,0),IF($T26="Nights",IF(ISNUMBER(Setup!$E$30),Setup!$E$30,0),IF(OR($T26="Exact amounts",$T26="Custom units"),0,1)))))) -> 0 | AE26: =IF($T26="",0,SUM($U26:$AD26)) -> 5 | AF26: =IF($AE26<=0,1,$AE26) -> 5 | AG26: =IF(ISNUMBER($E26),$E26,0) -> 68.3
A27: =IF($T27="","—",ROW()-7) -> 20 | B27: =TODAY()-14 -> 46218 | C27: Day trip to Sintra — van | D27: Eli | E27: 120 | F27: Travel & transport | G27: Equal | R27: =IF($T27="","",IF($D27="","Who paid?",IF(SUMPRODUCT((Setup!$B$21:$B$30=$D27)*1)=0,"Payer is not in the member list on Setup",IF($E27="","Amount missing — type the number in column E",IF(NOT(ISNUMBER($E27)),"Amount must be a plain number — no currency symbol, no text",IF(AND($T27="Custom units",$AE27<=0),"Custom units: nobody has units on this row — type a number for at least one person",IF($AE27<=0,"Nobody shares this row — check the person columns H–Q, and the Weight / Nights columns on Setup",IF(AND($T27="Exact amounts",ABS($AE27-$AG27)>0.01),"Exact amounts do not add up to the amount","OK")))))))) -> OK | S27: =IFERROR(IF(OR($T27="",$C$4=""),"—",ROUND($AG27*INDEX($U27:$AD27,1,MATCH($C$4,Setup!$B$21:$B$30,0))/$AF27,2)),"—") -> 24 | T27: =IF(AND($C27="",$D27="",NOT(ISNUMBER($E27))),"",IF($G27="",IF(Setup!$C$17="","Equal",Setup!$C$17),$G27)) -> Equal | U27: =IF($T27="",0,IF(OR(Setup!$B$21="",Setup!$C$21="No"),0,IF(ISNUMBER(H27),H27,IF($T27="Weights",IF(ISNUMBER(Setup!$D$21),Setup!$D$21,0),IF($T27="Nights",IF(ISNUMBER(Setup!$E$21),Setup!$E$21,0),IF(OR($T27="Exact amounts",$T27="Custom units"),0,1)))))) -> 1 | V27: =IF($T27="",0,IF(OR(Setup!$B$22="",Setup!$C$22="No"),0,IF(ISNUMBER(I27),I27,IF($T27="Weights",IF(ISNUMBER(Setup!$D$22),Setup!$D$22,0),IF($T27="Nights",IF(ISNUMBER(Setup!$E$22),Setup!$E$22,0),IF(OR($T27="Exact amounts",$T27="Custom units"),0,1)))))) -> 1 | W27: =IF($T27="",0,IF(OR(Setup!$B$23="",Setup!$C$23="No"),0,IF(ISNUMBER(J27),J27,IF($T27="Weights",IF(ISNUMBER(Setup!$D$23),Setup!$D$23,0),IF($T27="Nights",IF(ISNUMBER(Setup!$E$23),Setup!$E$23,0),IF(OR($T27="Exact amounts",$T27="Custom units"),0,1)))))) -> 1 | X27: =IF($T27="",0,IF(OR(Setup!$B$24="",Setup!$C$24="No"),0,IF(ISNUMBER(K27),K27,IF($T27="Weights",IF(ISNUMBER(Setup!$D$24),Setup!$D$24,0),IF($T27="Nights",IF(ISNUMBER(Setup!$E$24),Setup!$E$24,0),IF(OR($T27="Exact amounts",$T27="Custom units"),0,1)))))) -> 1 | Y27: =IF($T27="",0,IF(OR(Setup!$B$25="",Setup!$C$25="No"),0,IF(ISNUMBER(L27),L27,IF($T27="Weights",IF(ISNUMBER(Setup!$D$25),Setup!$D$25,0),IF($T27="Nights",IF(ISNUMBER(Setup!$E$25),Setup!$E$25,0),IF(OR($T27="Exact amounts",$T27="Custom units"),0,1)))))) -> 1 | Z27: =IF($T27="",0,IF(OR(Setup!$B$26="",Setup!$C$26="No"),0,IF(ISNUMBER(M27),M27,IF($T27="Weights",IF(ISNUMBER(Setup!$D$26),Setup!$D$26,0),IF($T27="Nights",IF(ISNUMBER(Setup!$E$26),Setup!$E$26,0),IF(OR($T27="Exact amounts",$T27="Custom units"),0,1)))))) -> 0 | AA27: =IF($T27="",0,IF(OR(Setup!$B$27="",Setup!$C$27="No"),0,IF(ISNUMBER(N27),N27,IF($T27="Weights",IF(ISNUMBER(Setup!$D$27),Setup!$D$27,0),IF($T27="Nights",IF(ISNUMBER(Setup!$E$27),Setup!$E$27,0),IF(OR($T27="Exact amounts",$T27="Custom units"),0,1)))))) -> 0 | AB27: =IF($T27="",0,IF(OR(Setup!$B$28="",Setup!$C$28="No"),0,IF(ISNUMBER(O27),O27,IF($T27="Weights",IF(ISNUMBER(Setup!$D$28),Setup!$D$28,0),IF($T27="Nights",IF(ISNUMBER(Setup!$E$28),Setup!$E$28,0),IF(OR($T27="Exact amounts",$T27="Custom units"),0,1)))))) -> 0 | AC27: =IF($T27="",0,IF(OR(Setup!$B$29="",Setup!$C$29="No"),0,IF(ISNUMBER(P27),P27,IF($T27="Weights",IF(ISNUMBER(Setup!$D$29),Setup!$D$29,0),IF($T27="Nights",IF(ISNUMBER(Setup!$E$29),Setup!$E$29,0),IF(OR($T27="Exact amounts",$T27="Custom units"),0,1)))))) -> 0 | AD27: =IF($T27="",0,IF(OR(Setup!$B$30="",Setup!$C$30="No"),0,IF(ISNUMBER(Q27),Q27,IF($T27="Weights",IF(ISNUMBER(Setup!$D$30),Setup!$D$30,0),IF($T27="Nights",IF(ISNUMBER(Setup!$E$30),Setup!$E$30,0),IF(OR($T27="Exact amounts",$T27="Custom units"),0,1)))))) -> 0 | AE27: =IF($T27="",0,SUM($U27:$AD27)) -> 5 | AF27: =IF($AE27<=0,1,$AE27) -> 5 | AG27: =IF(ISNUMBER($E27),$E27,0) -> 120
A28: =IF($T28="","—",ROW()-7) -> 21 | B28: =TODAY()-13 -> 46219 | C28: Souvenir prints (2 each for Anna & Ben) | D28: Dana | E28: 63 | F28: Gifts & celebration | G28: Custom units | H28: 2 | I28: 2 | J28: 1 | K28: 1 | L28: 1 | R28: =IF($T28="","",IF($D28="","Who paid?",IF(SUMPRODUCT((Setup!$B$21:$B$30=$D28)*1)=0,"Payer is not in the member list on Setup",IF($E28="","Amount missing — type the number in column E",IF(NOT(ISNUMBER($E28)),"Amount must be a plain number — no currency symbol, no text",IF(AND($T28="Custom units",$AE28<=0),"Custom units: nobody has units on this row — type a number for at least one person",IF($AE28<=0,"Nobody shares this row — check the person columns H–Q, and the Weight / Nights columns on Setup",IF(AND($T28="Exact amounts",ABS($AE28-$AG28)>0.01),"Exact amounts do not add up to the amount","OK")))))))) -> OK | S28: =IFERROR(IF(OR($T28="",$C$4=""),"—",ROUND($AG28*INDEX($U28:$AD28,1,MATCH($C$4,Setup!$B$21:$B$30,0))/$AF28,2)),"—") -> 18 | T28: =IF(AND($C28="",$D28="",NOT(ISNUMBER($E28))),"",IF($G28="",IF(Setup!$C$17="","Equal",Setup!$C$17),$G28)) -> Custom units | U28: =IF($T28="",0,IF(OR(Setup!$B$21="",Setup!$C$21="No"),0,IF(ISNUMBER(H28),H28,IF($T28="Weights",IF(ISNUMBER(Setup!$D$21),Setup!$D$21,0),IF($T28="Nights",IF(ISNUMBER(Setup!$E$21),Setup!$E$21,0),IF(OR($T28="Exact amounts",$T28="Custom units"),0,1)))))) -> 2 | V28: =IF($T28="",0,IF(OR(Setup!$B$22="",Setup!$C$22="No"),0,IF(ISNUMBER(I28),I28,IF($T28="Weights",IF(ISNUMBER(Setup!$D$22),Setup!$D$22,0),IF($T28="Nights",IF(ISNUMBER(Setup!$E$22),Setup!$E$22,0),IF(OR($T28="Exact amounts",$T28="Custom units"),0,1)))))) -> 2 | W28: =IF($T28="",0,IF(OR(Setup!$B$23="",Setup!$C$23="No"),0,IF(ISNUMBER(J28),J28,IF($T28="Weights",IF(ISNUMBER(Setup!$D$23),Setup!$D$23,0),IF($T28="Nights",IF(ISNUMBER(Setup!$E$23),Setup!$E$23,0),IF(OR($T28="Exact amounts",$T28="Custom units"),0,1)))))) -> 1 | X28: =IF($T28="",0,IF(OR(Setup!$B$24="",Setup!$C$24="No"),0,IF(ISNUMBER(K28),K28,IF($T28="Weights",IF(ISNUMBER(Setup!$D$24),Setup!$D$24,0),IF($T28="Nights",IF(ISNUMBER(Setup!$E$24),Setup!$E$24,0),IF(OR($T28="Exact amounts",$T28="Custom units"),0,1)))))) -> 1 | Y28: =IF($T28="",0,IF(OR(Setup!$B$25="",Setup!$C$25="No"),0,IF(ISNUMBER(L28),L28,IF($T28="Weights",IF(ISNUMBER(Setup!$D$25),Setup!$D$25,0),IF($T28="Nights",IF(ISNUMBER(Setup!$E$25),Setup!$E$25,0),IF(OR($T28="Exact amounts",$T28="Custom units"),0,1)))))) -> 1 | Z28: =IF($T28="",0,IF(OR(Setup!$B$26="",Setup!$C$26="No"),0,IF(ISNUMBER(M28),M28,IF($T28="Weights",IF(ISNUMBER(Setup!$D$26),Setup!$D$26,0),IF($T28="Nights",IF(ISNUMBER(Setup!$E$26),Setup!$E$26,0),IF(OR($T28="Exact amounts",$T28="Custom units"),0,1)))))) -> 0 | AA28: =IF($T28="",0,IF(OR(Setup!$B$27="",Setup!$C$27="No"),0,IF(ISNUMBER(N28),N28,IF($T28="Weights",IF(ISNUMBER(Setup!$D$27),Setup!$D$27,0),IF($T28="Nights",IF(ISNUMBER(Setup!$E$27),Setup!$E$27,0),IF(OR($T28="Exact amounts",$T28="Custom units"),0,1)))))) -> 0 | AB28: =IF($T28="",0,IF(OR(Setup!$B$28="",Setup!$C$28="No"),0,IF(ISNUMBER(O28),O28,IF($T28="Weights",IF(ISNUMBER(Setup!$D$28),Setup!$D$28,0),IF($T28="Nights",IF(ISNUMBER(Setup!$E$28),Setup!$E$28,0),IF(OR($T28="Exact amounts",$T28="Custom units"),0,1)))))) -> 0 | AC28: =IF($T28="",0,IF(OR(Setup!$B$29="",Setup!$C$29="No"),0,IF(ISNUMBER(P28),P28,IF($T28="Weights",IF(ISNUMBER(Setup!$D$29),Setup!$D$29,0),IF($T28="Nights",IF(ISNUMBER(Setup!$E$29),Setup!$E$29,0),IF(OR($T28="Exact amounts",$T28="Custom units"),0,1)))))) -> 0 | AD28: =IF($T28="",0,IF(OR(Setup!$B$30="",Setup!$C$30="No"),0,IF(ISNUMBER(Q28),Q28,IF($T28="Weights",IF(ISNUMBER(Setup!$D$30),Setup!$D$30,0),IF($T28="Nights",IF(ISNUMBER(Setup!$E$30),Setup!$E$30,0),IF(OR($T28="Exact amounts",$T28="Custom units"),0,1)))))) -> 0 | AE28: =IF($T28="",0,SUM($U28:$AD28)) -> 7 | AF28: =IF($AE28<=0,1,$AE28) -> 7 | AG28: =IF(ISNUMBER($E28),$E28,0) -> 63
A29: =IF($T29="","—",ROW()-7) -> 22 | B29: =TODAY()-12 -> 46220 | C29: Lunch at the market hall | D29: Anna | E29: 57.2 | F29: Eating out | G29: Equal | R29: =IF($T29="","",IF($D29="","Who paid?",IF(SUMPRODUCT((Setup!$B$21:$B$30=$D29)*1)=0,"Payer is not in the member list on Setup",IF($E29="","Amount missing — type the number in column E",IF(NOT(ISNUMBER($E29)),"Amount must be a plain number — no currency symbol, no text",IF(AND($T29="Custom units",$AE29<=0),"Custom units: nobody has units on this row — type a number for at least one person",IF($AE29<=0,"Nobody shares this row — check the person columns H–Q, and the Weight / Nights columns on Setup",IF(AND($T29="Exact amounts",ABS($AE29-$AG29)>0.01),"Exact amounts do not add up to the amount","OK")))))))) -> OK | S29: =IFERROR(IF(OR($T29="",$C$4=""),"—",ROUND($AG29*INDEX($U29:$AD29,1,MATCH($C$4,Setup!$B$21:$B$30,0))/$AF29,2)),"—") -> 11.44 | T29: =IF(AND($C29="",$D29="",NOT(ISNUMBER($E29))),"",IF($G29="",IF(Setup!$C$17="","Equal",Setup!$C$17),$G29)) -> Equal | U29: =IF($T29="",0,IF(OR(Setup!$B$21="",Setup!$C$21="No"),0,IF(ISNUMBER(H29),H29,IF($T29="Weights",IF(ISNUMBER(Setup!$D$21),Setup!$D$21,0),IF($T29="Nights",IF(ISNUMBER(Setup!$E$21),Setup!$E$21,0),IF(OR($T29="Exact amounts",$T29="Custom units"),0,1)))))) -> 1 | V29: =IF($T29="",0,IF(OR(Setup!$B$22="",Setup!$C$22="No"),0,IF(ISNUMBER(I29),I29,IF($T29="Weights",IF(ISNUMBER(Setup!$D$22),Setup!$D$22,0),IF($T29="Nights",IF(ISNUMBER(Setup!$E$22),Setup!$E$22,0),IF(OR($T29="Exact amounts",$T29="Custom units"),0,1)))))) -> 1 | W29: =IF($T29="",0,IF(OR(Setup!$B$23="",Setup!$C$23="No"),0,IF(ISNUMBER(J29),J29,IF($T29="Weights",IF(ISNUMBER(Setup!$D$23),Setup!$D$23,0),IF($T29="Nights",IF(ISNUMBER(Setup!$E$23),Setup!$E$23,0),IF(OR($T29="Exact amounts",$T29="Custom units"),0,1)))))) -> 1 | X29: =IF($T29="",0,IF(OR(Setup!$B$24="",Setup!$C$24="No"),0,IF(ISNUMBER(K29),K29,IF($T29="Weights",IF(ISNUMBER(Setup!$D$24),Setup!$D$24,0),IF($T29="Nights",IF(ISNUMBER(Setup!$E$24),Setup!$E$24,0),IF(OR($T29="Exact amounts",$T29="Custom units"),0,1)))))) -> 1 | Y29: =IF($T29="",0,IF(OR(Setup!$B$25="",Setup!$C$25="No"),0,IF(ISNUMBER(L29),L29,IF($T29="Weights",IF(ISNUMBER(Setup!$D$25),Setup!$D$25,0),IF($T29="Nights",IF(ISNUMBER(Setup!$E$25),Setup!$E$25,0),IF(OR($T29="Exact amounts",$T29="Custom units"),0,1)))))) -> 1 | Z29: =IF($T29="",0,IF(OR(Setup!$B$26="",Setup!$C$26="No"),0,IF(ISNUMBER(M29),M29,IF($T29="Weights",IF(ISNUMBER(Setup!$D$26),Setup!$D$26,0),IF($T29="Nights",IF(ISNUMBER(Setup!$E$26),Setup!$E$26,0),IF(OR($T29="Exact amounts",$T29="Custom units"),0,1)))))) -> 0 | AA29: =IF($T29="",0,IF(OR(Setup!$B$27="",Setup!$C$27="No"),0,IF(ISNUMBER(N29),N29,IF($T29="Weights",IF(ISNUMBER(Setup!$D$27),Setup!$D$27,0),IF($T29="Nights",IF(ISNUMBER(Setup!$E$27),Setup!$E$27,0),IF(OR($T29="Exact amounts",$T29="Custom units"),0,1)))))) -> 0 | AB29: =IF($T29="",0,IF(OR(Setup!$B$28="",Setup!$C$28="No"),0,IF(ISNUMBER(O29),O29,IF($T29="Weights",IF(ISNUMBER(Setup!$D$28),Setup!$D$28,0),IF($T29="Nights",IF(ISNUMBER(Setup!$E$28),Setup!$E$28,0),IF(OR($T29="Exact amounts",$T29="Custom units"),0,1)))))) -> 0 | AC29: =IF($T29="",0,IF(OR(Setup!$B$29="",Setup!$C$29="No"),0,IF(ISNUMBER(P29),P29,IF($T29="Weights",IF(ISNUMBER(Setup!$D$29),Setup!$D$29,0),IF($T29="Nights",IF(ISNUMBER(Setup!$E$29),Setup!$E$29,0),IF(OR($T29="Exact amounts",$T29="Custom units"),0,1)))))) -> 0 | AD29: =IF($T29="",0,IF(OR(Setup!$B$30="",Setup!$C$30="No"),0,IF(ISNUMBER(Q29),Q29,IF($T29="Weights",IF(ISNUMBER(Setup!$D$30),Setup!$D$30,0),IF($T29="Nights",IF(ISNUMBER(Setup!$E$30),Setup!$E$30,0),IF(OR($T29="Exact amounts",$T29="Custom units"),0,1)))))) -> 0 | AE29: =IF($T29="",0,SUM($U29:$AD29)) -> 5 | AF29: =IF($AE29<=0,1,$AE29) -> 5 | AG29: =IF(ISNUMBER($E29),$E29,0) -> 57.2
A30: =IF($T30="","—",ROW()-7) -> 23 | B30: =TODAY()-11 -> 46221 | C30: Fuel for the drive home | D30: Ben | E30: 42.9 | F30: Travel & transport | G30: Equal | R30: =IF($T30="","",IF($D30="","Who paid?",IF(SUMPRODUCT((Setup!$B$21:$B$30=$D30)*1)=0,"Payer is not in the member list on Setup",IF($E30="","Amount missing — type the number in column E",IF(NOT(ISNUMBER($E30)),"Amount must be a plain number — no currency symbol, no text",IF(AND($T30="Custom units",$AE30<=0),"Custom units: nobody has units on this row — type a number for at least one person",IF($AE30<=0,"Nobody shares this row — check the person columns H–Q, and the Weight / Nights columns on Setup",IF(AND($T30="Exact amounts",ABS($AE30-$AG30)>0.01),"Exact amounts do not add up to the amount","OK")))))))) -> OK | S30: =IFERROR(IF(OR($T30="",$C$4=""),"—",ROUND($AG30*INDEX($U30:$AD30,1,MATCH($C$4,Setup!$B$21:$B$30,0))/$AF30,2)),"—") -> 8.58 | T30: =IF(AND($C30="",$D30="",NOT(ISNUMBER($E30))),"",IF($G30="",IF(Setup!$C$17="","Equal",Setup!$C$17),$G30)) -> Equal | U30: =IF($T30="",0,IF(OR(Setup!$B$21="",Setup!$C$21="No"),0,IF(ISNUMBER(H30),H30,IF($T30="Weights",IF(ISNUMBER(Setup!$D$21),Setup!$D$21,0),IF($T30="Nights",IF(ISNUMBER(Setup!$E$21),Setup!$E$21,0),IF(OR($T30="Exact amounts",$T30="Custom units"),0,1)))))) -> 1 | V30: =IF($T30="",0,IF(OR(Setup!$B$22="",Setup!$C$22="No"),0,IF(ISNUMBER(I30),I30,IF($T30="Weights",IF(ISNUMBER(Setup!$D$22),Setup!$D$22,0),IF($T30="Nights",IF(ISNUMBER(Setup!$E$22),Setup!$E$22,0),IF(OR($T30="Exact amounts",$T30="Custom units"),0,1)))))) -> 1 | W30: =IF($T30="",0,IF(OR(Setup!$B$23="",Setup!$C$23="No"),0,IF(ISNUMBER(J30),J30,IF($T30="Weights",IF(ISNUMBER(Setup!$D$23),Setup!$D$23,0),IF($T30="Nights",IF(ISNUMBER(Setup!$E$23),Setup!$E$23,0),IF(OR($T30="Exact amounts",$T30="Custom units"),0,1)))))) -> 1 | X30: =IF($T30="",0,IF(OR(Setup!$B$24="",Setup!$C$24="No"),0,IF(ISNUMBER(K30),K30,IF($T30="Weights",IF(ISNUMBER(Setup!$D$24),Setup!$D$24,0),IF($T30="Nights",IF(ISNUMBER(Setup!$E$24),Setup!$E$24,0),IF(OR($T30="Exact amounts",$T30="Custom units"),0,1)))))) -> 1 | Y30: =IF($T30="",0,IF(OR(Setup!$B$25="",Setup!$C$25="No"),0,IF(ISNUMBER(L30),L30,IF($T30="Weights",IF(ISNUMBER(Setup!$D$25),Setup!$D$25,0),IF($T30="Nights",IF(ISNUMBER(Setup!$E$25),Setup!$E$25,0),IF(OR($T30="Exact amounts",$T30="Custom units"),0,1)))))) -> 1 | Z30: =IF($T30="",0,IF(OR(Setup!$B$26="",Setup!$C$26="No"),0,IF(ISNUMBER(M30),M30,IF($T30="Weights",IF(ISNUMBER(Setup!$D$26),Setup!$D$26,0),IF($T30="Nights",IF(ISNUMBER(Setup!$E$26),Setup!$E$26,0),IF(OR($T30="Exact amounts",$T30="Custom units"),0,1)))))) -> 0 | AA30: =IF($T30="",0,IF(OR(Setup!$B$27="",Setup!$C$27="No"),0,IF(ISNUMBER(N30),N30,IF($T30="Weights",IF(ISNUMBER(Setup!$D$27),Setup!$D$27,0),IF($T30="Nights",IF(ISNUMBER(Setup!$E$27),Setup!$E$27,0),IF(OR($T30="Exact amounts",$T30="Custom units"),0,1)))))) -> 0 | AB30: =IF($T30="",0,IF(OR(Setup!$B$28="",Setup!$C$28="No"),0,IF(ISNUMBER(O30),O30,IF($T30="Weights",IF(ISNUMBER(Setup!$D$28),Setup!$D$28,0),IF($T30="Nights",IF(ISNUMBER(Setup!$E$28),Setup!$E$28,0),IF(OR($T30="Exact amounts",$T30="Custom units"),0,1)))))) -> 0 | AC30: =IF($T30="",0,IF(OR(Setup!$B$29="",Setup!$C$29="No"),0,IF(ISNUMBER(P30),P30,IF($T30="Weights",IF(ISNUMBER(Setup!$D$29),Setup!$D$29,0),IF($T30="Nights",IF(ISNUMBER(Setup!$E$29),Setup!$E$29,0),IF(OR($T30="Exact amounts",$T30="Custom units"),0,1)))))) -> 0 | AD30: =IF($T30="",0,IF(OR(Setup!$B$30="",Setup!$C$30="No"),0,IF(ISNUMBER(Q30),Q30,IF($T30="Weights",IF(ISNUMBER(Setup!$D$30),Setup!$D$30,0),IF($T30="Nights",IF(ISNUMBER(Setup!$E$30),Setup!$E$30,0),IF(OR($T30="Exact amounts",$T30="Custom units"),0,1)))))) -> 0 | AE30: =IF($T30="",0,SUM($U30:$AD30)) -> 5 | AF30: =IF($AE30<=0,1,$AE30) -> 5 | AG30: =IF(ISNUMBER($E30),$E30,0) -> 42.9
A31: =IF($T31="","—",ROW()-7) -> 24 | B31: =TODAY()-5 -> 46227 | C31: Ben pays Anna back in cash | D31: Ben | E31: 50 | F31: Payback / cash to a person | G31: Exact amounts | H31: 50 | R31: =IF($T31="","",IF($D31="","Who paid?",IF(SUMPRODUCT((Setup!$B$21:$B$30=$D31)*1)=0,"Payer is not in the member list on Setup",IF($E31="","Amount missing — type the number in column E",IF(NOT(ISNUMBER($E31)),"Amount must be a plain number — no currency symbol, no text",IF(AND($T31="Custom units",$AE31<=0),"Custom units: nobody has units on this row — type a number for at least one person",IF($AE31<=0,"Nobody shares this row — check the person columns H–Q, and the Weight / Nights columns on Setup",IF(AND($T31="Exact amounts",ABS($AE31-$AG31)>0.01),"Exact amounts do not add up to the amount","OK")))))))) -> OK | S31: =IFERROR(IF(OR($T31="",$C$4=""),"—",ROUND($AG31*INDEX($U31:$AD31,1,MATCH($C$4,Setup!$B$21:$B$30,0))/$AF31,2)),"—") -> 50 | T31: =IF(AND($C31="",$D31="",NOT(ISNUMBER($E31))),"",IF($G31="",IF(Setup!$C$17="","Equal",Setup!$C$17),$G31)) -> Exact amounts | U31: =IF($T31="",0,IF(OR(Setup!$B$21="",Setup!$C$21="No"),0,IF(ISNUMBER(H31),H31,IF($T31="Weights",IF(ISNUMBER(Setup!$D$21),Setup!$D$21,0),IF($T31="Nights",IF(ISNUMBER(Setup!$E$21),Setup!$E$21,0),IF(OR($T31="Exact amounts",$T31="Custom units"),0,1)))))) -> 50 | V31: =IF($T31="",0,IF(OR(Setup!$B$22="",Setup!$C$22="No"),0,IF(ISNUMBER(I31),I31,IF($T31="Weights",IF(ISNUMBER(Setup!$D$22),Setup!$D$22,0),IF($T31="Nights",IF(ISNUMBER(Setup!$E$22),Setup!$E$22,0),IF(OR($T31="Exact amounts",$T31="Custom units"),0,1)))))) -> 0 | W31: =IF($T31="",0,IF(OR(Setup!$B$23="",Setup!$C$23="No"),0,IF(ISNUMBER(J31),J31,IF($T31="Weights",IF(ISNUMBER(Setup!$D$23),Setup!$D$23,0),IF($T31="Nights",IF(ISNUMBER(Setup!$E$23),Setup!$E$23,0),IF(OR($T31="Exact amounts",$T31="Custom units"),0,1)))))) -> 0 | X31: =IF($T31="",0,IF(OR(Setup!$B$24="",Setup!$C$24="No"),0,IF(ISNUMBER(K31),K31,IF($T31="Weights",IF(ISNUMBER(Setup!$D$24),Setup!$D$24,0),IF($T31="Nights",IF(ISNUMBER(Setup!$E$24),Setup!$E$24,0),IF(OR($T31="Exact amounts",$T31="Custom units"),0,1)))))) -> 0 | Y31: =IF($T31="",0,IF(OR(Setup!$B$25="",Setup!$C$25="No"),0,IF(ISNUMBER(L31),L31,IF($T31="Weights",IF(ISNUMBER(Setup!$D$25),Setup!$D$25,0),IF($T31="Nights",IF(ISNUMBER(Setup!$E$25),Setup!$E$25,0),IF(OR($T31="Exact amounts",$T31="Custom units"),0,1)))))) -> 0 | Z31: =IF($T31="",0,IF(OR(Setup!$B$26="",Setup!$C$26="No"),0,IF(ISNUMBER(M31),M31,IF($T31="Weights",IF(ISNUMBER(Setup!$D$26),Setup!$D$26,0),IF($T31="Nights",IF(ISNUMBER(Setup!$E$26),Setup!$E$26,0),IF(OR($T31="Exact amounts",$T31="Custom units"),0,1)))))) -> 0 | AA31: =IF($T31="",0,IF(OR(Setup!$B$27="",Setup!$C$27="No"),0,IF(ISNUMBER(N31),N31,IF($T31="Weights",IF(ISNUMBER(Setup!$D$27),Setup!$D$27,0),IF($T31="Nights",IF(ISNUMBER(Setup!$E$27),Setup!$E$27,0),IF(OR($T31="Exact amounts",$T31="Custom units"),0,1)))))) -> 0 | AB31: =IF($T31="",0,IF(OR(Setup!$B$28="",Setup!$C$28="No"),0,IF(ISNUMBER(O31),O31,IF($T31="Weights",IF(ISNUMBER(Setup!$D$28),Setup!$D$28,0),IF($T31="Nights",IF(ISNUMBER(Setup!$E$28),Setup!$E$28,0),IF(OR($T31="Exact amounts",$T31="Custom units"),0,1)))))) -> 0 | AC31: =IF($T31="",0,IF(OR(Setup!$B$29="",Setup!$C$29="No"),0,IF(ISNUMBER(P31),P31,IF($T31="Weights",IF(ISNUMBER(Setup!$D$29),Setup!$D$29,0),IF($T31="Nights",IF(ISNUMBER(Setup!$E$29),Setup!$E$29,0),IF(OR($T31="Exact amounts",$T31="Custom units"),0,1)))))) -> 0 | AD31: =IF($T31="",0,IF(OR(Setup!$B$30="",Setup!$C$30="No"),0,IF(ISNUMBER(Q31),Q31,IF($T31="Weights",IF(ISNUMBER(Setup!$D$30),Setup!$D$30,0),IF($T31="Nights",IF(ISNUMBER(Setup!$E$30),Setup!$E$30,0),IF(OR($T31="Exact amounts",$T31="Custom units"),0,1)))))) -> 0 | AE31: =IF($T31="",0,SUM($U31:$AD31)) -> 50 | AF31: =IF($AE31<=0,1,$AE31) -> 50 | AG31: =IF(ISNUMBER($E31),$E31,0) -> 50
A32: =IF($T32="","—",ROW()-7) -> — | R32: =IF($T32="","",IF($D32="","Who paid?",IF(SUMPRODUCT((Setup!$B$21:$B$30=$D32)*1)=0,"Payer is not in the member list on Setup",IF($E32="","Amount missing — type the number in column E",IF(NOT(ISNUMBER($E32)),"Amount must be a plain number — no currency symbol, no text",IF(AND($T32="Custom units",$AE32<=0),"Custom units: nobody has units on this row — type a number for at least one person",IF($AE32<=0,"Nobody shares this row — check the person columns H–Q, and the Weight / Nights columns on Setup",IF(AND($T32="Exact amounts",ABS($AE32-$AG32)>0.01),"Exact amounts do not add up to the amount","OK")))))))) | S32: =IFERROR(IF(OR($T32="",$C$4=""),"—",ROUND($AG32*INDEX($U32:$AD32,1,MATCH($C$4,Setup!$B$21:$B$30,0))/$AF32,2)),"—") -> — | T32: =IF(AND($C32="",$D32="",NOT(ISNUMBER($E32))),"",IF($G32="",IF(Setup!$C$17="","Equal",Setup!$C$17),$G32)) | U32: =IF($T32="",0,IF(OR(Setup!$B$21="",Setup!$C$21="No"),0,IF(ISNUMBER(H32),H32,IF($T32="Weights",IF(ISNUMBER(Setup!$D$21),Setup!$D$21,0),IF($T32="Nights",IF(ISNUMBER(Setup!$E$21),Setup!$E$21,0),IF(OR($T32="Exact amounts",$T32="Custom units"),0,1)))))) -> 0 | V32: =IF($T32="",0,IF(OR(Setup!$B$22="",Setup!$C$22="No"),0,IF(ISNUMBER(I32),I32,IF($T32="Weights",IF(ISNUMBER(Setup!$D$22),Setup!$D$22,0),IF($T32="Nights",IF(ISNUMBER(Setup!$E$22),Setup!$E$22,0),IF(OR($T32="Exact amounts",$T32="Custom units"),0,1)))))) -> 0 | W32: =IF($T32="",0,IF(OR(Setup!$B$23="",Setup!$C$23="No"),0,IF(ISNUMBER(J32),J32,IF($T32="Weights",IF(ISNUMBER(Setup!$D$23),Setup!$D$23,0),IF($T32="Nights",IF(ISNUMBER(Setup!$E$23),Setup!$E$23,0),IF(OR($T32="Exact amounts",$T32="Custom units"),0,1)))))) -> 0 | X32: =IF($T32="",0,IF(OR(Setup!$B$24="",Setup!$C$24="No"),0,IF(ISNUMBER(K32),K32,IF($T32="Weights",IF(ISNUMBER(Setup!$D$24),Setup!$D$24,0),IF($T32="Nights",IF(ISNUMBER(Setup!$E$24),Setup!$E$24,0),IF(OR($T32="Exact amounts",$T32="Custom units"),0,1)))))) -> 0 | Y32: =IF($T32="",0,IF(OR(Setup!$B$25="",Setup!$C$25="No"),0,IF(ISNUMBER(L32),L32,IF($T32="Weights",IF(ISNUMBER(Setup!$D$25),Setup!$D$25,0),IF($T32="Nights",IF(ISNUMBER(Setup!$E$25),Setup!$E$25,0),IF(OR($T32="Exact amounts",$T32="Custom units"),0,1)))))) -> 0 | Z32: =IF($T32="",0,IF(OR(Setup!$B$26="",Setup!$C$26="No"),0,IF(ISNUMBER(M32),M32,IF($T32="Weights",IF(ISNUMBER(Setup!$D$26),Setup!$D$26,0),IF($T32="Nights",IF(ISNUMBER(Setup!$E$26),Setup!$E$26,0),IF(OR($T32="Exact amounts",$T32="Custom units"),0,1)))))) -> 0 | AA32: =IF($T32="",0,IF(OR(Setup!$B$27="",Setup!$C$27="No"),0,IF(ISNUMBER(N32),N32,IF($T32="Weights",IF(ISNUMBER(Setup!$D$27),Setup!$D$27,0),IF($T32="Nights",IF(ISNUMBER(Setup!$E$27),Setup!$E$27,0),IF(OR($T32="Exact amounts",$T32="Custom units"),0,1)))))) -> 0 | AB32: =IF($T32="",0,IF(OR(Setup!$B$28="",Setup!$C$28="No"),0,IF(ISNUMBER(O32),O32,IF($T32="Weights",IF(ISNUMBER(Setup!$D$28),Setup!$D$28,0),IF($T32="Nights",IF(ISNUMBER(Setup!$E$28),Setup!$E$28,0),IF(OR($T32="Exact amounts",$T32="Custom units"),0,1)))))) -> 0 | AC32: =IF($T32="",0,IF(OR(Setup!$B$29="",Setup!$C$29="No"),0,IF(ISNUMBER(P32),P32,IF($T32="Weights",IF(ISNUMBER(Setup!$D$29),Setup!$D$29,0),IF($T32="Nights",IF(ISNUMBER(Setup!$E$29),Setup!$E$29,0),IF(OR($T32="Exact amounts",$T32="Custom units"),0,1)))))) -> 0 | AD32: =IF($T32="",0,IF(OR(Setup!$B$30="",Setup!$C$30="No"),0,IF(ISNUMBER(Q32),Q32,IF($T32="Weights",IF(ISNUMBER(Setup!$D$30),Setup!$D$30,0),IF($T32="Nights",IF(ISNUMBER(Setup!$E$30),Setup!$E$30,0),IF(OR($T32="Exact amounts",$T32="Custom units"),0,1)))))) -> 0 | AE32: =IF($T32="",0,SUM($U32:$AD32)) -> 0 | AF32: =IF($AE32<=0,1,$AE32) -> 1 | AG32: =IF(ISNUMBER($E32),$E32,0) -> 0
A33: =IF($T33="","—",ROW()-7) -> — | R33: =IF($T33="","",IF($D33="","Who paid?",IF(SUMPRODUCT((Setup!$B$21:$B$30=$D33)*1)=0,"Payer is not in the member list on Setup",IF($E33="","Amount missing — type the number in column E",IF(NOT(ISNUMBER($E33)),"Amount must be a plain number — no currency symbol, no text",IF(AND($T33="Custom units",$AE33<=0),"Custom units: nobody has units on this row — type a number for at least one person",IF($AE33<=0,"Nobody shares this row — check the person columns H–Q, and the Weight / Nights columns on Setup",IF(AND($T33="Exact amounts",ABS($AE33-$AG33)>0.01),"Exact amounts do not add up to the amount","OK")))))))) | S33: =IFERROR(IF(OR($T33="",$C$4=""),"—",ROUND($AG33*INDEX($U33:$AD33,1,MATCH($C$4,Setup!$B$21:$B$30,0))/$AF33,2)),"—") -> — | T33: =IF(AND($C33="",$D33="",NOT(ISNUMBER($E33))),"",IF($G33="",IF(Setup!$C$17="","Equal",Setup!$C$17),$G33)) | U33: =IF($T33="",0,IF(OR(Setup!$B$21="",Setup!$C$21="No"),0,IF(ISNUMBER(H33),H33,IF($T33="Weights",IF(ISNUMBER(Setup!$D$21),Setup!$D$21,0),IF($T33="Nights",IF(ISNUMBER(Setup!$E$21),Setup!$E$21,0),IF(OR($T33="Exact amounts",$T33="Custom units"),0,1)))))) -> 0 | V33: =IF($T33="",0,IF(OR(Setup!$B$22="",Setup!$C$22="No"),0,IF(ISNUMBER(I33),I33,IF($T33="Weights",IF(ISNUMBER(Setup!$D$22),Setup!$D$22,0),IF($T33="Nights",IF(ISNUMBER(Setup!$E$22),Setup!$E$22,0),IF(OR($T33="Exact amounts",$T33="Custom units"),0,1)))))) -> 0 | W33: =IF($T33="",0,IF(OR(Setup!$B$23="",Setup!$C$23="No"),0,IF(ISNUMBER(J33),J33,IF($T33="Weights",IF(ISNUMBER(Setup!$D$23),Setup!$D$23,0),IF($T33="Nights",IF(ISNUMBER(Setup!$E$23),Setup!$E$23,0),IF(OR($T33="Exact amounts",$T33="Custom units"),0,1)))))) -> 0 | X33: =IF($T33="",0,IF(OR(Setup!$B$24="",Setup!$C$24="No"),0,IF(ISNUMBER(K33),K33,IF($T33="Weights",IF(ISNUMBER(Setup!$D$24),Setup!$D$24,0),IF($T33="Nights",IF(ISNUMBER(Setup!$E$24),Setup!$E$24,0),IF(OR($T33="Exact amounts",$T33="Custom units"),0,1)))))) -> 0 | Y33: =IF($T33="",0,IF(OR(Setup!$B$25="",Setup!$C$25="No"),0,IF(ISNUMBER(L33),L33,IF($T33="Weights",IF(ISNUMBER(Setup!$D$25),Setup!$D$25,0),IF($T33="Nights",IF(ISNUMBER(Setup!$E$25),Setup!$E$25,0),IF(OR($T33="Exact amounts",$T33="Custom units"),0,1)))))) -> 0 | Z33: =IF($T33="",0,IF(OR(Setup!$B$26="",Setup!$C$26="No"),0,IF(ISNUMBER(M33),M33,IF($T33="Weights",IF(ISNUMBER(Setup!$D$26),Setup!$D$26,0),IF($T33="Nights",IF(ISNUMBER(Setup!$E$26),Setup!$E$26,0),IF(OR($T33="Exact amounts",$T33="Custom units"),0,1)))))) -> 0 | AA33: =IF($T33="",0,IF(OR(Setup!$B$27="",Setup!$C$27="No"),0,IF(ISNUMBER(N33),N33,IF($T33="Weights",IF(ISNUMBER(Setup!$D$27),Setup!$D$27,0),IF($T33="Nights",IF(ISNUMBER(Setup!$E$27),Setup!$E$27,0),IF(OR($T33="Exact amounts",$T33="Custom units"),0,1)))))) -> 0 | AB33: =IF($T33="",0,IF(OR(Setup!$B$28="",Setup!$C$28="No"),0,IF(ISNUMBER(O33),O33,IF($T33="Weights",IF(ISNUMBER(Setup!$D$28),Setup!$D$28,0),IF($T33="Nights",IF(ISNUMBER(Setup!$E$28),Setup!$E$28,0),IF(OR($T33="Exact amounts",$T33="Custom units"),0,1)))))) -> 0 | AC33: =IF($T33="",0,IF(OR(Setup!$B$29="",Setup!$C$29="No"),0,IF(ISNUMBER(P33),P33,IF($T33="Weights",IF(ISNUMBER(Setup!$D$29),Setup!$D$29,0),IF($T33="Nights",IF(ISNUMBER(Setup!$E$29),Setup!$E$29,0),IF(OR($T33="Exact amounts",$T33="Custom units"),0,1)))))) -> 0 | AD33: =IF($T33="",0,IF(OR(Setup!$B$30="",Setup!$C$30="No"),0,IF(ISNUMBER(Q33),Q33,IF($T33="Weights",IF(ISNUMBER(Setup!$D$30),Setup!$D$30,0),IF($T33="Nights",IF(ISNUMBER(Setup!$E$30),Setup!$E$30,0),IF(OR($T33="Exact amounts",$T33="Custom units"),0,1)))))) -> 0 | AE33: =IF($T33="",0,SUM($U33:$AD33)) -> 0 | AF33: =IF($AE33<=0,1,$AE33) -> 1 | AG33: =IF(ISNUMBER($E33),$E33,0) -> 0
A34: =IF($T34="","—",ROW()-7) -> — | R34: =IF($T34="","",IF($D34="","Who paid?",IF(SUMPRODUCT((Setup!$B$21:$B$30=$D34)*1)=0,"Payer is not in the member list on Setup",IF($E34="","Amount missing — type the number in column E",IF(NOT(ISNUMBER($E34)),"Amount must be a plain number — no currency symbol, no text",IF(AND($T34="Custom units",$AE34<=0),"Custom units: nobody has units on this row — type a number for at least one person",IF($AE34<=0,"Nobody shares this row — check the person columns H–Q, and the Weight / Nights columns on Setup",IF(AND($T34="Exact amounts",ABS($AE34-$AG34)>0.01),"Exact amounts do not add up to the amount","OK")))))))) | S34: =IFERROR(IF(OR($T34="",$C$4=""),"—",ROUND($AG34*INDEX($U34:$AD34,1,MATCH($C$4,Setup!$B$21:$B$30,0))/$AF34,2)),"—") -> — | T34: =IF(AND($C34="",$D34="",NOT(ISNUMBER($E34))),"",IF($G34="",IF(Setup!$C$17="","Equal",Setup!$C$17),$G34)) | U34: =IF($T34="",0,IF(OR(Setup!$B$21="",Setup!$C$21="No"),0,IF(ISNUMBER(H34),H34,IF($T34="Weights",IF(ISNUMBER(Setup!$D$21),Setup!$D$21,0),IF($T34="Nights",IF(ISNUMBER(Setup!$E$21),Setup!$E$21,0),IF(OR($T34="Exact amounts",$T34="Custom units"),0,1)))))) -> 0 | V34: =IF($T34="",0,IF(OR(Setup!$B$22="",Setup!$C$22="No"),0,IF(ISNUMBER(I34),I34,IF($T34="Weights",IF(ISNUMBER(Setup!$D$22),Setup!$D$22,0),IF($T34="Nights",IF(ISNUMBER(Setup!$E$22),Setup!$E$22,0),IF(OR($T34="Exact amounts",$T34="Custom units"),0,1)))))) -> 0 | W34: =IF($T34="",0,IF(OR(Setup!$B$23="",Setup!$C$23="No"),0,IF(ISNUMBER(J34),J34,IF($T34="Weights",IF(ISNUMBER(Setup!$D$23),Setup!$D$23,0),IF($T34="Nights",IF(ISNUMBER(Setup!$E$23),Setup!$E$23,0),IF(OR($T34="Exact amounts",$T34="Custom units"),0,1)))))) -> 0 | X34: =IF($T34="",0,IF(OR(Setup!$B$24="",Setup!$C$24="No"),0,IF(ISNUMBER(K34),K34,IF($T34="Weights",IF(ISNUMBER(Setup!$D$24),Setup!$D$24,0),IF($T34="Nights",IF(ISNUMBER(Setup!$E$24),Setup!$E$24,0),IF(OR($T34="Exact amounts",$T34="Custom units"),0,1)))))) -> 0 | Y34: =IF($T34="",0,IF(OR(Setup!$B$25="",Setup!$C$25="No"),0,IF(ISNUMBER(L34),L34,IF($T34="Weights",IF(ISNUMBER(Setup!$D$25),Setup!$D$25,0),IF($T34="Nights",IF(ISNUMBER(Setup!$E$25),Setup!$E$25,0),IF(OR($T34="Exact amounts",$T34="Custom units"),0,1)))))) -> 0 | Z34: =IF($T34="",0,IF(OR(Setup!$B$26="",Setup!$C$26="No"),0,IF(ISNUMBER(M34),M34,IF($T34="Weights",IF(ISNUMBER(Setup!$D$26),Setup!$D$26,0),IF($T34="Nights",IF(ISNUMBER(Setup!$E$26),Setup!$E$26,0),IF(OR($T34="Exact amounts",$T34="Custom units"),0,1)))))) -> 0 | AA34: =IF($T34="",0,IF(OR(Setup!$B$27="",Setup!$C$27="No"),0,IF(ISNUMBER(N34),N34,IF($T34="Weights",IF(ISNUMBER(Setup!$D$27),Setup!$D$27,0),IF($T34="Nights",IF(ISNUMBER(Setup!$E$27),Setup!$E$27,0),IF(OR($T34="Exact amounts",$T34="Custom units"),0,1)))))) -> 0 | AB34: =IF($T34="",0,IF(OR(Setup!$B$28="",Setup!$C$28="No"),0,IF(ISNUMBER(O34),O34,IF($T34="Weights",IF(ISNUMBER(Setup!$D$28),Setup!$D$28,0),IF($T34="Nights",IF(ISNUMBER(Setup!$E$28),Setup!$E$28,0),IF(OR($T34="Exact amounts",$T34="Custom units"),0,1)))))) -> 0 | AC34: =IF($T34="",0,IF(OR(Setup!$B$29="",Setup!$C$29="No"),0,IF(ISNUMBER(P34),P34,IF($T34="Weights",IF(ISNUMBER(Setup!$D$29),Setup!$D$29,0),IF($T34="Nights",IF(ISNUMBER(Setup!$E$29),Setup!$E$29,0),IF(OR($T34="Exact amounts",$T34="Custom units"),0,1)))))) -> 0 | AD34: =IF($T34="",0,IF(OR(Setup!$B$30="",Setup!$C$30="No"),0,IF(ISNUMBER(Q34),Q34,IF($T34="Weights",IF(ISNUMBER(Setup!$D$30),Setup!$D$30,0),IF($T34="Nights",IF(ISNUMBER(Setup!$E$30),Setup!$E$30,0),IF(OR($T34="Exact amounts",$T34="Custom units"),0,1)))))) -> 0 | AE34: =IF($T34="",0,SUM($U34:$AD34)) -> 0 | AF34: =IF($AE34<=0,1,$AE34) -> 1 | AG34: =IF(ISNUMBER($E34),$E34,0) -> 0
A35: =IF($T35="","—",ROW()-7) -> — | R35: =IF($T35="","",IF($D35="","Who paid?",IF(SUMPRODUCT((Setup!$B$21:$B$30=$D35)*1)=0,"Payer is not in the member list on Setup",IF($E35="","Amount missing — type the number in column E",IF(NOT(ISNUMBER($E35)),"Amount must be a plain number — no currency symbol, no text",IF(AND($T35="Custom units",$AE35<=0),"Custom units: nobody has units on this row — type a number for at least one person",IF($AE35<=0,"Nobody shares this row — check the person columns H–Q, and the Weight / Nights columns on Setup",IF(AND($T35="Exact amounts",ABS($AE35-$AG35)>0.01),"Exact amounts do not add up to the amount","OK")))))))) | S35: =IFERROR(IF(OR($T35="",$C$4=""),"—",ROUND($AG35*INDEX($U35:$AD35,1,MATCH($C$4,Setup!$B$21:$B$30,0))/$AF35,2)),"—") -> — | T35: =IF(AND($C35="",$D35="",NOT(ISNUMBER($E35))),"",IF($G35="",IF(Setup!$C$17="","Equal",Setup!$C$17),$G35)) | U35: =IF($T35="",0,IF(OR(Setup!$B$21="",Setup!$C$21="No"),0,IF(ISNUMBER(H35),H35,IF($T35="Weights",IF(ISNUMBER(Setup!$D$21),Setup!$D$21,0),IF($T35="Nights",IF(ISNUMBER(Setup!$E$21),Setup!$E$21,0),IF(OR($T35="Exact amounts",$T35="Custom units"),0,1)))))) -> 0 | V35: =IF($T35="",0,IF(OR(Setup!$B$22="",Setup!$C$22="No"),0,IF(ISNUMBER(I35),I35,IF($T35="Weights",IF(ISNUMBER(Setup!$D$22),Setup!$D$22,0),IF($T35="Nights",IF(ISNUMBER(Setup!$E$22),Setup!$E$22,0),IF(OR($T35="Exact amounts",$T35="Custom units"),0,1)))))) -> 0 | W35: =IF($T35="",0,IF(OR(Setup!$B$23="",Setup!$C$23="No"),0,IF(ISNUMBER(J35),J35,IF($T35="Weights",IF(ISNUMBER(Setup!$D$23),Setup!$D$23,0),IF($T35="Nights",IF(ISNUMBER(Setup!$E$23),Setup!$E$23,0),IF(OR($T35="Exact amounts",$T35="Custom units"),0,1)))))) -> 0 | X35: =IF($T35="",0,IF(OR(Setup!$B$24="",Setup!$C$24="No"),0,IF(ISNUMBER(K35),K35,IF($T35="Weights",IF(ISNUMBER(Setup!$D$24),Setup!$D$24,0),IF($T35="Nights",IF(ISNUMBER(Setup!$E$24),Setup!$E$24,0),IF(OR($T35="Exact amounts",$T35="Custom units"),0,1)))))) -> 0 | Y35: =IF($T35="",0,IF(OR(Setup!$B$25="",Setup!$C$25="No"),0,IF(ISNUMBER(L35),L35,IF($T35="Weights",IF(ISNUMBER(Setup!$D$25),Setup!$D$25,0),IF($T35="Nights",IF(ISNUMBER(Setup!$E$25),Setup!$E$25,0),IF(OR($T35="Exact amounts",$T35="Custom units"),0,1)))))) -> 0 | Z35: =IF($T35="",0,IF(OR(Setup!$B$26="",Setup!$C$26="No"),0,IF(ISNUMBER(M35),M35,IF($T35="Weights",IF(ISNUMBER(Setup!$D$26),Setup!$D$26,0),IF($T35="Nights",IF(ISNUMBER(Setup!$E$26),Setup!$E$26,0),IF(OR($T35="Exact amounts",$T35="Custom units"),0,1)))))) -> 0 | AA35: =IF($T35="",0,IF(OR(Setup!$B$27="",Setup!$C$27="No"),0,IF(ISNUMBER(N35),N35,IF($T35="Weights",IF(ISNUMBER(Setup!$D$27),Setup!$D$27,0),IF($T35="Nights",IF(ISNUMBER(Setup!$E$27),Setup!$E$27,0),IF(OR($T35="Exact amounts",$T35="Custom units"),0,1)))))) -> 0 | AB35: =IF($T35="",0,IF(OR(Setup!$B$28="",Setup!$C$28="No"),0,IF(ISNUMBER(O35),O35,IF($T35="Weights",IF(ISNUMBER(Setup!$D$28),Setup!$D$28,0),IF($T35="Nights",IF(ISNUMBER(Setup!$E$28),Setup!$E$28,0),IF(OR($T35="Exact amounts",$T35="Custom units"),0,1)))))) -> 0 | AC35: =IF($T35="",0,IF(OR(Setup!$B$29="",Setup!$C$29="No"),0,IF(ISNUMBER(P35),P35,IF($T35="Weights",IF(ISNUMBER(Setup!$D$29),Setup!$D$29,0),IF($T35="Nights",IF(ISNUMBER(Setup!$E$29),Setup!$E$29,0),IF(OR($T35="Exact amounts",$T35="Custom units"),0,1)))))) -> 0 | AD35: =IF($T35="",0,IF(OR(Setup!$B$30="",Setup!$C$30="No"),0,IF(ISNUMBER(Q35),Q35,IF($T35="Weights",IF(ISNUMBER(Setup!$D$30),Setup!$D$30,0),IF($T35="Nights",IF(ISNUMBER(Setup!$E$30),Setup!$E$30,0),IF(OR($T35="Exact amounts",$T35="Custom units"),0,1)))))) -> 0 | AE35: =IF($T35="",0,SUM($U35:$AD35)) -> 0 | AF35: =IF($AE35<=0,1,$AE35) -> 1 | AG35: =IF(ISNUMBER($E35),$E35,0) -> 0
A36: =IF($T36="","—",ROW()-7) -> — | R36: =IF($T36="","",IF($D36="","Who paid?",IF(SUMPRODUCT((Setup!$B$21:$B$30=$D36)*1)=0,"Payer is not in the member list on Setup",IF($E36="","Amount missing — type the number in column E",IF(NOT(ISNUMBER($E36)),"Amount must be a plain number — no currency symbol, no text",IF(AND($T36="Custom units",$AE36<=0),"Custom units: nobody has units on this row — type a number for at least one person",IF($AE36<=0,"Nobody shares this row — check the person columns H–Q, and the Weight / Nights columns on Setup",IF(AND($T36="Exact amounts",ABS($AE36-$AG36)>0.01),"Exact amounts do not add up to the amount","OK")))))))) | S36: =IFERROR(IF(OR($T36="",$C$4=""),"—",ROUND($AG36*INDEX($U36:$AD36,1,MATCH($C$4,Setup!$B$21:$B$30,0))/$AF36,2)),"—") -> — | T36: =IF(AND($C36="",$D36="",NOT(ISNUMBER($E36))),"",IF($G36="",IF(Setup!$C$17="","Equal",Setup!$C$17),$G36)) | U36: =IF($T36="",0,IF(OR(Setup!$B$21="",Setup!$C$21="No"),0,IF(ISNUMBER(H36),H36,IF($T36="Weights",IF(ISNUMBER(Setup!$D$21),Setup!$D$21,0),IF($T36="Nights",IF(ISNUMBER(Setup!$E$21),Setup!$E$21,0),IF(OR($T36="Exact amounts",$T36="Custom units"),0,1)))))) -> 0 | V36: =IF($T36="",0,IF(OR(Setup!$B$22="",Setup!$C$22="No"),0,IF(ISNUMBER(I36),I36,IF($T36="Weights",IF(ISNUMBER(Setup!$D$22),Setup!$D$22,0),IF($T36="Nights",IF(ISNUMBER(Setup!$E$22),Setup!$E$22,0),IF(OR($T36="Exact amounts",$T36="Custom units"),0,1)))))) -> 0 | W36: =IF($T36="",0,IF(OR(Setup!$B$23="",Setup!$C$23="No"),0,IF(ISNUMBER(J36),J36,IF($T36="Weights",IF(ISNUMBER(Setup!$D$23),Setup!$D$23,0),IF($T36="Nights",IF(ISNUMBER(Setup!$E$23),Setup!$E$23,0),IF(OR($T36="Exact amounts",$T36="Custom units"),0,1)))))) -> 0 | X36: =IF($T36="",0,IF(OR(Setup!$B$24="",Setup!$C$24="No"),0,IF(ISNUMBER(K36),K36,IF($T36="Weights",IF(ISNUMBER(Setup!$D$24),Setup!$D$24,0),IF($T36="Nights",IF(ISNUMBER(Setup!$E$24),Setup!$E$24,0),IF(OR($T36="Exact amounts",$T36="Custom units"),0,1)))))) -> 0 | Y36: =IF($T36="",0,IF(OR(Setup!$B$25="",Setup!$C$25="No"),0,IF(ISNUMBER(L36),L36,IF($T36="Weights",IF(ISNUMBER(Setup!$D$25),Setup!$D$25,0),IF($T36="Nights",IF(ISNUMBER(Setup!$E$25),Setup!$E$25,0),IF(OR($T36="Exact amounts",$T36="Custom units"),0,1)))))) -> 0 | Z36: =IF($T36="",0,IF(OR(Setup!$B$26="",Setup!$C$26="No"),0,IF(ISNUMBER(M36),M36,IF($T36="Weights",IF(ISNUMBER(Setup!$D$26),Setup!$D$26,0),IF($T36="Nights",IF(ISNUMBER(Setup!$E$26),Setup!$E$26,0),IF(OR($T36="Exact amounts",$T36="Custom units"),0,1)))))) -> 0 | AA36: =IF($T36="",0,IF(OR(Setup!$B$27="",Setup!$C$27="No"),0,IF(ISNUMBER(N36),N36,IF($T36="Weights",IF(ISNUMBER(Setup!$D$27),Setup!$D$27,0),IF($T36="Nights",IF(ISNUMBER(Setup!$E$27),Setup!$E$27,0),IF(OR($T36="Exact amounts",$T36="Custom units"),0,1)))))) -> 0 | AB36: =IF($T36="",0,IF(OR(Setup!$B$28="",Setup!$C$28="No"),0,IF(ISNUMBER(O36),O36,IF($T36="Weights",IF(ISNUMBER(Setup!$D$28),Setup!$D$28,0),IF($T36="Nights",IF(ISNUMBER(Setup!$E$28),Setup!$E$28,0),IF(OR($T36="Exact amounts",$T36="Custom units"),0,1)))))) -> 0 | AC36: =IF($T36="",0,IF(OR(Setup!$B$29="",Setup!$C$29="No"),0,IF(ISNUMBER(P36),P36,IF($T36="Weights",IF(ISNUMBER(Setup!$D$29),Setup!$D$29,0),IF($T36="Nights",IF(ISNUMBER(Setup!$E$29),Setup!$E$29,0),IF(OR($T36="Exact amounts",$T36="Custom units"),0,1)))))) -> 0 | AD36: =IF($T36="",0,IF(OR(Setup!$B$30="",Setup!$C$30="No"),0,IF(ISNUMBER(Q36),Q36,IF($T36="Weights",IF(ISNUMBER(Setup!$D$30),Setup!$D$30,0),IF($T36="Nights",IF(ISNUMBER(Setup!$E$30),Setup!$E$30,0),IF(OR($T36="Exact amounts",$T36="Custom units"),0,1)))))) -> 0 | AE36: =IF($T36="",0,SUM($U36:$AD36)) -> 0 | AF36: =IF($AE36<=0,1,$AE36) -> 1 | AG36: =IF(ISNUMBER($E36),$E36,0) -> 0
A37: =IF($T37="","—",ROW()-7) -> — | R37: =IF($T37="","",IF($D37="","Who paid?",IF(SUMPRODUCT((Setup!$B$21:$B$30=$D37)*1)=0,"Payer is not in the member list on Setup",IF($E37="","Amount missing — type the number in column E",IF(NOT(ISNUMBER($E37)),"Amount must be a plain number — no currency symbol, no text",IF(AND($T37="Custom units",$AE37<=0),"Custom units: nobody has units on this row — type a number for at least one person",IF($AE37<=0,"Nobody shares this row — check the person columns H–Q, and the Weight / Nights columns on Setup",IF(AND($T37="Exact amounts",ABS($AE37-$AG37)>0.01),"Exact amounts do not add up to the amount","OK")))))))) | S37: =IFERROR(IF(OR($T37="",$C$4=""),"—",ROUND($AG37*INDEX($U37:$AD37,1,MATCH($C$4,Setup!$B$21:$B$30,0))/$AF37,2)),"—") -> — | T37: =IF(AND($C37="",$D37="",NOT(ISNUMBER($E37))),"",IF($G37="",IF(Setup!$C$17="","Equal",Setup!$C$17),$G37)) | U37: =IF($T37="",0,IF(OR(Setup!$B$21="",Setup!$C$21="No"),0,IF(ISNUMBER(H37),H37,IF($T37="Weights",IF(ISNUMBER(Setup!$D$21),Setup!$D$21,0),IF($T37="Nights",IF(ISNUMBER(Setup!$E$21),Setup!$E$21,0),IF(OR($T37="Exact amounts",$T37="Custom units"),0,1)))))) -> 0 | V37: =IF($T37="",0,IF(OR(Setup!$B$22="",Setup!$C$22="No"),0,IF(ISNUMBER(I37),I37,IF($T37="Weights",IF(ISNUMBER(Setup!$D$22),Setup!$D$22,0),IF($T37="Nights",IF(ISNUMBER(Setup!$E$22),Setup!$E$22,0),IF(OR($T37="Exact amounts",$T37="Custom units"),0,1)))))) -> 0 | W37: =IF($T37="",0,IF(OR(Setup!$B$23="",Setup!$C$23="No"),0,IF(ISNUMBER(J37),J37,IF($T37="Weights",IF(ISNUMBER(Setup!$D$23),Setup!$D$23,0),IF($T37="Nights",IF(ISNUMBER(Setup!$E$23),Setup!$E$23,0),IF(OR($T37="Exact amounts",$T37="Custom units"),0,1)))))) -> 0 | X37: =IF($T37="",0,IF(OR(Setup!$B$24="",Setup!$C$24="No"),0,IF(ISNUMBER(K37),K37,IF($T37="Weights",IF(ISNUMBER(Setup!$D$24),Setup!$D$24,0),IF($T37="Nights",IF(ISNUMBER(Setup!$E$24),Setup!$E$24,0),IF(OR($T37="Exact amounts",$T37="Custom units"),0,1)))))) -> 0 | Y37: =IF($T37="",0,IF(OR(Setup!$B$25="",Setup!$C$25="No"),0,IF(ISNUMBER(L37),L37,IF($T37="Weights",IF(ISNUMBER(Setup!$D$25),Setup!$D$25,0),IF($T37="Nights",IF(ISNUMBER(Setup!$E$25),Setup!$E$25,0),IF(OR($T37="Exact amounts",$T37="Custom units"),0,1)))))) -> 0 | Z37: =IF($T37="",0,IF(OR(Setup!$B$26="",Setup!$C$26="No"),0,IF(ISNUMBER(M37),M37,IF($T37="Weights",IF(ISNUMBER(Setup!$D$26),Setup!$D$26,0),IF($T37="Nights",IF(ISNUMBER(Setup!$E$26),Setup!$E$26,0),IF(OR($T37="Exact amounts",$T37="Custom units"),0,1)))))) -> 0 | AA37: =IF($T37="",0,IF(OR(Setup!$B$27="",Setup!$C$27="No"),0,IF(ISNUMBER(N37),N37,IF($T37="Weights",IF(ISNUMBER(Setup!$D$27),Setup!$D$27,0),IF($T37="Nights",IF(ISNUMBER(Setup!$E$27),Setup!$E$27,0),IF(OR($T37="Exact amounts",$T37="Custom units"),0,1)))))) -> 0 | AB37: =IF($T37="",0,IF(OR(Setup!$B$28="",Setup!$C$28="No"),0,IF(ISNUMBER(O37),O37,IF($T37="Weights",IF(ISNUMBER(Setup!$D$28),Setup!$D$28,0),IF($T37="Nights",IF(ISNUMBER(Setup!$E$28),Setup!$E$28,0),IF(OR($T37="Exact amounts",$T37="Custom units"),0,1)))))) -> 0 | AC37: =IF($T37="",0,IF(OR(Setup!$B$29="",Setup!$C$29="No"),0,IF(ISNUMBER(P37),P37,IF($T37="Weights",IF(ISNUMBER(Setup!$D$29),Setup!$D$29,0),IF($T37="Nights",IF(ISNUMBER(Setup!$E$29),Setup!$E$29,0),IF(OR($T37="Exact amounts",$T37="Custom units"),0,1)))))) -> 0 | AD37: =IF($T37="",0,IF(OR(Setup!$B$30="",Setup!$C$30="No"),0,IF(ISNUMBER(Q37),Q37,IF($T37="Weights",IF(ISNUMBER(Setup!$D$30),Setup!$D$30,0),IF($T37="Nights",IF(ISNUMBER(Setup!$E$30),Setup!$E$30,0),IF(OR($T37="Exact amounts",$T37="Custom units"),0,1)))))) -> 0 | AE37: =IF($T37="",0,SUM($U37:$AD37)) -> 0 | AF37: =IF($AE37<=0,1,$AE37) -> 1 | AG37: =IF(ISNUMBER($E37),$E37,0) -> 0
A38: =IF($T38="","—",ROW()-7) -> — | R38: =IF($T38="","",IF($D38="","Who paid?",IF(SUMPRODUCT((Setup!$B$21:$B$30=$D38)*1)=0,"Payer is not in the member list on Setup",IF($E38="","Amount missing — type the number in column E",IF(NOT(ISNUMBER($E38)),"Amount must be a plain number — no currency symbol, no text",IF(AND($T38="Custom units",$AE38<=0),"Custom units: nobody has units on this row — type a number for at least one person",IF($AE38<=0,"Nobody shares this row — check the person columns H–Q, and the Weight / Nights columns on Setup",IF(AND($T38="Exact amounts",ABS($AE38-$AG38)>0.01),"Exact amounts do not add up to the amount","OK")))))))) | S38: =IFERROR(IF(OR($T38="",$C$4=""),"—",ROUND($AG38*INDEX($U38:$AD38,1,MATCH($C$4,Setup!$B$21:$B$30,0))/$AF38,2)),"—") -> — | T38: =IF(AND($C38="",$D38="",NOT(ISNUMBER($E38))),"",IF($G38="",IF(Setup!$C$17="","Equal",Setup!$C$17),$G38)) | U38: =IF($T38="",0,IF(OR(Setup!$B$21="",Setup!$C$21="No"),0,IF(ISNUMBER(H38),H38,IF($T38="Weights",IF(ISNUMBER(Setup!$D$21),Setup!$D$21,0),IF($T38="Nights",IF(ISNUMBER(Setup!$E$21),Setup!$E$21,0),IF(OR($T38="Exact amounts",$T38="Custom units"),0,1)))))) -> 0 | V38: =IF($T38="",0,IF(OR(Setup!$B$22="",Setup!$C$22="No"),0,IF(ISNUMBER(I38),I38,IF($T38="Weights",IF(ISNUMBER(Setup!$D$22),Setup!$D$22,0),IF($T38="Nights",IF(ISNUMBER(Setup!$E$22),Setup!$E$22,0),IF(OR($T38="Exact amounts",$T38="Custom units"),0,1)))))) -> 0 | W38: =IF($T38="",0,IF(OR(Setup!$B$23="",Setup!$C$23="No"),0,IF(ISNUMBER(J38),J38,IF($T38="Weights",IF(ISNUMBER(Setup!$D$23),Setup!$D$23,0),IF($T38="Nights",IF(ISNUMBER(Setup!$E$23),Setup!$E$23,0),IF(OR($T38="Exact amounts",$T38="Custom units"),0,1)))))) -> 0 | X38: =IF($T38="",0,IF(OR(Setup!$B$24="",Setup!$C$24="No"),0,IF(ISNUMBER(K38),K38,IF($T38="Weights",IF(ISNUMBER(Setup!$D$24),Setup!$D$24,0),IF($T38="Nights",IF(ISNUMBER(Setup!$E$24),Setup!$E$24,0),IF(OR($T38="Exact amounts",$T38="Custom units"),0,1)))))) -> 0 | Y38: =IF($T38="",0,IF(OR(Setup!$B$25="",Setup!$C$25="No"),0,IF(ISNUMBER(L38),L38,IF($T38="Weights",IF(ISNUMBER(Setup!$D$25),Setup!$D$25,0),IF($T38="Nights",IF(ISNUMBER(Setup!$E$25),Setup!$E$25,0),IF(OR($T38="Exact amounts",$T38="Custom units"),0,1)))))) -> 0 | Z38: =IF($T38="",0,IF(OR(Setup!$B$26="",Setup!$C$26="No"),0,IF(ISNUMBER(M38),M38,IF($T38="Weights",IF(ISNUMBER(Setup!$D$26),Setup!$D$26,0),IF($T38="Nights",IF(ISNUMBER(Setup!$E$26),Setup!$E$26,0),IF(OR($T38="Exact amounts",$T38="Custom units"),0,1)))))) -> 0 | AA38: =IF($T38="",0,IF(OR(Setup!$B$27="",Setup!$C$27="No"),0,IF(ISNUMBER(N38),N38,IF($T38="Weights",IF(ISNUMBER(Setup!$D$27),Setup!$D$27,0),IF($T38="Nights",IF(ISNUMBER(Setup!$E$27),Setup!$E$27,0),IF(OR($T38="Exact amounts",$T38="Custom units"),0,1)))))) -> 0 | AB38: =IF($T38="",0,IF(OR(Setup!$B$28="",Setup!$C$28="No"),0,IF(ISNUMBER(O38),O38,IF($T38="Weights",IF(ISNUMBER(Setup!$D$28),Setup!$D$28,0),IF($T38="Nights",IF(ISNUMBER(Setup!$E$28),Setup!$E$28,0),IF(OR($T38="Exact amounts",$T38="Custom units"),0,1)))))) -> 0 | AC38: =IF($T38="",0,IF(OR(Setup!$B$29="",Setup!$C$29="No"),0,IF(ISNUMBER(P38),P38,IF($T38="Weights",IF(ISNUMBER(Setup!$D$29),Setup!$D$29,0),IF($T38="Nights",IF(ISNUMBER(Setup!$E$29),Setup!$E$29,0),IF(OR($T38="Exact amounts",$T38="Custom units"),0,1)))))) -> 0 | AD38: =IF($T38="",0,IF(OR(Setup!$B$30="",Setup!$C$30="No"),0,IF(ISNUMBER(Q38),Q38,IF($T38="Weights",IF(ISNUMBER(Setup!$D$30),Setup!$D$30,0),IF($T38="Nights",IF(ISNUMBER(Setup!$E$30),Setup!$E$30,0),IF(OR($T38="Exact amounts",$T38="Custom units"),0,1)))))) -> 0 | AE38: =IF($T38="",0,SUM($U38:$AD38)) -> 0 | AF38: =IF($AE38<=0,1,$AE38) -> 1 | AG38: =IF(ISNUMBER($E38),$E38,0) -> 0
A39: =IF($T39="","—",ROW()-7) -> — | R39: =IF($T39="","",IF($D39="","Who paid?",IF(SUMPRODUCT((Setup!$B$21:$B$30=$D39)*1)=0,"Payer is not in the member list on Setup",IF($E39="","Amount missing — type the number in column E",IF(NOT(ISNUMBER($E39)),"Amount must be a plain number — no currency symbol, no text",IF(AND($T39="Custom units",$AE39<=0),"Custom units: nobody has units on this row — type a number for at least one person",IF($AE39<=0,"Nobody shares this row — check the person columns H–Q, and the Weight / Nights columns on Setup",IF(AND($T39="Exact amounts",ABS($AE39-$AG39)>0.01),"Exact amounts do not add up to the amount","OK")))))))) | S39: =IFERROR(IF(OR($T39="",$C$4=""),"—",ROUND($AG39*INDEX($U39:$AD39,1,MATCH($C$4,Setup!$B$21:$B$30,0))/$AF39,2)),"—") -> — | T39: =IF(AND($C39="",$D39="",NOT(ISNUMBER($E39))),"",IF($G39="",IF(Setup!$C$17="","Equal",Setup!$C$17),$G39)) | U39: =IF($T39="",0,IF(OR(Setup!$B$21="",Setup!$C$21="No"),0,IF(ISNUMBER(H39),H39,IF($T39="Weights",IF(ISNUMBER(Setup!$D$21),Setup!$D$21,0),IF($T39="Nights",IF(ISNUMBER(Setup!$E$21),Setup!$E$21,0),IF(OR($T39="Exact amounts",$T39="Custom units"),0,1)))))) -> 0 | V39: =IF($T39="",0,IF(OR(Setup!$B$22="",Setup!$C$22="No"),0,IF(ISNUMBER(I39),I39,IF($T39="Weights",IF(ISNUMBER(Setup!$D$22),Setup!$D$22,0),IF($T39="Nights",IF(ISNUMBER(Setup!$E$22),Setup!$E$22,0),IF(OR($T39="Exact amounts",$T39="Custom units"),0,1)))))) -> 0 | W39: =IF($T39="",0,IF(OR(Setup!$B$23="",Setup!$C$23="No"),0,IF(ISNUMBER(J39),J39,IF($T39="Weights",IF(ISNUMBER(Setup!$D$23),Setup!$D$23,0),IF($T39="Nights",IF(ISNUMBER(Setup!$E$23),Setup!$E$23,0),IF(OR($T39="Exact amounts",$T39="Custom units"),0,1)))))) -> 0 | X39: =IF($T39="",0,IF(OR(Setup!$B$24="",Setup!$C$24="No"),0,IF(ISNUMBER(K39),K39,IF($T39="Weights",IF(ISNUMBER(Setup!$D$24),Setup!$D$24,0),IF($T39="Nights",IF(ISNUMBER(Setup!$E$24),Setup!$E$24,0),IF(OR($T39="Exact amounts",$T39="Custom units"),0,1)))))) -> 0 | Y39: =IF($T39="",0,IF(OR(Setup!$B$25="",Setup!$C$25="No"),0,IF(ISNUMBER(L39),L39,IF($T39="Weights",IF(ISNUMBER(Setup!$D$25),Setup!$D$25,0),IF($T39="Nights",IF(ISNUMBER(Setup!$E$25),Setup!$E$25,0),IF(OR($T39="Exact amounts",$T39="Custom units"),0,1)))))) -> 0 | Z39: =IF($T39="",0,IF(OR(Setup!$B$26="",Setup!$C$26="No"),0,IF(ISNUMBER(M39),M39,IF($T39="Weights",IF(ISNUMBER(Setup!$D$26),Setup!$D$26,0),IF($T39="Nights",IF(ISNUMBER(Setup!$E$26),Setup!$E$26,0),IF(OR($T39="Exact amounts",$T39="Custom units"),0,1)))))) -> 0 | AA39: =IF($T39="",0,IF(OR(Setup!$B$27="",Setup!$C$27="No"),0,IF(ISNUMBER(N39),N39,IF($T39="Weights",IF(ISNUMBER(Setup!$D$27),Setup!$D$27,0),IF($T39="Nights",IF(ISNUMBER(Setup!$E$27),Setup!$E$27,0),IF(OR($T39="Exact amounts",$T39="Custom units"),0,1)))))) -> 0 | AB39: =IF($T39="",0,IF(OR(Setup!$B$28="",Setup!$C$28="No"),0,IF(ISNUMBER(O39),O39,IF($T39="Weights",IF(ISNUMBER(Setup!$D$28),Setup!$D$28,0),IF($T39="Nights",IF(ISNUMBER(Setup!$E$28),Setup!$E$28,0),IF(OR($T39="Exact amounts",$T39="Custom units"),0,1)))))) -> 0 | AC39: =IF($T39="",0,IF(OR(Setup!$B$29="",Setup!$C$29="No"),0,IF(ISNUMBER(P39),P39,IF($T39="Weights",IF(ISNUMBER(Setup!$D$29),Setup!$D$29,0),IF($T39="Nights",IF(ISNUMBER(Setup!$E$29),Setup!$E$29,0),IF(OR($T39="Exact amounts",$T39="Custom units"),0,1)))))) -> 0 | AD39: =IF($T39="",0,IF(OR(Setup!$B$30="",Setup!$C$30="No"),0,IF(ISNUMBER(Q39),Q39,IF($T39="Weights",IF(ISNUMBER(Setup!$D$30),Setup!$D$30,0),IF($T39="Nights",IF(ISNUMBER(Setup!$E$30),Setup!$E$30,0),IF(OR($T39="Exact amounts",$T39="Custom units"),0,1)))))) -> 0 | AE39: =IF($T39="",0,SUM($U39:$AD39)) -> 0 | AF39: =IF($AE39<=0,1,$AE39) -> 1 | AG39: =IF(ISNUMBER($E39),$E39,0) -> 0
A40: =IF($T40="","—",ROW()-7) -> — | R40: =IF($T40="","",IF($D40="","Who paid?",IF(SUMPRODUCT((Setup!$B$21:$B$30=$D40)*1)=0,"Payer is not in the member list on Setup",IF($E40="","Amount missing — type the number in column E",IF(NOT(ISNUMBER($E40)),"Amount must be a plain number — no currency symbol, no text",IF(AND($T40="Custom units",$AE40<=0),"Custom units: nobody has units on this row — type a number for at least one person",IF($AE40<=0,"Nobody shares this row — check the person columns H–Q, and the Weight / Nights columns on Setup",IF(AND($T40="Exact amounts",ABS($AE40-$AG40)>0.01),"Exact amounts do not add up to the amount","OK")))))))) | S40: =IFERROR(IF(OR($T40="",$C$4=""),"—",ROUND($AG40*INDEX($U40:$AD40,1,MATCH($C$4,Setup!$B$21:$B$30,0))/$AF40,2)),"—") -> — | T40: =IF(AND($C40="",$D40="",NOT(ISNUMBER($E40))),"",IF($G40="",IF(Setup!$C$17="","Equal",Setup!$C$17),$G40)) | U40: =IF($T40="",0,IF(OR(Setup!$B$21="",Setup!$C$21="No"),0,IF(ISNUMBER(H40),H40,IF($T40="Weights",IF(ISNUMBER(Setup!$D$21),Setup!$D$21,0),IF($T40="Nights",IF(ISNUMBER(Setup!$E$21),Setup!$E$21,0),IF(OR($T40="Exact amounts",$T40="Custom units"),0,1)))))) -> 0 | V40: =IF($T40="",0,IF(OR(Setup!$B$22="",Setup!$C$22="No"),0,IF(ISNUMBER(I40),I40,IF($T40="Weights",IF(ISNUMBER(Setup!$D$22),Setup!$D$22,0),IF($T40="Nights",IF(ISNUMBER(Setup!$E$22),Setup!$E$22,0),IF(OR($T40="Exact amounts",$T40="Custom units"),0,1)))))) -> 0 | W40: =IF($T40="",0,IF(OR(Setup!$B$23="",Setup!$C$23="No"),0,IF(ISNUMBER(J40),J40,IF($T40="Weights",IF(ISNUMBER(Setup!$D$23),Setup!$D$23,0),IF($T40="Nights",IF(ISNUMBER(Setup!$E$23),Setup!$E$23,0),IF(OR($T40="Exact amounts",$T40="Custom units"),0,1)))))) -> 0 | X40: =IF($T40="",0,IF(OR(Setup!$B$24="",Setup!$C$24="No"),0,IF(ISNUMBER(K40),K40,IF($T40="Weights",IF(ISNUMBER(Setup!$D$24),Setup!$D$24,0),IF($T40="Nights",IF(ISNUMBER(Setup!$E$24),Setup!$E$24,0),IF(OR($T40="Exact amounts",$T40="Custom units"),0,1)))))) -> 0 | Y40: =IF($T40="",0,IF(OR(Setup!$B$25="",Setup!$C$25="No"),0,IF(ISNUMBER(L40),L40,IF($T40="Weights",IF(ISNUMBER(Setup!$D$25),Setup!$D$25,0),IF($T40="Nights",IF(ISNUMBER(Setup!$E$25),Setup!$E$25,0),IF(OR($T40="Exact amounts",$T40="Custom units"),0,1)))))) -> 0 | Z40: =IF($T40="",0,IF(OR(Setup!$B$26="",Setup!$C$26="No"),0,IF(ISNUMBER(M40),M40,IF($T40="Weights",IF(ISNUMBER(Setup!$D$26),Setup!$D$26,0),IF($T40="Nights",IF(ISNUMBER(Setup!$E$26),Setup!$E$26,0),IF(OR($T40="Exact amounts",$T40="Custom units"),0,1)))))) -> 0 | AA40: =IF($T40="",0,IF(OR(Setup!$B$27="",Setup!$C$27="No"),0,IF(ISNUMBER(N40),N40,IF($T40="Weights",IF(ISNUMBER(Setup!$D$27),Setup!$D$27,0),IF($T40="Nights",IF(ISNUMBER(Setup!$E$27),Setup!$E$27,0),IF(OR($T40="Exact amounts",$T40="Custom units"),0,1)))))) -> 0 | AB40: =IF($T40="",0,IF(OR(Setup!$B$28="",Setup!$C$28="No"),0,IF(ISNUMBER(O40),O40,IF($T40="Weights",IF(ISNUMBER(Setup!$D$28),Setup!$D$28,0),IF($T40="Nights",IF(ISNUMBER(Setup!$E$28),Setup!$E$28,0),IF(OR($T40="Exact amounts",$T40="Custom units"),0,1)))))) -> 0 | AC40: =IF($T40="",0,IF(OR(Setup!$B$29="",Setup!$C$29="No"),0,IF(ISNUMBER(P40),P40,IF($T40="Weights",IF(ISNUMBER(Setup!$D$29),Setup!$D$29,0),IF($T40="Nights",IF(ISNUMBER(Setup!$E$29),Setup!$E$29,0),IF(OR($T40="Exact amounts",$T40="Custom units"),0,1)))))) -> 0 | AD40: =IF($T40="",0,IF(OR(Setup!$B$30="",Setup!$C$30="No"),0,IF(ISNUMBER(Q40),Q40,IF($T40="Weights",IF(ISNUMBER(Setup!$D$30),Setup!$D$30,0),IF($T40="Nights",IF(ISNUMBER(Setup!$E$30),Setup!$E$30,0),IF(OR($T40="Exact amounts",$T40="Custom units"),0,1)))))) -> 0 | AE40: =IF($T40="",0,SUM($U40:$AD40)) -> 0 | AF40: =IF($AE40<=0,1,$AE40) -> 1 | AG40: =IF(ISNUMBER($E40),$E40,0) -> 0
A41: =IF($T41="","—",ROW()-7) -> — | R41: =IF($T41="","",IF($D41="","Who paid?",IF(SUMPRODUCT((Setup!$B$21:$B$30=$D41)*1)=0,"Payer is not in the member list on Setup",IF($E41="","Amount missing — type the number in column E",IF(NOT(ISNUMBER($E41)),"Amount must be a plain number — no currency symbol, no text",IF(AND($T41="Custom units",$AE41<=0),"Custom units: nobody has units on this row — type a number for at least one person",IF($AE41<=0,"Nobody shares this row — check the person columns H–Q, and the Weight / Nights columns on Setup",IF(AND($T41="Exact amounts",ABS($AE41-$AG41)>0.01),"Exact amounts do not add up to the amount","OK")))))))) | S41: =IFERROR(IF(OR($T41="",$C$4=""),"—",ROUND($AG41*INDEX($U41:$AD41,1,MATCH($C$4,Setup!$B$21:$B$30,0))/$AF41,2)),"—") -> — | T41: =IF(AND($C41="",$D41="",NOT(ISNUMBER($E41))),"",IF($G41="",IF(Setup!$C$17="","Equal",Setup!$C$17),$G41)) | U41: =IF($T41="",0,IF(OR(Setup!$B$21="",Setup!$C$21="No"),0,IF(ISNUMBER(H41),H41,IF($T41="Weights",IF(ISNUMBER(Setup!$D$21),Setup!$D$21,0),IF($T41="Nights",IF(ISNUMBER(Setup!$E$21),Setup!$E$21,0),IF(OR($T41="Exact amounts",$T41="Custom units"),0,1)))))) -> 0 | V41: =IF($T41="",0,IF(OR(Setup!$B$22="",Setup!$C$22="No"),0,IF(ISNUMBER(I41),I41,IF($T41="Weights",IF(ISNUMBER(Setup!$D$22),Setup!$D$22,0),IF($T41="Nights",IF(ISNUMBER(Setup!$E$22),Setup!$E$22,0),IF(OR($T41="Exact amounts",$T41="Custom units"),0,1)))))) -> 0 | W41: =IF($T41="",0,IF(OR(Setup!$B$23="",Setup!$C$23="No"),0,IF(ISNUMBER(J41),J41,IF($T41="Weights",IF(ISNUMBER(Setup!$D$23),Setup!$D$23,0),IF($T41="Nights",IF(ISNUMBER(Setup!$E$23),Setup!$E$23,0),IF(OR($T41="Exact amounts",$T41="Custom units"),0,1)))))) -> 0 | X41: =IF($T41="",0,IF(OR(Setup!$B$24="",Setup!$C$24="No"),0,IF(ISNUMBER(K41),K41,IF($T41="Weights",IF(ISNUMBER(Setup!$D$24),Setup!$D$24,0),IF($T41="Nights",IF(ISNUMBER(Setup!$E$24),Setup!$E$24,0),IF(OR($T41="Exact amounts",$T41="Custom units"),0,1)))))) -> 0 | Y41: =IF($T41="",0,IF(OR(Setup!$B$25="",Setup!$C$25="No"),0,IF(ISNUMBER(L41),L41,IF($T41="Weights",IF(ISNUMBER(Setup!$D$25),Setup!$D$25,0),IF($T41="Nights",IF(ISNUMBER(Setup!$E$25),Setup!$E$25,0),IF(OR($T41="Exact amounts",$T41="Custom units"),0,1)))))) -> 0 | Z41: =IF($T41="",0,IF(OR(Setup!$B$26="",Setup!$C$26="No"),0,IF(ISNUMBER(M41),M41,IF($T41="Weights",IF(ISNUMBER(Setup!$D$26),Setup!$D$26,0),IF($T41="Nights",IF(ISNUMBER(Setup!$E$26),Setup!$E$26,0),IF(OR($T41="Exact amounts",$T41="Custom units"),0,1)))))) -> 0 | AA41: =IF($T41="",0,IF(OR(Setup!$B$27="",Setup!$C$27="No"),0,IF(ISNUMBER(N41),N41,IF($T41="Weights",IF(ISNUMBER(Setup!$D$27),Setup!$D$27,0),IF($T41="Nights",IF(ISNUMBER(Setup!$E$27),Setup!$E$27,0),IF(OR($T41="Exact amounts",$T41="Custom units"),0,1)))))) -> 0 | AB41: =IF($T41="",0,IF(OR(Setup!$B$28="",Setup!$C$28="No"),0,IF(ISNUMBER(O41),O41,IF($T41="Weights",IF(ISNUMBER(Setup!$D$28),Setup!$D$28,0),IF($T41="Nights",IF(ISNUMBER(Setup!$E$28),Setup!$E$28,0),IF(OR($T41="Exact amounts",$T41="Custom units"),0,1)))))) -> 0 | AC41: =IF($T41="",0,IF(OR(Setup!$B$29="",Setup!$C$29="No"),0,IF(ISNUMBER(P41),P41,IF($T41="Weights",IF(ISNUMBER(Setup!$D$29),Setup!$D$29,0),IF($T41="Nights",IF(ISNUMBER(Setup!$E$29),Setup!$E$29,0),IF(OR($T41="Exact amounts",$T41="Custom units"),0,1)))))) -> 0 | AD41: =IF($T41="",0,IF(OR(Setup!$B$30="",Setup!$C$30="No"),0,IF(ISNUMBER(Q41),Q41,IF($T41="Weights",IF(ISNUMBER(Setup!$D$30),Setup!$D$30,0),IF($T41="Nights",IF(ISNUMBER(Setup!$E$30),Setup!$E$30,0),IF(OR($T41="Exact amounts",$T41="Custom units"),0,1)))))) -> 0 | AE41: =IF($T41="",0,SUM($U41:$AD41)) -> 0 | AF41: =IF($AE41<=0,1,$AE41) -> 1 | AG41: =IF(ISNUMBER($E41),$E41,0) -> 0
A42: =IF($T42="","—",ROW()-7) -> — | R42: =IF($T42="","",IF($D42="","Who paid?",IF(SUMPRODUCT((Setup!$B$21:$B$30=$D42)*1)=0,"Payer is not in the member list on Setup",IF($E42="","Amount missing — type the number in column E",IF(NOT(ISNUMBER($E42)),"Amount must be a plain number — no currency symbol, no text",IF(AND($T42="Custom units",$AE42<=0),"Custom units: nobody has units on this row — type a number for at least one person",IF($AE42<=0,"Nobody shares this row — check the person columns H–Q, and the Weight / Nights columns on Setup",IF(AND($T42="Exact amounts",ABS($AE42-$AG42)>0.01),"Exact amounts do not add up to the amount","OK")))))))) | S42: =IFERROR(IF(OR($T42="",$C$4=""),"—",ROUND($AG42*INDEX($U42:$AD42,1,MATCH($C$4,Setup!$B$21:$B$30,0))/$AF42,2)),"—") -> — | T42: =IF(AND($C42="",$D42="",NOT(ISNUMBER($E42))),"",IF($G42="",IF(Setup!$C$17="","Equal",Setup!$C$17),$G42)) | U42: =IF($T42="",0,IF(OR(Setup!$B$21="",Setup!$C$21="No"),0,IF(ISNUMBER(H42),H42,IF($T42="Weights",IF(ISNUMBER(Setup!$D$21),Setup!$D$21,0),IF($T42="Nights",IF(ISNUMBER(Setup!$E$21),Setup!$E$21,0),IF(OR($T42="Exact amounts",$T42="Custom units"),0,1)))))) -> 0 | V42: =IF($T42="",0,IF(OR(Setup!$B$22="",Setup!$C$22="No"),0,IF(ISNUMBER(I42),I42,IF($T42="Weights",IF(ISNUMBER(Setup!$D$22),Setup!$D$22,0),IF($T42="Nights",IF(ISNUMBER(Setup!$E$22),Setup!$E$22,0),IF(OR($T42="Exact amounts",$T42="Custom units"),0,1)))))) -> 0 | W42: =IF($T42="",0,IF(OR(Setup!$B$23="",Setup!$C$23="No"),0,IF(ISNUMBER(J42),J42,IF($T42="Weights",IF(ISNUMBER(Setup!$D$23),Setup!$D$23,0),IF($T42="Nights",IF(ISNUMBER(Setup!$E$23),Setup!$E$23,0),IF(OR($T42="Exact amounts",$T42="Custom units"),0,1)))))) -> 0 | X42: =IF($T42="",0,IF(OR(Setup!$B$24="",Setup!$C$24="No"),0,IF(ISNUMBER(K42),K42,IF($T42="Weights",IF(ISNUMBER(Setup!$D$24),Setup!$D$24,0),IF($T42="Nights",IF(ISNUMBER(Setup!$E$24),Setup!$E$24,0),IF(OR($T42="Exact amounts",$T42="Custom units"),0,1)))))) -> 0 | Y42: =IF($T42="",0,IF(OR(Setup!$B$25="",Setup!$C$25="No"),0,IF(ISNUMBER(L42),L42,IF($T42="Weights",IF(ISNUMBER(Setup!$D$25),Setup!$D$25,0),IF($T42="Nights",IF(ISNUMBER(Setup!$E$25),Setup!$E$25,0),IF(OR($T42="Exact amounts",$T42="Custom units"),0,1)))))) -> 0 | Z42: =IF($T42="",0,IF(OR(Setup!$B$26="",Setup!$C$26="No"),0,IF(ISNUMBER(M42),M42,IF($T42="Weights",IF(ISNUMBER(Setup!$D$26),Setup!$D$26,0),IF($T42="Nights",IF(ISNUMBER(Setup!$E$26),Setup!$E$26,0),IF(OR($T42="Exact amounts",$T42="Custom units"),0,1)))))) -> 0 | AA42: =IF($T42="",0,IF(OR(Setup!$B$27="",Setup!$C$27="No"),0,IF(ISNUMBER(N42),N42,IF($T42="Weights",IF(ISNUMBER(Setup!$D$27),Setup!$D$27,0),IF($T42="Nights",IF(ISNUMBER(Setup!$E$27),Setup!$E$27,0),IF(OR($T42="Exact amounts",$T42="Custom units"),0,1)))))) -> 0 | AB42: =IF($T42="",0,IF(OR(Setup!$B$28="",Setup!$C$28="No"),0,IF(ISNUMBER(O42),O42,IF($T42="Weights",IF(ISNUMBER(Setup!$D$28),Setup!$D$28,0),IF($T42="Nights",IF(ISNUMBER(Setup!$E$28),Setup!$E$28,0),IF(OR($T42="Exact amounts",$T42="Custom units"),0,1)))))) -> 0 | AC42: =IF($T42="",0,IF(OR(Setup!$B$29="",Setup!$C$29="No"),0,IF(ISNUMBER(P42),P42,IF($T42="Weights",IF(ISNUMBER(Setup!$D$29),Setup!$D$29,0),IF($T42="Nights",IF(ISNUMBER(Setup!$E$29),Setup!$E$29,0),IF(OR($T42="Exact amounts",$T42="Custom units"),0,1)))))) -> 0 | AD42: =IF($T42="",0,IF(OR(Setup!$B$30="",Setup!$C$30="No"),0,IF(ISNUMBER(Q42),Q42,IF($T42="Weights",IF(ISNUMBER(Setup!$D$30),Setup!$D$30,0),IF($T42="Nights",IF(ISNUMBER(Setup!$E$30),Setup!$E$30,0),IF(OR($T42="Exact amounts",$T42="Custom units"),0,1)))))) -> 0 | AE42: =IF($T42="",0,SUM($U42:$AD42)) -> 0 | AF42: =IF($AE42<=0,1,$AE42) -> 1 | AG42: =IF(ISNUMBER($E42),$E42,0) -> 0
A43: =IF($T43="","—",ROW()-7) -> — | R43: =IF($T43="","",IF($D43="","Who paid?",IF(SUMPRODUCT((Setup!$B$21:$B$30=$D43)*1)=0,"Payer is not in the member list on Setup",IF($E43="","Amount missing — type the number in column E",IF(NOT(ISNUMBER($E43)),"Amount must be a plain number — no currency symbol, no text",IF(AND($T43="Custom units",$AE43<=0),"Custom units: nobody has units on this row — type a number for at least one person",IF($AE43<=0,"Nobody shares this row — check the person columns H–Q, and the Weight / Nights columns on Setup",IF(AND($T43="Exact amounts",ABS($AE43-$AG43)>0.01),"Exact amounts do not add up to the amount","OK")))))))) | S43: =IFERROR(IF(OR($T43="",$C$4=""),"—",ROUND($AG43*INDEX($U43:$AD43,1,MATCH($C$4,Setup!$B$21:$B$30,0))/$AF43,2)),"—") -> — | T43: =IF(AND($C43="",$D43="",NOT(ISNUMBER($E43))),"",IF($G43="",IF(Setup!$C$17="","Equal",Setup!$C$17),$G43)) | U43: =IF($T43="",0,IF(OR(Setup!$B$21="",Setup!$C$21="No"),0,IF(ISNUMBER(H43),H43,IF($T43="Weights",IF(ISNUMBER(Setup!$D$21),Setup!$D$21,0),IF($T43="Nights",IF(ISNUMBER(Setup!$E$21),Setup!$E$21,0),IF(OR($T43="Exact amounts",$T43="Custom units"),0,1)))))) -> 0 | V43: =IF($T43="",0,IF(OR(Setup!$B$22="",Setup!$C$22="No"),0,IF(ISNUMBER(I43),I43,IF($T43="Weights",IF(ISNUMBER(Setup!$D$22),Setup!$D$22,0),IF($T43="Nights",IF(ISNUMBER(Setup!$E$22),Setup!$E$22,0),IF(OR($T43="Exact amounts",$T43="Custom units"),0,1)))))) -> 0 | W43: =IF($T43="",0,IF(OR(Setup!$B$23="",Setup!$C$23="No"),0,IF(ISNUMBER(J43),J43,IF($T43="Weights",IF(ISNUMBER(Setup!$D$23),Setup!$D$23,0),IF($T43="Nights",IF(ISNUMBER(Setup!$E$23),Setup!$E$23,0),IF(OR($T43="Exact amounts",$T43="Custom units"),0,1)))))) -> 0 | X43: =IF($T43="",0,IF(OR(Setup!$B$24="",Setup!$C$24="No"),0,IF(ISNUMBER(K43),K43,IF($T43="Weights",IF(ISNUMBER(Setup!$D$24),Setup!$D$24,0),IF($T43="Nights",IF(ISNUMBER(Setup!$E$24),Setup!$E$24,0),IF(OR($T43="Exact amounts",$T43="Custom units"),0,1)))))) -> 0 | Y43: =IF($T43="",0,IF(OR(Setup!$B$25="",Setup!$C$25="No"),0,IF(ISNUMBER(L43),L43,IF($T43="Weights",IF(ISNUMBER(Setup!$D$25),Setup!$D$25,0),IF($T43="Nights",IF(ISNUMBER(Setup!$E$25),Setup!$E$25,0),IF(OR($T43="Exact amounts",$T43="Custom units"),0,1)))))) -> 0 | Z43: =IF($T43="",0,IF(OR(Setup!$B$26="",Setup!$C$26="No"),0,IF(ISNUMBER(M43),M43,IF($T43="Weights",IF(ISNUMBER(Setup!$D$26),Setup!$D$26,0),IF($T43="Nights",IF(ISNUMBER(Setup!$E$26),Setup!$E$26,0),IF(OR($T43="Exact amounts",$T43="Custom units"),0,1)))))) -> 0 | AA43: =IF($T43="",0,IF(OR(Setup!$B$27="",Setup!$C$27="No"),0,IF(ISNUMBER(N43),N43,IF($T43="Weights",IF(ISNUMBER(Setup!$D$27),Setup!$D$27,0),IF($T43="Nights",IF(ISNUMBER(Setup!$E$27),Setup!$E$27,0),IF(OR($T43="Exact amounts",$T43="Custom units"),0,1)))))) -> 0 | AB43: =IF($T43="",0,IF(OR(Setup!$B$28="",Setup!$C$28="No"),0,IF(ISNUMBER(O43),O43,IF($T43="Weights",IF(ISNUMBER(Setup!$D$28),Setup!$D$28,0),IF($T43="Nights",IF(ISNUMBER(Setup!$E$28),Setup!$E$28,0),IF(OR($T43="Exact amounts",$T43="Custom units"),0,1)))))) -> 0 | AC43: =IF($T43="",0,IF(OR(Setup!$B$29="",Setup!$C$29="No"),0,IF(ISNUMBER(P43),P43,IF($T43="Weights",IF(ISNUMBER(Setup!$D$29),Setup!$D$29,0),IF($T43="Nights",IF(ISNUMBER(Setup!$E$29),Setup!$E$29,0),IF(OR($T43="Exact amounts",$T43="Custom units"),0,1)))))) -> 0 | AD43: =IF($T43="",0,IF(OR(Setup!$B$30="",Setup!$C$30="No"),0,IF(ISNUMBER(Q43),Q43,IF($T43="Weights",IF(ISNUMBER(Setup!$D$30),Setup!$D$30,0),IF($T43="Nights",IF(ISNUMBER(Setup!$E$30),Setup!$E$30,0),IF(OR($T43="Exact amounts",$T43="Custom units"),0,1)))))) -> 0 | AE43: =IF($T43="",0,SUM($U43:$AD43)) -> 0 | AF43: =IF($AE43<=0,1,$AE43) -> 1 | AG43: =IF(ISNUMBER($E43),$E43,0) -> 0
... A307: =IF($T307="","—",ROW()-7) -> — | R307: =IF($T307="","",IF($D307="","Who paid?",IF(SUMPRODUCT((Setup!$B$21:$B$30=$D307)*1)=0,"Payer is not in the member list on Setup",IF($E307="","Amount missing — type the number in column E",IF(NOT(ISNUMBER($E307)),"Amount must be a plain number — no currency symbol, no text",IF(AND($T307="Custom units",$AE307<=0),"Custom units: nobody has units on this row — type a number for at least one person",IF($AE307<=0,"Nobody shares this row — check the person columns H–Q, and the Weight / Nights columns on Setup",IF(AND($T307="Exact amounts",ABS($AE307-$AG307)>0.01),"Exact amounts do not add up to the amount","OK")))))))) | S307: =IFERROR(IF(OR($T307="",$C$4=""),"—",ROUND($AG307*INDEX($U307:$AD307,1,MATCH($C$4,Setup!$B$21:$B$30,0))/$AF307,2)),"—") -> — | T307: =IF(AND($C307="",$D307="",NOT(ISNUMBER($E307))),"",IF($G307="",IF(Setup!$C$17="","Equal",Setup!$C$17),$G307)) | U307: =IF($T307="",0,IF(OR(Setup!$B$21="",Setup!$C$21="No"),0,IF(ISNUMBER(H307),H307,IF($T307="Weights",IF(ISNUMBER(Setup!$D$21),Setup!$D$21,0),IF($T307="Nights",IF(ISNUMBER(Setup!$E$21),Setup!$E$21,0),IF(OR($T307="Exact amounts",$T307="Custom units"),0,1)))))) -> 0 | V307: =IF($T307="",0,IF(OR(Setup!$B$22="",Setup!$C$22="No"),0,IF(ISNUMBER(I307),I307,IF($T307="Weights",IF(ISNUMBER(Setup!$D$22),Setup!$D$22,0),IF($T307="Nights",IF(ISNUMBER(Setup!$E$22),Setup!$E$22,0),IF(OR($T307="Exact amounts",$T307="Custom units"),0,1)))))) -> 0 | W307: =IF($T307="",0,IF(OR(Setup!$B$23="",Setup!$C$23="No"),0,IF(ISNUMBER(J307),J307,IF($T307="Weights",IF(ISNUMBER(Setup!$D$23),Setup!$D$23,0),IF($T307="Nights",IF(ISNUMBER(Setup!$E$23),Setup!$E$23,0),IF(OR($T307="Exact amounts",$T307="Custom units"),0,1)))))) -> 0 | X307: =IF($T307="",0,IF(OR(Setup!$B$24="",Setup!$C$24="No"),0,IF(ISNUMBER(K307),K307,IF($T307="Weights",IF(ISNUMBER(Setup!$D$24),Setup!$D$24,0),IF($T307="Nights",IF(ISNUMBER(Setup!$E$24),Setup!$E$24,0),IF(OR($T307="Exact amounts",$T307="Custom units"),0,1)))))) -> 0 | Y307: =IF($T307="",0,IF(OR(Setup!$B$25="",Setup!$C$25="No"),0,IF(ISNUMBER(L307),L307,IF($T307="Weights",IF(ISNUMBER(Setup!$D$25),Setup!$D$25,0),IF($T307="Nights",IF(ISNUMBER(Setup!$E$25),Setup!$E$25,0),IF(OR($T307="Exact amounts",$T307="Custom units"),0,1)))))) -> 0 | Z307: =IF($T307="",0,IF(OR(Setup!$B$26="",Setup!$C$26="No"),0,IF(ISNUMBER(M307),M307,IF($T307="Weights",IF(ISNUMBER(Setup!$D$26),Setup!$D$26,0),IF($T307="Nights",IF(ISNUMBER(Setup!$E$26),Setup!$E$26,0),IF(OR($T307="Exact amounts",$T307="Custom units"),0,1)))))) -> 0 | AA307: =IF($T307="",0,IF(OR(Setup!$B$27="",Setup!$C$27="No"),0,IF(ISNUMBER(N307),N307,IF($T307="Weights",IF(ISNUMBER(Setup!$D$27),Setup!$D$27,0),IF($T307="Nights",IF(ISNUMBER(Setup!$E$27),Setup!$E$27,0),IF(OR($T307="Exact amounts",$T307="Custom units"),0,1)))))) -> 0 | AB307: =IF($T307="",0,IF(OR(Setup!$B$28="",Setup!$C$28="No"),0,IF(ISNUMBER(O307),O307,IF($T307="Weights",IF(ISNUMBER(Setup!$D$28),Setup!$D$28,0),IF($T307="Nights",IF(ISNUMBER(Setup!$E$28),Setup!$E$28,0),IF(OR($T307="Exact amounts",$T307="Custom units"),0,1)))))) -> 0 | AC307: =IF($T307="",0,IF(OR(Setup!$B$29="",Setup!$C$29="No"),0,IF(ISNUMBER(P307),P307,IF($T307="Weights",IF(ISNUMBER(Setup!$D$29),Setup!$D$29,0),IF($T307="Nights",IF(ISNUMBER(Setup!$E$29),Setup!$E$29,0),IF(OR($T307="Exact amounts",$T307="Custom units"),0,1)))))) -> 0 | AD307: =IF($T307="",0,IF(OR(Setup!$B$30="",Setup!$C$30="No"),0,IF(ISNUMBER(Q307),Q307,IF($T307="Weights",IF(ISNUMBER(Setup!$D$30),Setup!$D$30,0),IF($T307="Nights",IF(ISNUMBER(Setup!$E$30),Setup!$E$30,0),IF(OR($T307="Exact amounts",$T307="Custom units"),0,1)))))) -> 0 | AE307: =IF($T307="",0,SUM($U307:$AD307)) -> 0 | AF307: =IF($AE307<=0,1,$AE307) -> 1 | AG307: =IF(ISNUMBER($E307),$E307,0) -> 0
A308: ▲ Last row (307). Insert new rows INSIDE the table, then copy the full row above onto the new row (it carries the formulas) before typing. Never add rows below this line.

Sheet Who Owes What
A1: Who Owes What | J1: =IFERROR(SUMPRODUCT((Expenses!$T$8:$T$307<>"")*1),0) -> 24
A2: Paid − fair share = balance. Plus is 'gets money back', minus is 'owes'. Never type on this sheet.
B4: =IF(Setup!$C$16="","Total group spend","Total group spend ("&Setup!$C$16&")") -> Total group spend (€) | C4: Expenses logged | D4: Per active person | E4: =IF(Setup!$C$16="","Still to settle","Still to settle ("&Setup!$C$16&")") -> Still to settle (€) | F4: Transfers needed | G4: Data check
B5: =IF($J$1=0,"—",IFERROR(ROUND(SUM(Expenses!$AG$8:$AG$307),2),0)) -> 5001.85 | C5: =IF($J$1=0,"—",$J$1) -> 24 | D5: =IF(OR($J$1=0,SUMPRODUCT((Setup!$B$21:$B$30<>"")*(Setup!$C$21:$C$30<>"No"))=0),"—",IFERROR(ROUND(SUM(Expenses!$AG$8:$AG$307)/SUMPRODUCT((Setup!$B$21:$B$30<>"")*(Setup!$C$21:$C$30<>"No")),2),"—")) -> 1000.37 | E5: =IF($J$1=0,"—",IFERROR(ROUND(SUMIF($F$10:$F$19,">"&0.009),2),0)) -> 1659.04 | F5: =IF($J$1=0,"—",IFERROR(COUNTIF('Settle Up'!$V$10:$V$18,">="&0.01),0)) -> 4 | G5: =IF($J$1=0,"—",IF(SUMPRODUCT((Setup!$G$21:$G$30<>"")*1)>0,"Duplicate member name on Setup — give every member a unique name",IF(COUNTIF(Expenses!$R$8:$R$307,"OK")=$J$1,"All good","Fix "&($J$1-COUNTIF(Expenses!$R$8:$R$307,"OK"))&" row(s) — see Check column"))) -> All good
B6: =IF(OR($J$1=0,COUNT(Expenses!$B$8:$B$307)=0),"add your first expense on the Expenses sheet","period "&TEXT(MIN(Expenses!$B$8:$B$307),"yyyy-mm-dd")&" → "&TEXT(MAX(Expenses!$B$8:$B$307),"yyyy-mm-dd")) -> period yyyy-00-dd → yyyy-00-dd | C6: =IF($J$1=0,"start on the Expenses sheet","of 300 rows used") -> of 300 rows used | D6: =IF(SUMPRODUCT((Setup!$B$21:$B$30<>"")*(Setup!$C$21:$C$30<>"No"))=0,"give people a name on Setup","average across "&SUMPRODUCT((Setup!$B$21:$B$30<>"")*(Setup!$C$21:$C$30<>"No"))&" people") -> average across 5 people | E6: everything still owed — the plan may move the odd cent | F6: never more than 9 for 10 people | G6: every logged row must say OK
B8: =IF($J$1=0,"—",IFERROR(IF(MAX($F$10:$F$19)<0.01,"All settled — nothing to transfer.",INDEX($B$10:$B$19,MATCH(MAX($F$10:$F$19),$F$10:$F$19,0))&" is owed the most ("&TEXT(MAX($F$10:$F$19),"0.00")&") · "&INDEX($B$10:$B$19,MATCH(MIN($F$10:$F$19),$F$10:$F$19,0))&" owes the most ("&TEXT(-MIN($F$10:$F$19),"0.00")&")"),"—")) -> Anna is owed the most (1.269) · Dana owes the most (682)
A9: # | B9: Member | C9: Active? | D9: =IF(Setup!$C$16="","Paid","Paid ("&Setup!$C$16&")") -> Paid (€) | E9: =IF(Setup!$C$16="","Fair share","Fair share ("&Setup!$C$16&")") -> Fair share (€) | F9: =IF(Setup!$C$16="","Balance (+ gets back / − owes)","Balance in "&Setup!$C$16&" (+ gets back / − owes)") -> Balance in € (+ gets back / − owes) | G9: Status | H9: % of total spend
A10: 1 | B10: =IF(Setup!$B$21="","—",Setup!$B$21) -> Anna | C10: =IF($B10="—","—",IF(Setup!$C$21="No","No","Yes")) -> Yes | D10: =IF(OR($B10="—",$J$1=0),"—",IFERROR(SUMPRODUCT((Expenses!$D$8:$D$307=$B10)*Expenses!$AG$8:$AG$307),0)) -> 2587.1 | E10: =IF(OR($B10="—",$J$1=0),"—",IFERROR(SUMPRODUCT(Expenses!$AG$8:$AG$307*Expenses!$U$8:$U$307/Expenses!$AF$8:$AF$307),0)) -> 1318.0975 | F10: =IF(OR($B10="—",$J$1=0),"—",IFERROR(ROUND($D10-$E10,2),0)) -> 1269 | G10: =IF(OR($B10="—",$J$1=0),"—",IF($F10>0.009,"gets back",IF($F10<-0.009,"owes","settled"))) -> gets back | H10: =IF(OR($B10="—",$J$1=0),"—",IFERROR(IF(SUM($E$10:$E$19)=0,"—",$E10/SUM($E$10:$E$19)),"—")) -> 0.263522
A11: 2 | B11: =IF(Setup!$B$22="","—",Setup!$B$22) -> Ben | C11: =IF($B11="—","—",IF(Setup!$C$22="No","No","Yes")) -> Yes | D11: =IF(OR($B11="—",$J$1=0),"—",IFERROR(SUMPRODUCT((Expenses!$D$8:$D$307=$B11)*Expenses!$AG$8:$AG$307),0)) -> 1519.2 | E11: =IF(OR($B11="—",$J$1=0),"—",IFERROR(SUMPRODUCT(Expenses!$AG$8:$AG$307*Expenses!$V$8:$V$307/Expenses!$AF$8:$AF$307),0)) -> 1129.1642 | F11: =IF(OR($B11="—",$J$1=0),"—",IFERROR(ROUND($D11-$E11,2),0)) -> 390.04 | G11: =IF(OR($B11="—",$J$1=0),"—",IF($F11>0.009,"gets back",IF($F11<-0.009,"owes","settled"))) -> gets back | H11: =IF(OR($B11="—",$J$1=0),"—",IFERROR(IF(SUM($E$10:$E$19)=0,"—",$E11/SUM($E$10:$E$19)),"—")) -> 0.22574931
A12: 3 | B12: =IF(Setup!$B$23="","—",Setup!$B$23) -> Chris | C12: =IF($B12="—","—",IF(Setup!$C$23="No","No","Yes")) -> Yes | D12: =IF(OR($B12="—",$J$1=0),"—",IFERROR(SUMPRODUCT((Expenses!$D$8:$D$307=$B12)*Expenses!$AG$8:$AG$307),0)) -> 353.6 | E12: =IF(OR($B12="—",$J$1=0),"—",IFERROR(SUMPRODUCT(Expenses!$AG$8:$AG$307*Expenses!$W$8:$W$307/Expenses!$AF$8:$AF$307),0)) -> 1012.5308 | F12: =IF(OR($B12="—",$J$1=0),"—",IFERROR(ROUND($D12-$E12,2),0)) -> -658.93 | G12: =IF(OR($B12="—",$J$1=0),"—",IF($F12>0.009,"gets back",IF($F12<-0.009,"owes","settled"))) -> owes | H12: =IF(OR($B12="—",$J$1=0),"—",IFERROR(IF(SUM($E$10:$E$19)=0,"—",$E12/SUM($E$10:$E$19)),"—")) -> 0.20243127
A13: 4 | B13: =IF(Setup!$B$24="","—",Setup!$B$24) -> Dana | C13: =IF($B13="—","—",IF(Setup!$C$24="No","No","Yes")) -> Yes | D13: =IF(OR($B13="—",$J$1=0),"—",IFERROR(SUMPRODUCT((Expenses!$D$8:$D$307=$B13)*Expenses!$AG$8:$AG$307),0)) -> 279.15 | E13: =IF(OR($B13="—",$J$1=0),"—",IFERROR(SUMPRODUCT(Expenses!$AG$8:$AG$307*Expenses!$X$8:$X$307/Expenses!$AF$8:$AF$307),0)) -> 960.6975 | F13: =IF(OR($B13="—",$J$1=0),"—",IFERROR(ROUND($D13-$E13,2),0)) -> -681.55 | G13: =IF(OR($B13="—",$J$1=0),"—",IF($F13>0.009,"gets back",IF($F13<-0.009,"owes","settled"))) -> owes | H13: =IF(OR($B13="—",$J$1=0),"—",IFERROR(IF(SUM($E$10:$E$19)=0,"—",$E13/SUM($E$10:$E$19)),"—")) -> 0.19206843
A14: 5 | B14: =IF(Setup!$B$25="","—",Setup!$B$25) -> Eli | C14: =IF($B14="—","—",IF(Setup!$C$25="No","No","Yes")) -> Yes | D14: =IF(OR($B14="—",$J$1=0),"—",IFERROR(SUMPRODUCT((Expenses!$D$8:$D$307=$B14)*Expenses!$AG$8:$AG$307),0)) -> 262.8 | E14: =IF(OR($B14="—",$J$1=0),"—",IFERROR(SUMPRODUCT(Expenses!$AG$8:$AG$307*Expenses!$Y$8:$Y$307/Expenses!$AF$8:$AF$307),0)) -> 581.36 | F14: =IF(OR($B14="—",$J$1=0),"—",IFERROR(ROUND($D14-$E14,2),0)) -> -318.56 | G14: =IF(OR($B14="—",$J$1=0),"—",IF($F14>0.009,"gets back",IF($F14<-0.009,"owes","settled"))) -> owes | H14: =IF(OR($B14="—",$J$1=0),"—",IFERROR(IF(SUM($E$10:$E$19)=0,"—",$E14/SUM($E$10:$E$19)),"—")) -> 0.116229
A15: 6 | B15: =IF(Setup!$B$26="","—",Setup!$B$26) -> — | C15: =IF($B15="—","—",IF(Setup!$C$26="No","No","Yes")) -> — | D15: =IF(OR($B15="—",$J$1=0),"—",IFERROR(SUMPRODUCT((Expenses!$D$8:$D$307=$B15)*Expenses!$AG$8:$AG$307),0)) -> — | E15: =IF(OR($B15="—",$J$1=0),"—",IFERROR(SUMPRODUCT(Expenses!$AG$8:$AG$307*Expenses!$Z$8:$Z$307/Expenses!$AF$8:$AF$307),0)) -> — | F15: =IF(OR($B15="—",$J$1=0),"—",IFERROR(ROUND($D15-$E15,2),0)) -> — | G15: =IF(OR($B15="—",$J$1=0),"—",IF($F15>0.009,"gets back",IF($F15<-0.009,"owes","settled"))) -> — | H15: =IF(OR($B15="—",$J$1=0),"—",IFERROR(IF(SUM($E$10:$E$19)=0,"—",$E15/SUM($E$10:$E$19)),"—")) -> —
A16: 7 | B16: =IF(Setup!$B$27="","—",Setup!$B$27) -> — | C16: =IF($B16="—","—",IF(Setup!$C$27="No","No","Yes")) -> — | D16: =IF(OR($B16="—",$J$1=0),"—",IFERROR(SUMPRODUCT((Expenses!$D$8:$D$307=$B16)*Expenses!$AG$8:$AG$307),0)) -> — | E16: =IF(OR($B16="—",$J$1=0),"—",IFERROR(SUMPRODUCT(Expenses!$AG$8:$AG$307*Expenses!$AA$8:$AA$307/Expenses!$AF$8:$AF$307),0)) -> — | F16: =IF(OR($B16="—",$J$1=0),"—",IFERROR(ROUND($D16-$E16,2),0)) -> — | G16: =IF(OR($B16="—",$J$1=0),"—",IF($F16>0.009,"gets back",IF($F16<-0.009,"owes","settled"))) -> — | H16: =IF(OR($B16="—",$J$1=0),"—",IFERROR(IF(SUM($E$10:$E$19)=0,"—",$E16/SUM($E$10:$E$19)),"—")) -> —
A17: 8 | B17: =IF(Setup!$B$28="","—",Setup!$B$28) -> — | C17: =IF($B17="—","—",IF(Setup!$C$28="No","No","Yes")) -> — | D17: =IF(OR($B17="—",$J$1=0),"—",IFERROR(SUMPRODUCT((Expenses!$D$8:$D$307=$B17)*Expenses!$AG$8:$AG$307),0)) -> — | E17: =IF(OR($B17="—",$J$1=0),"—",IFERROR(SUMPRODUCT(Expenses!$AG$8:$AG$307*Expenses!$AB$8:$AB$307/Expenses!$AF$8:$AF$307),0)) -> — | F17: =IF(OR($B17="—",$J$1=0),"—",IFERROR(ROUND($D17-$E17,2),0)) -> — | G17: =IF(OR($B17="—",$J$1=0),"—",IF($F17>0.009,"gets back",IF($F17<-0.009,"owes","settled"))) -> — | H17: =IF(OR($B17="—",$J$1=0),"—",IFERROR(IF(SUM($E$10:$E$19)=0,"—",$E17/SUM($E$10:$E$19)),"—")) -> —
A18: 9 | B18: =IF(Setup!$B$29="","—",Setup!$B$29) -> — | C18: =IF($B18="—","—",IF(Setup!$C$29="No","No","Yes")) -> — | D18: =IF(OR($B18="—",$J$1=0),"—",IFERROR(SUMPRODUCT((Expenses!$D$8:$D$307=$B18)*Expenses!$AG$8:$AG$307),0)) -> — | E18: =IF(OR($B18="—",$J$1=0),"—",IFERROR(SUMPRODUCT(Expenses!$AG$8:$AG$307*Expenses!$AC$8:$AC$307/Expenses!$AF$8:$AF$307),0)) -> — | F18: =IF(OR($B18="—",$J$1=0),"—",IFERROR(ROUND($D18-$E18,2),0)) -> — | G18: =IF(OR($B18="—",$J$1=0),"—",IF($F18>0.009,"gets back",IF($F18<-0.009,"owes","settled"))) -> — | H18: =IF(OR($B18="—",$J$1=0),"—",IFERROR(IF(SUM($E$10:$E$19)=0,"—",$E18/SUM($E$10:$E$19)),"—")) -> —
A19: 10 | B19: =IF(Setup!$B$30="","—",Setup!$B$30) -> — | C19: =IF($B19="—","—",IF(Setup!$C$30="No","No","Yes")) -> — | D19: =IF(OR($B19="—",$J$1=0),"—",IFERROR(SUMPRODUCT((Expenses!$D$8:$D$307=$B19)*Expenses!$AG$8:$AG$307),0)) -> — | E19: =IF(OR($B19="—",$J$1=0),"—",IFERROR(SUMPRODUCT(Expenses!$AG$8:$AG$307*Expenses!$AD$8:$AD$307/Expenses!$AF$8:$AF$307),0)) -> — | F19: =IF(OR($B19="—",$J$1=0),"—",IFERROR(ROUND($D19-$E19,2),0)) -> — | G19: =IF(OR($B19="—",$J$1=0),"—",IF($F19>0.009,"gets back",IF($F19<-0.009,"owes","settled"))) -> — | H19: =IF(OR($B19="—",$J$1=0),"—",IFERROR(IF(SUM($E$10:$E$19)=0,"—",$E19/SUM($E$10:$E$19)),"—")) -> —
B20: Total | D20: =IF($J$1=0,"—",IFERROR(SUM(D$10:D$19),0)) -> 5001.85 | E20: =IF($J$1=0,"—",IFERROR(SUM(E$10:E$19),0)) -> 5001.85 | F20: =IF($J$1=0,"—",IFERROR(ROUND(SUM($D$10:$D$19)-SUM($E$10:$E$19),2),0)) -> 0 | G20: =IF($J$1=0,"—",IF(ABS(ROUND(SUM($D$10:$D$19)-SUM($E$10:$E$19),2))<0.005,"Every cent accounted for","Some rows are not shared by anyone — see the Check column")) -> Every cent accounted for
B22: Biggest single expense | C22: =IF($J$1=0,"—",IFERROR(MAX(Expenses!$AG$8:$AG$307),0)) -> 1450
B23: Average per expense | C23: =IF(OR($J$1=0,COUNT(Expenses!$AG$8:$AG$307)=0),"—",IFERROR(ROUND(SUM(Expenses!$AG$8:$AG$307)/$J$1,2),0)) -> 208.41

Sheet Settle Up
A1: Settle Up — the payback plan
A2: At most 9 transfers for 10 people. The plan clears every balance to the cent; anything a row leaves unshared stays visible in 'Left over after plan' and is named in the Check column on Expenses. Tick each transfer off in 'Done?'. Never type in the hidden columns J:V.
B4: =IF('Who Owes What'!$J$1=0,"Nothing logged yet — start on the Expenses sheet.",IF(AND(ISNUMBER('Who Owes What'!$F$20),ABS('Who Owes What'!$F$20)>0.01),"⚠ Fix the flagged rows on the Expenses sheet first — the balances do not add up to 0.",IF(COUNTIF($V$10:$V$18,">="&0.01)=0,"Nothing to settle — everyone is square.",COUNTIF($V$10:$V$18,">="&0.01)&" transfer(s) clear all balances. Tick them off in 'Done?'."))) -> 4 transfer(s) clear all balances. Tick them off in 'Done?'.
J7: balance P1 | K7: balance P2 | L7: balance P3 | M7: balance P4 | N7: balance P5 | O7: balance P6 | P7: balance P7 | Q7: balance P8 | R7: balance P9 | S7: balance P10 | T7: creditor idx (row 8: largest creditor) | U7: debtor idx (row 8: rounding cent) | V7: amount
J8: =IF('Who Owes What'!$J$1=0,0,IFERROR(IF(ISNUMBER('Who Owes What'!$F$10),ROUND('Who Owes What'!$F$10,2),0),0)) -> 1269 | K8: =IF('Who Owes What'!$J$1=0,0,IFERROR(IF(ISNUMBER('Who Owes What'!$F$11),ROUND('Who Owes What'!$F$11,2),0),0)) -> 390.04 | L8: =IF('Who Owes What'!$J$1=0,0,IFERROR(IF(ISNUMBER('Who Owes What'!$F$12),ROUND('Who Owes What'!$F$12,2),0),0)) -> -658.93 | M8: =IF('Who Owes What'!$J$1=0,0,IFERROR(IF(ISNUMBER('Who Owes What'!$F$13),ROUND('Who Owes What'!$F$13,2),0),0)) -> -681.55 | N8: =IF('Who Owes What'!$J$1=0,0,IFERROR(IF(ISNUMBER('Who Owes What'!$F$14),ROUND('Who Owes What'!$F$14,2),0),0)) -> -318.56 | O8: =IF('Who Owes What'!$J$1=0,0,IFERROR(IF(ISNUMBER('Who Owes What'!$F$15),ROUND('Who Owes What'!$F$15,2),0),0)) -> 0 | P8: =IF('Who Owes What'!$J$1=0,0,IFERROR(IF(ISNUMBER('Who Owes What'!$F$16),ROUND('Who Owes What'!$F$16,2),0),0)) -> 0 | Q8: =IF('Who Owes What'!$J$1=0,0,IFERROR(IF(ISNUMBER('Who Owes What'!$F$17),ROUND('Who Owes What'!$F$17,2),0),0)) -> 0 | R8: =IF('Who Owes What'!$J$1=0,0,IFERROR(IF(ISNUMBER('Who Owes What'!$F$18),ROUND('Who Owes What'!$F$18,2),0),0)) -> 0 | S8: =IF('Who Owes What'!$J$1=0,0,IFERROR(IF(ISNUMBER('Who Owes What'!$F$19),ROUND('Who Owes What'!$F$19,2),0),0)) -> 0 | T8: =IFERROR(MATCH(MAX($J$8:$S$8),$J$8:$S$8,0),1) -> 1 | U8: =IFERROR(IF(ABS(ROUND(SUM($J$8:$S$8),2))>0.09,0,-ROUND(SUM($J$8:$S$8),2)),0) -> 0
A9: # | B9: Who pays | C9: → | D9: Who receives | E9: =IF(Setup!$C$16="","Amount","Amount ("&Setup!$C$16&")") -> Amount (€) | F9: Done? | G9: Note (date, PayPal, cash …)
A10: =IF($V10<=0.005,"—",ROW()-9) -> 1 | B10: =IFERROR(IF($V10<=0.005,"—",INDEX('Who Owes What'!$B$10:$B$19,$U10)),"—") -> Dana | C10: =IF($V10<=0.005,"","→") -> → | D10: =IFERROR(IF($V10<=0.005,"—",INDEX('Who Owes What'!$B$10:$B$19,$T10)),"—") -> Anna | E10: =IF($V10<=0.005,"—",$V10) -> 681.55 | J10: =IFERROR(ROUND($J$8,2)+IF($T$8=1,$U$8,0),0) -> 1269 | K10: =IFERROR(ROUND($K$8,2)+IF($T$8=2,$U$8,0),0) -> 390.04 | L10: =IFERROR(ROUND($L$8,2)+IF($T$8=3,$U$8,0),0) -> -658.93 | M10: =IFERROR(ROUND($M$8,2)+IF($T$8=4,$U$8,0),0) -> -681.55 | N10: =IFERROR(ROUND($N$8,2)+IF($T$8=5,$U$8,0),0) -> -318.56 | O10: =IFERROR(ROUND($O$8,2)+IF($T$8=6,$U$8,0),0) -> 0 | P10: =IFERROR(ROUND($P$8,2)+IF($T$8=7,$U$8,0),0) -> 0 | Q10: =IFERROR(ROUND($Q$8,2)+IF($T$8=8,$U$8,0),0) -> 0 | R10: =IFERROR(ROUND($R$8,2)+IF($T$8=9,$U$8,0),0) -> 0 | S10: =IFERROR(ROUND($S$8,2)+IF($T$8=10,$U$8,0),0) -> 0 | T10: =IFERROR(MATCH(MAX($J10:$S10),$J10:$S10,0),0) -> 1 | U10: =IFERROR(MATCH(MIN($J10:$S10),$J10:$S10,0),0) -> 4 | V10: =IFERROR(ROUND(MIN(MAX($J10:$S10),-MIN($J10:$S10)),2),0) -> 681.55
A11: =IF($V11<=0.005,"—",ROW()-9) -> 2 | B11: =IFERROR(IF($V11<=0.005,"—",INDEX('Who Owes What'!$B$10:$B$19,$U11)),"—") -> Chris | C11: =IF($V11<=0.005,"","→") -> → | D11: =IFERROR(IF($V11<=0.005,"—",INDEX('Who Owes What'!$B$10:$B$19,$T11)),"—") -> Anna | E11: =IF($V11<=0.005,"—",$V11) -> 587.45 | J11: =IFERROR(ROUND(J10+IF($U10=1,$V10,0)-IF($T10=1,$V10,0),2),0) -> 587.45 | K11: =IFERROR(ROUND(K10+IF($U10=2,$V10,0)-IF($T10=2,$V10,0),2),0) -> 390.04 | L11: =IFERROR(ROUND(L10+IF($U10=3,$V10,0)-IF($T10=3,$V10,0),2),0) -> -658.93 | M11: =IFERROR(ROUND(M10+IF($U10=4,$V10,0)-IF($T10=4,$V10,0),2),0) -> 0 | N11: =IFERROR(ROUND(N10+IF($U10=5,$V10,0)-IF($T10=5,$V10,0),2),0) -> -318.56 | O11: =IFERROR(ROUND(O10+IF($U10=6,$V10,0)-IF($T10=6,$V10,0),2),0) -> 0 | P11: =IFERROR(ROUND(P10+IF($U10=7,$V10,0)-IF($T10=7,$V10,0),2),0) -> 0 | Q11: =IFERROR(ROUND(Q10+IF($U10=8,$V10,0)-IF($T10=8,$V10,0),2),0) -> 0 | R11: =IFERROR(ROUND(R10+IF($U10=9,$V10,0)-IF($T10=9,$V10,0),2),0) -> 0 | S11: =IFERROR(ROUND(S10+IF($U10=10,$V10,0)-IF($T10=10,$V10,0),2),0) -> 0 | T11: =IFERROR(MATCH(MAX($J11:$S11),$J11:$S11,0),0) -> 1 | U11: =IFERROR(MATCH(MIN($J11:$S11),$J11:$S11,0),0) -> 3 | V11: =IFERROR(ROUND(MIN(MAX($J11:$S11),-MIN($J11:$S11)),2),0) -> 587.45
A12: =IF($V12<=0.005,"—",ROW()-9) -> 3 | B12: =IFERROR(IF($V12<=0.005,"—",INDEX('Who Owes What'!$B$10:$B$19,$U12)),"—") -> Eli | C12: =IF($V12<=0.005,"","→") -> → | D12: =IFERROR(IF($V12<=0.005,"—",INDEX('Who Owes What'!$B$10:$B$19,$T12)),"—") -> Ben | E12: =IF($V12<=0.005,"—",$V12) -> 318.56 | J12: =IFERROR(ROUND(J11+IF($U11=1,$V11,0)-IF($T11=1,$V11,0),2),0) -> 0 | K12: =IFERROR(ROUND(K11+IF($U11=2,$V11,0)-IF($T11=2,$V11,0),2),0) -> 390.04 | L12: =IFERROR(ROUND(L11+IF($U11=3,$V11,0)-IF($T11=3,$V11,0),2),0) -> -71.48 | M12: =IFERROR(ROUND(M11+IF($U11=4,$V11,0)-IF($T11=4,$V11,0),2),0) -> 0 | N12: =IFERROR(ROUND(N11+IF($U11=5,$V11,0)-IF($T11=5,$V11,0),2),0) -> -318.56 | O12: =IFERROR(ROUND(O11+IF($U11=6,$V11,0)-IF($T11=6,$V11,0),2),0) -> 0 | P12: =IFERROR(ROUND(P11+IF($U11=7,$V11,0)-IF($T11=7,$V11,0),2),0) -> 0 | Q12: =IFERROR(ROUND(Q11+IF($U11=8,$V11,0)-IF($T11=8,$V11,0),2),0) -> 0 | R12: =IFERROR(ROUND(R11+IF($U11=9,$V11,0)-IF($T11=9,$V11,0),2),0) -> 0 | S12: =IFERROR(ROUND(S11+IF($U11=10,$V11,0)-IF($T11=10,$V11,0),2),0) -> 0 | T12: =IFERROR(MATCH(MAX($J12:$S12),$J12:$S12,0),0) -> 2 | U12: =IFERROR(MATCH(MIN($J12:$S12),$J12:$S12,0),0) -> 5 | V12: =IFERROR(ROUND(MIN(MAX($J12:$S12),-MIN($J12:$S12)),2),0) -> 318.56
A13: =IF($V13<=0.005,"—",ROW()-9) -> 4 | B13: =IFERROR(IF($V13<=0.005,"—",INDEX('Who Owes What'!$B$10:$B$19,$U13)),"—") -> Chris | C13: =IF($V13<=0.005,"","→") -> → | D13: =IFERROR(IF($V13<=0.005,"—",INDEX('Who Owes What'!$B$10:$B$19,$T13)),"—") -> Ben | E13: =IF($V13<=0.005,"—",$V13) -> 71.48 | J13: =IFERROR(ROUND(J12+IF($U12=1,$V12,0)-IF($T12=1,$V12,0),2),0) -> 0 | K13: =IFERROR(ROUND(K12+IF($U12=2,$V12,0)-IF($T12=2,$V12,0),2),0) -> 71.48 | L13: =IFERROR(ROUND(L12+IF($U12=3,$V12,0)-IF($T12=3,$V12,0),2),0) -> -71.48 | M13: =IFERROR(ROUND(M12+IF($U12=4,$V12,0)-IF($T12=4,$V12,0),2),0) -> 0 | N13: =IFERROR(ROUND(N12+IF($U12=5,$V12,0)-IF($T12=5,$V12,0),2),0) -> 0 | O13: =IFERROR(ROUND(O12+IF($U12=6,$V12,0)-IF($T12=6,$V12,0),2),0) -> 0 | P13: =IFERROR(ROUND(P12+IF($U12=7,$V12,0)-IF($T12=7,$V12,0),2),0) -> 0 | Q13: =IFERROR(ROUND(Q12+IF($U12=8,$V12,0)-IF($T12=8,$V12,0),2),0) -> 0 | R13: =IFERROR(ROUND(R12+IF($U12=9,$V12,0)-IF($T12=9,$V12,0),2),0) -> 0 | S13: =IFERROR(ROUND(S12+IF($U12=10,$V12,0)-IF($T12=10,$V12,0),2),0) -> 0 | T13: =IFERROR(MATCH(MAX($J13:$S13),$J13:$S13,0),0) -> 2 | U13: =IFERROR(MATCH(MIN($J13:$S13),$J13:$S13,0),0) -> 3 | V13: =IFERROR(ROUND(MIN(MAX($J13:$S13),-MIN($J13:$S13)),2),0) -> 71.48
A14: =IF($V14<=0.005,"—",ROW()-9) -> — | B14: =IFERROR(IF($V14<=0.005,"—",INDEX('Who Owes What'!$B$10:$B$19,$U14)),"—") -> — | C14: =IF($V14<=0.005,"","→") | D14: =IFERROR(IF($V14<=0.005,"—",INDEX('Who Owes What'!$B$10:$B$19,$T14)),"—") -> — | E14: =IF($V14<=0.005,"—",$V14) -> — | J14: =IFERROR(ROUND(J13+IF($U13=1,$V13,0)-IF($T13=1,$V13,0),2),0) -> 0 | K14: =IFERROR(ROUND(K13+IF($U13=2,$V13,0)-IF($T13=2,$V13,0),2),0) -> 0 | L14: =IFERROR(ROUND(L13+IF($U13=3,$V13,0)-IF($T13=3,$V13,0),2),0) -> 0 | M14: =IFERROR(ROUND(M13+IF($U13=4,$V13,0)-IF($T13=4,$V13,0),2),0) -> 0 | N14: =IFERROR(ROUND(N13+IF($U13=5,$V13,0)-IF($T13=5,$V13,0),2),0) -> 0 | O14: =IFERROR(ROUND(O13+IF($U13=6,$V13,0)-IF($T13=6,$V13,0),2),0) -> 0 | P14: =IFERROR(ROUND(P13+IF($U13=7,$V13,0)-IF($T13=7,$V13,0),2),0) -> 0 | Q14: =IFERROR(ROUND(Q13+IF($U13=8,$V13,0)-IF($T13=8,$V13,0),2),0) -> 0 | R14: =IFERROR(ROUND(R13+IF($U13=9,$V13,0)-IF($T13=9,$V13,0),2),0) -> 0 | S14: =IFERROR(ROUND(S13+IF($U13=10,$V13,0)-IF($T13=10,$V13,0),2),0) -> 0 | T14: =IFERROR(MATCH(MAX($J14:$S14),$J14:$S14,0),0) -> 1 | U14: =IFERROR(MATCH(MIN($J14:$S14),$J14:$S14,0),0) -> 1 | V14: =IFERROR(ROUND(MIN(MAX($J14:$S14),-MIN($J14:$S14)),2),0) -> 0
A15: =IF($V15<=0.005,"—",ROW()-9) -> — | B15: =IFERROR(IF($V15<=0.005,"—",INDEX('Who Owes What'!$B$10:$B$19,$U15)),"—") -> — | C15: =IF($V15<=0.005,"","→") | D15: =IFERROR(IF($V15<=0.005,"—",INDEX('Who Owes What'!$B$10:$B$19,$T15)),"—") -> — | E15: =IF($V15<=0.005,"—",$V15) -> — | J15: =IFERROR(ROUND(J14+IF($U14=1,$V14,0)-IF($T14=1,$V14,0),2),0) -> 0 | K15: =IFERROR(ROUND(K14+IF($U14=2,$V14,0)-IF($T14=2,$V14,0),2),0) -> 0 | L15: =IFERROR(ROUND(L14+IF($U14=3,$V14,0)-IF($T14=3,$V14,0),2),0) -> 0 | M15: =IFERROR(ROUND(M14+IF($U14=4,$V14,0)-IF($T14=4,$V14,0),2),0) -> 0 | N15: =IFERROR(ROUND(N14+IF($U14=5,$V14,0)-IF($T14=5,$V14,0),2),0) -> 0 | O15: =IFERROR(ROUND(O14+IF($U14=6,$V14,0)-IF($T14=6,$V14,0),2),0) -> 0 | P15: =IFERROR(ROUND(P14+IF($U14=7,$V14,0)-IF($T14=7,$V14,0),2),0) -> 0 | Q15: =IFERROR(ROUND(Q14+IF($U14=8,$V14,0)-IF($T14=8,$V14,0),2),0) -> 0 | R15: =IFERROR(ROUND(R14+IF($U14=9,$V14,0)-IF($T14=9,$V14,0),2),0) -> 0 | S15: =IFERROR(ROUND(S14+IF($U14=10,$V14,0)-IF($T14=10,$V14,0),2),0) -> 0 | T15: =IFERROR(MATCH(MAX($J15:$S15),$J15:$S15,0),0) -> 1 | U15: =IFERROR(MATCH(MIN($J15:$S15),$J15:$S15,0),0) -> 1 | V15: =IFERROR(ROUND(MIN(MAX($J15:$S15),-MIN($J15:$S15)),2),0) -> 0
A16: =IF($V16<=0.005,"—",ROW()-9) -> — | B16: =IFERROR(IF($V16<=0.005,"—",INDEX('Who Owes What'!$B$10:$B$19,$U16)),"—") -> — | C16: =IF($V16<=0.005,"","→") | D16: =IFERROR(IF($V16<=0.005,"—",INDEX('Who Owes What'!$B$10:$B$19,$T16)),"—") -> — | E16: =IF($V16<=0.005,"—",$V16) -> — | J16: =IFERROR(ROUND(J15+IF($U15=1,$V15,0)-IF($T15=1,$V15,0),2),0) -> 0 | K16: =IFERROR(ROUND(K15+IF($U15=2,$V15,0)-IF($T15=2,$V15,0),2),0) -> 0 | L16: =IFERROR(ROUND(L15+IF($U15=3,$V15,0)-IF($T15=3,$V15,0),2),0) -> 0 | M16: =IFERROR(ROUND(M15+IF($U15=4,$V15,0)-IF($T15=4,$V15,0),2),0) -> 0 | N16: =IFERROR(ROUND(N15+IF($U15=5,$V15,0)-IF($T15=5,$V15,0),2),0) -> 0 | O16: =IFERROR(ROUND(O15+IF($U15=6,$V15,0)-IF($T15=6,$V15,0),2),0) -> 0 | P16: =IFERROR(ROUND(P15+IF($U15=7,$V15,0)-IF($T15=7,$V15,0),2),0) -> 0 | Q16: =IFERROR(ROUND(Q15+IF($U15=8,$V15,0)-IF($T15=8,$V15,0),2),0) -> 0 | R16: =IFERROR(ROUND(R15+IF($U15=9,$V15,0)-IF($T15=9,$V15,0),2),0) -> 0 | S16: =IFERROR(ROUND(S15+IF($U15=10,$V15,0)-IF($T15=10,$V15,0),2),0) -> 0 | T16: =IFERROR(MATCH(MAX($J16:$S16),$J16:$S16,0),0) -> 1 | U16: =IFERROR(MATCH(MIN($J16:$S16),$J16:$S16,0),0) -> 1 | V16: =IFERROR(ROUND(MIN(MAX($J16:$S16),-MIN($J16:$S16)),2),0) -> 0
A17: =IF($V17<=0.005,"—",ROW()-9) -> — | B17: =IFERROR(IF($V17<=0.005,"—",INDEX('Who Owes What'!$B$10:$B$19,$U17)),"—") -> — | C17: =IF($V17<=0.005,"","→") | D17: =IFERROR(IF($V17<=0.005,"—",INDEX('Who Owes What'!$B$10:$B$19,$T17)),"—") -> — | E17: =IF($V17<=0.005,"—",$V17) -> — | J17: =IFERROR(ROUND(J16+IF($U16=1,$V16,0)-IF($T16=1,$V16,0),2),0) -> 0 | K17: =IFERROR(ROUND(K16+IF($U16=2,$V16,0)-IF($T16=2,$V16,0),2),0) -> 0 | L17: =IFERROR(ROUND(L16+IF($U16=3,$V16,0)-IF($T16=3,$V16,0),2),0) -> 0 | M17: =IFERROR(ROUND(M16+IF($U16=4,$V16,0)-IF($T16=4,$V16,0),2),0) -> 0 | N17: =IFERROR(ROUND(N16+IF($U16=5,$V16,0)-IF($T16=5,$V16,0),2),0) -> 0 | O17: =IFERROR(ROUND(O16+IF($U16=6,$V16,0)-IF($T16=6,$V16,0),2),0) -> 0 | P17: =IFERROR(ROUND(P16+IF($U16=7,$V16,0)-IF($T16=7,$V16,0),2),0) -> 0 | Q17: =IFERROR(ROUND(Q16+IF($U16=8,$V16,0)-IF($T16=8,$V16,0),2),0) -> 0 | R17: =IFERROR(ROUND(R16+IF($U16=9,$V16,0)-IF($T16=9,$V16,0),2),0) -> 0 | S17: =IFERROR(ROUND(S16+IF($U16=10,$V16,0)-IF($T16=10,$V16,0),2),0) -> 0 | T17: =IFERROR(MATCH(MAX($J17:$S17),$J17:$S17,0),0) -> 1 | U17: =IFERROR(MATCH(MIN($J17:$S17),$J17:$S17,0),0) -> 1 | V17: =IFERROR(ROUND(MIN(MAX($J17:$S17),-MIN($J17:$S17)),2),0) -> 0
A18: =IF($V18<=0.005,"—",ROW()-9) -> — | B18: =IFERROR(IF($V18<=0.005,"—",INDEX('Who Owes What'!$B$10:$B$19,$U18)),"—") -> — | C18: =IF($V18<=0.005,"","→") | D18: =IFERROR(IF($V18<=0.005,"—",INDEX('Who Owes What'!$B$10:$B$19,$T18)),"—") -> — | E18: =IF($V18<=0.005,"—",$V18) -> — | J18: =IFERROR(ROUND(J17+IF($U17=1,$V17,0)-IF($T17=1,$V17,0),2),0) -> 0 | K18: =IFERROR(ROUND(K17+IF($U17=2,$V17,0)-IF($T17=2,$V17,0),2),0) -> 0 | L18: =IFERROR(ROUND(L17+IF($U17=3,$V17,0)-IF($T17=3,$V17,0),2),0) -> 0 | M18: =IFERROR(ROUND(M17+IF($U17=4,$V17,0)-IF($T17=4,$V17,0),2),0) -> 0 | N18: =IFERROR(ROUND(N17+IF($U17=5,$V17,0)-IF($T17=5,$V17,0),2),0) -> 0 | O18: =IFERROR(ROUND(O17+IF($U17=6,$V17,0)-IF($T17=6,$V17,0),2),0) -> 0 | P18: =IFERROR(ROUND(P17+IF($U17=7,$V17,0)-IF($T17=7,$V17,0),2),0) -> 0 | Q18: =IFERROR(ROUND(Q17+IF($U17=8,$V17,0)-IF($T17=8,$V17,0),2),0) -> 0 | R18: =IFERROR(ROUND(R17+IF($U17=9,$V17,0)-IF($T17=9,$V17,0),2),0) -> 0 | S18: =IFERROR(ROUND(S17+IF($U17=10,$V17,0)-IF($T17=10,$V17,0),2),0) -> 0 | T18: =IFERROR(MATCH(MAX($J18:$S18),$J18:$S18,0),0) -> 1 | U18: =IFERROR(MATCH(MIN($J18:$S18),$J18:$S18,0),0) -> 1 | V18: =IFERROR(ROUND(MIN(MAX($J18:$S18),-MIN($J18:$S18)),2),0) -> 0
J19: =IFERROR(ROUND(J18+IF($U18=1,$V18,0)-IF($T18=1,$V18,0),2),0) -> 0 | K19: =IFERROR(ROUND(K18+IF($U18=2,$V18,0)-IF($T18=2,$V18,0),2),0) -> 0 | L19: =IFERROR(ROUND(L18+IF($U18=3,$V18,0)-IF($T18=3,$V18,0),2),0) -> 0 | M19: =IFERROR(ROUND(M18+IF($U18=4,$V18,0)-IF($T18=4,$V18,0),2),0) -> 0 | N19: =IFERROR(ROUND(N18+IF($U18=5,$V18,0)-IF($T18=5,$V18,0),2),0) -> 0 | O19: =IFERROR(ROUND(O18+IF($U18=6,$V18,0)-IF($T18=6,$V18,0),2),0) -> 0 | P19: =IFERROR(ROUND(P18+IF($U18=7,$V18,0)-IF($T18=7,$V18,0),2),0) -> 0 | Q19: =IFERROR(ROUND(Q18+IF($U18=8,$V18,0)-IF($T18=8,$V18,0),2),0) -> 0 | R19: =IFERROR(ROUND(R18+IF($U18=9,$V18,0)-IF($T18=9,$V18,0),2),0) -> 0 | S19: =IFERROR(ROUND(S18+IF($U18=10,$V18,0)-IF($T18=10,$V18,0),2),0) -> 0 | T19: =IFERROR(MATCH(MAX($J19:$S19),$J19:$S19,0),0) -> 1 | U19: =IFERROR(MATCH(MIN($J19:$S19),$J19:$S19,0),0) -> 1 | V19: =IFERROR(ROUND(MIN(MAX($J19:$S19),-MIN($J19:$S19)),2),0) -> 0
D20: Left over after plan (must be 0.00) | E20: =IF('Who Owes What'!$J$1=0,"—",IFERROR(ROUND(MAX(SUMIF($J$19:$S$19,">"&0.009),-SUMIF($J$19:$S$19,"<-0.009")),2),0)) -> 0
D21: Total transferred | E21: =IF('Who Owes What'!$J$1=0,"—",IFERROR(SUMIF($V$10:$V$18,">="&0.01),0)) -> 1659.04
D22: Ticked off | E22: =IF(COUNTIF($V$10:$V$18,">="&0.01)=0,"—",COUNTIF($F$10:$F$18,"Yes")&" of "&COUNTIF($V$10:$V$18,">="&0.01)&" done") -> 0 of 4 done
B24: How the plan is built: the person who owes the most pays the person who is owed the most, and each transfer settles at least one of them completely. That is why 10 people never need more than 9 transfers. It is not claimed to be the mathematically smallest possible number. Balances are rounded to whole cents, so the odd cent goes to whoever is owed the most — one person can end up a cent or two off their balance above, and the plan still closes at 0.00.
