Workbook

Sheet Start Here
B2: Client Project & Capacity Tracker
B3: One file for every project, every promise, the invoice status you type in, and every free hour you have left.
B5: FIRST 15 MINUTES
B6: 0 · Delete the 8 EXAMPLE rows — Projects rows 5–7 and Deliverables rows 5–9. They are filled in so the Dashboard and the colour warnings show something real the moment you open the file.
B7: 1 · Projects — type your live jobs: Client, Project, Status, Fee agreed, Due. The Project name in column C is the key of the whole file: the Deliverables dropdown and every per-project total are built from it.
B8: 2 · Deliverables — one row per thing you owe. Pick the project from the dropdown, set the Due date and the Planned hours.
B9: 3 · Week Capacity — overwrite the 25 h per week with YOUR real available hours, and put holidays into Blocked / time off.
B10: 4 · Dashboard — read, never type. Excel locks it read-only; Google Sheets drops that lock on import, so just don't type on it there.
B12: THE FIT CHECK — Week Capacity, top block: type the hours a new enquiry needs and the date the client wants. You get YES / TIGHT / NO with the number behind it. It answers only from the hours YOU entered — it does not estimate how long work takes and does not know your speed.
B13: SET ONCE — Projects row 3: B3 = your payment term in days (default 30), E3 = your target hourly rate (optional). Both drive the colour warnings and nothing else.
B14: GREY MEANS CALCULATED — never type in a grey cell. The white cells and the four yellow ones (Projects B3 and E3, Week Capacity B5 and B6) are yours.
B15: CURRENCY — numbers are currency-neutral on purpose. Want € or $? Select columns I:J and L:N on Projects (skip K, that one is a date) → Format → Currency. Nothing breaks.
... B24: Questions or a formula that misbehaves? Message us on Etsy — we answer within 48 hours (1–2 business days).

Sheet Dashboard
A1: Dashboard | J1: =IF(ISNUMBER(Projects!$B$3),Projects!$B$3,30) -> 30
A2: ="Everything here computes itself — never type on this sheet. All countdowns relative to "&TEXT(YEAR(TODAY()),"0000")&"-"&TEXT(MONTH(TODAY()),"00")&"-"&TEXT(DAY(TODAY()),"00") -> Everything here computes itself — never type on this sheet. All countdowns relative to 2026-07-29 | J2: =IF(ISNUMBER(Projects!$E$3),Projects!$E$3,"")
J3: =IF(ISNUMBER('Week Capacity'!$F$15),'Week Capacity'!$F$15,0) -> 22
A4: THIS WEEK & AHEAD
A5: Free hours this week | D5: Load next 4 weeks | G5: Committed hours this week (incl. overdue)
A6: =IFERROR(IF(ISNUMBER('Week Capacity'!$F$15),'Week Capacity'!$F$15,"—"),"—") -> 22 | D6: =IFERROR(IF(SUM('Week Capacity'!$C$15:$C$18)<=0,"—",(SUM('Week Capacity'!$D$15:$D$18)+SUM('Week Capacity'!$E$15:$E$18))/SUM('Week Capacity'!$C$15:$C$18)),"—") -> 0.32 | G6: =IFERROR(IF(ISNUMBER('Week Capacity'!$D$15),'Week Capacity'!$D$15,"—"),"—") -> 3
A8: PROMISES
A9: Next deadline in days (minus = late) | D9: Deliverables past their due date | G9: Open deliverables
A10: =IF(COUNT(Deliverables!$J$5:$J$304)=0,"—",MIN(Deliverables!$J$5:$J$304)) -> -8 | D10: =IF(COUNT(Deliverables!$J$5:$J$304)=0,"—",COUNTIF(Deliverables!$J$5:$J$304,"<0")) -> 1 | G10: =IF(COUNTA(Deliverables!$D$5:$D$304)=0,"—",COUNTA(Deliverables!$D$5:$D$304)-COUNTIFS(Deliverables!$A$5:$A$304,">0",Deliverables!$F$5:$F$304,"Delivered")-COUNTIFS(Deliverables!$A$5:$A$304,">0",Deliverables!$F$5:$F$304,"Approved")-COUNTIFS(Deliverables!$A$5:$A$304,">0",Deliverables!$F$5:$F$304,"Cancelled")) -> 4
A11: =IF(COUNT(Deliverables!$J$5:$J$304)=0,"Nothing scheduled yet — add a deliverable with a due date.",IFERROR(IF(MIN(Deliverables!$J$5:$J$304)<0,"Most overdue: ","Next up: ")&INDEX(Deliverables!$D$5:$D$304,MATCH(MIN(Deliverables!$J$5:$J$304),Deliverables!$J$5:$J$304,0))&" · "&INDEX(Deliverables!$B$5:$B$304,MATCH(MIN(Deliverables!$J$5:$J$304),Deliverables!$J$5:$J$304,0))&" · "&TEXT(ABS(MIN(Deliverables!$J$5:$J$304)),"0")&IF(MIN(Deliverables!$J$5:$J$304)<0," days late"," days to go"),"—")) -> Most overdue: Logo concepts (3 routes) · Brand refresh · 8 days late
A13: MONEY (your currency — no tax of any kind is calculated)
A14: Delivered, not invoiced | D14: Older than the payment term you set | G14: Awaiting payment
A15: =IF(COUNTA(Deliverables!$D$5:$D$304)=0,"—",COUNTIFS(Deliverables!$F$5:$F$304,"Delivered",Deliverables!$L$5:$L$304,"Not yet")+COUNTIFS(Deliverables!$F$5:$F$304,"Approved",Deliverables!$L$5:$L$304,"Not yet")) -> 1 | D15: =IF(COUNTA(Projects!$C$5:$C$64)=0,"—",IF(NOT(ISNUMBER(Projects!$B$3)),"set term",IFERROR(SUMIFS(Projects!$N$5:$N$64,Projects!$O$5:$O$64,">"&Projects!$B$3),"—"))) -> 2400 | G15: =IF(COUNTA(Projects!$C$5:$C$64)=0,"—",IFERROR(SUMIF(Projects!$N$5:$N$64,">0"),"—")) -> 2400
A16: =IF(NOT(ISNUMBER(Projects!$B$3)),"Set your payment term in Projects B3.",IFERROR(COUNTIFS(Projects!$O$5:$O$64,">"&Projects!$B$3),0)&" invoice(s) older than the "&Projects!$B$3&"-day payment term you set.") -> 1 invoice(s) older than the 30-day payment term you set.
A17: ="Booked "&IF(COUNTA(Projects!$C$5:$C$64)=0,"—",FIXED(SUM(Projects!$I$5:$I$64)-IFERROR(SUMIFS(Projects!$I$5:$I$64,Projects!$E$5:$E$64,"Cancelled"),0),2))&" · Invoiced "&IF(COUNTA(Projects!$C$5:$C$64)=0,"—",FIXED(SUM(Projects!$J$5:$J$64)-IFERROR(SUMIFS(Projects!$J$5:$J$64,Projects!$E$5:$E$64,"Cancelled"),0),2))&" · Still to invoice "&IF(COUNTA(Projects!$C$5:$C$64)=0,"—",FIXED(IFERROR(SUMIFS(Projects!$M$5:$M$64,Projects!$M$5:$M$64,">0",Projects!$E$5:$E$64,"<>Cancelled"),0),2))&" (your currency — no tax of any kind is calculated)" -> Booked 10.000,00 · Invoiced 5.400,00 · Still to invoice 4.600,00 (your currency — no tax of any kind is calculated)
A19: HOW TO READ THIS
A20: Green = room to say yes. Amber = tight, only by moving a date. Red = you are already over; something has to give.
A21: Every number here comes from Projects, Deliverables and Week Capacity. Change a number there and this sheet follows.
A23: Print: set up for one portrait page (A1:H24). Google Sheets does not import print settings — set them once under File → Print.

Sheet Projects
A1: Projects
A2: One row per client project. Amounts live here and nowhere else. Grey columns calculate themselves — never type in them.
A3: Payment term (days) → | B3: 30 | D3: Target rate / hour → | F3: optional — turns 'Rate / hour so far' amber whenever it drops below this
A4: # | B4: Client | C4: Project | D4: Service type | E4: Status | F4: Started | G4: Due (final) | H4: Days left | I4: Fee agreed | J4: Invoiced | K4: Invoiced on | L4: Paid | M4: Still to invoice | N4: Awaiting payment | O4: Days since invoice | P4: Hours quoted | Q4: Hours logged | R4: Hours left | S4: Rate / hour so far | T4: Deliverables done | U4: Notes
A5: =IF($C5="","",ROW()-4) -> 1 | B5: EXAMPLE — delete this row | C5: Brand refresh | D5: Design | E5: In progress | F5: =TODAY()-24 -> 46208 | G5: =TODAY()+16 -> 46248 | H5: =IF($G5="","—",IF(OR($E5="Approved",$E5="Closed",$E5="Cancelled"),"—",IFERROR(INT($G5)-TODAY(),"—"))) -> 16 | I5: 4800 | J5: 2400 | K5: =TODAY()-38 -> 46194 | M5: =IF($C5="","—",IF($I5="","—",IFERROR($I5-$J5,"—"))) -> 2400 | N5: =IF($C5="","—",IF($J5="","—",IFERROR($J5-$L5,"—"))) -> 2400 | O5: =IF($K5="","—",IF(NOT(ISNUMBER($N5)),"—",IF($N5<=0,"—",IFERROR(TODAY()-INT($K5),"—")))) -> 38 | P5: 40 | Q5: =IF($C5="","—",IFERROR(SUMIFS(Deliverables!$H$5:$H$304,Deliverables!$B$5:$B$304,SUBSTITUTE(SUBSTITUTE(SUBSTITUTE($C5,"~","~~"),"*","~*"),"?","~?")),"—")) -> 5 | R5: =IF($C5="","—",IF($P5="","—",IF(ISNUMBER($Q5),IFERROR($P5-$Q5,"—"),"—"))) -> 35 | S5: =IF($C5="","—",IFERROR(IF(AND(ISNUMBER($Q5),$Q5>0,ISNUMBER($I5)),ROUND($I5/$Q5,1),"—"),"—")) -> 960 | T5: =IF($C5="","—",IF(COUNTIF(Deliverables!$B$5:$B$304,SUBSTITUTE(SUBSTITUTE(SUBSTITUTE($C5,"~","~~"),"*","~*"),"?","~?"))=0,"—",COUNTIFS(Deliverables!$B$5:$B$304,SUBSTITUTE(SUBSTITUTE(SUBSTITUTE($C5,"~","~~"),"*","~*"),"?","~?"),Deliverables!$F$5:$F$304,"Delivered")+COUNTIFS(Deliverables!$B$5:$B$304,SUBSTITUTE(SUBSTITUTE(SUBSTITUTE($C5,"~","~~"),"*","~*"),"?","~?"),Deliverables!$F$5:$F$304,"Approved")&" / "&COUNTIF(Deliverables!$B$5:$B$304,SUBSTITUTE(SUBSTITUTE(SUBSTITUTE($C5,"~","~~"),"*","~*"),"?","~?")))) -> 0 / 2 | U5: First invoice is older than the payment term — see the red cell in column O.
A6: =IF($C6="","",ROW()-4) -> 2 | B6: EXAMPLE — delete this row | C6: Website copy | D6: Copywriting | E6: Booked | F6: =TODAY()-6 -> 46226 | G6: =TODAY()+27 -> 46259 | H6: =IF($G6="","—",IF(OR($E6="Approved",$E6="Closed",$E6="Cancelled"),"—",IFERROR(INT($G6)-TODAY(),"—"))) -> 27 | I6: 2200 | M6: =IF($C6="","—",IF($I6="","—",IFERROR($I6-$J6,"—"))) -> 2200 | N6: =IF($C6="","—",IF($J6="","—",IFERROR($J6-$L6,"—"))) -> — | O6: =IF($K6="","—",IF(NOT(ISNUMBER($N6)),"—",IF($N6<=0,"—",IFERROR(TODAY()-INT($K6),"—")))) -> — | P6: 18 | Q6: =IF($C6="","—",IFERROR(SUMIFS(Deliverables!$H$5:$H$304,Deliverables!$B$5:$B$304,SUBSTITUTE(SUBSTITUTE(SUBSTITUTE($C6,"~","~~"),"*","~*"),"?","~?")),"—")) -> 2 | R6: =IF($C6="","—",IF($P6="","—",IF(ISNUMBER($Q6),IFERROR($P6-$Q6,"—"),"—"))) -> 16 | S6: =IF($C6="","—",IFERROR(IF(AND(ISNUMBER($Q6),$Q6>0,ISNUMBER($I6)),ROUND($I6/$Q6,1),"—"),"—")) -> 1100 | T6: =IF($C6="","—",IF(COUNTIF(Deliverables!$B$5:$B$304,SUBSTITUTE(SUBSTITUTE(SUBSTITUTE($C6,"~","~~"),"*","~*"),"?","~?"))=0,"—",COUNTIFS(Deliverables!$B$5:$B$304,SUBSTITUTE(SUBSTITUTE(SUBSTITUTE($C6,"~","~~"),"*","~*"),"?","~?"),Deliverables!$F$5:$F$304,"Delivered")+COUNTIFS(Deliverables!$B$5:$B$304,SUBSTITUTE(SUBSTITUTE(SUBSTITUTE($C6,"~","~~"),"*","~*"),"?","~?"),Deliverables!$F$5:$F$304,"Approved")&" / "&COUNTIF(Deliverables!$B$5:$B$304,SUBSTITUTE(SUBSTITUTE(SUBSTITUTE($C6,"~","~~"),"*","~*"),"?","~?")))) -> 0 / 1 | U6: Nothing invoiced yet — column M shows what is still to invoice.
A7: =IF($C7="","",ROW()-4) -> 3 | B7: EXAMPLE — delete this row | C7: Q3 retainer | D7: Retainer | E7: In progress | F7: =TODAY()-52 -> 46180 | G7: =TODAY()+9 -> 46241 | H7: =IF($G7="","—",IF(OR($E7="Approved",$E7="Closed",$E7="Cancelled"),"—",IFERROR(INT($G7)-TODAY(),"—"))) -> 9 | I7: 3000 | J7: 3000 | K7: =TODAY()-12 -> 46220 | L7: 3000 | M7: =IF($C7="","—",IF($I7="","—",IFERROR($I7-$J7,"—"))) -> 0 | N7: =IF($C7="","—",IF($J7="","—",IFERROR($J7-$L7,"—"))) -> 0 | O7: =IF($K7="","—",IF(NOT(ISNUMBER($N7)),"—",IF($N7<=0,"—",IFERROR(TODAY()-INT($K7),"—")))) -> — | P7: 24 | Q7: =IF($C7="","—",IFERROR(SUMIFS(Deliverables!$H$5:$H$304,Deliverables!$B$5:$B$304,SUBSTITUTE(SUBSTITUTE(SUBSTITUTE($C7,"~","~~"),"*","~*"),"?","~?")),"—")) -> 6 | R7: =IF($C7="","—",IF($P7="","—",IF(ISNUMBER($Q7),IFERROR($P7-$Q7,"—"),"—"))) -> 18 | S7: =IF($C7="","—",IFERROR(IF(AND(ISNUMBER($Q7),$Q7>0,ISNUMBER($I7)),ROUND($I7/$Q7,1),"—"),"—")) -> 500 | T7: =IF($C7="","—",IF(COUNTIF(Deliverables!$B$5:$B$304,SUBSTITUTE(SUBSTITUTE(SUBSTITUTE($C7,"~","~~"),"*","~*"),"?","~?"))=0,"—",COUNTIFS(Deliverables!$B$5:$B$304,SUBSTITUTE(SUBSTITUTE(SUBSTITUTE($C7,"~","~~"),"*","~*"),"?","~?"),Deliverables!$F$5:$F$304,"Delivered")+COUNTIFS(Deliverables!$B$5:$B$304,SUBSTITUTE(SUBSTITUTE(SUBSTITUTE($C7,"~","~~"),"*","~*"),"?","~?"),Deliverables!$F$5:$F$304,"Approved")&" / "&COUNTIF(Deliverables!$B$5:$B$304,SUBSTITUTE(SUBSTITUTE(SUBSTITUTE($C7,"~","~~"),"*","~*"),"?","~?")))) -> 1 / 2 | U7: Fully invoiced and paid — columns N and O go quiet.
A8: =IF($C8="","",ROW()-4) | H8: =IF($G8="","—",IF(OR($E8="Approved",$E8="Closed",$E8="Cancelled"),"—",IFERROR(INT($G8)-TODAY(),"—"))) -> — | M8: =IF($C8="","—",IF($I8="","—",IFERROR($I8-$J8,"—"))) -> — | N8: =IF($C8="","—",IF($J8="","—",IFERROR($J8-$L8,"—"))) -> — | O8: =IF($K8="","—",IF(NOT(ISNUMBER($N8)),"—",IF($N8<=0,"—",IFERROR(TODAY()-INT($K8),"—")))) -> — | Q8: =IF($C8="","—",IFERROR(SUMIFS(Deliverables!$H$5:$H$304,Deliverables!$B$5:$B$304,SUBSTITUTE(SUBSTITUTE(SUBSTITUTE($C8,"~","~~"),"*","~*"),"?","~?")),"—")) -> — | R8: =IF($C8="","—",IF($P8="","—",IF(ISNUMBER($Q8),IFERROR($P8-$Q8,"—"),"—"))) -> — | S8: =IF($C8="","—",IFERROR(IF(AND(ISNUMBER($Q8),$Q8>0,ISNUMBER($I8)),ROUND($I8/$Q8,1),"—"),"—")) -> — | T8: =IF($C8="","—",IF(COUNTIF(Deliverables!$B$5:$B$304,SUBSTITUTE(SUBSTITUTE(SUBSTITUTE($C8,"~","~~"),"*","~*"),"?","~?"))=0,"—",COUNTIFS(Deliverables!$B$5:$B$304,SUBSTITUTE(SUBSTITUTE(SUBSTITUTE($C8,"~","~~"),"*","~*"),"?","~?"),Deliverables!$F$5:$F$304,"Delivered")+COUNTIFS(Deliverables!$B$5:$B$304,SUBSTITUTE(SUBSTITUTE(SUBSTITUTE($C8,"~","~~"),"*","~*"),"?","~?"),Deliverables!$F$5:$F$304,"Approved")&" / "&COUNTIF(Deliverables!$B$5:$B$304,SUBSTITUTE(SUBSTITUTE(SUBSTITUTE($C8,"~","~~"),"*","~*"),"?","~?")))) -> —
A9: =IF($C9="","",ROW()-4) | H9: =IF($G9="","—",IF(OR($E9="Approved",$E9="Closed",$E9="Cancelled"),"—",IFERROR(INT($G9)-TODAY(),"—"))) -> — | M9: =IF($C9="","—",IF($I9="","—",IFERROR($I9-$J9,"—"))) -> — | N9: =IF($C9="","—",IF($J9="","—",IFERROR($J9-$L9,"—"))) -> — | O9: =IF($K9="","—",IF(NOT(ISNUMBER($N9)),"—",IF($N9<=0,"—",IFERROR(TODAY()-INT($K9),"—")))) -> — | Q9: =IF($C9="","—",IFERROR(SUMIFS(Deliverables!$H$5:$H$304,Deliverables!$B$5:$B$304,SUBSTITUTE(SUBSTITUTE(SUBSTITUTE($C9,"~","~~"),"*","~*"),"?","~?")),"—")) -> — | R9: =IF($C9="","—",IF($P9="","—",IF(ISNUMBER($Q9),IFERROR($P9-$Q9,"—"),"—"))) -> — | S9: =IF($C9="","—",IFERROR(IF(AND(ISNUMBER($Q9),$Q9>0,ISNUMBER($I9)),ROUND($I9/$Q9,1),"—"),"—")) -> — | T9: =IF($C9="","—",IF(COUNTIF(Deliverables!$B$5:$B$304,SUBSTITUTE(SUBSTITUTE(SUBSTITUTE($C9,"~","~~"),"*","~*"),"?","~?"))=0,"—",COUNTIFS(Deliverables!$B$5:$B$304,SUBSTITUTE(SUBSTITUTE(SUBSTITUTE($C9,"~","~~"),"*","~*"),"?","~?"),Deliverables!$F$5:$F$304,"Delivered")+COUNTIFS(Deliverables!$B$5:$B$304,SUBSTITUTE(SUBSTITUTE(SUBSTITUTE($C9,"~","~~"),"*","~*"),"?","~?"),Deliverables!$F$5:$F$304,"Approved")&" / "&COUNTIF(Deliverables!$B$5:$B$304,SUBSTITUTE(SUBSTITUTE(SUBSTITUTE($C9,"~","~~"),"*","~*"),"?","~?")))) -> —
A10: =IF($C10="","",ROW()-4) | H10: =IF($G10="","—",IF(OR($E10="Approved",$E10="Closed",$E10="Cancelled"),"—",IFERROR(INT($G10)-TODAY(),"—"))) -> — | M10: =IF($C10="","—",IF($I10="","—",IFERROR($I10-$J10,"—"))) -> — | N10: =IF($C10="","—",IF($J10="","—",IFERROR($J10-$L10,"—"))) -> — | O10: =IF($K10="","—",IF(NOT(ISNUMBER($N10)),"—",IF($N10<=0,"—",IFERROR(TODAY()-INT($K10),"—")))) -> — | Q10: =IF($C10="","—",IFERROR(SUMIFS(Deliverables!$H$5:$H$304,Deliverables!$B$5:$B$304,SUBSTITUTE(SUBSTITUTE(SUBSTITUTE($C10,"~","~~"),"*","~*"),"?","~?")),"—")) -> — | R10: =IF($C10="","—",IF($P10="","—",IF(ISNUMBER($Q10),IFERROR($P10-$Q10,"—"),"—"))) -> — | S10: =IF($C10="","—",IFERROR(IF(AND(ISNUMBER($Q10),$Q10>0,ISNUMBER($I10)),ROUND($I10/$Q10,1),"—"),"—")) -> — | T10: =IF($C10="","—",IF(COUNTIF(Deliverables!$B$5:$B$304,SUBSTITUTE(SUBSTITUTE(SUBSTITUTE($C10,"~","~~"),"*","~*"),"?","~?"))=0,"—",COUNTIFS(Deliverables!$B$5:$B$304,SUBSTITUTE(SUBSTITUTE(SUBSTITUTE($C10,"~","~~"),"*","~*"),"?","~?"),Deliverables!$F$5:$F$304,"Delivered")+COUNTIFS(Deliverables!$B$5:$B$304,SUBSTITUTE(SUBSTITUTE(SUBSTITUTE($C10,"~","~~"),"*","~*"),"?","~?"),Deliverables!$F$5:$F$304,"Approved")&" / "&COUNTIF(Deliverables!$B$5:$B$304,SUBSTITUTE(SUBSTITUTE(SUBSTITUTE($C10,"~","~~"),"*","~*"),"?","~?")))) -> —
A11: =IF($C11="","",ROW()-4) | H11: =IF($G11="","—",IF(OR($E11="Approved",$E11="Closed",$E11="Cancelled"),"—",IFERROR(INT($G11)-TODAY(),"—"))) -> — | M11: =IF($C11="","—",IF($I11="","—",IFERROR($I11-$J11,"—"))) -> — | N11: =IF($C11="","—",IF($J11="","—",IFERROR($J11-$L11,"—"))) -> — | O11: =IF($K11="","—",IF(NOT(ISNUMBER($N11)),"—",IF($N11<=0,"—",IFERROR(TODAY()-INT($K11),"—")))) -> — | Q11: =IF($C11="","—",IFERROR(SUMIFS(Deliverables!$H$5:$H$304,Deliverables!$B$5:$B$304,SUBSTITUTE(SUBSTITUTE(SUBSTITUTE($C11,"~","~~"),"*","~*"),"?","~?")),"—")) -> — | R11: =IF($C11="","—",IF($P11="","—",IF(ISNUMBER($Q11),IFERROR($P11-$Q11,"—"),"—"))) -> — | S11: =IF($C11="","—",IFERROR(IF(AND(ISNUMBER($Q11),$Q11>0,ISNUMBER($I11)),ROUND($I11/$Q11,1),"—"),"—")) -> — | T11: =IF($C11="","—",IF(COUNTIF(Deliverables!$B$5:$B$304,SUBSTITUTE(SUBSTITUTE(SUBSTITUTE($C11,"~","~~"),"*","~*"),"?","~?"))=0,"—",COUNTIFS(Deliverables!$B$5:$B$304,SUBSTITUTE(SUBSTITUTE(SUBSTITUTE($C11,"~","~~"),"*","~*"),"?","~?"),Deliverables!$F$5:$F$304,"Delivered")+COUNTIFS(Deliverables!$B$5:$B$304,SUBSTITUTE(SUBSTITUTE(SUBSTITUTE($C11,"~","~~"),"*","~*"),"?","~?"),Deliverables!$F$5:$F$304,"Approved")&" / "&COUNTIF(Deliverables!$B$5:$B$304,SUBSTITUTE(SUBSTITUTE(SUBSTITUTE($C11,"~","~~"),"*","~*"),"?","~?")))) -> —
A12: =IF($C12="","",ROW()-4) | H12: =IF($G12="","—",IF(OR($E12="Approved",$E12="Closed",$E12="Cancelled"),"—",IFERROR(INT($G12)-TODAY(),"—"))) -> — | M12: =IF($C12="","—",IF($I12="","—",IFERROR($I12-$J12,"—"))) -> — | N12: =IF($C12="","—",IF($J12="","—",IFERROR($J12-$L12,"—"))) -> — | O12: =IF($K12="","—",IF(NOT(ISNUMBER($N12)),"—",IF($N12<=0,"—",IFERROR(TODAY()-INT($K12),"—")))) -> — | Q12: =IF($C12="","—",IFERROR(SUMIFS(Deliverables!$H$5:$H$304,Deliverables!$B$5:$B$304,SUBSTITUTE(SUBSTITUTE(SUBSTITUTE($C12,"~","~~"),"*","~*"),"?","~?")),"—")) -> — | R12: =IF($C12="","—",IF($P12="","—",IF(ISNUMBER($Q12),IFERROR($P12-$Q12,"—"),"—"))) -> — | S12: =IF($C12="","—",IFERROR(IF(AND(ISNUMBER($Q12),$Q12>0,ISNUMBER($I12)),ROUND($I12/$Q12,1),"—"),"—")) -> — | T12: =IF($C12="","—",IF(COUNTIF(Deliverables!$B$5:$B$304,SUBSTITUTE(SUBSTITUTE(SUBSTITUTE($C12,"~","~~"),"*","~*"),"?","~?"))=0,"—",COUNTIFS(Deliverables!$B$5:$B$304,SUBSTITUTE(SUBSTITUTE(SUBSTITUTE($C12,"~","~~"),"*","~*"),"?","~?"),Deliverables!$F$5:$F$304,"Delivered")+COUNTIFS(Deliverables!$B$5:$B$304,SUBSTITUTE(SUBSTITUTE(SUBSTITUTE($C12,"~","~~"),"*","~*"),"?","~?"),Deliverables!$F$5:$F$304,"Approved")&" / "&COUNTIF(Deliverables!$B$5:$B$304,SUBSTITUTE(SUBSTITUTE(SUBSTITUTE($C12,"~","~~"),"*","~*"),"?","~?")))) -> —
A13: =IF($C13="","",ROW()-4) | H13: =IF($G13="","—",IF(OR($E13="Approved",$E13="Closed",$E13="Cancelled"),"—",IFERROR(INT($G13)-TODAY(),"—"))) -> — | M13: =IF($C13="","—",IF($I13="","—",IFERROR($I13-$J13,"—"))) -> — | N13: =IF($C13="","—",IF($J13="","—",IFERROR($J13-$L13,"—"))) -> — | O13: =IF($K13="","—",IF(NOT(ISNUMBER($N13)),"—",IF($N13<=0,"—",IFERROR(TODAY()-INT($K13),"—")))) -> — | Q13: =IF($C13="","—",IFERROR(SUMIFS(Deliverables!$H$5:$H$304,Deliverables!$B$5:$B$304,SUBSTITUTE(SUBSTITUTE(SUBSTITUTE($C13,"~","~~"),"*","~*"),"?","~?")),"—")) -> — | R13: =IF($C13="","—",IF($P13="","—",IF(ISNUMBER($Q13),IFERROR($P13-$Q13,"—"),"—"))) -> — | S13: =IF($C13="","—",IFERROR(IF(AND(ISNUMBER($Q13),$Q13>0,ISNUMBER($I13)),ROUND($I13/$Q13,1),"—"),"—")) -> — | T13: =IF($C13="","—",IF(COUNTIF(Deliverables!$B$5:$B$304,SUBSTITUTE(SUBSTITUTE(SUBSTITUTE($C13,"~","~~"),"*","~*"),"?","~?"))=0,"—",COUNTIFS(Deliverables!$B$5:$B$304,SUBSTITUTE(SUBSTITUTE(SUBSTITUTE($C13,"~","~~"),"*","~*"),"?","~?"),Deliverables!$F$5:$F$304,"Delivered")+COUNTIFS(Deliverables!$B$5:$B$304,SUBSTITUTE(SUBSTITUTE(SUBSTITUTE($C13,"~","~~"),"*","~*"),"?","~?"),Deliverables!$F$5:$F$304,"Approved")&" / "&COUNTIF(Deliverables!$B$5:$B$304,SUBSTITUTE(SUBSTITUTE(SUBSTITUTE($C13,"~","~~"),"*","~*"),"?","~?")))) -> —
A14: =IF($C14="","",ROW()-4) | H14: =IF($G14="","—",IF(OR($E14="Approved",$E14="Closed",$E14="Cancelled"),"—",IFERROR(INT($G14)-TODAY(),"—"))) -> — | M14: =IF($C14="","—",IF($I14="","—",IFERROR($I14-$J14,"—"))) -> — | N14: =IF($C14="","—",IF($J14="","—",IFERROR($J14-$L14,"—"))) -> — | O14: =IF($K14="","—",IF(NOT(ISNUMBER($N14)),"—",IF($N14<=0,"—",IFERROR(TODAY()-INT($K14),"—")))) -> — | Q14: =IF($C14="","—",IFERROR(SUMIFS(Deliverables!$H$5:$H$304,Deliverables!$B$5:$B$304,SUBSTITUTE(SUBSTITUTE(SUBSTITUTE($C14,"~","~~"),"*","~*"),"?","~?")),"—")) -> — | R14: =IF($C14="","—",IF($P14="","—",IF(ISNUMBER($Q14),IFERROR($P14-$Q14,"—"),"—"))) -> — | S14: =IF($C14="","—",IFERROR(IF(AND(ISNUMBER($Q14),$Q14>0,ISNUMBER($I14)),ROUND($I14/$Q14,1),"—"),"—")) -> — | T14: =IF($C14="","—",IF(COUNTIF(Deliverables!$B$5:$B$304,SUBSTITUTE(SUBSTITUTE(SUBSTITUTE($C14,"~","~~"),"*","~*"),"?","~?"))=0,"—",COUNTIFS(Deliverables!$B$5:$B$304,SUBSTITUTE(SUBSTITUTE(SUBSTITUTE($C14,"~","~~"),"*","~*"),"?","~?"),Deliverables!$F$5:$F$304,"Delivered")+COUNTIFS(Deliverables!$B$5:$B$304,SUBSTITUTE(SUBSTITUTE(SUBSTITUTE($C14,"~","~~"),"*","~*"),"?","~?"),Deliverables!$F$5:$F$304,"Approved")&" / "&COUNTIF(Deliverables!$B$5:$B$304,SUBSTITUTE(SUBSTITUTE(SUBSTITUTE($C14,"~","~~"),"*","~*"),"?","~?")))) -> —
A15: =IF($C15="","",ROW()-4) | H15: =IF($G15="","—",IF(OR($E15="Approved",$E15="Closed",$E15="Cancelled"),"—",IFERROR(INT($G15)-TODAY(),"—"))) -> — | M15: =IF($C15="","—",IF($I15="","—",IFERROR($I15-$J15,"—"))) -> — | N15: =IF($C15="","—",IF($J15="","—",IFERROR($J15-$L15,"—"))) -> — | O15: =IF($K15="","—",IF(NOT(ISNUMBER($N15)),"—",IF($N15<=0,"—",IFERROR(TODAY()-INT($K15),"—")))) -> — | Q15: =IF($C15="","—",IFERROR(SUMIFS(Deliverables!$H$5:$H$304,Deliverables!$B$5:$B$304,SUBSTITUTE(SUBSTITUTE(SUBSTITUTE($C15,"~","~~"),"*","~*"),"?","~?")),"—")) -> — | R15: =IF($C15="","—",IF($P15="","—",IF(ISNUMBER($Q15),IFERROR($P15-$Q15,"—"),"—"))) -> — | S15: =IF($C15="","—",IFERROR(IF(AND(ISNUMBER($Q15),$Q15>0,ISNUMBER($I15)),ROUND($I15/$Q15,1),"—"),"—")) -> — | T15: =IF($C15="","—",IF(COUNTIF(Deliverables!$B$5:$B$304,SUBSTITUTE(SUBSTITUTE(SUBSTITUTE($C15,"~","~~"),"*","~*"),"?","~?"))=0,"—",COUNTIFS(Deliverables!$B$5:$B$304,SUBSTITUTE(SUBSTITUTE(SUBSTITUTE($C15,"~","~~"),"*","~*"),"?","~?"),Deliverables!$F$5:$F$304,"Delivered")+COUNTIFS(Deliverables!$B$5:$B$304,SUBSTITUTE(SUBSTITUTE(SUBSTITUTE($C15,"~","~~"),"*","~*"),"?","~?"),Deliverables!$F$5:$F$304,"Approved")&" / "&COUNTIF(Deliverables!$B$5:$B$304,SUBSTITUTE(SUBSTITUTE(SUBSTITUTE($C15,"~","~~"),"*","~*"),"?","~?")))) -> —
A16: =IF($C16="","",ROW()-4) | H16: =IF($G16="","—",IF(OR($E16="Approved",$E16="Closed",$E16="Cancelled"),"—",IFERROR(INT($G16)-TODAY(),"—"))) -> — | M16: =IF($C16="","—",IF($I16="","—",IFERROR($I16-$J16,"—"))) -> — | N16: =IF($C16="","—",IF($J16="","—",IFERROR($J16-$L16,"—"))) -> — | O16: =IF($K16="","—",IF(NOT(ISNUMBER($N16)),"—",IF($N16<=0,"—",IFERROR(TODAY()-INT($K16),"—")))) -> — | Q16: =IF($C16="","—",IFERROR(SUMIFS(Deliverables!$H$5:$H$304,Deliverables!$B$5:$B$304,SUBSTITUTE(SUBSTITUTE(SUBSTITUTE($C16,"~","~~"),"*","~*"),"?","~?")),"—")) -> — | R16: =IF($C16="","—",IF($P16="","—",IF(ISNUMBER($Q16),IFERROR($P16-$Q16,"—"),"—"))) -> — | S16: =IF($C16="","—",IFERROR(IF(AND(ISNUMBER($Q16),$Q16>0,ISNUMBER($I16)),ROUND($I16/$Q16,1),"—"),"—")) -> — | T16: =IF($C16="","—",IF(COUNTIF(Deliverables!$B$5:$B$304,SUBSTITUTE(SUBSTITUTE(SUBSTITUTE($C16,"~","~~"),"*","~*"),"?","~?"))=0,"—",COUNTIFS(Deliverables!$B$5:$B$304,SUBSTITUTE(SUBSTITUTE(SUBSTITUTE($C16,"~","~~"),"*","~*"),"?","~?"),Deliverables!$F$5:$F$304,"Delivered")+COUNTIFS(Deliverables!$B$5:$B$304,SUBSTITUTE(SUBSTITUTE(SUBSTITUTE($C16,"~","~~"),"*","~*"),"?","~?"),Deliverables!$F$5:$F$304,"Approved")&" / "&COUNTIF(Deliverables!$B$5:$B$304,SUBSTITUTE(SUBSTITUTE(SUBSTITUTE($C16,"~","~~"),"*","~*"),"?","~?")))) -> —
A17: =IF($C17="","",ROW()-4) | H17: =IF($G17="","—",IF(OR($E17="Approved",$E17="Closed",$E17="Cancelled"),"—",IFERROR(INT($G17)-TODAY(),"—"))) -> — | M17: =IF($C17="","—",IF($I17="","—",IFERROR($I17-$J17,"—"))) -> — | N17: =IF($C17="","—",IF($J17="","—",IFERROR($J17-$L17,"—"))) -> — | O17: =IF($K17="","—",IF(NOT(ISNUMBER($N17)),"—",IF($N17<=0,"—",IFERROR(TODAY()-INT($K17),"—")))) -> — | Q17: =IF($C17="","—",IFERROR(SUMIFS(Deliverables!$H$5:$H$304,Deliverables!$B$5:$B$304,SUBSTITUTE(SUBSTITUTE(SUBSTITUTE($C17,"~","~~"),"*","~*"),"?","~?")),"—")) -> — | R17: =IF($C17="","—",IF($P17="","—",IF(ISNUMBER($Q17),IFERROR($P17-$Q17,"—"),"—"))) -> — | S17: =IF($C17="","—",IFERROR(IF(AND(ISNUMBER($Q17),$Q17>0,ISNUMBER($I17)),ROUND($I17/$Q17,1),"—"),"—")) -> — | T17: =IF($C17="","—",IF(COUNTIF(Deliverables!$B$5:$B$304,SUBSTITUTE(SUBSTITUTE(SUBSTITUTE($C17,"~","~~"),"*","~*"),"?","~?"))=0,"—",COUNTIFS(Deliverables!$B$5:$B$304,SUBSTITUTE(SUBSTITUTE(SUBSTITUTE($C17,"~","~~"),"*","~*"),"?","~?"),Deliverables!$F$5:$F$304,"Delivered")+COUNTIFS(Deliverables!$B$5:$B$304,SUBSTITUTE(SUBSTITUTE(SUBSTITUTE($C17,"~","~~"),"*","~*"),"?","~?"),Deliverables!$F$5:$F$304,"Approved")&" / "&COUNTIF(Deliverables!$B$5:$B$304,SUBSTITUTE(SUBSTITUTE(SUBSTITUTE($C17,"~","~~"),"*","~*"),"?","~?")))) -> —
A18: =IF($C18="","",ROW()-4) | H18: =IF($G18="","—",IF(OR($E18="Approved",$E18="Closed",$E18="Cancelled"),"—",IFERROR(INT($G18)-TODAY(),"—"))) -> — | M18: =IF($C18="","—",IF($I18="","—",IFERROR($I18-$J18,"—"))) -> — | N18: =IF($C18="","—",IF($J18="","—",IFERROR($J18-$L18,"—"))) -> — | O18: =IF($K18="","—",IF(NOT(ISNUMBER($N18)),"—",IF($N18<=0,"—",IFERROR(TODAY()-INT($K18),"—")))) -> — | Q18: =IF($C18="","—",IFERROR(SUMIFS(Deliverables!$H$5:$H$304,Deliverables!$B$5:$B$304,SUBSTITUTE(SUBSTITUTE(SUBSTITUTE($C18,"~","~~"),"*","~*"),"?","~?")),"—")) -> — | R18: =IF($C18="","—",IF($P18="","—",IF(ISNUMBER($Q18),IFERROR($P18-$Q18,"—"),"—"))) -> — | S18: =IF($C18="","—",IFERROR(IF(AND(ISNUMBER($Q18),$Q18>0,ISNUMBER($I18)),ROUND($I18/$Q18,1),"—"),"—")) -> — | T18: =IF($C18="","—",IF(COUNTIF(Deliverables!$B$5:$B$304,SUBSTITUTE(SUBSTITUTE(SUBSTITUTE($C18,"~","~~"),"*","~*"),"?","~?"))=0,"—",COUNTIFS(Deliverables!$B$5:$B$304,SUBSTITUTE(SUBSTITUTE(SUBSTITUTE($C18,"~","~~"),"*","~*"),"?","~?"),Deliverables!$F$5:$F$304,"Delivered")+COUNTIFS(Deliverables!$B$5:$B$304,SUBSTITUTE(SUBSTITUTE(SUBSTITUTE($C18,"~","~~"),"*","~*"),"?","~?"),Deliverables!$F$5:$F$304,"Approved")&" / "&COUNTIF(Deliverables!$B$5:$B$304,SUBSTITUTE(SUBSTITUTE(SUBSTITUTE($C18,"~","~~"),"*","~*"),"?","~?")))) -> —
A19: =IF($C19="","",ROW()-4) | H19: =IF($G19="","—",IF(OR($E19="Approved",$E19="Closed",$E19="Cancelled"),"—",IFERROR(INT($G19)-TODAY(),"—"))) -> — | M19: =IF($C19="","—",IF($I19="","—",IFERROR($I19-$J19,"—"))) -> — | N19: =IF($C19="","—",IF($J19="","—",IFERROR($J19-$L19,"—"))) -> — | O19: =IF($K19="","—",IF(NOT(ISNUMBER($N19)),"—",IF($N19<=0,"—",IFERROR(TODAY()-INT($K19),"—")))) -> — | Q19: =IF($C19="","—",IFERROR(SUMIFS(Deliverables!$H$5:$H$304,Deliverables!$B$5:$B$304,SUBSTITUTE(SUBSTITUTE(SUBSTITUTE($C19,"~","~~"),"*","~*"),"?","~?")),"—")) -> — | R19: =IF($C19="","—",IF($P19="","—",IF(ISNUMBER($Q19),IFERROR($P19-$Q19,"—"),"—"))) -> — | S19: =IF($C19="","—",IFERROR(IF(AND(ISNUMBER($Q19),$Q19>0,ISNUMBER($I19)),ROUND($I19/$Q19,1),"—"),"—")) -> — | T19: =IF($C19="","—",IF(COUNTIF(Deliverables!$B$5:$B$304,SUBSTITUTE(SUBSTITUTE(SUBSTITUTE($C19,"~","~~"),"*","~*"),"?","~?"))=0,"—",COUNTIFS(Deliverables!$B$5:$B$304,SUBSTITUTE(SUBSTITUTE(SUBSTITUTE($C19,"~","~~"),"*","~*"),"?","~?"),Deliverables!$F$5:$F$304,"Delivered")+COUNTIFS(Deliverables!$B$5:$B$304,SUBSTITUTE(SUBSTITUTE(SUBSTITUTE($C19,"~","~~"),"*","~*"),"?","~?"),Deliverables!$F$5:$F$304,"Approved")&" / "&COUNTIF(Deliverables!$B$5:$B$304,SUBSTITUTE(SUBSTITUTE(SUBSTITUTE($C19,"~","~~"),"*","~*"),"?","~?")))) -> —
... A64: =IF($C64="","",ROW()-4) | H64: =IF($G64="","—",IF(OR($E64="Approved",$E64="Closed",$E64="Cancelled"),"—",IFERROR(INT($G64)-TODAY(),"—"))) -> — | M64: =IF($C64="","—",IF($I64="","—",IFERROR($I64-$J64,"—"))) -> — | N64: =IF($C64="","—",IF($J64="","—",IFERROR($J64-$L64,"—"))) -> — | O64: =IF($K64="","—",IF(NOT(ISNUMBER($N64)),"—",IF($N64<=0,"—",IFERROR(TODAY()-INT($K64),"—")))) -> — | Q64: =IF($C64="","—",IFERROR(SUMIFS(Deliverables!$H$5:$H$304,Deliverables!$B$5:$B$304,SUBSTITUTE(SUBSTITUTE(SUBSTITUTE($C64,"~","~~"),"*","~*"),"?","~?")),"—")) -> — | R64: =IF($C64="","—",IF($P64="","—",IF(ISNUMBER($Q64),IFERROR($P64-$Q64,"—"),"—"))) -> — | S64: =IF($C64="","—",IFERROR(IF(AND(ISNUMBER($Q64),$Q64>0,ISNUMBER($I64)),ROUND($I64/$Q64,1),"—"),"—")) -> — | T64: =IF($C64="","—",IF(COUNTIF(Deliverables!$B$5:$B$304,SUBSTITUTE(SUBSTITUTE(SUBSTITUTE($C64,"~","~~"),"*","~*"),"?","~?"))=0,"—",COUNTIFS(Deliverables!$B$5:$B$304,SUBSTITUTE(SUBSTITUTE(SUBSTITUTE($C64,"~","~~"),"*","~*"),"?","~?"),Deliverables!$F$5:$F$304,"Delivered")+COUNTIFS(Deliverables!$B$5:$B$304,SUBSTITUTE(SUBSTITUTE(SUBSTITUTE($C64,"~","~~"),"*","~*"),"?","~?"),Deliverables!$F$5:$F$304,"Approved")&" / "&COUNTIF(Deliverables!$B$5:$B$304,SUBSTITUTE(SUBSTITUTE(SUBSTITUTE($C64,"~","~~"),"*","~*"),"?","~?")))) -> —

Sheet Deliverables
A1: Deliverables
A2: One row per thing you owe. Due date and Planned hours here become the weekly load on Week Capacity.
B3: Fill in Projects first — this dropdown builds itself from Projects, column C.
A4: # | B4: Project | C4: Linked? | D4: Deliverable / milestone | E4: Due date | F4: Status | G4: Planned hours | H4: Hours logged | I4: Hours left | J4: Days left | K4: Week (Mon) | L4: Invoice status | M4: Deadline | N4: Waiting on | O4: Notes
A5: =IF($D5="","",ROW()-4) -> 1 | B5: Brand refresh | C5: =IF($B5="","",IF(COUNTIF(Projects!$C$5:$C$64,SUBSTITUTE(SUBSTITUTE(SUBSTITUTE($B5,"~","~~"),"*","~*"),"?","~?"))>0,"✓","not in Projects")) -> ✓ | D5: Logo concepts (3 routes) | E5: =TODAY()-8 -> 46224 | F5: In progress | G5: 8 | H5: 5 | I5: =IF($D5="","—",IF(OR($F5="Delivered",$F5="Approved",$F5="Cancelled"),"—",IF(AND($G5="",$H5=""),"—",IFERROR(MAX(0,N($G5)-N($H5)),"—")))) -> 3 | J5: =IF($E5="","—",IF(OR($F5="Delivered",$F5="Approved",$F5="Cancelled"),"—",IFERROR(INT($E5)-TODAY(),"—"))) -> -8 | K5: =IF($E5="","—",IFERROR(INT($E5)-WEEKDAY(INT($E5),3),"—")) -> 46223 | L5: Not yet | M5: Hard date | N5: Me | O5: EXAMPLE — delete. Past its due date, so it turns red and carries into this week.
A6: =IF($D6="","",ROW()-4) -> 2 | B6: Brand refresh | C6: =IF($B6="","",IF(COUNTIF(Projects!$C$5:$C$64,SUBSTITUTE(SUBSTITUTE(SUBSTITUTE($B6,"~","~~"),"*","~*"),"?","~?"))>0,"✓","not in Projects")) -> ✓ | D6: Brand guidelines PDF | E6: =TODAY()+11 -> 46243 | F6: Not started | G6: 12 | I6: =IF($D6="","—",IF(OR($F6="Delivered",$F6="Approved",$F6="Cancelled"),"—",IF(AND($G6="",$H6=""),"—",IFERROR(MAX(0,N($G6)-N($H6)),"—")))) -> 12 | J6: =IF($E6="","—",IF(OR($F6="Delivered",$F6="Approved",$F6="Cancelled"),"—",IFERROR(INT($E6)-TODAY(),"—"))) -> 11 | K6: =IF($E6="","—",IFERROR(INT($E6)-WEEKDAY(INT($E6),3),"—")) -> 46237 | L6: Not yet | M6: Can move | N6: Me | O6: EXAMPLE — delete. 'Can move' means the Fit Check may shift it out of a full week.
A7: =IF($D7="","",ROW()-4) -> 3 | B7: Website copy | C7: =IF($B7="","",IF(COUNTIF(Projects!$C$5:$C$64,SUBSTITUTE(SUBSTITUTE(SUBSTITUTE($B7,"~","~~"),"*","~*"),"?","~?"))>0,"✓","not in Projects")) -> ✓ | D7: Homepage + 4 subpages | E7: =TODAY()+5 -> 46237 | F7: In progress | G7: 10 | H7: 2 | I7: =IF($D7="","—",IF(OR($F7="Delivered",$F7="Approved",$F7="Cancelled"),"—",IF(AND($G7="",$H7=""),"—",IFERROR(MAX(0,N($G7)-N($H7)),"—")))) -> 8 | J7: =IF($E7="","—",IF(OR($F7="Delivered",$F7="Approved",$F7="Cancelled"),"—",IFERROR(INT($E7)-TODAY(),"—"))) -> 5 | K7: =IF($E7="","—",IFERROR(INT($E7)-WEEKDAY(INT($E7),3),"—")) -> 46237 | L7: Not yet | M7: Hard date | N7: Client | O7: EXAMPLE — delete.
A8: =IF($D8="","",ROW()-4) -> 4 | B8: Q3 retainer | C8: =IF($B8="","",IF(COUNTIF(Projects!$C$5:$C$64,SUBSTITUTE(SUBSTITUTE(SUBSTITUTE($B8,"~","~~"),"*","~*"),"?","~?"))>0,"✓","not in Projects")) -> ✓ | D8: July social set | E8: =TODAY()-9 -> 46223 | F8: Delivered | G8: 6 | H8: 6 | I8: =IF($D8="","—",IF(OR($F8="Delivered",$F8="Approved",$F8="Cancelled"),"—",IF(AND($G8="",$H8=""),"—",IFERROR(MAX(0,N($G8)-N($H8)),"—")))) -> — | J8: =IF($E8="","—",IF(OR($F8="Delivered",$F8="Approved",$F8="Cancelled"),"—",IFERROR(INT($E8)-TODAY(),"—"))) -> — | K8: =IF($E8="","—",IFERROR(INT($E8)-WEEKDAY(INT($E8),3),"—")) -> 46223 | L8: Not yet | M8: Can move | N8: Client | O8: EXAMPLE — delete. Delivered but not invoiced — the amber cell in column L is money you have not billed.
A9: =IF($D9="","",ROW()-4) -> 5 | B9: Q3 retainer | C9: =IF($B9="","",IF(COUNTIF(Projects!$C$5:$C$64,SUBSTITUTE(SUBSTITUTE(SUBSTITUTE($B9,"~","~~"),"*","~*"),"?","~?"))>0,"✓","not in Projects")) -> ✓ | D9: August campaign brief | E9: =TODAY()+18 -> 46250 | F9: Not started | G9: 9 | I9: =IF($D9="","—",IF(OR($F9="Delivered",$F9="Approved",$F9="Cancelled"),"—",IF(AND($G9="",$H9=""),"—",IFERROR(MAX(0,N($G9)-N($H9)),"—")))) -> 9 | J9: =IF($E9="","—",IF(OR($F9="Delivered",$F9="Approved",$F9="Cancelled"),"—",IFERROR(INT($E9)-TODAY(),"—"))) -> 18 | K9: =IF($E9="","—",IFERROR(INT($E9)-WEEKDAY(INT($E9),3),"—")) -> 46244 | L9: Not yet | M9: Can move | N9: Me | O9: EXAMPLE — delete.
A10: =IF($D10="","",ROW()-4) | C10: =IF($B10="","",IF(COUNTIF(Projects!$C$5:$C$64,SUBSTITUTE(SUBSTITUTE(SUBSTITUTE($B10,"~","~~"),"*","~*"),"?","~?"))>0,"✓","not in Projects")) | I10: =IF($D10="","—",IF(OR($F10="Delivered",$F10="Approved",$F10="Cancelled"),"—",IF(AND($G10="",$H10=""),"—",IFERROR(MAX(0,N($G10)-N($H10)),"—")))) -> — | J10: =IF($E10="","—",IF(OR($F10="Delivered",$F10="Approved",$F10="Cancelled"),"—",IFERROR(INT($E10)-TODAY(),"—"))) -> — | K10: =IF($E10="","—",IFERROR(INT($E10)-WEEKDAY(INT($E10),3),"—")) -> —
A11: =IF($D11="","",ROW()-4) | C11: =IF($B11="","",IF(COUNTIF(Projects!$C$5:$C$64,SUBSTITUTE(SUBSTITUTE(SUBSTITUTE($B11,"~","~~"),"*","~*"),"?","~?"))>0,"✓","not in Projects")) | I11: =IF($D11="","—",IF(OR($F11="Delivered",$F11="Approved",$F11="Cancelled"),"—",IF(AND($G11="",$H11=""),"—",IFERROR(MAX(0,N($G11)-N($H11)),"—")))) -> — | J11: =IF($E11="","—",IF(OR($F11="Delivered",$F11="Approved",$F11="Cancelled"),"—",IFERROR(INT($E11)-TODAY(),"—"))) -> — | K11: =IF($E11="","—",IFERROR(INT($E11)-WEEKDAY(INT($E11),3),"—")) -> —
A12: =IF($D12="","",ROW()-4) | C12: =IF($B12="","",IF(COUNTIF(Projects!$C$5:$C$64,SUBSTITUTE(SUBSTITUTE(SUBSTITUTE($B12,"~","~~"),"*","~*"),"?","~?"))>0,"✓","not in Projects")) | I12: =IF($D12="","—",IF(OR($F12="Delivered",$F12="Approved",$F12="Cancelled"),"—",IF(AND($G12="",$H12=""),"—",IFERROR(MAX(0,N($G12)-N($H12)),"—")))) -> — | J12: =IF($E12="","—",IF(OR($F12="Delivered",$F12="Approved",$F12="Cancelled"),"—",IFERROR(INT($E12)-TODAY(),"—"))) -> — | K12: =IF($E12="","—",IFERROR(INT($E12)-WEEKDAY(INT($E12),3),"—")) -> —
A13: =IF($D13="","",ROW()-4) | C13: =IF($B13="","",IF(COUNTIF(Projects!$C$5:$C$64,SUBSTITUTE(SUBSTITUTE(SUBSTITUTE($B13,"~","~~"),"*","~*"),"?","~?"))>0,"✓","not in Projects")) | I13: =IF($D13="","—",IF(OR($F13="Delivered",$F13="Approved",$F13="Cancelled"),"—",IF(AND($G13="",$H13=""),"—",IFERROR(MAX(0,N($G13)-N($H13)),"—")))) -> — | J13: =IF($E13="","—",IF(OR($F13="Delivered",$F13="Approved",$F13="Cancelled"),"—",IFERROR(INT($E13)-TODAY(),"—"))) -> — | K13: =IF($E13="","—",IFERROR(INT($E13)-WEEKDAY(INT($E13),3),"—")) -> —
A14: =IF($D14="","",ROW()-4) | C14: =IF($B14="","",IF(COUNTIF(Projects!$C$5:$C$64,SUBSTITUTE(SUBSTITUTE(SUBSTITUTE($B14,"~","~~"),"*","~*"),"?","~?"))>0,"✓","not in Projects")) | I14: =IF($D14="","—",IF(OR($F14="Delivered",$F14="Approved",$F14="Cancelled"),"—",IF(AND($G14="",$H14=""),"—",IFERROR(MAX(0,N($G14)-N($H14)),"—")))) -> — | J14: =IF($E14="","—",IF(OR($F14="Delivered",$F14="Approved",$F14="Cancelled"),"—",IFERROR(INT($E14)-TODAY(),"—"))) -> — | K14: =IF($E14="","—",IFERROR(INT($E14)-WEEKDAY(INT($E14),3),"—")) -> —
A15: =IF($D15="","",ROW()-4) | C15: =IF($B15="","",IF(COUNTIF(Projects!$C$5:$C$64,SUBSTITUTE(SUBSTITUTE(SUBSTITUTE($B15,"~","~~"),"*","~*"),"?","~?"))>0,"✓","not in Projects")) | I15: =IF($D15="","—",IF(OR($F15="Delivered",$F15="Approved",$F15="Cancelled"),"—",IF(AND($G15="",$H15=""),"—",IFERROR(MAX(0,N($G15)-N($H15)),"—")))) -> — | J15: =IF($E15="","—",IF(OR($F15="Delivered",$F15="Approved",$F15="Cancelled"),"—",IFERROR(INT($E15)-TODAY(),"—"))) -> — | K15: =IF($E15="","—",IFERROR(INT($E15)-WEEKDAY(INT($E15),3),"—")) -> —
A16: =IF($D16="","",ROW()-4) | C16: =IF($B16="","",IF(COUNTIF(Projects!$C$5:$C$64,SUBSTITUTE(SUBSTITUTE(SUBSTITUTE($B16,"~","~~"),"*","~*"),"?","~?"))>0,"✓","not in Projects")) | I16: =IF($D16="","—",IF(OR($F16="Delivered",$F16="Approved",$F16="Cancelled"),"—",IF(AND($G16="",$H16=""),"—",IFERROR(MAX(0,N($G16)-N($H16)),"—")))) -> — | J16: =IF($E16="","—",IF(OR($F16="Delivered",$F16="Approved",$F16="Cancelled"),"—",IFERROR(INT($E16)-TODAY(),"—"))) -> — | K16: =IF($E16="","—",IFERROR(INT($E16)-WEEKDAY(INT($E16),3),"—")) -> —
A17: =IF($D17="","",ROW()-4) | C17: =IF($B17="","",IF(COUNTIF(Projects!$C$5:$C$64,SUBSTITUTE(SUBSTITUTE(SUBSTITUTE($B17,"~","~~"),"*","~*"),"?","~?"))>0,"✓","not in Projects")) | I17: =IF($D17="","—",IF(OR($F17="Delivered",$F17="Approved",$F17="Cancelled"),"—",IF(AND($G17="",$H17=""),"—",IFERROR(MAX(0,N($G17)-N($H17)),"—")))) -> — | J17: =IF($E17="","—",IF(OR($F17="Delivered",$F17="Approved",$F17="Cancelled"),"—",IFERROR(INT($E17)-TODAY(),"—"))) -> — | K17: =IF($E17="","—",IFERROR(INT($E17)-WEEKDAY(INT($E17),3),"—")) -> —
A18: =IF($D18="","",ROW()-4) | C18: =IF($B18="","",IF(COUNTIF(Projects!$C$5:$C$64,SUBSTITUTE(SUBSTITUTE(SUBSTITUTE($B18,"~","~~"),"*","~*"),"?","~?"))>0,"✓","not in Projects")) | I18: =IF($D18="","—",IF(OR($F18="Delivered",$F18="Approved",$F18="Cancelled"),"—",IF(AND($G18="",$H18=""),"—",IFERROR(MAX(0,N($G18)-N($H18)),"—")))) -> — | J18: =IF($E18="","—",IF(OR($F18="Delivered",$F18="Approved",$F18="Cancelled"),"—",IFERROR(INT($E18)-TODAY(),"—"))) -> — | K18: =IF($E18="","—",IFERROR(INT($E18)-WEEKDAY(INT($E18),3),"—")) -> —
A19: =IF($D19="","",ROW()-4) | C19: =IF($B19="","",IF(COUNTIF(Projects!$C$5:$C$64,SUBSTITUTE(SUBSTITUTE(SUBSTITUTE($B19,"~","~~"),"*","~*"),"?","~?"))>0,"✓","not in Projects")) | I19: =IF($D19="","—",IF(OR($F19="Delivered",$F19="Approved",$F19="Cancelled"),"—",IF(AND($G19="",$H19=""),"—",IFERROR(MAX(0,N($G19)-N($H19)),"—")))) -> — | J19: =IF($E19="","—",IF(OR($F19="Delivered",$F19="Approved",$F19="Cancelled"),"—",IFERROR(INT($E19)-TODAY(),"—"))) -> — | K19: =IF($E19="","—",IFERROR(INT($E19)-WEEKDAY(INT($E19),3),"—")) -> —
A20: =IF($D20="","",ROW()-4) | C20: =IF($B20="","",IF(COUNTIF(Projects!$C$5:$C$64,SUBSTITUTE(SUBSTITUTE(SUBSTITUTE($B20,"~","~~"),"*","~*"),"?","~?"))>0,"✓","not in Projects")) | I20: =IF($D20="","—",IF(OR($F20="Delivered",$F20="Approved",$F20="Cancelled"),"—",IF(AND($G20="",$H20=""),"—",IFERROR(MAX(0,N($G20)-N($H20)),"—")))) -> — | J20: =IF($E20="","—",IF(OR($F20="Delivered",$F20="Approved",$F20="Cancelled"),"—",IFERROR(INT($E20)-TODAY(),"—"))) -> — | K20: =IF($E20="","—",IFERROR(INT($E20)-WEEKDAY(INT($E20),3),"—")) -> —
A21: =IF($D21="","",ROW()-4) | C21: =IF($B21="","",IF(COUNTIF(Projects!$C$5:$C$64,SUBSTITUTE(SUBSTITUTE(SUBSTITUTE($B21,"~","~~"),"*","~*"),"?","~?"))>0,"✓","not in Projects")) | I21: =IF($D21="","—",IF(OR($F21="Delivered",$F21="Approved",$F21="Cancelled"),"—",IF(AND($G21="",$H21=""),"—",IFERROR(MAX(0,N($G21)-N($H21)),"—")))) -> — | J21: =IF($E21="","—",IF(OR($F21="Delivered",$F21="Approved",$F21="Cancelled"),"—",IFERROR(INT($E21)-TODAY(),"—"))) -> — | K21: =IF($E21="","—",IFERROR(INT($E21)-WEEKDAY(INT($E21),3),"—")) -> —
... A304: =IF($D304="","",ROW()-4) | C304: =IF($B304="","",IF(COUNTIF(Projects!$C$5:$C$64,SUBSTITUTE(SUBSTITUTE(SUBSTITUTE($B304,"~","~~"),"*","~*"),"?","~?"))>0,"✓","not in Projects")) | I304: =IF($D304="","—",IF(OR($F304="Delivered",$F304="Approved",$F304="Cancelled"),"—",IF(AND($G304="",$H304=""),"—",IFERROR(MAX(0,N($G304)-N($H304)),"—")))) -> — | J304: =IF($E304="","—",IF(OR($F304="Delivered",$F304="Approved",$F304="Cancelled"),"—",IFERROR(INT($E304)-TODAY(),"—"))) -> — | K304: =IF($E304="","—",IFERROR(INT($E304)-WEEKDAY(INT($E304),3),"—")) -> —

Sheet Week Capacity
A1: Week Capacity & Fit Check
A2: 26 weeks, rolling from this Monday. You type only in Available hours, Blocked / time off, Note — and in the two yellow Fit Check cells.
A4: FIT CHECK — a new enquiry just landed: can you take it?
A5: Hours the new job needs →
A6: Wanted delivery date →
A7: That week starts (Mon) | B7: =IF($B$6="","—",IFERROR(INT($B$6)-WEEKDAY(INT($B$6),3),"—")) -> —
A8: Free hours in that week | B8: =IF(OR($B$5="",$B$6=""),"—",IF(NOT(ISNUMBER($B$7)),"—",IF(OR($B$7<$A$15,$B$7>$A$40),"outside the 26-week window",IFERROR(SUMIFS($F$15:$F$40,$A$15:$A$40,$B$7),"—")))) -> —
A9: Free hours before that week | B9: =IF(OR($B$5="",$B$6=""),"—",IF(NOT(ISNUMBER($B$7)),"—",IFERROR(SUMIFS($F$15:$F$40,$A$15:$A$40,">="&INT($A$15),$A$15:$A$40,"<"&INT($B$7)),"—"))) -> —
A10: Movable work in that week | B10: =IF(NOT(ISNUMBER($B$7)),"—",IFERROR(SUMIFS($H$15:$H$40,$A$15:$A$40,$B$7),"—")) -> —
A11: VERDICT | B11: =IF(OR($B$5="",$B$6=""),"Enter hours and a date above.",IF(NOT(ISNUMBER($B$8)),"That date is outside the 26-week window.",IF($B$8>=$B$5,"YES — fits in that week ("&TEXT($B$8-$B$5,"0.0")&" h to spare).",IF($B$8+$B$10>=$B$5,"TIGHT — only by moving "&TEXT($B$5-$B$8,"0.0")&" h of movable work out of that week.",IF($B$9+$B$8>=$B$5,"NO for that week alone — but "&TEXT($B$9+$B$8,"0.0")&" h are free between now and that date: start earlier or split the job.","NO — "&TEXT($B$5-$B$9-$B$8,"0.0")&" h short even if you start today."))))) -> Enter hours and a date above.
A12: Overdue hours carried into this week | B12: =IFERROR(SUMIFS(Deliverables!$I$5:$I$304,Deliverables!$K$5:$K$304,"<"&INT($A$15)),0) -> 3
A13: Table starts (Mon) | B13: =TODAY()-WEEKDAY(TODAY(),3) -> 46230 | C13: type any date over this to freeze the window — the table snaps to that week's Monday
A14: Week starting (Mon) | B14: Week | C14: Available hours | D14: Committed hours | E14: Blocked / time off | F14: Free hours | G14: Load | H14: Movable hours | I14: Open deadlines | J14: Note
A15: =IFERROR(INT($B$13)-WEEKDAY(INT($B$13),3),TODAY()-WEEKDAY(TODAY(),3)) -> 46230 | B15: =IFERROR("Week "&TEXT(WEEKNUM($A15,21),"0"),"—") -> Week 31 | C15: 25 | D15: =IFERROR(SUMIFS(Deliverables!$I$5:$I$304,Deliverables!$K$5:$K$304,$A15)+SUMIFS(Deliverables!$I$5:$I$304,Deliverables!$K$5:$K$304,"<"&INT($A15)),0) -> 3 | F15: =IF(NOT(ISNUMBER($C15)),"—",IFERROR($C15-N($D15)-N($E15),"—")) -> 22 | G15: =IF(OR(NOT(ISNUMBER($C15)),$C15<=0),"—",IFERROR(($D15+N($E15))/$C15,"—")) -> 0.12 | H15: =IFERROR(SUMIFS(Deliverables!$I$5:$I$304,Deliverables!$K$5:$K$304,$A15,Deliverables!$M$5:$M$304,"Can move")+SUMIFS(Deliverables!$I$5:$I$304,Deliverables!$K$5:$K$304,"<"&INT($A15),Deliverables!$M$5:$M$304,"Can move"),0) -> 0 | I15: =IFERROR(COUNTIFS(Deliverables!$K$5:$K$304,$A15,Deliverables!$F$5:$F$304,"<>Delivered",Deliverables!$F$5:$F$304,"<>Approved",Deliverables!$F$5:$F$304,"<>Cancelled"),0) -> 0
A16: =A15+7 -> 46237 | B16: =IFERROR("Week "&TEXT(WEEKNUM($A16,21),"0"),"—") -> Week 32 | C16: 25 | D16: =IFERROR(SUMIFS(Deliverables!$I$5:$I$304,Deliverables!$K$5:$K$304,$A16),0) -> 20 | F16: =IF(NOT(ISNUMBER($C16)),"—",IFERROR($C16-N($D16)-N($E16),"—")) -> 5 | G16: =IF(OR(NOT(ISNUMBER($C16)),$C16<=0),"—",IFERROR(($D16+N($E16))/$C16,"—")) -> 0.8 | H16: =IFERROR(SUMIFS(Deliverables!$I$5:$I$304,Deliverables!$K$5:$K$304,$A16,Deliverables!$M$5:$M$304,"Can move"),0) -> 12 | I16: =IFERROR(COUNTIFS(Deliverables!$K$5:$K$304,$A16,Deliverables!$F$5:$F$304,"<>Delivered",Deliverables!$F$5:$F$304,"<>Approved",Deliverables!$F$5:$F$304,"<>Cancelled"),0) -> 2
A17: =A16+7 -> 46244 | B17: =IFERROR("Week "&TEXT(WEEKNUM($A17,21),"0"),"—") -> Week 33 | C17: 25 | D17: =IFERROR(SUMIFS(Deliverables!$I$5:$I$304,Deliverables!$K$5:$K$304,$A17),0) -> 9 | F17: =IF(NOT(ISNUMBER($C17)),"—",IFERROR($C17-N($D17)-N($E17),"—")) -> 16 | G17: =IF(OR(NOT(ISNUMBER($C17)),$C17<=0),"—",IFERROR(($D17+N($E17))/$C17,"—")) -> 0.36 | H17: =IFERROR(SUMIFS(Deliverables!$I$5:$I$304,Deliverables!$K$5:$K$304,$A17,Deliverables!$M$5:$M$304,"Can move"),0) -> 9 | I17: =IFERROR(COUNTIFS(Deliverables!$K$5:$K$304,$A17,Deliverables!$F$5:$F$304,"<>Delivered",Deliverables!$F$5:$F$304,"<>Approved",Deliverables!$F$5:$F$304,"<>Cancelled"),0) -> 1
A18: =A17+7 -> 46251 | B18: =IFERROR("Week "&TEXT(WEEKNUM($A18,21),"0"),"—") -> Week 34 | C18: 25 | D18: =IFERROR(SUMIFS(Deliverables!$I$5:$I$304,Deliverables!$K$5:$K$304,$A18),0) -> 0 | F18: =IF(NOT(ISNUMBER($C18)),"—",IFERROR($C18-N($D18)-N($E18),"—")) -> 25 | G18: =IF(OR(NOT(ISNUMBER($C18)),$C18<=0),"—",IFERROR(($D18+N($E18))/$C18,"—")) -> 0 | H18: =IFERROR(SUMIFS(Deliverables!$I$5:$I$304,Deliverables!$K$5:$K$304,$A18,Deliverables!$M$5:$M$304,"Can move"),0) -> 0 | I18: =IFERROR(COUNTIFS(Deliverables!$K$5:$K$304,$A18,Deliverables!$F$5:$F$304,"<>Delivered",Deliverables!$F$5:$F$304,"<>Approved",Deliverables!$F$5:$F$304,"<>Cancelled"),0) -> 0
A19: =A18+7 -> 46258 | B19: =IFERROR("Week "&TEXT(WEEKNUM($A19,21),"0"),"—") -> Week 35 | C19: 25 | D19: =IFERROR(SUMIFS(Deliverables!$I$5:$I$304,Deliverables!$K$5:$K$304,$A19),0) -> 0 | F19: =IF(NOT(ISNUMBER($C19)),"—",IFERROR($C19-N($D19)-N($E19),"—")) -> 25 | G19: =IF(OR(NOT(ISNUMBER($C19)),$C19<=0),"—",IFERROR(($D19+N($E19))/$C19,"—")) -> 0 | H19: =IFERROR(SUMIFS(Deliverables!$I$5:$I$304,Deliverables!$K$5:$K$304,$A19,Deliverables!$M$5:$M$304,"Can move"),0) -> 0 | I19: =IFERROR(COUNTIFS(Deliverables!$K$5:$K$304,$A19,Deliverables!$F$5:$F$304,"<>Delivered",Deliverables!$F$5:$F$304,"<>Approved",Deliverables!$F$5:$F$304,"<>Cancelled"),0) -> 0
A20: =A19+7 -> 46265 | B20: =IFERROR("Week "&TEXT(WEEKNUM($A20,21),"0"),"—") -> Week 36 | C20: 25 | D20: =IFERROR(SUMIFS(Deliverables!$I$5:$I$304,Deliverables!$K$5:$K$304,$A20),0) -> 0 | F20: =IF(NOT(ISNUMBER($C20)),"—",IFERROR($C20-N($D20)-N($E20),"—")) -> 25 | G20: =IF(OR(NOT(ISNUMBER($C20)),$C20<=0),"—",IFERROR(($D20+N($E20))/$C20,"—")) -> 0 | H20: =IFERROR(SUMIFS(Deliverables!$I$5:$I$304,Deliverables!$K$5:$K$304,$A20,Deliverables!$M$5:$M$304,"Can move"),0) -> 0 | I20: =IFERROR(COUNTIFS(Deliverables!$K$5:$K$304,$A20,Deliverables!$F$5:$F$304,"<>Delivered",Deliverables!$F$5:$F$304,"<>Approved",Deliverables!$F$5:$F$304,"<>Cancelled"),0) -> 0
A21: =A20+7 -> 46272 | B21: =IFERROR("Week "&TEXT(WEEKNUM($A21,21),"0"),"—") -> Week 37 | C21: 25 | D21: =IFERROR(SUMIFS(Deliverables!$I$5:$I$304,Deliverables!$K$5:$K$304,$A21),0) -> 0 | F21: =IF(NOT(ISNUMBER($C21)),"—",IFERROR($C21-N($D21)-N($E21),"—")) -> 25 | G21: =IF(OR(NOT(ISNUMBER($C21)),$C21<=0),"—",IFERROR(($D21+N($E21))/$C21,"—")) -> 0 | H21: =IFERROR(SUMIFS(Deliverables!$I$5:$I$304,Deliverables!$K$5:$K$304,$A21,Deliverables!$M$5:$M$304,"Can move"),0) -> 0 | I21: =IFERROR(COUNTIFS(Deliverables!$K$5:$K$304,$A21,Deliverables!$F$5:$F$304,"<>Delivered",Deliverables!$F$5:$F$304,"<>Approved",Deliverables!$F$5:$F$304,"<>Cancelled"),0) -> 0
A22: =A21+7 -> 46279 | B22: =IFERROR("Week "&TEXT(WEEKNUM($A22,21),"0"),"—") -> Week 38 | C22: 25 | D22: =IFERROR(SUMIFS(Deliverables!$I$5:$I$304,Deliverables!$K$5:$K$304,$A22),0) -> 0 | F22: =IF(NOT(ISNUMBER($C22)),"—",IFERROR($C22-N($D22)-N($E22),"—")) -> 25 | G22: =IF(OR(NOT(ISNUMBER($C22)),$C22<=0),"—",IFERROR(($D22+N($E22))/$C22,"—")) -> 0 | H22: =IFERROR(SUMIFS(Deliverables!$I$5:$I$304,Deliverables!$K$5:$K$304,$A22,Deliverables!$M$5:$M$304,"Can move"),0) -> 0 | I22: =IFERROR(COUNTIFS(Deliverables!$K$5:$K$304,$A22,Deliverables!$F$5:$F$304,"<>Delivered",Deliverables!$F$5:$F$304,"<>Approved",Deliverables!$F$5:$F$304,"<>Cancelled"),0) -> 0
A23: =A22+7 -> 46286 | B23: =IFERROR("Week "&TEXT(WEEKNUM($A23,21),"0"),"—") -> Week 39 | C23: 25 | D23: =IFERROR(SUMIFS(Deliverables!$I$5:$I$304,Deliverables!$K$5:$K$304,$A23),0) -> 0 | F23: =IF(NOT(ISNUMBER($C23)),"—",IFERROR($C23-N($D23)-N($E23),"—")) -> 25 | G23: =IF(OR(NOT(ISNUMBER($C23)),$C23<=0),"—",IFERROR(($D23+N($E23))/$C23,"—")) -> 0 | H23: =IFERROR(SUMIFS(Deliverables!$I$5:$I$304,Deliverables!$K$5:$K$304,$A23,Deliverables!$M$5:$M$304,"Can move"),0) -> 0 | I23: =IFERROR(COUNTIFS(Deliverables!$K$5:$K$304,$A23,Deliverables!$F$5:$F$304,"<>Delivered",Deliverables!$F$5:$F$304,"<>Approved",Deliverables!$F$5:$F$304,"<>Cancelled"),0) -> 0
A24: =A23+7 -> 46293 | B24: =IFERROR("Week "&TEXT(WEEKNUM($A24,21),"0"),"—") -> Week 40 | C24: 25 | D24: =IFERROR(SUMIFS(Deliverables!$I$5:$I$304,Deliverables!$K$5:$K$304,$A24),0) -> 0 | F24: =IF(NOT(ISNUMBER($C24)),"—",IFERROR($C24-N($D24)-N($E24),"—")) -> 25 | G24: =IF(OR(NOT(ISNUMBER($C24)),$C24<=0),"—",IFERROR(($D24+N($E24))/$C24,"—")) -> 0 | H24: =IFERROR(SUMIFS(Deliverables!$I$5:$I$304,Deliverables!$K$5:$K$304,$A24,Deliverables!$M$5:$M$304,"Can move"),0) -> 0 | I24: =IFERROR(COUNTIFS(Deliverables!$K$5:$K$304,$A24,Deliverables!$F$5:$F$304,"<>Delivered",Deliverables!$F$5:$F$304,"<>Approved",Deliverables!$F$5:$F$304,"<>Cancelled"),0) -> 0
A25: =A24+7 -> 46300 | B25: =IFERROR("Week "&TEXT(WEEKNUM($A25,21),"0"),"—") -> Week 41 | C25: 25 | D25: =IFERROR(SUMIFS(Deliverables!$I$5:$I$304,Deliverables!$K$5:$K$304,$A25),0) -> 0 | F25: =IF(NOT(ISNUMBER($C25)),"—",IFERROR($C25-N($D25)-N($E25),"—")) -> 25 | G25: =IF(OR(NOT(ISNUMBER($C25)),$C25<=0),"—",IFERROR(($D25+N($E25))/$C25,"—")) -> 0 | H25: =IFERROR(SUMIFS(Deliverables!$I$5:$I$304,Deliverables!$K$5:$K$304,$A25,Deliverables!$M$5:$M$304,"Can move"),0) -> 0 | I25: =IFERROR(COUNTIFS(Deliverables!$K$5:$K$304,$A25,Deliverables!$F$5:$F$304,"<>Delivered",Deliverables!$F$5:$F$304,"<>Approved",Deliverables!$F$5:$F$304,"<>Cancelled"),0) -> 0
A26: =A25+7 -> 46307 | B26: =IFERROR("Week "&TEXT(WEEKNUM($A26,21),"0"),"—") -> Week 42 | C26: 25 | D26: =IFERROR(SUMIFS(Deliverables!$I$5:$I$304,Deliverables!$K$5:$K$304,$A26),0) -> 0 | F26: =IF(NOT(ISNUMBER($C26)),"—",IFERROR($C26-N($D26)-N($E26),"—")) -> 25 | G26: =IF(OR(NOT(ISNUMBER($C26)),$C26<=0),"—",IFERROR(($D26+N($E26))/$C26,"—")) -> 0 | H26: =IFERROR(SUMIFS(Deliverables!$I$5:$I$304,Deliverables!$K$5:$K$304,$A26,Deliverables!$M$5:$M$304,"Can move"),0) -> 0 | I26: =IFERROR(COUNTIFS(Deliverables!$K$5:$K$304,$A26,Deliverables!$F$5:$F$304,"<>Delivered",Deliverables!$F$5:$F$304,"<>Approved",Deliverables!$F$5:$F$304,"<>Cancelled"),0) -> 0
A27: =A26+7 -> 46314 | B27: =IFERROR("Week "&TEXT(WEEKNUM($A27,21),"0"),"—") -> Week 43 | C27: 25 | D27: =IFERROR(SUMIFS(Deliverables!$I$5:$I$304,Deliverables!$K$5:$K$304,$A27),0) -> 0 | F27: =IF(NOT(ISNUMBER($C27)),"—",IFERROR($C27-N($D27)-N($E27),"—")) -> 25 | G27: =IF(OR(NOT(ISNUMBER($C27)),$C27<=0),"—",IFERROR(($D27+N($E27))/$C27,"—")) -> 0 | H27: =IFERROR(SUMIFS(Deliverables!$I$5:$I$304,Deliverables!$K$5:$K$304,$A27,Deliverables!$M$5:$M$304,"Can move"),0) -> 0 | I27: =IFERROR(COUNTIFS(Deliverables!$K$5:$K$304,$A27,Deliverables!$F$5:$F$304,"<>Delivered",Deliverables!$F$5:$F$304,"<>Approved",Deliverables!$F$5:$F$304,"<>Cancelled"),0) -> 0
... A40: =A39+7 -> 46405 | B40: =IFERROR("Week "&TEXT(WEEKNUM($A40,21),"0"),"—") -> Week 3 | C40: 25 | D40: =IFERROR(SUMIFS(Deliverables!$I$5:$I$304,Deliverables!$K$5:$K$304,$A40),0) -> 0 | F40: =IF(NOT(ISNUMBER($C40)),"—",IFERROR($C40-N($D40)-N($E40),"—")) -> 25 | G40: =IF(OR(NOT(ISNUMBER($C40)),$C40<=0),"—",IFERROR(($D40+N($E40))/$C40,"—")) -> 0 | H40: =IFERROR(SUMIFS(Deliverables!$I$5:$I$304,Deliverables!$K$5:$K$304,$A40,Deliverables!$M$5:$M$304,"Can move"),0) -> 0 | I40: =IFERROR(COUNTIFS(Deliverables!$K$5:$K$304,$A40,Deliverables!$F$5:$F$304,"<>Delivered",Deliverables!$F$5:$F$304,"<>Approved",Deliverables!$F$5:$F$304,"<>Cancelled"),0) -> 0
A42: Row 1 of this table also carries everything that is already overdue — late work still costs hours.

Sheet Lists
A1: Consulting | B1: Lead | C1: Not started | D1: Not yet | E1: Hard date | F1: Me
A2: Design | B2: Quoted | C2: In progress | D2: Ready to invoice | E2: Can move | F2: Client
A3: Development | B3: Booked | C3: With client | D3: Invoiced | F3: Subcontractor
A4: Copywriting | B4: In progress | C4: Delivered | D4: Paid
A5: Editing | B5: With client | C5: Approved
A6: Translation | B6: Delivered | C6: Blocked
A7: Photography | B7: Approved | C7: Cancelled
A8: Video | B8: On hold
A9: Marketing | B9: Cancelled
A10: Training | B10: Closed
A11: Retainer
A12: Other
A14: These six columns feed every dropdown in this file.
A15: A = Service type · B = Project status · C = Deliverable status · D = Invoice status · E = Deadline · F = Waiting on
A16: Rename an entry here and the dropdown follows — but rename it in the sheets too, or the colour rules stop matching.
A17: To ADD an entry, type it in the next free cell of that column, then widen the range under Data → Data validation.
A18: Leave no empty cells inside a column — a gap creates an empty line in the dropdown.
